Workbook

Sheet Cover Page 
A1: aq
B11: PROPOSED BILLS OF QUANTITIES FOR KANESHIE BLOCK N REDEVELOPMENT
F23: DATE:9/30/2026

Sheet GEN SUMMARY
A1: PROJECT: BLOCK N REDEVELOPMENT
A2: LOCATION: KANESHIE
A3: CLIENT: STATE HOUSING LIMITED
A4: ='Cover Page '!F23 -> DATE:9/30/2026
A5: ITEM | B5: GENERAL SUMMARY | D5: GHC
A7: A | B7: PRELIMINARIES AND GENERAL ITEMS | D7: ='PRELIMS & GEN. ITEMS'!F40 -> 6123000
A9: B | B9: SUBSTRUCTURE (ALL PROVISIONAL) | D9: =SUBSTRUCTURE!F19 -> 11462308
A11: C | B11: GROUND FLOOR (INCL. M1 PARKING LEVEL) | D11: ='GROUND FLR '!F25 -> 3564210.3
A13: D | B13: FIRST FLOOR (INCL. M2 PARKING LEVEL) | D13: ='1ST FLR '!F25 -> 3329563.1
A15: E | B15: SECOND FLOOR (INCL. MEZZANINE PARKING LEVEL) | D15: ='2ND FLR'!F25 -> 4022915.7
A17: F | B17: THIRD FLOOR | D17: ='3RD FLR'!F25 -> 4846104.7
A19: G | B19: FOURTH FLOOR | D19: ='4TH FLR '!F25 -> 4493131.5
A21: H | B21: FIFTH FLOOR | D21: ='5TH FLR '!F25 -> 4413966.8
A23: J | B23: SIXTH FLOOR | D23: ='6TH FLR '!F25 -> 4486311.7
A25: K | B25: SEVENTH FLOOR | D25: ='7TH FLR '!F25 -> 4431733.9
A27: L | B27: EIGHTH FLOOR | D27: ='8TH FLR '!F25 -> 4427887.7
A29: M | B29: NINTH FLOOR | D29: ='9TH FLR '!F27 -> 4096981.5
A31: N | B31: TENTH FLOOR | D31: ='10TH FLR '!F25 -> 3426769.9
A33: P | B33: ELEVENTH LEVEL - ROOF TOP TERRACE | D33: ='11TH FLR'!F27 -> 2622767.4
A35: Q | B35: TWELFTH LEVEL - ROOF LEVEL & LIFT CORE | D35: ='12TH FLR '!F19 -> 532030.67
A37: R | B37: LIFTS AND PROVISIONAL SUMS | D37: ='LIFTS & PS'!F17 -> 4354000
B39: SUB - TOTAL (1) | C39: GHC | D39: =SUM(D6:D37) -> 70633683
B42: ADD: STATUTORY LEVIES AND TAXES | C42: 0.2 | D42: =D39*C42 -> 14126737
B44: TOTAL COST OF THE WORKS | C44: GHC | D44: =D42+D39 -> 84760419

Sheet PRELIMS & GEN. ITEMS
A1: ='GEN SUMMARY'!A1 -> PROJECT: BLOCK N REDEVELOPMENT
A2: ='GEN SUMMARY'!A2 -> LOCATION: KANESHIE
A3: ='GEN SUMMARY'!A3 -> CLIENT: STATE HOUSING LIMITED
A4: ='GEN SUMMARY'!A4 -> DATE:9/30/2026
B6: BILL NO.1- PRELIMINARIES BILL AND GENERAL CONDITIONS
A7: ITEM | B7: DESCRIPTION | C7: QTY | D7: UNIT | E7: RATE | F7: AMOUNT GHS
B9: SUMMARY
B11: COLLECTION
B12: Page 2 | F12: =F73 -> 0
B14: Page 3 | F14: =F105 -> 0
B16: Page 4 | F16: =F136 -> 910000
B18: Page 5 | F18: =F162 -> 245000
B20: Page 6 | F20: =F185 -> 0
B22: Page 7 | F22: =F215 -> 3000000
B24: Page 8 | F24: =F240 -> 801000
B26: Page 9 | F26: =F267 -> 650000
B28: Page 10 | F28: =F294 -> 60000
B30: Page 11 | F30: =F324 -> 282000
B32: Page 12 | F32: =F354 -> 90000
B34: Page 13 | F34: =F369 -> 25000
B36: Page 14 | F36: =F378 -> 60000
B40: PRELIMINARIES AND GENERAL ITEMS | F40: =SUM(F12:F38) -> 6123000
B41: TOTAL CARRIED TO GENERAL SUMMARY
A42: A | B42: Generally
B43: The contractor shall be deemed to have allowed against each item a rate which complies with all the requirements of the “Preliminaries”. All unpriced preliminaries items shall be deemed to have been included in the general pricing of the works. All item containing “Preliminaries” shall apply to the whole of the works The contractor shall be deemed to have allowed against each item or in his rates of complying with all the requirements of the “Preliminaries”. All item containing “Preliminaries” shall apply to the whole of the works
A45: B | B45: Names of Parties
B46: The names of parties referred to in these Bills of Quantities and in the Conditions of Contract are as follows:-
B47: ENTERPRISE LIFE COMPANY LIMITED
A49: C | B49: ALL DRAWINGS
B50: The drawings used for the preparation of the bills of quantities are scheduled at the Appendix
A52: D | B52: Format of Bills of Quantities
B53: Major portions of this Bills of Quantities have been prepared in accordance with the "Standard Method of Measurement of Building Works", Seventh (7th) Edition (metric) Revised SMM7R (metric) dated July 1998 issued by the Royal Institution of Chartered Surveyors (R.I.C.S.) and the building Employers Confederation (B.E.C.) both of the United Kingdom. However, departures from this method of measurement (see General Notes on Method of Measurement) have been effected to reduce the number of measured Labour items and also to simplify certain other measured items. The Contractor must allow for this departures in his/her pricing so that his/her tender figure shall represent the total cost of all items of works involved in the project. No claim for extra payment will be entertained on the ground that method of the measurement adopted does not comply with the said Standard Method of Measurement.
A55: E | B55: Prohibition of Use
B56: The quantities given in the Bills of Quantities are not intended for ordering of materials/components. Quantities for use in ordering materials/components must be calculated by the Contractor by measurement on site or from contract drawings.
A58: F | B58: Site Location
B59: The Site is located at: Accra in the Greater Accra Region The Contractor is to visit and examine the site and satisfy himself as to the site conditions and facilities for obtaining special materials and shall obtain generally his own information on all matters affecting the execution of the Works.
A61: G | B61: Overtime
B62: The Contractor shall be held to have made all enquiries as to the source of his labour and to have made all provisions in his tender for every cost to him of providing and maintaining the labour force necessary to complete the contract including all extra and additional works in the contract Time, including all overtime and weekend working which he considers he shall require and supervisory cost associated therewith. No extra will be allowed on the contract Sum for this Clause.
A64: H | B64: Definition of Abbreviations
B65: Abbreviations have been used in the Bills of Quantities for the units of measurement and the Contractor should take due notice of the under-mentioned:
B66: m3/ m3/cu. m. - Cubic Metre
B67: m2/ m2/sq. m. - Square Metre
B68: lm - Linear Metre
B69: mm - Millimetre
B70: kg - Kilogramme
B71: T/ton - Tonne
B72: No./Nr. - Number
B73: TO COLLECTION | F73: =SUM(F42:F72) -> 0
A74: A | B74: Alterations to the Bills of Quantities
B75: No alterations or qualifications of any kind whatsoever shall be made by the Contractor to the text of the Bills of Quantities unless authorised or directed in writing by the Engineer or Quantity Surveyor. If any unauthorised alteration or qualification is made by the Contractor, it will be ignored and the text prepared text will be rigidly adhered to.
A77: B | B77: Preamble References
B78: To avoid long descriptions and repetitions, certain description of measured items contain only brief details of materials and/or workmanship and reference to a preamble clause. Whether specifically referred to or not, items in the preambles section in these Bills of Quantities are deemed to qualify and be part of every description of measured work to which they refer and shall be deemed to have been taken into consideration in pricing the whole of these Bills of Quantities.
A80: C | B80: Priced Bills of Quantities
B81: Should there be a difference between a Contractor's Tender Sum and the arithmetically corrected Tender Figure of the "measured works" (after a complete technical and arithmetical check) an adjustment will be made to the rates by agreement. Conversely, a percentage adjustment shall be calculated by using the total amount of the errors in relation to the value of the "measured works" and thus leaving the original Tender Sum unaltered. Variations to the "measured works" in both approaches shall be subject to the same rate amendments or percentage adjustments respectively.
A83: D | B83: Provisional Sum
B84: The Provisional Sum in these Bills of Quantities are used solely to indicate a gross amount inclusive of Contractor's profit and all other elements of loss. These sums will be expended or deducted in whole or in part as required by the Engineer and no claim for loss of profit will be entertained in this respect. The Contractor must not order expenditure against any work covered by Provisional Sums unless receipt of order in writing from the Engineer.
A86: E | B86: Prime Cost (PC) Sums
B87: Prime Cost (PC) Sums included in these Bills of Quantities are for goods to be supplied by a Supplier or work to be executed by a Contractor both to be nominated by the Engineer, P.C. Sums shall be understood to mean the NET amount expended in favour of such persons after deducting all discounts and shall include all taxes (where applicable) and the cost of packing, carriage/freight and delivery as specified. All such PC Sums are at the complete disposal of the Engineer who may direct how they are expended, deducted in whole or in part from the Contract Sum. Following a PC Sum, provision has been made for the Contractor to insert an element of profit and attendance. The Contractor shall express the element of profit as a percentage of the PC Sum and that of attendance as a lump sum.
A89: F | B89: Price Adjustment
B90: There shall be no adjustment for fluctuations
A92: G | B92: Description of the Works
B93: The works shall comprise the construction the following facilities including external services and works. Included in this document are the following:
B94: PRELIMINARIES AND GENERAL CONDITIONS
B95: DEMOLITION / ALTERATIONS/RENOVATIONS
B96: CONCRETE WORKS
B97: MASONRY
B98: STURCTURAL / CARCASING METAL / TIMBER CLADDING/COVERING LININGS/SHEATHING/DRY PARTITIONING
B99: WINDOWS/DOORS/STAIRS
B100: SURFACE FINISHES
B101: FURNITURE/EQUIPMENT
B102: ELECTRICAL/FIRE
B103: PLUMBING INSTALLATION
B104: VENTILATION /AIR CONDITIONING SYSTEMS ELEVATOR INSALLATION EXTERNAL WORKS
B105: TO COLLECTION | F105: =SUM(F74:F104) -> 0
A106: A | B106: Assistance to Consultant, Etc.
B107: Allow a sum for providing all reasonable information, labour and facilities required by the Supervising Consultant (Resident Clerk of works, Engineer, Architect, Etc) in carrying out their duties in connection with this contract per specification.
A109: B | B109: Performance Guarantee
B110: The Contractor shall be required within twenty eight (28) days of receiving the acceptance letter to enter into a written, signed and witnessed guarantee to guarantee the due performance of the works in the sum of ten percent (10%) of the total amount of the contract for performance guarantee . | F110: =RATES!$D$142 -> 250000
B111: The acceptance of a Performance Guarantee obtained by the Contractor with a Bank Company shall be at the sole discretion of the Employer. The guarantee will remain in force until such time as the Contractor has made good the defects notified to him/her by the Engineer in accordance with the Conditions of Contract.
A113: C | B113: Advance Payment Guarantee
B114: Should any advance be given, the Contractor shall provide as a condition precedent, an acceptable advance guarantee from a Bank covering the amount of the advance until its repayment in full. | F114: =RATES!$D$143 -> 150000
B116: All Risks Insurance
A117: D | B117: Provide and maintain All Risks Insurance for the Works, plant, materials, and temporary works including third-party liability, in accordance with the Conditions of Contract. | F117: =RATES!$D$144 -> 450000
A120: E | B120: Direct Payments
B121: The Direct Payment are for works, materials/components to be provided either by the Employer or by persons directly contracted to/or directly engaged by him/her. The sums will not be paid to or through the Contractor. They will be deducted in full from the contract sum as and when the works and materials/components are delivered.
A123: F | B123: Setting Out the Works
B124: At commencement of the contract and during progress of the works, the Contractor shall set out the whole of the works in accordance with the drawings and in conjunction with levels and measurements taken on the site and shall be responsible for the accuracy thereof, and if inaccurate, for making alterations as required by the Engineer. | F124: =RATES!$D$145 -> 60000
B125: The Contractor shall perform all setting out by a method to be approved by the Engineer and provide all instruments, templates, rods and setting out boards etc. as may be necessary for this purpose and where required maintain these for reference during the progress of the works.
B126: The Contractor shall protect and preserve all bench marks, site rails, pegs and other items used for setting out the works.
A128: G | B128: Existing Materials on Site
B129: Sand, gravel, vegetable soil, turf and other materials obtained from the site shall remain the property of the Employer until removed from the site in accordance with the contract. Excavations shall not be made or enlarged for the purpose of obtaining such materials. These materials shall not be used for any purpose other than for the execution of the works.
A131: H | B131: Maintenance of Services
B132: The Contractor shall protect, uphold, temporarily direct and maintain all pipes, ducts, drains, sewers, service mains, overhead cables and the like during the execution of the works. The Contractor shall make good damage to any cause within its control at its own expense or pay any costs and charges in connection therewith. Approval shall be obtained at least two (2) weeks in advance if any services have to be interrupted.
A134: H | B134: Temporary Accommodation for the Employer
B135: The Contractor shall at his/her own expense provide and erect suitable offices of not less than fifty (50) square metres in floor area for the exclusive use of the Client's consultants complete with plan chest, tables and chairs, other furniture and equipment including the supply of electricity.(N/A)
B136: TO COLLECTION | F136: =SUM(F106:F135) -> 910000
A137: A | B137: Semi-Permanent Name/Project Display Board
B138: The Contractor shall provide a steel framed and steel sheet notice board at the entrance of the site bearing the names of the Project, Contractor, 3-D architects impression of the project and all Consultants. The size, design and colour of the notice board shall be subject to the approval of the Engineer. | F138: =RATES!$D$146 -> 25000
A140: B | B140: Advertising Right
B141: The Contractor shall not display any other notice or advertisement in any form on any part of the site, works, hoardings or adjoining ground without the prior approval in writing of the Engineer.
...

Sheet SUBSTRUCTURE
A1: ='PRELIMS & GEN. ITEMS'!A1 -> PROJECT: BLOCK N REDEVELOPMENT
A2: ='PRELIMS & GEN. ITEMS'!A2 -> LOCATION: KANESHIE
A3: ='PRELIMS & GEN. ITEMS'!A3 -> CLIENT: STATE HOUSING LIMITED
A4: ='PRELIMS & GEN. ITEMS'!A4 -> DATE:9/30/2026
A5: ITEM | B5: DESCRIPTION | C5: QTY | D5: UNIT | E5: RATE | F5: AMOUNT - GHC | G5: Measurement basis / calculation
B7: MAIN BUILDING
B9: SUBSTRUCTURE (ALL PROVISIONAL)
B11: BILL SUMMARY
A13: A | B13: D GROUNDWORK (D20 EXCAVATION AND FILLING) | F13: =F43 -> 3068497.2
A15: B | B15: E IN SITU CONCRETE | F15: =F83 -> 8350767.6
A17: C | B17: BLOCK WORK | F17: =F92 -> 43043
B19: =B9 -> SUBSTRUCTURE (ALL PROVISIONAL) | E19: GHC | F19: =SUM(F13:F18) -> 11462308
B20: To Bill General Summary
B23: BILL NR. 2 - SUBSTRUCTURE
B25: D GROUNDWORK (D20 EXCAVATION AND FILLING)
B26: Site Preparation
A27: A | B27: Clear site of all vegetation, grub up their roots and dispose-off (Block N plot and Parking-22 forecourt) | C27: =TAKEOFF!$H$29 -> 2299.0095 | D27: m2 | E27: =RATES!$D$7 -> 15 | F27: =C27*E27 -> 34485.143 | G27: 40.85*38.27+35.2*20.9
A29: B | B29: Excavate oversite to remove vegetable soil average 150mm deep and deposit on site for re-use average 50m from excavation | C29: =TAKEOFF!$H$32 -> 1800 | D29: m2 | E29: =RATES!$D$8 -> 28 | F29: =C29*E29 -> 50400 | G29: (41.0+2*2.0)*(36.0+2*2.0)
A31: C | B31: Excavate raft foundation to reduce levels maximum depth 4.00m | C31: =TAKEOFF!$H$35 -> 7200 | D31: m3 | E31: =RATES!$D$9 -> 85 | F31: =C31*E31 -> 612000 | G31: (45.0*40.0)*4.0
A33: D | B33: Fill to make up levels over raft average 1000mm thick with waterproof external membrane and high strength biaxial geogrid; compacted | C33: =TAKEOFF!$H$40 -> 1445.3447 | D33: m3 | E33: =RATES!$D$10 -> 220 | F33: =C33*E33 -> 317975.84 | G33: 41.0*36.0*1.0-(69.445*0.25*1.0)-(13.294*1.0)
A35: E | B35: Fill to make up levels below raft 1700mm thick with 300mm thick compacted crushed rock layers between geogrid layers until formation level is reached | C35: =TAKEOFF!$H$43 -> 3060 | D35: m3 | E35: =RATES!$D$11 -> 480 | F35: =C35*E35 -> 1468800 | G35: (45.0*40.0)*1.7
A37: F | B37: Backfill and compact selected excavated material around foundations | C37: =TAKEOFF!$H$47 -> 745.2 | D37: m3 | E37: =RATES!$D$12 -> 60 | F37: =C37*E37 -> 44712 | G37: ((45.0*40.0)-(41.0*36.0))*(4.0-1.7)
A39: G | B39: Load up surplus excavated material and remove from site | C39: =TAKEOFF!$H$52 -> 6454.8 | D39: m3 | E39: =RATES!$D$13 -> 75 | F39: =C39*E39 -> 484110 | G39: (45.0*40.0)*4.0-((45.0*40.0)-(41.0*36.0))*(4.0-1.7)
A41: H | B41: Approved imported granular material hardcore filling to make up levels: depositing and compacting in layers 150mm maximum thickness | C41: =TAKEOFF!$H$55 -> 221.4 | D41: m3 | E41: =RATES!$D$14 -> 253 | F41: =C41*E41 -> 56014.2 | G41: 41.0*36.0*0.15
B43: =B25 -> D GROUNDWORK (D20 EXCAVATION AND FILLING) | F43: =SUM(F26:F42) -> 3068497.2
B44: Carried to Bill Summary
B47: E IN SITU CONCRETE
B49: E10 Plain in-situ concrete (1:4:8 - 38mm aggregate) as described in:
A50: A | B50: Blinding 100mm thick under raft | C50: =TAKEOFF!$H$60 -> 147.6 | D50: m3 | E50: =RATES!$D$15 -> 1650 | F50: =C50*E50 -> 243540 | G50: 41.0*36.0*0.10
A52: B | B52: 150mm thick bed | C52: =TAKEOFF!$H$63 -> 221.4 | D52: m3 | E52: =RATES!$D$16 -> 1925 | F52: =C52*E52 -> 426195 | G52: 41.0*36.0*0.15
B54: Vibrated in-situ concrete C40 as described in:
A55: C | B55: Concrete walls (raft to ground floor) | C55: =TAKEOFF!$H$69 -> 22.569625 | D55: m3 | E55: =RATES!$D$20 -> 2310 | F55: =C55*E55 -> 52135.834 | G55: (22.05+21.825+25.57)*0.25*1.3
A57: D | B57: Concrete in raft 1300mm thick | C57: =TAKEOFF!$H$72 -> 1918.8 | D57: m3 | E57: =RATES!$D$19 -> 2310 | F57: =C57*E57 -> 4432428 | G57: 41.0*36.0*1.3
A59: E | B59: Concrete in columns (raft to ground floor) | C59: =TAKEOFF!$H$83 -> 17.281875 | D59: m3 | E59: =RATES!$D$21 -> 2310 | F59: =C59*E59 -> 39921.131 | G59: 5*0.75*0.5*1.3+1*0.75*0.5*1.3+2*0.75*0.5*1.3+1*0.75*0.5*1.3+3*1.2*0.3*1.3+6*1.2*0.3*1.3+1*1.2*0.3*1.3+15*1.2*0.3*1.3+1*(2.85*0.25+0.825*0.25)*1.3
B61: E30 REINFORCEMENT - High tensile yield round bar reinforcement (standard):
A62: F | B62: 20mm diameter in raft | C62: =TAKEOFF!$H$87 -> 2.466 | D62: t | E62: =RATES!$D$32 -> 14300 | F62: =C62*E62 -> 35263.8 | G62: 2.466
A64: G | B64: 25mm diameter in raft | C64: =TAKEOFF!$H$90 -> 184.672 | D64: t | E64: =RATES!$D$33 -> 14300 | F64: =C64*E64 -> 2640809.6 | G64: 184.672
A66: H | B66: 10mm diameter links to columns & walls (raft to ground floor) | C66: =TAKEOFF!$H$95 -> 4.029 | D66: t | E66: =RATES!$D$29 -> 14300 | F66: =C66*E66 -> 57614.7 | G66: 3.252+0.517+0.260
A68: J | B68: 12mm diameter to walls (raft to ground floor) | C68: =TAKEOFF!$H$99 -> 1.253 | D68: t | E68: =RATES!$D$30 -> 14300 | F68: =C68*E68 -> 17917.9 | G68: 0.863+0.390
A70: K | B70: 25mm diameter to columns & walls (raft to ground floor) | C70: =TAKEOFF!$H$104 -> 21.306 | D70: t | E70: =RATES!$D$33 -> 14300 | F70: =C70*E70 -> 304675.8 | G70: 6.531+9.840+4.935
A72: L | B72: 20mm diameter in columns (raft to ground floor) | C72: =TAKEOFF!$H$107 -> 0.338 | D72: t | E72: =RATES!$D$32 -> 14300 | F72: =C72*E72 -> 4833.4 | G72: 0.338
B74: E20 FORMWORK
A75: M | B75: Concrete walls (both faces) | C75: =TAKEOFF!$H$113 -> 180.557 | D75: m2 | E75: =RATES!$D$36 -> 165 | F75: =C75*E75 -> 29791.905 | G75: 2*(22.05+21.825+25.57)*1.3
A77: N | B77: Edges of bed 150mm high | C77: =TAKEOFF!$H$116 -> 154 | D77: m | E77: =RATES!$D$40 -> 65 | F77: =C77*E77 -> 10010 | G77: 2*(41.0+36.0)
A79: P | B79: Edges of raft 1300mm high | C79: =TAKEOFF!$H$119 -> 200.2 | D79: m2 | E79: =RATES!$D$41 -> 165 | F79: =C79*E79 -> 33033 | G79: 2*(41.0+36.0)*1.3
A81: Q | B81: Sides of columns (raft to ground floor) | C81: =TAKEOFF!$H$130 -> 136.955 | D81: m2 | E81: =RATES!$D$37 -> 165 | F81: =C81*E81 -> 22597.575 | G81: 5*2*(0.75+0.5)*1.3+1*2*(0.75+0.5)*1.3+2*2*(0.75+0.5)*1.3+1*2*(0.75+0.5)*1.3+3*2*(1.2+0.3)*1.3+6*2*(1.2+0.3)*1.3+1*2*(1.2+0.3)*1.3+15*2*(1.2+0.3)*1.3+1*2*(2.85+1.075)*1.3
B83: =B47 -> E IN SITU CONCRETE | F83: =SUM(F49:F82) -> 8350767.6
B84: Carried to Bill Summary
B87: BLOCK WORK
B89: Solid sandcrete blockwork in cement and sand (1:4) mortar:
A90: A | B90: 150mm walls to plinth | C90: =TAKEOFF!$H$135 -> 200.2 | D90: m2 | E90: =RATES!$D$46 -> 215 | F90: =C90*E90 -> 43043 | G90: 2*(41.0+36.0)*1.3
B92: =B87 -> BLOCK WORK | F92: =SUM(F89:F91) -> 43043
B93: Carried to Bill Summary
B96: Raft top SSL -1.000; formation -4.000 (STR-001). Raft 41.0 x 36.0m measured on STR-001/STR-002.

Sheet GROUND FLR 
A1: ='PRELIMS & GEN. ITEMS'!A1 -> PROJECT: BLOCK N REDEVELOPMENT
A2: ='PRELIMS & GEN. ITEMS'!A2 -> LOCATION: KANESHIE
A3: ='PRELIMS & GEN. ITEMS'!A3 -> CLIENT: STATE HOUSING LIMITED
A4: ='PRELIMS & GEN. ITEMS'!A4 -> DATE:9/30/2026
A5: ITEM | B5: DESCRIPTION | C5: QTY | D5: UNIT | E5: RATE | F5: AMOUNT - GHC | G5: Measurement basis / calculation
B7: MAIN BUILDING
B9: GROUND FLOOR (INCL. M1 PARKING LEVEL 1B)
B11: BILL SUMMARY
A13: A | B13: ELEMENT NO. 1: IN SITU CONCRETE/LARGE PRECAST CONCRETE | F13: =F92 -> 2337940.4
A15: B | B15: ELEMENT NO. 2: MASONRY | F15: =F103 -> 209940.8
A17: C | B17: ELEMENT NO. 4: WINDOWS/DOORS | F17: =F169 -> 406389.1
A19: D | B19: ELEMENT NO. 5: FLOOR FINISHES | F19: =F192 -> 311872.36
A21: E | B21: ELEMENT NO. 6: WALL FINISHES | F21: =F209 -> 157798.45
A23: F | B23: ELEMENT NO. 7: PAINTING AND DECORATING | F23: =F231 -> 140269.25
B25: =B9 -> GROUND FLOOR (INCL. M1 PARKING LEVEL 1B) | E25: GHC | F25: =SUM(F13:F24) -> 3564210.3
B26: To Bill General Summary
B29: BILL NR. 3 - GROUND FLOOR
B31: ELEMENT NO. 1: IN SITU CONCRETE/LARGE PRECAST CONCRETE
B33: Vibrated in-situ concrete C40 as described in:
A34: A | B34: Suspended slab 250mm thick | C34: =TAKEOFF!$H$143 -> 172.275 | D34: m3 | E34: =RATES!$D$22 -> 2310 | F34: =C34*E34 -> 397955.25 | G34: 689.1*0.25
A36: B | B36: Beams (downstands below slab) | C36: =TAKEOFF!$H$146 -> 7.119 | D36: m3 | E36: =RATES!$D$23 -> 2310 | F36: =C36*E36 -> 16444.89 | G36: 67.8*0.3*0.35
A38: C | B38: Columns | C38: =TAKEOFF!$H$159 -> 52.4775 | D38: m3 | E38: =RATES!$D$21 -> 2310 | F38: =C38*E38 -> 121223.02 | G38: 5*0.75*0.5*3.6+1*0.75*0.5*3.6+2*0.75*0.5*3.6+1*0.75*0.5*1.95+1*0.75*0.5*2.45+3*1.2*0.3*3.6+6*1.2*0.3*3.6+1*1.2*0.3*3.6+15*1.2*0.3*1.95+15*1.2*0.3*2.45+1*(2.85*0.25+0.825*0.25)*3.6
A40: D | B40: Concrete wall - shear walls to main & emergency stair cores, 250mm thick | C40: =TAKEOFF!$H$164 -> 49.88975 | D40: m3 | E40: =RATES!$D$20 -> 2310 | F40: =C40*E40 -> 115245.32 | G40: 22.05*3.6*0.25+25.57*2.25*0.25+25.57*2.45*0.25
A42: E | B42: Concrete wall - lift walls, 250mm thick | C42: =TAKEOFF!$H$167 -> 19.6425 | D42: m3 | E42: =RATES!$D$20 -> 2310 | F42: =C42*E42 -> 45374.175 | G42: 21.825*3.6*0.25
A44: F | B44: Stairs | C44: =TAKEOFF!$H$175 -> 16.00903 | D44: m3 | E44: =RATES!$D$24 -> 2310 | F44: =C44*E44 -> 36980.86 | G44: (2.966*3.85/3.3+2.625)+(2.966*2.5/3.3+2.625)+(2.966*2.7/3.3+2.625)
A46: G | B46: Lintels 150 x 225mm over door and window openings | C46: =TAKEOFF!$H$199 -> 3.324375 | D46: m3 | E46: =RATES!$D$25 -> 1925 | F46: =C46*E46 -> 6399.4219 | G46: (1*(1.8+0.3)+6*(0.9+0.3)+1*(0.9+0.3)+1*(3.2+0.3)+6*(0.75+0.3)+2*(0.7+0.3)+3*(1+0.3)+2*(0.9+0.3)+3*(1.8+0.3)+2*(1.8+0.3)+2*(2.4+0.3)+1*(5.05+0.3)+2*(4.2+0.3)+1*(3.6+0.3)+1*(1.8+0.3)+1*(1.8+0.3)+1*(3.5+0.3)+3*(3.6+0.3)+2*(2.4+0.3)+2*(2.1+0.3)+4*(0.9...
B48: E20 FORMWORK - Formwork as described to:
A49: H | B49: Soffits of suspended slab | C49: =TAKEOFF!$H$203 -> 689.1 | D49: m2 | E49: =RATES!$D$38 -> 165 | F49: =C49*E49 -> 113701.5 | G49: 689.1
A51: J | B51: Edges of suspended slab 250mm high | C51: =TAKEOFF!$H$206 -> 238.4 | D51: m | E51: =RATES!$D$40 -> 65 | F51: =C51*E51 -> 15496 | G51: 238.4
A53: K | B53: Sides and soffits of beams | C53: =TAKEOFF!$H$209 -> 67.8 | D53: m2 | E53: =RATES!$D$39 -> 165 | F53: =C53*E53 -> 11187 | G53: 67.8*(2*0.35+0.3)
A55: L | B55: Columns | C55: =TAKEOFF!$H$222 -> 417.26 | D55: m2 | E55: =RATES!$D$37 -> 165 | F55: =C55*E55 -> 68847.9 | G55: 5*2*(0.75+0.5)*3.6+1*2*(0.75+0.5)*3.6+2*2*(0.75+0.5)*3.6+1*2*(0.75+0.5)*1.95+1*2*(0.75+0.5)*2.45+3*2*(1.2+0.3)*3.6+6*2*(1.2+0.3)*3.6+1*2*(1.2+0.3)*3.6+15*2*(1.2+0.3)*1.95+15*2*(1.2+0.3)*2.45+1*2*(2.85+1.075)*3.6
A57: M | B57: Concrete wall (both faces) | C57: =TAKEOFF!$H$228 -> 556.258 | D57: m2 | E57: =RATES!$D$36 -> 165 | F57: =C57*E57 -> 91782.57 | G57: 2*22.05*3.6+2*21.825*3.6+2*25.57*2.25+2*25.57*2.45
A59: N | B59: Soffits of stair flights, landings and risers | C59: =TAKEOFF!$H$239 -> 99.7992 | D59: m2 | E59: =RATES!$D$42 -> 165 | F59: =C59*E59 -> 16466.868 | G59: (2*3.424*1.8+15.0+22*0.15*1.8)+(2*3.424*1.8+15.0+22*0.15*1.8)+(2*3.424*1.8+15.0+22*0.15*1.8)
A61: P | B61: Side and soffits of lintel / coping | C61: =TAKEOFF!$H$263 -> 59.1 | D61: m2 | E61: =RATES!$D$43 -> 165 | F61: =C61*E61 -> 9751.5 | G61: (1*(1.8+0.3)+6*(0.9+0.3)+1*(0.9+0.3)+1*(3.2+0.3)+6*(0.75+0.3)+2*(0.7+0.3)+3*(1+0.3)+2*(0.9+0.3)+3*(1.8+0.3)+2*(1.8+0.3)+2*(2.4+0.3)+1*(5.05+0.3)+2*(4.2+0.3)+1*(3.6+0.3)+1*(1.8+0.3)+1*(1.8+0.3)+1*(3.5+0.3)+3*(3.6+0.3)+2*(2.4+0.3)+2*(2.1+0.3)+4*(0.9...
B63: E30 REINFORCEMENT - High tensile yield round bar reinforcement (standard) to BS 4449:
A64: Q | B64: 10mm diameter in columns | C64: =TAKEOFF!$H$268 -> 6.028 | D64: t | E64: =RATES!$D$29 -> 14300 | F64: =C64*E64 -> 86200.4 | G64: 4.372+1.656
A66: R | B66: 20mm diameter in columns | C66: =TAKEOFF!$H$271 -> 0.599 | D66: t | E66: =RATES!$D$32 -> 14300 | F66: =C66*E66 -> 8565.7 | G66: 0.599
A68: S | B68: 25mm diameter in columns | C68: =TAKEOFF!$H$275 -> 14.386 | D68: t | E68: =RATES!$D$33 -> 14300 | F68: =C68*E68 -> 205719.8 | G68: 10.083+4.303
A70: T | B70: 10mm diameter in beams (links) | C70: =TAKEOFF!$H$278 -> 1.126 | D70: t | E70: =RATES!$D$29 -> 14300 | F70: =C70*E70 -> 16101.8 | G70: 1.126
A72: U | B72: 16mm diameter in beams | C72: =TAKEOFF!$H$281 -> 0.576 | D72: t | E72: =RATES!$D$31 -> 14300 | F72: =C72*E72 -> 8236.8 | G72: 0.576
A74: V | B74: 20mm diameter in beams | C74: =TAKEOFF!$H$284 -> 0.814 | D74: t | E74: =RATES!$D$32 -> 14300 | F74: =C74*E74 -> 11640.2 | G74: 0.814
A76: W | B76: 25mm diameter in beams | C76: =TAKEOFF!$H$287 -> 2.438 | D76: t | E76: =RATES!$D$33 -> 14300 | F76: =C76*E76 -> 34863.4 | G76: 2.438
A78: X | B78: 10mm diameter in shear & lift walls (links) | C78: =TAKEOFF!$H$292 -> 2.785 | D78: t | E78: =RATES!$D$29 -> 14300 | F78: =C78*E78 -> 39825.5 | G78: 1.374+0.751+0.660
A80: Y | B80: 12mm diameter in shear, lift & ramp walls | C80: =TAKEOFF!$H$298 -> 5.415 | D80: t | E80: =RATES!$D$30 -> 14300 | F80: =C80*E80 -> 77434.5 | G80: 2.268+1.472+0.840+0.835
A82: Z | B82: 25mm diameter in shear & lift walls | C82: =TAKEOFF!$H$303 -> 22.198 | D82: t | E82: =RATES!$D$33 -> 14300 | F82: =C82*E82 -> 317431.4 | G82: 10.865+6.137+5.196
A84: A | B84: 12mm diameter in stairs | C84: =TAKEOFF!$H$307 -> 1.32 | D84: t | E84: =RATES!$D$30 -> 14300 | F84: =C84*E84 -> 18876 | G84: 0.880+0.440
A86: B | B86: 16mm diameter in stairs | C86: =TAKEOFF!$H$311 -> 1.886 | D86: t | E86: =RATES!$D$31 -> 14300 | F86: =C86*E86 -> 26969.8 | G86: 1.192+0.694
A88: C | B88: 12mm diameter for suspended slab | C88: =TAKEOFF!$H$314 -> 25.574 | D88: t | E88: =RATES!$D$30 -> 14300 | F88: =C88*E88 -> 365708.2 | G88: 25.574
A90: D | B90: 16mm diameter for suspended slab | C90: =TAKEOFF!$H$317 -> 3.742 | D90: t | E90: =RATES!$D$31 -> 14300 | F90: =C90*E90 -> 53510.6 | G90: 3.742
B92: =B31 -> ELEMENT NO. 1: IN SITU CONCRETE/LARGE PRECAST CONCRETE | F92: =SUM(F33:F91) -> 2337940.4
B93: Carried to Bill Summary
B96: ELEMENT NO. 2: MASONRY
B98: F10 BRICK/BLOCK WALL - Solid sandcrete blockwork in cement and sand (1:4) mortar as described in:
A99: A | B99: 150mm thick wall | C99: =TAKEOFF!$H$344 -> 810.64435 | D99: m2 | E99: =RATES!$D$46 -> 215 | F99: =C99*E99 -> 174288.54 | G99: 203.6*3.6+(1*1.8*(3.05-2.4)+6*0.9*(3.05-2.2)+1*0.9*(3.05-2.35)+1*3.2*(3.05-2.2)+6*0.75*(3.05-2.2)+2*0.7*(3.05-2.2)+3*1*(3.05-2.2)+2*0.9*(3.05-2.2)+3*1.8*(3.05-2.2)+2*1.8*(3.05-2.2)+2*2.4*(3.05-2.2)+1*5.05*(3.05-2.2)+2*4.2*(3.05-2.157)+1*3.6*(3.05-...
A101: B | B101: 200mm thick wall | C101: =TAKEOFF!$H$369 -> 134.53685 | D101: m2 | E101: =RATES!$D$47 -> 265 | F101: =C101*E101 -> 35652.265 | G101: 33.8*3.6+(1*1.8*(3.05-2.4)+6*0.9*(3.05-2.2)+1*0.9*(3.05-2.35)+1*3.2*(3.05-2.2)+6*0.75*(3.05-2.2)+2*0.7*(3.05-2.2)+3*1*(3.05-2.2)+2*0.9*(3.05-2.2)+3*1.8*(3.05-2.2)+2*1.8*(3.05-2.2)+2*2.4*(3.05-2.2)+1*5.05*(3.05-2.2)+2*4.2*(3.05-2.157)+1*3.6*(3.05-1...
B103: =B96 -> ELEMENT NO. 2: MASONRY | F103: =SUM(F98:F102) -> 209940.8
B104: Carried to Bill Summary
B107: ELEMENT NO. 4: WINDOWS/DOORS
B109: L20 DOORS - Supply and fix the following door assemblies complete with frames, ironmongery sets to steel doors and all accessories:
A110: A | B110: 1800mm x 2400mm 2-hour fire-rated double-leaf galvanised steel door (D1) | C110: =TAKEOFF!$H$374 -> 1 | D110: nr | E110: =RATES!$D$74 -> 18500 | F110: =C110*E110 -> 18500 | G110: 1
A112: B | B112: 900mm x 2200mm single leaf timber panel door (D3) | C112: =TAKEOFF!$H$377 -> 6 | D112: nr | E112: =RATES!$D$76 -> 3400 | F112: =C112*E112 -> 20400 | G112: 6
A114: C | B114: 900mm x 2350mm single leaf timber panel door with fanlight (D4) | C114: =TAKEOFF!$H$380 -> 1 | D114: nr | E114: =RATES!$D$77 -> 3900 | F114: =C114*E114 -> 3900 | G114: 1
A116: D | B116: 3200mm x 2200mm 4-panel galvanised steel framed tempered glass sliding door assembly (D5) | C116: =TAKEOFF!$H$383 -> 1 | D116: nr | E116: =RATES!$D$78 -> 16500 | F116: =C116*E116 -> 16500 | G116: 1
A118: E | B118: 750mm x 2200mm single leaf timber flush door (D6) | C118: =TAKEOFF!$H$386 -> 6 | D118: nr | E118: =RATES!$D$79 -> 1900 | F118: =C118*E118 -> 11400 | G118: 6
A120: F | B120: 700mm x 2200mm single-leaf 2-hour fire-rated galvanised steel door (D7) | C120: =TAKEOFF!$H$389 -> 2 | D120: nr | E120: =RATES!$D$80 -> 6800 | F120: =C120*E120 -> 13600 | G120: 2
A122: G | B122: 1000mm x 2200mm 1-hour fire-rated galvanised steel single-leaf security door assembly - emergency stairs (ED1) | C122: =TAKEOFF!$H$392 -> 3 | D122: nr | E122: =RATES!$D$82 -> 7200 | F122: =C122*E122 -> 21600 | G122: 3
A124: H | B124: 900mm x 2200mm 1-hour fire-rated galvanised steel single-leaf security door assembly (D9) | C124: =TAKEOFF!$H$395 -> 2 | D124: nr | E124: =RATES!$D$84 -> 6900 | F124: =C124*E124 -> 13800 | G124: 2
A126: J | B126: 1800mm x 2200mm double-leaf 2-hour fire-rated galvanised steel refuse room door (MD1) | C126: =TAKEOFF!$H$398 -> 3 | D126: nr | E126: =RATES!$D$85 -> 14500 | F126: =C126*E126 -> 43500 | G126: 3
A128: K | B128: 1800mm x 2200mm double-leaf double-swing galvanised steel framed tempered glass door (GD1) | C128: =TAKEOFF!$H$401 -> 2 | D128: nr | E128: =RATES!$D$91 -> 12500 | F128: =C128*E128 -> 25000 | G128: 2
A130: L | B130: 2400mm x 2200mm double-leaf double-swing galvanised steel framed tempered glass door (DW1) | C130: =TAKEOFF!$H$404 -> 2 | D130: nr | E130: =RATES!$D$92 -> 15500 | F130: =C130*E130 -> 31000 | G130: 2
A132: M | B132: 5050mm x 2200mm double-leaf double-swing galvanised steel framed tempered glass door with fanlight and fixed side windows (DW2) | C132: =TAKEOFF!$H$407 -> 1 | D132: nr | E132: =RATES!$D$93 -> 33000 | F132: =C132*E132 -> 33000 | G132: 1
A134: N | B134: Metal roller shutter door 4200mm x 2157mm (RD1) | C134: =TAKEOFF!$H$410 -> 2 | D134: nr | E134: =RATES!$D$99 -> 23000 | F134: =C134*E134 -> 46000 | G134: 2
A136: P | B136: 50mm x 150mm frames (to timber doors) | C136: =TAKEOFF!$H$415 -> 68.3 | D136: m | E136: =RATES!$D$100 -> 125 | F136: =C136*E136 -> 8537.5 | G136: 6*(2*2.2+0.9)+1*(2*2.35+0.9)+6*(2*2.2+0.75)
A138: Q | B138: 50mm x 12mm door stop | C138: =TAKEOFF!$H$420 -> 68.3 | D138: m | E138: =RATES!$D$101 -> 28 | F138: =C138*E138 -> 1912.4 | G138: 6*(2*2.2+0.9)+1*(2*2.35+0.9)+6*(2*2.2+0.75)
B140: CF | F140: =SUM(F106:F138) -> 308649.9
B141: BF | F141: =F140 -> 308649.9
B143: Ironmongery - Supply and fix the following approved ironmongery to hardwood with accompanying patented screws:
A144: R | B144: Pair 100mm brass butt hinges | C144: =TAKEOFF!$H$424 -> 20 | D144: pr | E144: =RATES!$D$102 -> 125 | F144: =C144*E144 -> 2500 | G144: 20
A146: S | B146: Ordinary locks | C146: =TAKEOFF!$H$427 -> 7 | D146: nr | E146: =RATES!$D$103 -> 480 | F146: =C146*E146 -> 3360 | G146: 7
A148: T | B148: Approved high quality mortice indicator lock | C148: =TAKEOFF!$H$430 -> 6 | D148: nr | E148: =RATES!$D$104 -> 560 | F148: =C148*E148 -> 3360 | G148: 6
B150: ALUMINIUM GLAZED WINDOWS - Supply and install Italian extruded aluminium glazed windows, ALCOA R50 series, powder coated aluminium profile, glazed with 6mm tinted reflective glass secured onto galvanized steel sub-frames, complete with all accessories as per Architect's detail:
A151: U | B151: 4 x 2 bay alu. framed glass awning window 3600mm x 1900mm (W1) | C151: =TAKEOFF!$H$434 -> 1 | D151: nr | E151: =RATES!$D$108 -> 10533.6 | F151: =C151*E151 -> 10533.6 | G151: 1
A153: V | B153: 2 bay alu. framed glass sliding window 1800mm x 1500mm (W3) | C153: =TAKEOFF!$H$437 -> 1 | D153: nr | E153: =RATES!$D$110 -> 4158 | F153: =C153*E153 -> 4158 | G153: 1
A155: W | B155: 2 bay alu. framed glass sliding window 1800mm x 1900mm (W5) | C155: =TAKEOFF!$H$440 -> 1 | D155: nr | E155: =RATES!$D$112 -> 5266.8 | F155: =C155*E155 -> 5266.8 | G155: 1
A157: X | B157: L-shaped alu. framed fixed glass window 1750mm x 1750mm x 1500mm (W6) | C157: =TAKEOFF!$H$443 -> 1 | D157: nr | E157: =RATES!$D$113 -> 8085 | F157: =C157*E157 -> 8085 | G157: 1
A159: Y | B159: 3 bay alu. framed glass sliding window 3600mm x 2200mm (W14) | C159: =TAKEOFF!$H$446 -> 3 | D159: nr | E159: =RATES!$D$121 -> 12196.8 | F159: =C159*E159 -> 36590.4 | G159: 3
A161: Z | B161: 3 x 2 alu. framed glass awning window 2400mm x 1900mm (W16) | C161: =TAKEOFF!$H$449 -> 2 | D161: nr | E161: =RATES!$D$123 -> 7022.4 | F161: =C161*E161 -> 14044.8 | G161: 2
A163: A | B163: 3 bay alu. framed glass sliding window 2100mm x 900mm (W19) | C163: =TAKEOFF!$H$452 -> 2 | D163: nr | E163: =RATES!$D$126 -> 2910.6 | F163: =C163*E163 -> 5821.2 | G163: 2
A165: B | B165: 2 bay alu. framed glass sliding window 900mm x 600mm (HW1) | C165: =TAKEOFF!$H$455 -> 4 | D165: nr | E165: =RATES!$D$128 -> 831.6 | F165: =C165*E165 -> 3326.4 | G165: 4
A167: C | B167: 2 bay alu. framed glass sliding window 750mm x 600mm (HW2) | C167: =TAKEOFF!$H$458 -> 1 | D167: nr | E167: =RATES!$D$129 -> 693 | F167: =C167*E167 -> 693 | G167: 1
B169: =B107 -> ELEMENT NO. 4: WINDOWS/DOORS | F169: =SUM(F141:F168) -> 406389.1
B170: Carried to Bill Summary
B173: ELEMENT NO. 5: FLOOR FINISHES
B175: M10/M40 FLOOR FINISHES
A176: A | B176: 25mm cement and sand (1:3) screeded finish laid level on concrete and finished smooth with steel trowel | C176: =TAKEOFF!$H$463 -> 749.4 | D176: m2 | E176: =RATES!$D$50 -> 68 | F176: =C176*E176 -> 50959.2 | G176: 749.4
A178: B | B178: 12mm cement and sand (1:4) screeded bed laid level on concrete floor to receive floor tiles | C178: =TAKEOFF!$H$478 -> 844.62 | D178: m2 | E178: =RATES!$D$51 -> 48 | F178: =C178*E178 -> 40541.76 | G178: 749.4+(2*1.8*3.0+22*0.15*1.8+2.2*3.75+1.8*3.75)+(2*1.8*3.0+22*0.15*1.8+2.2*3.75+1.8*3.75)+(2*1.8*3.0+22*0.15*1.8+2.2*3.75+1.8*3.75)
A180: C | B180: 400x400mm non-slip porcelain floor tiles to washrooms & WCs, adhesive, grout and cutting | C180: =TAKEOFF!$H$481 -> 18.1 | D180: m2 | E180: =RATES!$D$53 -> 230 | F180: =C180*E180 -> 4163 | G180: 18.1
A182: D | B182: 500x500mm matte R11 porcelain tiles to staircases (treads, risers and landings) | C182: =TAKEOFF!$H$495 -> 95.22 | D182: m2 | E182: =RATES!$D$54 -> 270 | F182: =C182*E182 -> 25709.4 | G182: (2*1.8*3.0+22*0.15*1.8+2.2*3.75+1.8*3.75)+(2*1.8*3.0+22*0.15*1.8+2.2*3.75+1.8*3.75)+(2*1.8*3.0+22*0.15*1.8+2.2*3.75+1.8*3.75)
A184: E | B184: 600x600mm semi-polished porcelain floor tiles to habitable rooms, shops & offices | C184: =TAKEOFF!$H$498 -> 208.6 | D184: m2 | E184: =RATES!$D$55 -> 265 | F184: =C184*E184 -> 55279 | G184: 208.6
A186: F | B186: 600x1200mm semi-polished porcelain floor tiles to stair/lift lobbies & reception | C186: =TAKEOFF!$H$501 -> 52 | D186: m2 | E186: =RATES!$D$56 -> 330 | F186: =C186*E186 -> 17160 | G186: 52.0
...

Sheet 1ST FLR 
A1: ='PRELIMS & GEN. ITEMS'!A1 -> PROJECT: BLOCK N REDEVELOPMENT
A2: ='PRELIMS & GEN. ITEMS'!A2 -> LOCATION: KANESHIE
A3: ='PRELIMS & GEN. ITEMS'!A3 -> CLIENT: STATE HOUSING LIMITED
A4: ='PRELIMS & GEN. ITEMS'!A4 -> DATE:9/30/2026
A5: ITEM | B5: DESCRIPTION | C5: QTY | D5: UNIT | E5: RATE | F5: AMOUNT - GHC | G5: Measurement basis / calculation
B7: MAIN BUILDING
B9: FIRST FLOOR - LEVEL 2A PARKING (INCL. M2 LEVEL 2B)
B11: BILL SUMMARY
A13: A | B13: ELEMENT NO. 1: IN SITU CONCRETE/LARGE PRECAST CONCRETE | F13: =F93 -> 2886751.5
A15: B | B15: ELEMENT NO. 2: MASONRY | F15: =F104 -> 76177.553
A17: C | B17: ELEMENT NO. 4: WINDOWS/DOORS | F17: =F113 -> 21600
A19: D | B19: ELEMENT NO. 5: FLOOR FINISHES | F19: =F131 -> 227701.44
A21: E | B21: ELEMENT NO. 6: WALL FINISHES | F21: =F141 -> 63462.63
A23: F | B23: ELEMENT NO. 7: PAINTING AND DECORATING | F23: =F156 -> 53869.883
B25: =B9 -> FIRST FLOOR - LEVEL 2A PARKING (INCL. M2 LEVEL 2B) | E25: GHC | F25: =SUM(F13:F24) -> 3329563.1
B26: To Bill General Summary
B28: BILL NR. 4 - FIRST FLOOR
B30: ELEMENT NO. 1: IN SITU CONCRETE/LARGE PRECAST CONCRETE
B32: Vibrated in-situ concrete C40 as described in:
A33: A | B33: Suspended slab 250mm thick | C33: =TAKEOFF!$H$658 -> 347.05 | D33: m3 | E33: =RATES!$D$22 -> 2310 | F33: =C33*E33 -> 801685.5 | G33: 737.6*0.25+650.6*0.25
A35: B | B35: Beams (downstands below slab) | C35: =TAKEOFF!$H$663 -> 18.2385 | D35: m3 | E35: =RATES!$D$23 -> 2310 | F35: =C35*E35 -> 42130.935 | G35: 81.1*0.3*0.35+43.5*0.2*0.35+63.6*0.3*0.35
A37: C | B37: Columns | C37: =TAKEOFF!$H$674 -> 32.569688 | D37: m3 | E37: =RATES!$D$21 -> 2310 | F37: =C37*E37 -> 75235.978 | G37: 5*0.75*0.5*2.45+1*0.75*0.5*2.45+2*0.75*0.5*2.45+1*0.75*0.5*2.45+3*1.2*0.3*2.45+6*1.2*0.3*2.45+1*1.2*0.3*2.45+15*1.2*0.3*2.45+1*(2.85*0.25+0.825*0.25)*2.45
A39: D | B39: Concrete wall - shear walls to main & emergency stair cores, 250mm thick | C39: =TAKEOFF!$H$678 -> 29.16725 | D39: m3 | E39: =RATES!$D$20 -> 2310 | F39: =C39*E39 -> 67376.348 | G39: 22.05*2.45*0.25+25.57*2.45*0.25
A41: E | B41: Concrete wall - lift walls, 250mm thick | C41: =TAKEOFF!$H$681 -> 13.367813 | D41: m3 | E41: =RATES!$D$20 -> 2310 | F41: =C41*E41 -> 30879.647 | G41: 21.825*2.45*0.25
A43: F | B43: Stairs | C43: =TAKEOFF!$H$687 -> 10.103455 | D43: m3 | E43: =RATES!$D$24 -> 2310 | F43: =C43*E43 -> 23338.98 | G43: (2.966*2.7/3.3+2.625)+(2.966*2.7/3.3+2.625)
A45: G | B45: Lintels 150 x 225mm over door and window openings | C45: =TAKEOFF!$H$690 -> 0.131625 | D45: m3 | E45: =RATES!$D$25 -> 1925 | F45: =C45*E45 -> 253.37813 | G45: (3*(1+0.3))*0.15*0.225
B47: E20 FORMWORK - Formwork as described to:
A48: H | B48: Soffits of suspended slab | C48: =TAKEOFF!$H$695 -> 1388.2 | D48: m2 | E48: =RATES!$D$38 -> 165 | F48: =C48*E48 -> 229053 | G48: 737.6+650.6
A50: J | B50: Edges of suspended slab 250mm high | C50: =TAKEOFF!$H$699 -> 410.8 | D50: m | E50: =RATES!$D$40 -> 65 | F50: =C50*E50 -> 26702 | G50: 185.9+224.9
A52: K | B52: Sides and soffits of beams | C52: =TAKEOFF!$H$704 -> 183.85 | D52: m2 | E52: =RATES!$D$39 -> 165 | F52: =C52*E52 -> 30335.25 | G52: 81.1*(2*0.35+0.3)+43.5*(2*0.35+0.2)+63.6*(2*0.35+0.3)
A54: L | B54: Columns | C54: =TAKEOFF!$H$715 -> 258.1075 | D54: m2 | E54: =RATES!$D$37 -> 165 | F54: =C54*E54 -> 42587.738 | G54: 5*2*(0.75+0.5)*2.45+1*2*(0.75+0.5)*2.45+2*2*(0.75+0.5)*2.45+1*2*(0.75+0.5)*2.45+3*2*(1.2+0.3)*2.45+6*2*(1.2+0.3)*2.45+1*2*(1.2+0.3)*2.45+15*2*(1.2+0.3)*2.45+1*2*(2.85+1.075)*2.45
A56: M | B56: Concrete wall (both faces) | C56: =TAKEOFF!$H$720 -> 340.2805 | D56: m2 | E56: =RATES!$D$36 -> 165 | F56: =C56*E56 -> 56146.283 | G56: 2*22.05*2.45+2*21.825*2.45+2*25.57*2.45
A58: N | B58: Soffits of stair flights, landings and risers | C58: =TAKEOFF!$H$728 -> 66.5328 | D58: m2 | E58: =RATES!$D$42 -> 165 | F58: =C58*E58 -> 10977.912 | G58: (2*3.424*1.8+15.0+22*0.15*1.8)+(2*3.424*1.8+15.0+22*0.15*1.8)
A60: P | B60: Side and soffits of lintel / coping | C60: =TAKEOFF!$H$731 -> 2.34 | D60: m2 | E60: =RATES!$D$43 -> 165 | F60: =C60*E60 -> 386.1 | G60: (3*(1+0.3))*(2*0.225+0.15)
B64: E30 REINFORCEMENT - High tensile yield round bar reinforcement (standard) to BS 4449:
A65: Q | B65: 10mm diameter in columns | C65: =TAKEOFF!$H$736 -> 4.373 | D65: t | E65: =RATES!$D$29 -> 14300 | F65: =C65*E65 -> 62533.9 | G65: 2.717+1.656
A67: R | B67: 20mm diameter in columns | C67: =TAKEOFF!$H$740 -> 0.616 | D67: t | E67: =RATES!$D$32 -> 14300 | F67: =C67*E67 -> 8808.8 | G67: 0.462+0.154
A69: S | B69: 25mm diameter in columns | C69: =TAKEOFF!$H$744 -> 8.696 | D69: t | E69: =RATES!$D$33 -> 14300 | F69: =C69*E69 -> 124352.8 | G69: 4.634+4.062
A71: T | B71: 10mm diameter in beams (links) | C71: =TAKEOFF!$H$748 -> 1.621 | D71: t | E71: =RATES!$D$29 -> 14300 | F71: =C71*E71 -> 23180.3 | G71: 0.977+0.644
A73: U | B73: 16mm diameter in beams | C73: =TAKEOFF!$H$752 -> 1.223 | D73: t | E73: =RATES!$D$31 -> 14300 | F73: =C73*E73 -> 17488.9 | G73: 0.763+0.460
A75: V | B75: 20mm diameter in beams | C75: =TAKEOFF!$H$756 -> 1.599 | D75: t | E75: =RATES!$D$32 -> 14300 | F75: =C75*E75 -> 22865.7 | G75: 0.797+0.802
A77: W | B77: 25mm diameter in beams | C77: =TAKEOFF!$H$760 -> 4.597 | D77: t | E77: =RATES!$D$33 -> 14300 | F77: =C77*E77 -> 65737.1 | G77: 2.973+1.624
A79: X | B79: 10mm diameter in shear & lift walls (links) | C79: =TAKEOFF!$H$765 -> 1.7 | D79: t | E79: =RATES!$D$29 -> 14300 | F79: =C79*E79 -> 24310 | G79: 0.520+0.520+0.660
A81: Y | B81: 12mm diameter in shear, lift & ramp walls | C81: =TAKEOFF!$H$770 -> 2.226 | D81: t | E81: =RATES!$D$30 -> 14300 | F81: =C81*E81 -> 31831.8 | G81: 0.699+0.692+0.835
A83: Z | B83: 25mm diameter in shear & lift walls | C83: =TAKEOFF!$H$775 -> 14.417 | D83: t | E83: =RATES!$D$33 -> 14300 | F83: =C83*E83 -> 206163.1 | G83: 4.539+4.682+5.196
A85: A | B85: 12mm diameter in stairs | C85: =TAKEOFF!$H$779 -> 0.88 | D85: t | E85: =RATES!$D$30 -> 14300 | F85: =C85*E85 -> 12584 | G85: 0.440+0.440
A87: B | B87: 16mm diameter in stairs | C87: =TAKEOFF!$H$783 -> 1.434 | D87: t | E87: =RATES!$D$31 -> 14300 | F87: =C87*E87 -> 20506.2 | G87: 0.740+0.694
A89: C | B89: 12mm diameter for suspended slab | C89: =TAKEOFF!$H$787 -> 51.723 | D89: t | E89: =RATES!$D$30 -> 14300 | F89: =C89*E89 -> 739638.9 | G89: 27.947+23.776
A91: D | B91: 16mm diameter for suspended slab | C91: =TAKEOFF!$H$791 -> 6.27 | D91: t | E91: =RATES!$D$31 -> 14300 | F91: =C91*E91 -> 89661 | G91: 2.528+3.742
B93: =B30 -> ELEMENT NO. 1: IN SITU CONCRETE/LARGE PRECAST CONCRETE | F93: =SUM(F32:F92) -> 2886751.5
B94: Carried to Bill Summary
B97: ELEMENT NO. 2: MASONRY
B99: F10 BRICK/BLOCK WALL - Solid sandcrete blockwork in cement and sand (1:4) mortar as described in:
A100: A | B100: 150mm thick wall | C100: =TAKEOFF!$H$797 -> 242.93895 | D100: m2 | E100: =RATES!$D$46 -> 215 | F100: =C100*E100 -> 52231.874 | G100: 98.4*2.45+(3*1*(3.05-2.2))*0.729
A102: B | B102: 200mm thick wall | C102: =TAKEOFF!$H$801 -> 90.36105 | D102: m2 | E102: =RATES!$D$47 -> 265 | F102: =C102*E102 -> 23945.678 | G102: 36.6*2.45+(3*1*(3.05-2.2))*0.271
B104: =B97 -> ELEMENT NO. 2: MASONRY | F104: =SUM(F99:F103) -> 76177.553
B105: Carried to Bill Summary
B108: ELEMENT NO. 4: WINDOWS/DOORS
B110: L20 DOORS - Supply and fix the following door assemblies complete with frames, ironmongery sets to steel doors and all accessories:
A111: A | B111: 1000mm x 2200mm 1-hour fire-rated galvanised steel single-leaf security door assembly - emergency stairs (ED1) | C111: =TAKEOFF!$H$806 -> 3 | D111: nr | E111: =RATES!$D$82 -> 7200 | F111: =C111*E111 -> 21600 | G111: 3
B113: =B108 -> ELEMENT NO. 4: WINDOWS/DOORS | F113: =SUM(F110:F112) -> 21600
B114: Carried to Bill Summary
B116: ELEMENT NO. 5: FLOOR FINISHES
B118: M10/M40 FLOOR FINISHES
A119: A | B119: 25mm cement and sand (1:3) screeded finish laid level on concrete and finished smooth with steel trowel | C119: =TAKEOFF!$H$811 -> 54.8 | D119: m2 | E119: =RATES!$D$50 -> 68 | F119: =C119*E119 -> 3726.4 | G119: 54.8
A121: B | B121: 12mm cement and sand (1:4) screeded bed laid level on concrete floor to receive floor tiles | C121: =TAKEOFF!$H$822 -> 118.28 | D121: m2 | E121: =RATES!$D$51 -> 48 | F121: =C121*E121 -> 5677.44 | G121: 54.8+(2*1.8*3.0+22*0.15*1.8+2.2*3.75+1.8*3.75)+(2*1.8*3.0+22*0.15*1.8+2.2*3.75+1.8*3.75)
A123: C | B123: 500x500mm matte R11 porcelain tiles to staircases (treads, risers and landings) | C123: =TAKEOFF!$H$832 -> 63.48 | D123: m2 | E123: =RATES!$D$54 -> 270 | F123: =C123*E123 -> 17139.6 | G123: (2*1.8*3.0+22*0.15*1.8+2.2*3.75+1.8*3.75)+(2*1.8*3.0+22*0.15*1.8+2.2*3.75+1.8*3.75)
A125: D | B125: 600x1200mm semi-polished porcelain floor tiles to stair/lift lobbies & reception | C125: =TAKEOFF!$H$835 -> 32.7 | D125: m2 | E125: =RATES!$D$56 -> 330 | F125: =C125*E125 -> 10791 | G125: 32.7
A127: E | B127: 600x600mm non-slip R11 porcelain tiles to corridors, terraces, verandah & service areas | C127: =TAKEOFF!$H$838 -> 22.2 | D127: m2 | E127: =RATES!$D$57 -> 250 | F127: =C127*E127 -> 5550 | G127: 22.2
A129: F | B129: Seamless polyurethane (PU) resin screed / PU coating to parking decks & ramps | C129: =TAKEOFF!$H$841 -> 637.3 | D129: m2 | E129: =RATES!$D$59 -> 290 | F129: =C129*E129 -> 184817 | G129: 637.3
B131: =B116 -> ELEMENT NO. 5: FLOOR FINISHES | F131: =SUM(F118:F130) -> 227701.44
B132: Carried to Bill Summary
B134: ELEMENT NO. 6: WALL FINISHES
B136: M20 PLASTERED/RENDERED COATINGS - 12.5mm cement and sand (1:3) rendering as described on blockwork or concrete to:
A137: A | B137: Interior walls | C137: =TAKEOFF!$H$852 -> 404.525 | D137: m2 | E137: =RATES!$D$48 -> 78 | F137: =C137*E137 -> 31552.95 | G137: (2*(98.4+36.6)+2*25.8-16.8-134.3)*2.45-0-2*(3*1*2.2)-(0)
A139: B | B139: External walls | C139: =TAKEOFF!$H$856 -> 362.61 | D139: m2 | E139: =RATES!$D$49 -> 88 | F139: =C139*E139 -> 31909.68 | G139: 134.3*2.7-(0)
B141: =B134 -> ELEMENT NO. 6: WALL FINISHES | F141: =SUM(F136:F140) -> 63462.63
B142: Carried to Bill Summary
B145: ELEMENT NO. 7: PAINTING AND DECORATING
B147: M60 PAINTING - Prepare and apply two undercoats and finishing coat of emulsion paint on:
A148: A | B148: Interior walls | C148: =TAKEOFF!$H$867 -> 404.525 | D148: m2 | E148: =RATES!$D$61 -> 45 | F148: =C148*E148 -> 18203.625 | G148: (2*(98.4+36.6)+2*25.8-16.8-134.3)*2.45-0-2*(3*1*2.2)-(0)
A150: B | B150: Exterior walls | C150: =TAKEOFF!$H$871 -> 362.61 | D150: m2 | E150: =RATES!$D$62 -> 62 | F150: =C150*E150 -> 22481.82 | G150: 134.3*2.7-(0)
A152: C | B152: Columns and walls; girth exceeding 300mm (exposed faces, ground & parking levels) | C152: =TAKEOFF!$H$882 -> 258.1075 | D152: m2 | E152: =RATES!$D$61 -> 45 | F152: =C152*E152 -> 11614.838 | G152: 5*2*(0.75+0.5)*2.45+1*2*(0.75+0.5)*2.45+2*2*(0.75+0.5)*2.45+1*2*(0.75+0.5)*2.45+3*2*(1.2+0.3)*2.45+6*2*(1.2+0.3)*2.45+1*2*(1.2+0.3)*2.45+15*2*(1.2+0.3)*2.45+1*2*(2.85+1.075)*2.45
A154: D | B154: Soffit of plaster board ceilings | C154: =TAKEOFF!$H$885 -> 32.7 | D154: m2 | E154: =RATES!$D$63 -> 48 | F154: =C154*E154 -> 1569.6 | G154: 32.7
B156: =B145 -> ELEMENT NO. 7: PAINTING AND DECORATING | F156: =SUM(F147:F155) -> 53869.883
B157: Carried to Bill Summary
B160: Doors and windows: schedules ARCH-501/502 give building totals only (no tags on plans); quantities are allocated to floors pro-rata to measured habitable / washroom areas. Building totals equal the schedules.

Sheet 2ND FLR
A1: ='PRELIMS & GEN. ITEMS'!A1 -> PROJECT: BLOCK N REDEVELOPMENT
A2: ='PRELIMS & GEN. ITEMS'!A2 -> LOCATION: KANESHIE
A3: ='PRELIMS & GEN. ITEMS'!A3 -> CLIENT: STATE HOUSING LIMITED
A4: ='PRELIMS & GEN. ITEMS'!A4 -> DATE:9/30/2026
A5: ITEM | B5: DESCRIPTION | C5: QTY | D5: UNIT | E5: RATE | F5: AMOUNT - GHC | G5: Measurement basis / calculation
B7: MAIN BUILDING
B9: SECOND FLOOR - LEVEL 3A PARKING (INCL. MEZZANINE LEVEL 3B)
B11: BILL SUMMARY
A13: A | B13: ELEMENT NO. 1: IN SITU CONCRETE/LARGE PRECAST CONCRETE | F13: =F91 -> 3157591.3
A15: B | B15: ELEMENT NO. 2: MASONRY | F15: =F102 -> 175769.91
A17: C | B17: ELEMENT NO. 4: WINDOWS/DOORS | F17: =F111 -> 43200
A19: D | B19: ELEMENT NO. 5: FLOOR FINISHES | F19: =F130 -> 370064.94
A21: E | B21: ELEMENT NO. 6: WALL FINISHES | F21: =F141 -> 158847.63
A23: F | B23: ELEMENT NO. 7: PAINTING AND DECORATING | F23: =F156 -> 117441.9
B25: =B9 -> SECOND FLOOR - LEVEL 3A PARKING (INCL. MEZZANINE LEVEL 3B) | E25: GHC | F25: =SUM(F13:F24) -> 4022915.7
B26: To Bill General Summary
B28: BILL NR. 5 - SECOND FLOOR
B30: ELEMENT NO. 1: IN SITU CONCRETE/LARGE PRECAST CONCRETE
B32: Vibrated in-situ concrete C40 as described in:
A33: A | B33: Suspended slab 250mm thick | C33: =TAKEOFF!$H$894 -> 323.1 | D33: m3 | E33: =RATES!$D$22 -> 2310 | F33: =C33*E33 -> 746361 | G33: 737.5*0.25+554.9*0.25
A35: B | B35: Beams (downstands below slab) | C35: =TAKEOFF!$H$899 -> 18.151 | D35: m3 | E35: =RATES!$D$23 -> 2310 | F35: =C35*E35 -> 41928.81 | G35: 79.9*0.3*0.35+43*0.2*0.35+64.3*0.3*0.35
A37: C | B37: Columns | C37: =TAKEOFF!$H$910 -> 44.4525 | D37: m3 | E37: =RATES!$D$21 -> 2310 | F37: =C37*E37 -> 102685.27 | G37: 5*0.75*0.5*3.8+1*0.75*0.5*3.8+2*0.75*0.5*3.8+1*0.75*0.5*2.75+3*1.2*0.3*3.8+6*1.2*0.3*3.8+1*1.2*0.3*3.8+15*1.2*0.3*2.75+1*(2.85*0.25+0.825*0.25)*3.8
A39: D | B39: Concrete wall - shear walls to main & emergency stair cores, 250mm thick | C39: =TAKEOFF!$H$914 -> 38.526875 | D39: m3 | E39: =RATES!$D$20 -> 2310 | F39: =C39*E39 -> 88997.081 | G39: 22.05*3.8*0.25+25.57*2.75*0.25
A41: E | B41: Concrete wall - lift walls, 250mm thick | C41: =TAKEOFF!$H$917 -> 20.73375 | D41: m3 | E41: =RATES!$D$20 -> 2310 | F41: =C41*E41 -> 47894.962 | G41: 21.825*3.8*0.25
A43: F | B43: Stairs | C43: =TAKEOFF!$H$923 -> 11.586455 | D43: m3 | E43: =RATES!$D$24 -> 2310 | F43: =C43*E43 -> 26764.71 | G43: (2.966*4.05/3.3+2.625)+(2.966*3/3.3+2.625)
A45: G | B45: Lintels 150 x 225mm over door and window openings | C45: =TAKEOFF!$H$927 -> 0.26325 | D45: m3 | E45: =RATES!$D$25 -> 1925 | F45: =C45*E45 -> 506.75625 | G45: (3*(1+0.3))*0.15*0.225+(3*(1+0.3))*0.15*0.225
B47: E20 FORMWORK - Formwork as described to:
A48: H | B48: Soffits of suspended slab | C48: =TAKEOFF!$H$932 -> 1292.4 | D48: m2 | E48: =RATES!$D$38 -> 165 | F48: =C48*E48 -> 213246 | G48: 737.5+554.9
A50: J | B50: Edges of suspended slab 250mm high | C50: =TAKEOFF!$H$936 -> 402.9 | D50: m | E50: =RATES!$D$40 -> 65 | F50: =C50*E50 -> 26188.5 | G50: 186.5+216.4
A52: K | B52: Sides and soffits of beams | C52: =TAKEOFF!$H$941 -> 182.9 | D52: m2 | E52: =RATES!$D$39 -> 165 | F52: =C52*E52 -> 30178.5 | G52: 79.9*(2*0.35+0.3)+43*(2*0.35+0.2)+64.3*(2*0.35+0.3)
A54: L | B54: Columns | C54: =TAKEOFF!$H$952 -> 350.455 | D54: m2 | E54: =RATES!$D$37 -> 165 | F54: =C54*E54 -> 57825.075 | G54: 5*2*(0.75+0.5)*3.8+1*2*(0.75+0.5)*3.8+2*2*(0.75+0.5)*3.8+1*2*(0.75+0.5)*2.75+3*2*(1.2+0.3)*3.8+6*2*(1.2+0.3)*3.8+1*2*(1.2+0.3)*3.8+15*2*(1.2+0.3)*2.75+1*2*(2.85+1.075)*3.8
A56: M | B56: Concrete wall (both faces) | C56: =TAKEOFF!$H$957 -> 474.085 | D56: m2 | E56: =RATES!$D$36 -> 165 | F56: =C56*E56 -> 78224.025 | G56: 2*22.05*3.8+2*21.825*3.8+2*25.57*2.75
A58: N | B58: Soffits of stair flights, landings and risers | C58: =TAKEOFF!$H$965 -> 66.5328 | D58: m2 | E58: =RATES!$D$42 -> 165 | F58: =C58*E58 -> 10977.912 | G58: (2*3.424*1.8+15.0+22*0.15*1.8)+(2*3.424*1.8+15.0+22*0.15*1.8)
A60: P | B60: Side and soffits of lintel / coping | C60: =TAKEOFF!$H$969 -> 4.68 | D60: m2 | E60: =RATES!$D$43 -> 165 | F60: =C60*E60 -> 772.2 | G60: (3*(1+0.3))*(2*0.225+0.15)+(3*(1+0.3))*(2*0.225+0.15)
B62: E30 REINFORCEMENT - High tensile yield round bar reinforcement (standard) to BS 4449:
A63: Q | B63: 10mm diameter in columns | C63: =TAKEOFF!$H$974 -> 4.895 | D63: t | E63: =RATES!$D$29 -> 14300 | F63: =C63*E63 -> 69998.5 | G63: 3.239+1.656
A65: R | B65: 20mm diameter in columns | C65: =TAKEOFF!$H$978 -> 3.788 | D65: t | E65: =RATES!$D$32 -> 14300 | F65: =C65*E65 -> 54168.4 | G65: 0.622+3.166
A67: S | B67: 25mm diameter in columns | C67: =TAKEOFF!$H$981 -> 6.238 | D67: t | E67: =RATES!$D$33 -> 14300 | F67: =C67*E67 -> 89203.4 | G67: 6.238
A69: T | B69: 10mm diameter in beams (links) | C69: =TAKEOFF!$H$985 -> 1.481 | D69: t | E69: =RATES!$D$29 -> 14300 | F69: =C69*E69 -> 21178.3 | G69: 0.902+0.579
A71: U | B71: 16mm diameter in beams | C71: =TAKEOFF!$H$989 -> 1.146 | D71: t | E71: =RATES!$D$31 -> 14300 | F71: =C71*E71 -> 16387.8 | G71: 0.740+0.406
A73: V | B73: 20mm diameter in beams | C73: =TAKEOFF!$H$993 -> 1.968 | D73: t | E73: =RATES!$D$32 -> 14300 | F73: =C73*E73 -> 28142.4 | G73: 0.797+1.171
A75: W | B75: 25mm diameter in beams | C75: =TAKEOFF!$H$997 -> 3.312 | D75: t | E75: =RATES!$D$33 -> 14300 | F75: =C75*E75 -> 47361.6 | G75: 2.427+0.885
A77: X | B77: 10mm diameter in shear & lift walls (links) | C77: =TAKEOFF!$H$1002 -> 2.293 | D77: t | E77: =RATES!$D$29 -> 14300 | F77: =C77*E77 -> 32789.9 | G77: 0.780+0.780+0.733
A79: Y | B79: 12mm diameter in shear, lift & ramp walls | C79: =TAKEOFF!$H$1007 -> 3.113 | D79: t | E79: =RATES!$D$30 -> 14300 | F79: =C79*E79 -> 44515.9 | G79: 1.092+1.082+0.939
A81: Z | B81: 25mm diameter in shear & lift walls | C81: =TAKEOFF!$H$1012 -> 18.203 | D81: t | E81: =RATES!$D$33 -> 14300 | F81: =C81*E81 -> 260302.9 | G81: 6.196+6.390+5.617
A83: A | B83: 12mm diameter in stairs | C83: =TAKEOFF!$H$1016 -> 0.88 | D83: t | E83: =RATES!$D$30 -> 14300 | F83: =C83*E83 -> 12584 | G83: 0.440+0.440
A85: B | B85: 16mm diameter in stairs | C85: =TAKEOFF!$H$1020 -> 1.434 | D85: t | E85: =RATES!$D$31 -> 14300 | F85: =C85*E85 -> 20506.2 | G85: 0.740+0.694
A87: C | B87: 12mm diameter for suspended slab | C87: =TAKEOFF!$H$1024 -> 69.056 | D87: t | E87: =RATES!$D$30 -> 14300 | F87: =C87*E87 -> 987500.8 | G87: 35.127+33.929
A89: D | B89: 16mm diameter for suspended slab | C89: =TAKEOFF!$H$1027 -> 0.028 | D89: t | E89: =RATES!$D$31 -> 14300 | F89: =C89*E89 -> 400.4 | G89: 0.028
B91: =B30 -> ELEMENT NO. 1: IN SITU CONCRETE/LARGE PRECAST CONCRETE | F91: =SUM(F32:F90) -> 3157591.3
B92: Carried to Bill Summary
B95: ELEMENT NO. 2: MASONRY
B97: F10 BRICK/BLOCK WALL - Solid sandcrete blockwork in cement and sand (1:4) mortar as described in:
A98: A | B98: 150mm thick wall | C98: =TAKEOFF!$H$1035 -> 670.72735 | D98: m2 | E98: =RATES!$D$46 -> 215 | F98: =C98*E98 -> 144206.38 | G98: 144.5*2.45+(3*1*(3.05-2.2))*0.896+127.5*2.45+(3*1*(3.05-2.2))*0.801
A100: B | B100: 200mm thick wall | C100: =TAKEOFF!$H$1041 -> 119.10765 | D100: m2 | E100: =RATES!$D$47 -> 265 | F100: =C100*E100 -> 31563.527 | G100: 16.7*2.45+(3*1*(3.05-2.2))*0.104+31.6*2.45+(3*1*(3.05-2.2))*0.199
B102: =B95 -> ELEMENT NO. 2: MASONRY | F102: =SUM(F97:F101) -> 175769.91
B103: Carried to Bill Summary
B106: ELEMENT NO. 4: WINDOWS/DOORS
B108: L20 DOORS - Supply and fix the following door assemblies complete with frames, ironmongery sets to steel doors and all accessories:
A109: A | B109: 1000mm x 2200mm 1-hour fire-rated galvanised steel single-leaf security door assembly - emergency stairs (ED1) | C109: =TAKEOFF!$H$1047 -> 6 | D109: nr | E109: =RATES!$D$82 -> 7200 | F109: =C109*E109 -> 43200 | G109: 3+3
B111: =B106 -> ELEMENT NO. 4: WINDOWS/DOORS | F111: =SUM(F108:F110) -> 43200
B112: Carried to Bill Summary
B115: ELEMENT NO. 5: FLOOR FINISHES
B117: M10/M40 FLOOR FINISHES
A118: A | B118: 25mm cement and sand (1:3) screeded finish laid level on concrete and finished smooth with steel trowel | C118: =TAKEOFF!$H$1053 -> 23.3 | D118: m2 | E118: =RATES!$D$50 -> 68 | F118: =C118*E118 -> 1584.4 | G118: 3.3+20.0
A120: B | B120: 12mm cement and sand (1:4) screeded bed laid level on concrete floor to receive floor tiles | C120: =TAKEOFF!$H$1065 -> 86.78 | D120: m2 | E120: =RATES!$D$51 -> 48 | F120: =C120*E120 -> 4165.44 | G120: 3.3+20.0+(2*1.8*3.0+22*0.15*1.8+2.2*3.75+1.8*3.75)+(2*1.8*3.0+22*0.15*1.8+2.2*3.75+1.8*3.75)
A122: C | B122: 500x500mm matte R11 porcelain tiles to staircases (treads, risers and landings) | C122: =TAKEOFF!$H$1075 -> 63.48 | D122: m2 | E122: =RATES!$D$54 -> 270 | F122: =C122*E122 -> 17139.6 | G122: (2*1.8*3.0+22*0.15*1.8+2.2*3.75+1.8*3.75)+(2*1.8*3.0+22*0.15*1.8+2.2*3.75+1.8*3.75)
A124: D | B124: 600x600mm semi-polished porcelain floor tiles to habitable rooms, shops & offices | C124: =TAKEOFF!$H$1078 -> 3.3 | D124: m2 | E124: =RATES!$D$55 -> 265 | F124: =C124*E124 -> 874.5 | G124: 3.3
A126: E | B126: 600x600mm non-slip R11 porcelain tiles to corridors, terraces, verandah & service areas | C126: =TAKEOFF!$H$1081 -> 20 | D126: m2 | E126: =RATES!$D$57 -> 250 | F126: =C126*E126 -> 5000 | G126: 20.0
A128: F | B128: Seamless polyurethane (PU) resin screed / PU coating to parking decks & ramps | C128: =TAKEOFF!$H$1085 -> 1176.9 | D128: m2 | E128: =RATES!$D$59 -> 290 | F128: =C128*E128 -> 341301 | G128: 685.4+491.5
B130: =B115 -> ELEMENT NO. 5: FLOOR FINISHES | F130: =SUM(F117:F129) -> 370064.94
B131: Carried to Bill Summary
B134: ELEMENT NO. 6: WALL FINISHES
B136: M20 PLASTERED/RENDERED COATINGS - 12.5mm cement and sand (1:3) rendering as described on blockwork or concrete to:
A137: A | B137: Interior walls | C137: =TAKEOFF!$H$1103 -> 1044.985 | D137: m2 | E137: =RATES!$D$48 -> 78 | F137: =C137*E137 -> 81508.83 | G137: (2*(144.5+16.7)+2*35.1-16.8-134.0)*2.45-0-2*(3*1*2.2)-(0)+(2*(127.5+31.6)+2*42.8-16.8-191.5)*2.45-0-2*(3*1*2.2)-(0)
A139: B | B139: External walls | C139: =TAKEOFF!$H$1109 -> 878.85 | D139: m2 | E139: =RATES!$D$49 -> 88 | F139: =C139*E139 -> 77338.8 | G139: 134.0*2.7-(0)+191.5*2.7-(0)
B141: =B134 -> ELEMENT NO. 6: WALL FINISHES | F141: =SUM(F136:F140) -> 158847.63
B142: Carried to Bill Summary
B145: ELEMENT NO. 7: PAINTING AND DECORATING
B147: M60 PAINTING - Prepare and apply two undercoats and finishing coat of emulsion paint on:
A148: A | B148: Interior walls | C148: =TAKEOFF!$H$1127 -> 1044.985 | D148: m2 | E148: =RATES!$D$61 -> 45 | F148: =C148*E148 -> 47024.325 | G148: (2*(144.5+16.7)+2*35.1-16.8-134.0)*2.45-0-2*(3*1*2.2)-(0)+(2*(127.5+31.6)+2*42.8-16.8-191.5)*2.45-0-2*(3*1*2.2)-(0)
A150: B | B150: Exterior walls | C150: =TAKEOFF!$H$1133 -> 878.85 | D150: m2 | E150: =RATES!$D$62 -> 62 | F150: =C150*E150 -> 54488.7 | G150: 134.0*2.7-(0)+191.5*2.7-(0)
A152: C | B152: Columns and walls; girth exceeding 300mm (exposed faces, ground & parking levels) | C152: =TAKEOFF!$H$1144 -> 350.455 | D152: m2 | E152: =RATES!$D$61 -> 45 | F152: =C152*E152 -> 15770.475 | G152: 5*2*(0.75+0.5)*3.8+1*2*(0.75+0.5)*3.8+2*2*(0.75+0.5)*3.8+1*2*(0.75+0.5)*2.75+3*2*(1.2+0.3)*3.8+6*2*(1.2+0.3)*3.8+1*2*(1.2+0.3)*3.8+15*2*(1.2+0.3)*2.75+1*2*(2.85+1.075)*3.8
A154: D | B154: Soffit of plaster board ceilings | C154: =TAKEOFF!$H$1147 -> 3.3 | D154: m2 | E154: =RATES!$D$63 -> 48 | F154: =C154*E154 -> 158.4 | G154: 3.3
B156: =B145 -> ELEMENT NO. 7: PAINTING AND DECORATING | F156: =SUM(F147:F155) -> 117441.9
B157: Carried to Bill Summary
B160: Doors and windows: schedules ARCH-501/502 give building totals only (no tags on plans); quantities are allocated to floors pro-rata to measured habitable / washroom areas. Building totals equal the schedules.

Sheet 3RD FLR
A1: ='PRELIMS & GEN. ITEMS'!A1 -> PROJECT: BLOCK N REDEVELOPMENT
A2: ='PRELIMS & GEN. ITEMS'!A2 -> LOCATION: KANESHIE
A3: ='PRELIMS & GEN. ITEMS'!A3 -> CLIENT: STATE HOUSING LIMITED
A4: ='PRELIMS & GEN. ITEMS'!A4 -> DATE:9/30/2026
A5: ITEM | B5: DESCRIPTION | C5: QTY | D5: UNIT | E5: RATE | F5: AMOUNT - GHC | G5: Measurement basis / calculation
B7: MAIN BUILDING
B9: THIRD FLOOR
B11: BILL SUMMARY
A13: A | B13: ELEMENT NO. 1: IN SITU CONCRETE/LARGE PRECAST CONCRETE | F13: =F90 -> 2839785
A15: B | B15: ELEMENT NO. 2: MASONRY | F15: =F101 -> 420081.85
A17: C | B17: ELEMENT NO. 4: WINDOWS/DOORS | F17: =F190 -> 691235.75
A19: D | B19: ELEMENT NO. 5: FLOOR FINISHES | F19: =F210 -> 385700.14
A21: E | B21: ELEMENT NO. 6: WALL FINISHES | F21: =F226 -> 315809.63
A23: F | B23: ELEMENT NO. 7: PAINTING AND DECORATING | F23: =F245 -> 193492.32
B25: =B9 -> THIRD FLOOR | E25: GHC | F25: =SUM(F13:F24) -> 4846104.7
B26: To Bill General Summary
B29: BILL NR. 6 - THIRD FLOOR
B31: ELEMENT NO. 1: IN SITU CONCRETE/LARGE PRECAST CONCRETE
B33: Vibrated in-situ concrete C40 as described in:
A34: A | B34: Suspended slab 250mm thick | C34: =TAKEOFF!$H$1155 -> 318.475 | D34: m3 | E34: =RATES!$D$22 -> 2310 | F34: =C34*E34 -> 735677.25 | G34: 1273.9*0.25
A36: B | B36: Beams (downstands below slab) | C36: =TAKEOFF!$H$1159 -> 12.544 | D36: m3 | E36: =RATES!$D$23 -> 2310 | F36: =C36*E36 -> 28976.64 | G36: 97.4*0.3*0.35+33.1*0.2*0.35
A38: C | B38: Columns | C38: =TAKEOFF!$H$1170 -> 40.545937 | D38: m3 | E38: =RATES!$D$21 -> 2310 | F38: =C38*E38 -> 93661.116 | G38: 5*0.75*0.5*3.05+1*0.75*0.5*3.05+2*0.75*0.5*3.05+1*0.75*0.5*3.05+3*1.2*0.3*3.05+6*1.2*0.3*3.05+1*1.2*0.3*3.05+15*1.2*0.3*3.05+1*(2.85*0.25+0.825*0.25)*3.05
A40: D | B40: Concrete wall - shear walls to main & emergency stair cores, 250mm thick | C40: =TAKEOFF!$H$1174 -> 36.31025 | D40: m3 | E40: =RATES!$D$20 -> 2310 | F40: =C40*E40 -> 83876.677 | G40: 22.05*3.05*0.25+25.57*3.05*0.25
A42: E | B42: Concrete wall - lift walls, 250mm thick | C42: =TAKEOFF!$H$1177 -> 16.641562 | D42: m3 | E42: =RATES!$D$20 -> 2310 | F42: =C42*E42 -> 38442.009 | G42: 21.825*3.05*0.25
A44: F | B44: Stairs | C44: =TAKEOFF!$H$1183 -> 11.182 | D44: m3 | E44: =RATES!$D$24 -> 2310 | F44: =C44*E44 -> 25830.42 | G44: (2.966*3.3/3.3+2.625)+(2.966*3.3/3.3+2.625)
A46: G | B46: Lintels 150 x 225mm over door and window openings | C46: =TAKEOFF!$H$1220 -> 7.90425 | D46: m3 | E46: =RATES!$D$25 -> 1925 | F46: =C46*E46 -> 15215.681 | G46: (10*(1+0.3)+19*(0.9+0.3)+21*(0.75+0.3)+2*(0.7+0.3)+3*(1.2+0.3)+3*(1+0.3)+3*(1+0.3)+2*(0.9+0.3)+1*(1.5+0.3)+3*(0.9+0.3)+5*(0.75+0.3)+1*(0.45+0.3)+3*(0.6+0.3)+1*(3+0.3)+4*(1.6+0.3)+3*(1.3+0.3)+5*(1.8+0.3)+1*(1.2+0.3)+7*(1.8+0.3)+13*(0.9+0.3)+2*(1.8+...
B48: E20 FORMWORK - Formwork as described to:
A49: H | B49: Soffits of suspended slab | C49: =TAKEOFF!$H$1224 -> 1273.9 | D49: m2 | E49: =RATES!$D$38 -> 165 | F49: =C49*E49 -> 210193.5 | G49: 1273.9
A51: J | B51: Edges of suspended slab 250mm high | C51: =TAKEOFF!$H$1227 -> 232.4 | D51: m | E51: =RATES!$D$40 -> 65 | F51: =C51*E51 -> 15106 | G51: 232.4
A53: K | B53: Sides and soffits of beams | C53: =TAKEOFF!$H$1231 -> 127.19 | D53: m2 | E53: =RATES!$D$39 -> 165 | F53: =C53*E53 -> 20986.35 | G53: 97.4*(2*0.35+0.3)+33.1*(2*0.35+0.2)
A55: L | B55: Columns | C55: =TAKEOFF!$H$1242 -> 321.3175 | D55: m2 | E55: =RATES!$D$37 -> 165 | F55: =C55*E55 -> 53017.387 | G55: 5*2*(0.75+0.5)*3.05+1*2*(0.75+0.5)*3.05+2*2*(0.75+0.5)*3.05+1*2*(0.75+0.5)*3.05+3*2*(1.2+0.3)*3.05+6*2*(1.2+0.3)*3.05+1*2*(1.2+0.3)*3.05+15*2*(1.2+0.3)*3.05+1*2*(2.85+1.075)*3.05
A57: M | B57: Concrete wall (both faces) | C57: =TAKEOFF!$H$1247 -> 423.6145 | D57: m2 | E57: =RATES!$D$36 -> 165 | F57: =C57*E57 -> 69896.393 | G57: 2*22.05*3.05+2*21.825*3.05+2*25.57*3.05
A59: N | B59: Soffits of stair flights, landings and risers | C59: =TAKEOFF!$H$1255 -> 66.5328 | D59: m2 | E59: =RATES!$D$42 -> 165 | F59: =C59*E59 -> 10977.912 | G59: (2*3.424*1.8+15.0+22*0.15*1.8)+(2*3.424*1.8+15.0+22*0.15*1.8)
A61: P | B61: Side and soffits of lintel / coping | C61: =TAKEOFF!$H$1292 -> 140.52 | D61: m2 | E61: =RATES!$D$43 -> 165 | F61: =C61*E61 -> 23185.8 | G61: (10*(1+0.3)+19*(0.9+0.3)+21*(0.75+0.3)+2*(0.7+0.3)+3*(1.2+0.3)+3*(1+0.3)+3*(1+0.3)+2*(0.9+0.3)+1*(1.5+0.3)+3*(0.9+0.3)+5*(0.75+0.3)+1*(0.45+0.3)+3*(0.6+0.3)+1*(3+0.3)+4*(1.6+0.3)+3*(1.3+0.3)+5*(1.8+0.3)+1*(1.2+0.3)+7*(1.8+0.3)+13*(0.9+0.3)+2*(1.8+...
B63: E30 REINFORCEMENT - High tensile yield round bar reinforcement (standard) to BS 4449:
A64: Q | B64: 10mm diameter in columns | C64: =TAKEOFF!$H$1296 -> 4.551 | D64: t | E64: =RATES!$D$29 -> 14300 | F64: =C64*E64 -> 65079.3 | G64: 4.551
A66: R | B66: 20mm diameter in columns | C66: =TAKEOFF!$H$1299 -> 7.133 | D66: t | E66: =RATES!$D$32 -> 14300 | F66: =C66*E66 -> 102001.9 | G66: 7.133
A68: S | B68: 10mm diameter in beams (links) | C68: =TAKEOFF!$H$1302 -> 1.164 | D68: t | E68: =RATES!$D$29 -> 14300 | F68: =C68*E68 -> 16645.2 | G68: 1.164
A70: T | B70: 16mm diameter in beams | C70: =TAKEOFF!$H$1305 -> 1.003 | D70: t | E70: =RATES!$D$31 -> 14300 | F70: =C70*E70 -> 14342.9 | G70: 1.003
A72: U | B72: 20mm diameter in beams | C72: =TAKEOFF!$H$1308 -> 2.162 | D72: t | E72: =RATES!$D$32 -> 14300 | F72: =C72*E72 -> 30916.6 | G72: 2.162
A74: V | B74: 25mm diameter in beams | C74: =TAKEOFF!$H$1311 -> 2.016 | D74: t | E74: =RATES!$D$33 -> 14300 | F74: =C74*E74 -> 28828.8 | G74: 2.016
A76: W | B76: 10mm diameter in shear & lift walls (links) | C76: =TAKEOFF!$H$1315 -> 2.078 | D76: t | E76: =RATES!$D$29 -> 14300 | F76: =C76*E76 -> 29715.4 | G76: 1.442+0.636
A78: X | B78: 12mm diameter in shear, lift & ramp walls | C78: =TAKEOFF!$H$1319 -> 2.783 | D78: t | E78: =RATES!$D$30 -> 14300 | F78: =C78*E78 -> 39796.9 | G78: 1.917+0.866
A80: Y | B80: 25mm diameter in shear & lift walls | C80: =TAKEOFF!$H$1323 -> 16.755 | D80: t | E80: =RATES!$D$33 -> 14300 | F80: =C80*E80 -> 239596.5 | G80: 11.314+5.441
A82: Z | B82: 12mm diameter in stairs | C82: =TAKEOFF!$H$1326 -> 0.88 | D82: t | E82: =RATES!$D$30 -> 14300 | F82: =C82*E82 -> 12584 | G82: 0.880
A84: A | B84: 16mm diameter in stairs | C84: =TAKEOFF!$H$1329 -> 1.434 | D84: t | E84: =RATES!$D$31 -> 14300 | F84: =C84*E84 -> 20506.2 | G84: 1.434
A86: B | B86: 12mm diameter for suspended slab | C86: =TAKEOFF!$H$1332 -> 56.828 | D86: t | E86: =RATES!$D$30 -> 14300 | F86: =C86*E86 -> 812640.4 | G86: 56.828
A88: C | B88: 16mm diameter for suspended slab | C88: =TAKEOFF!$H$1335 -> 0.146 | D88: t | E88: =RATES!$D$31 -> 14300 | F88: =C88*E88 -> 2087.8 | G88: 0.146
B90: =B31 -> ELEMENT NO. 1: IN SITU CONCRETE/LARGE PRECAST CONCRETE | F90: =SUM(F33:F89) -> 2839785
B91: Carried to Bill Summary
B94: ELEMENT NO. 2: MASONRY
B96: F10 BRICK/BLOCK WALL - Solid sandcrete blockwork in cement and sand (1:4) mortar as described in:
A97: A | B97: 150mm thick wall | C97: =TAKEOFF!$H$1375 -> 1750.301 | D97: m2 | E97: =RATES!$D$46 -> 215 | F97: =C97*E97 -> 376314.71 | G97: 500.0*3.05+(10*1*(3.05-2.2)+19*0.9*(3.05-2.2)+21*0.75*(3.05-2.2)+2*0.7*(3.05-2.2)+3*1.2*(3.05-2.2)+3*1*(3.05-2.2)+3*1*(3.05-2.2)+2*0.9*(3.05-2.2)+1*1.5*(3.05-2.2)+3*0.9*(3.05-2.2)+5*0.75*(3.05-2.2)+1*0.45*(3.05-2.2)+3*0.6*(3.05-2.2)+1*3*(3.05-2.2)...
A99: B | B99: 200mm thick wall | C99: =TAKEOFF!$H$1413 -> 165.159 | D99: m2 | E99: =RATES!$D$47 -> 265 | F99: =C99*E99 -> 43767.135 | G99: 47.2*3.05+(10*1*(3.05-2.2)+19*0.9*(3.05-2.2)+21*0.75*(3.05-2.2)+2*0.7*(3.05-2.2)+3*1.2*(3.05-2.2)+3*1*(3.05-2.2)+3*1*(3.05-2.2)+2*0.9*(3.05-2.2)+1*1.5*(3.05-2.2)+3*0.9*(3.05-2.2)+5*0.75*(3.05-2.2)+1*0.45*(3.05-2.2)+3*0.6*(3.05-2.2)+1*3*(3.05-2.2)+...
B101: =B94 -> ELEMENT NO. 2: MASONRY | F101: =SUM(F96:F100) -> 420081.85
B102: Carried to Bill Summary
B105: ELEMENT NO. 4: WINDOWS/DOORS
B107: L20 DOORS - Supply and fix the following door assemblies complete with frames, ironmongery sets to steel doors and all accessories:
A108: A | B108: 1000mm x 2200mm 1-hour fire-rated galvanised steel single-leaf security door assembly (D2) | C108: =TAKEOFF!$H$1418 -> 10 | D108: nr | E108: =RATES!$D$75 -> 7800 | F108: =C108*E108 -> 78000 | G108: 10
A110: B | B110: 900mm x 2200mm single leaf timber panel door (D3) | C110: =TAKEOFF!$H$1421 -> 19 | D110: nr | E110: =RATES!$D$76 -> 3400 | F110: =C110*E110 -> 64600 | G110: 19
A112: C | B112: 750mm x 2200mm single leaf timber flush door (D6) | C112: =TAKEOFF!$H$1424 -> 21 | D112: nr | E112: =RATES!$D$79 -> 1900 | F112: =C112*E112 -> 39900 | G112: 21
A114: D | B114: 700mm x 2200mm single-leaf 2-hour fire-rated galvanised steel door (D7) | C114: =TAKEOFF!$H$1427 -> 2 | D114: nr | E114: =RATES!$D$80 -> 6800 | F114: =C114*E114 -> 13600 | G114: 2
A116: E | B116: 1200mm x 2200mm 1-hour fire-rated leaf-and-a-half galvanised steel security door assembly (D8) | C116: =TAKEOFF!$H$1430 -> 3 | D116: nr | E116: =RATES!$D$81 -> 9800 | F116: =C116*E116 -> 29400 | G116: 3
A118: F | B118: 1000mm x 2200mm 1-hour fire-rated galvanised steel single-leaf security door assembly - emergency stairs (ED1) | C118: =TAKEOFF!$H$1433 -> 3 | D118: nr | E118: =RATES!$D$82 -> 7200 | F118: =C118*E118 -> 21600 | G118: 3
A120: G | B120: 1000mm x 2200mm 1-hour fire-rated galvanised steel single-leaf security door with translucent glass panel (ED2) | C120: =TAKEOFF!$H$1436 -> 3 | D120: nr | E120: =RATES!$D$83 -> 8100 | F120: =C120*E120 -> 24300 | G120: 3
A122: H | B122: 900mm x 2200mm 1-hour fire-rated galvanised steel single-leaf security door assembly (D9) | C122: =TAKEOFF!$H$1439 -> 2 | D122: nr | E122: =RATES!$D$84 -> 6900 | F122: =C122*E122 -> 13800 | G122: 2
A124: J | B124: 1500mm x 2200mm timber bi-fold door (FD1) | C124: =TAKEOFF!$H$1442 -> 1 | D124: nr | E124: =RATES!$D$86 -> 4600 | F124: =C124*E124 -> 4600 | G124: 1
A126: K | B126: 900mm x 2200mm screw-fixed galvanised steel service access panel (M1) | C126: =TAKEOFF!$H$1445 -> 3 | D126: nr | E126: =RATES!$D$87 -> 2900 | F126: =C126*E126 -> 8700 | G126: 3
A128: L | B128: 750mm x 2200mm screw-fixed galvanised steel service access panel (M2) | C128: =TAKEOFF!$H$1448 -> 5 | D128: nr | E128: =RATES!$D$88 -> 2600 | F128: =C128*E128 -> 13000 | G128: 5
A130: M | B130: 450mm x 2200mm screw-fixed galvanised steel service access panel (M3) | C130: =TAKEOFF!$H$1451 -> 1 | D130: nr | E130: =RATES!$D$89 -> 1900 | F130: =C130*E130 -> 1900 | G130: 1
A132: N | B132: 600mm x 2200mm screw-fixed galvanised steel service access panel (M5) | C132: =TAKEOFF!$H$1454 -> 3 | D132: nr | E132: =RATES!$D$90 -> 2200 | F132: =C132*E132 -> 6600 | G132: 3
A134: P | B134: 3000mm x 2200mm 3-panel galvanised steel framed tempered glass sliding door (SD1) | C134: =TAKEOFF!$H$1457 -> 1 | D134: nr | E134: =RATES!$D$94 -> 14500 | F134: =C134*E134 -> 14500 | G134: 1
A136: Q | B136: 1600mm x 2200mm 2-panel galvanised steel framed tempered glass sliding door (SD2) | C136: =TAKEOFF!$H$1460 -> 4 | D136: nr | E136: =RATES!$D$95 -> 8800 | F136: =C136*E136 -> 35200 | G136: 4
A138: R | B138: 1300mm x 2200mm 2-panel galvanised steel framed tempered glass sliding door (SD3) | C138: =TAKEOFF!$H$1463 -> 3 | D138: nr | E138: =RATES!$D$96 -> 7600 | F138: =C138*E138 -> 22800 | G138: 3
A140: S | B140: 1800mm x 2200mm 2-panel galvanised steel framed tempered glass sliding door (SD4) | C140: =TAKEOFF!$H$1466 -> 5 | D140: nr | E140: =RATES!$D$97 -> 9300 | F140: =C140*E140 -> 46500 | G140: 5
A142: T | B142: 1200mm x 2200mm 2-panel galvanised steel framed tempered glass sliding door (SD5) | C142: =TAKEOFF!$H$1469 -> 1 | D142: nr | E142: =RATES!$D$98 -> 7200 | F142: =C142*E142 -> 7200 | G142: 1
A144: U | B144: 50mm x 150mm frames (to timber doors) | C144: =TAKEOFF!$H$1474 -> 214.75 | D144: m | E144: =RATES!$D$100 -> 125 | F144: =C144*E144 -> 26843.75 | G144: 19*(2*2.2+0.9)+21*(2*2.2+0.75)+1*(2*2.2+1.5)
A146: V | B146: 50mm x 12mm door stop | C146: =TAKEOFF!$H$1479 -> 214.75 | D146: m | E146: =RATES!$D$101 -> 28 | F146: =C146*E146 -> 6013 | G146: 19*(2*2.2+0.9)+21*(2*2.2+0.75)+1*(2*2.2+1.5)
B148: Ironmongery - Supply and fix the following approved ironmongery to hardwood with accompanying patented screws:
A149: W | B149: Pair 100mm brass butt hinges | C149: =TAKEOFF!$H$1483 -> 60 | D149: pr | E149: =RATES!$D$102 -> 125 | F149: =C149*E149 -> 7500 | G149: 60
A151: X | B151: Ordinary locks | C151: =TAKEOFF!$H$1486 -> 19 | D151: nr | E151: =RATES!$D$103 -> 480 | F151: =C151*E151 -> 9120 | G151: 19
A153: Y | B153: Approved high quality mortice indicator lock | C153: =TAKEOFF!$H$1489 -> 21 | D153: nr | E153: =RATES!$D$104 -> 560 | F153: =C153*E153 -> 11760 | G153: 21
B155: ALUMINIUM GLAZED WINDOWS - Supply and install Italian extruded aluminium glazed windows, ALCOA R50 series, powder coated aluminium profile, glazed with 6mm tinted reflective glass secured onto galvanized steel sub-frames, complete with all accessories as per Architect's detail:
A156: Z | B156: 2 bay alu. framed glass sliding window 1800mm x 1300mm (W2) | C156: =TAKEOFF!$H$1493 -> 7 | D156: nr | E156: =RATES!$D$109 -> 3603.6 | F156: =C156*E156 -> 25225.2 | G156: 7
A158: A | B158: 1 bay alu. framed glass awning window 900mm x 1300mm (W4) | C158: =TAKEOFF!$H$1496 -> 13 | D158: nr | E158: =RATES!$D$111 -> 1801.8 | F158: =C158*E158 -> 23423.4 | G158: 13
A160: B | B160: 2 bay alu. framed glass sliding window 1800mm x 1600mm (W7) | C160: =TAKEOFF!$H$1499 -> 2 | D160: nr | E160: =RATES!$D$114 -> 4435.2 | F160: =C160*E160 -> 8870.4 | G160: 2
A162: C | B162: 1 x 3 bay alu. framed glass awning window 1200mm x 1900mm (W8) | C162: =TAKEOFF!$H$1502 -> 4 | D162: nr | E162: =RATES!$D$115 -> 3511.2 | F162: =C162*E162 -> 14044.8 | G162: 4
A164: D | B164: 2 bay alu. framed glass sliding window 1200mm x 1150mm (W9) | C164: =TAKEOFF!$H$1505 -> 10 | D164: nr | E164: =RATES!$D$116 -> 2125.2 | F164: =C164*E164 -> 21252 | G164: 10
A166: E | B166: 2 bay alu. framed glass sliding window 1200mm x 1200mm (W10) | C166: =TAKEOFF!$H$1508 -> 1 | D166: nr | E166: =RATES!$D$117 -> 2217.6 | F166: =C166*E166 -> 2217.6 | G166: 1
A168: F | B168: 2 bay alu. framed glass sliding window 1500mm x 1300mm (W11) | C168: =TAKEOFF!$H$1511 -> 8 | D168: nr | E168: =RATES!$D$118 -> 3003 | F168: =C168*E168 -> 24024 | G168: 8
A170: G | B170: 2 bay alu. framed glass sliding window 1500mm x 1150mm (W12) | C170: =TAKEOFF!$H$1514 -> 4 | D170: nr | E170: =RATES!$D$119 -> 2656.5 | F170: =C170*E170 -> 10626 | G170: 4
A172: H | B172: 3 bay alu. framed glass awning window 2400mm x 1300mm (W13) | C172: =TAKEOFF!$H$1517 -> 1 | D172: nr | E172: =RATES!$D$120 -> 4804.8 | F172: =C172*E172 -> 4804.8 | G172: 1
A174: J | B174: 3 bay alu. framed glass sliding window 3000mm x 1600mm (W15) | C174: =TAKEOFF!$H$1520 -> 1 | D174: nr | E174: =RATES!$D$122 -> 7392 | F174: =C174*E174 -> 7392 | G174: 1
A176: K | B176: 2 x 3 alu. framed glass awning window 1800mm x 1900mm (W17) | C176: =TAKEOFF!$H$1523 -> 4 | D176: nr | E176: =RATES!$D$124 -> 5266.8 | F176: =C176*E176 -> 21067.2 | G176: 4
A178: L | B178: 1 bay alu. framed glass awning window 750mm x 1300mm (W18) | C178: =TAKEOFF!$H$1526 -> 1 | D178: nr | E178: =RATES!$D$125 -> 1501.5 | F178: =C178*E178 -> 1501.5 | G178: 1
A180: M | B180: 2 x 3 alu. framed glass awning window 1450mm x 1900mm (W20) | C180: =TAKEOFF!$H$1529 -> 1 | D180: nr | E180: =RATES!$D$127 -> 4242.7 | F180: =C180*E180 -> 4242.7 | G180: 1
A182: N | B182: 2 bay alu. framed glass sliding window 900mm x 600mm (HW1) | C182: =TAKEOFF!$H$1532 -> 12 | D182: nr | E182: =RATES!$D$128 -> 831.6 | F182: =C182*E182 -> 9979.2 | G182: 12
A184: P | B184: 2 bay alu. framed glass sliding window 750mm x 600mm (HW2) | C184: =TAKEOFF!$H$1535 -> 5 | D184: nr | E184: =RATES!$D$129 -> 693 | F184: =C184*E184 -> 3465 | G184: 5
A186: Q | B186: 2 bay alu. framed glass sliding window 600mm x 600mm (HW3) | C186: =TAKEOFF!$H$1538 -> 1 | D186: nr | E186: =RATES!$D$130 -> 554.4 | F186: =C186*E186 -> 554.4 | G186: 1
A188: R | B188: 2 bay alu. framed glass sliding window 1200mm x 600mm (HW4) | C188: =TAKEOFF!$H$1541 -> 1 | D188: nr | E188: =RATES!$D$131 -> 1108.8 | F188: =C188*E188 -> 1108.8 | G188: 1
...

Sheet 4TH FLR 
A1: ='PRELIMS & GEN. ITEMS'!A1 -> PROJECT: BLOCK N REDEVELOPMENT
A2: ='PRELIMS & GEN. ITEMS'!A2 -> LOCATION: KANESHIE
A3: ='PRELIMS & GEN. ITEMS'!A3 -> CLIENT: STATE HOUSING LIMITED
A4: ='PRELIMS & GEN. ITEMS'!A4 -> DATE:9/30/2026
A5: ITEM | B5: DESCRIPTION | C5: QTY | D5: UNIT | E5: RATE | F5: AMOUNT - GHC | G5: Measurement basis / calculation
B7: MAIN BUILDING
B9: FOURTH FLOOR
B11: BILL SUMMARY
A13: A | B13: ELEMENT NO. 1: IN SITU CONCRETE/LARGE PRECAST CONCRETE | F13: =F92 -> 2663932.8
A15: B | B15: ELEMENT NO. 2: MASONRY | F15: =F103 -> 385904.19
A17: C | B17: ELEMENT NO. 4: WINDOWS/DOORS | F17: =F193 -> 613374.5
A19: D | B19: ELEMENT NO. 5: FLOOR FINISHES | F19: =F213 -> 344765.54
A21: E | B21: ELEMENT NO. 6: WALL FINISHES | F21: =F229 -> 304843.68
A23: F | B23: ELEMENT NO. 7: PAINTING AND DECORATING | F23: =F249 -> 180310.77
B25: =B9 -> FOURTH FLOOR | E25: GHC | F25: =SUM(F13:F24) -> 4493131.5
B26: To Bill General Summary
B29: BILL NR. 7 - FOURTH FLOOR
B31: ELEMENT NO. 1: IN SITU CONCRETE/LARGE PRECAST CONCRETE
B33: Vibrated in-situ concrete C40 as described in:
A34: A | B34: Suspended slab 250mm thick | C34: =TAKEOFF!$H$1766 -> 283.65 | D34: m3 | E34: =RATES!$D$22 -> 2310 | F34: =C34*E34 -> 655231.5 | G34: 1134.6*0.25
A36: B | B36: Beams (downstands below slab) | C36: =TAKEOFF!$H$1770 -> 19.831 | D36: m3 | E36: =RATES!$D$23 -> 2310 | F36: =C36*E36 -> 45809.61 | G36: 166.8*0.3*0.35+33.1*0.2*0.35
A38: C | B38: Columns | C38: =TAKEOFF!$H$1781 -> 40.545937 | D38: m3 | E38: =RATES!$D$21 -> 2310 | F38: =C38*E38 -> 93661.116 | G38: 5*0.75*0.5*3.05+1*0.75*0.5*3.05+2*0.75*0.5*3.05+1*0.75*0.5*3.05+3*1.2*0.3*3.05+6*1.2*0.3*3.05+1*1.2*0.3*3.05+15*1.2*0.3*3.05+1*(2.85*0.25+0.825*0.25)*3.05
A40: D | B40: Concrete wall - shear walls to main & emergency stair cores, 250mm thick | C40: =TAKEOFF!$H$1785 -> 36.31025 | D40: m3 | E40: =RATES!$D$20 -> 2310 | F40: =C40*E40 -> 83876.677 | G40: 22.05*3.05*0.25+25.57*3.05*0.25
A42: E | B42: Concrete wall - lift walls, 250mm thick | C42: =TAKEOFF!$H$1788 -> 16.641562 | D42: m3 | E42: =RATES!$D$20 -> 2310 | F42: =C42*E42 -> 38442.009 | G42: 21.825*3.05*0.25
A44: F | B44: Stairs | C44: =TAKEOFF!$H$1794 -> 11.182 | D44: m3 | E44: =RATES!$D$24 -> 2310 | F44: =C44*E44 -> 25830.42 | G44: (2.966*3.3/3.3+2.625)+(2.966*3.3/3.3+2.625)
A46: G | B46: Lintels 150 x 225mm over door and window openings | C46: =TAKEOFF!$H$1831 -> 7.1769375 | D46: m3 | E46: =RATES!$D$25 -> 1925 | F46: =C46*E46 -> 13815.605 | G46: (8*(1+0.3)+15*(0.9+0.3)+22*(0.75+0.3)+1*(0.7+0.3)+3*(1.2+0.3)+3*(1+0.3)+3*(1+0.3)+2*(0.9+0.3)+1*(1.5+0.3)+3*(0.9+0.3)+5*(0.75+0.3)+1*(0.45+0.3)+3*(0.6+0.3)+1*(3+0.3)+4*(1.6+0.3)+2*(1.3+0.3)+4*(1.8+0.3)+1*(1.2+0.3)+6*(1.8+0.3)+10*(0.9+0.3)+2*(1.8+0...
B48: E20 FORMWORK - Formwork as described to:
A49: H | B49: Soffits of suspended slab | C49: =TAKEOFF!$H$1835 -> 1134.6 | D49: m2 | E49: =RATES!$D$38 -> 165 | F49: =C49*E49 -> 187209 | G49: 1134.6
A51: J | B51: Edges of suspended slab 250mm high | C51: =TAKEOFF!$H$1838 -> 294.6 | D51: m | E51: =RATES!$D$40 -> 65 | F51: =C51*E51 -> 19149 | G51: 294.6
A53: K | B53: Sides and soffits of beams | C53: =TAKEOFF!$H$1842 -> 196.59 | D53: m2 | E53: =RATES!$D$39 -> 165 | F53: =C53*E53 -> 32437.35 | G53: 166.8*(2*0.35+0.3)+33.1*(2*0.35+0.2)
A55: L | B55: Columns | C55: =TAKEOFF!$H$1853 -> 321.3175 | D55: m2 | E55: =RATES!$D$37 -> 165 | F55: =C55*E55 -> 53017.387 | G55: 5*2*(0.75+0.5)*3.05+1*2*(0.75+0.5)*3.05+2*2*(0.75+0.5)*3.05+1*2*(0.75+0.5)*3.05+3*2*(1.2+0.3)*3.05+6*2*(1.2+0.3)*3.05+1*2*(1.2+0.3)*3.05+15*2*(1.2+0.3)*3.05+1*2*(2.85+1.075)*3.05
A57: M | B57: Concrete wall (both faces) | C57: =TAKEOFF!$H$1858 -> 423.6145 | D57: m2 | E57: =RATES!$D$36 -> 165 | F57: =C57*E57 -> 69896.393 | G57: 2*22.05*3.05+2*21.825*3.05+2*25.57*3.05
A59: N | B59: Soffits of stair flights, landings and risers | C59: =TAKEOFF!$H$1866 -> 66.5328 | D59: m2 | E59: =RATES!$D$42 -> 165 | F59: =C59*E59 -> 10977.912 | G59: (2*3.424*1.8+15.0+22*0.15*1.8)+(2*3.424*1.8+15.0+22*0.15*1.8)
A61: P | B61: Side and soffits of lintel / coping | C61: =TAKEOFF!$H$1903 -> 127.59 | D61: m2 | E61: =RATES!$D$43 -> 165 | F61: =C61*E61 -> 21052.35 | G61: (8*(1+0.3)+15*(0.9+0.3)+22*(0.75+0.3)+1*(0.7+0.3)+3*(1.2+0.3)+3*(1+0.3)+3*(1+0.3)+2*(0.9+0.3)+1*(1.5+0.3)+3*(0.9+0.3)+5*(0.75+0.3)+1*(0.45+0.3)+3*(0.6+0.3)+1*(3+0.3)+4*(1.6+0.3)+2*(1.3+0.3)+4*(1.8+0.3)+1*(1.2+0.3)+6*(1.8+0.3)+10*(0.9+0.3)+2*(1.8+0...
B63: E30 REINFORCEMENT - High tensile yield round bar reinforcement (standard) to BS 4449:
A64: Q | B64: 10mm diameter in columns | C64: =TAKEOFF!$H$1907 -> 4.551 | D64: t | E64: =RATES!$D$29 -> 14300 | F64: =C64*E64 -> 65079.3 | G64: 4.551
A66: R | B66: 20mm diameter in columns | C66: =TAKEOFF!$H$1910 -> 7.133 | D66: t | E66: =RATES!$D$32 -> 14300 | F66: =C66*E66 -> 102001.9 | G66: 7.133
A68: S | B68: 10mm diameter in beams (links) | C68: =TAKEOFF!$H$1913 -> 1.806 | D68: t | E68: =RATES!$D$29 -> 14300 | F68: =C68*E68 -> 25825.8 | G68: 1.806
A70: T | B70: 16mm diameter in beams | C70: =TAKEOFF!$H$1916 -> 1.248 | D70: t | E70: =RATES!$D$31 -> 14300 | F70: =C70*E70 -> 17846.4 | G70: 1.248
A72: U | B72: 20mm diameter in beams | C72: =TAKEOFF!$H$1919 -> 2.135 | D72: t | E72: =RATES!$D$32 -> 14300 | F72: =C72*E72 -> 30530.5 | G72: 2.135
A74: V | B74: 25mm diameter in beams | C74: =TAKEOFF!$H$1922 -> 5.507 | D74: t | E74: =RATES!$D$33 -> 14300 | F74: =C74*E74 -> 78750.1 | G74: 5.507
A76: W | B76: 10mm diameter in shear & lift walls (links) | C76: =TAKEOFF!$H$1926 -> 2.078 | D76: t | E76: =RATES!$D$29 -> 14300 | F76: =C76*E76 -> 29715.4 | G76: 1.442+0.636
A78: X | B78: 12mm diameter in shear, lift & ramp walls | C78: =TAKEOFF!$H$1930 -> 2.783 | D78: t | E78: =RATES!$D$30 -> 14300 | F78: =C78*E78 -> 39796.9 | G78: 1.917+0.866
A80: Y | B80: 20mm diameter in shear & lift walls | C80: =TAKEOFF!$H$1933 -> 6.904 | D80: t | E80: =RATES!$D$32 -> 14300 | F80: =C80*E80 -> 98727.2 | G80: 6.904
A82: Z | B82: 25mm diameter in shear & lift walls | C82: =TAKEOFF!$H$1936 -> 5.441 | D82: t | E82: =RATES!$D$33 -> 14300 | F82: =C82*E82 -> 77806.3 | G82: 5.441
A84: A | B84: 12mm diameter in stairs | C84: =TAKEOFF!$H$1939 -> 0.88 | D84: t | E84: =RATES!$D$30 -> 14300 | F84: =C84*E84 -> 12584 | G84: 0.880
A86: B | B86: 16mm diameter in stairs | C86: =TAKEOFF!$H$1942 -> 1.434 | D86: t | E86: =RATES!$D$31 -> 14300 | F86: =C86*E86 -> 20506.2 | G86: 1.434
A88: C | B88: 12mm diameter for suspended slab | C88: =TAKEOFF!$H$1945 -> 49.804 | D88: t | E88: =RATES!$D$30 -> 14300 | F88: =C88*E88 -> 712197.2 | G88: 49.804
A90: D | B90: 16mm diameter for suspended slab | C90: =TAKEOFF!$H$1948 -> 0.151 | D90: t | E90: =RATES!$D$31 -> 14300 | F90: =C90*E90 -> 2159.3 | G90: 0.151
B92: =B31 -> ELEMENT NO. 1: IN SITU CONCRETE/LARGE PRECAST CONCRETE | F92: =SUM(F33:F91) -> 2663932.8
B93: Carried to Bill Summary
B96: ELEMENT NO. 2: MASONRY
B98: F10 BRICK/BLOCK WALL - Solid sandcrete blockwork in cement and sand (1:4) mortar as described in:
A99: A | B99: 150mm thick wall | C99: =TAKEOFF!$H$1988 -> 1555.9225 | D99: m2 | E99: =RATES!$D$46 -> 215 | F99: =C99*E99 -> 334523.33 | G99: 443.9*3.05+(8*1*(3.05-2.2)+15*0.9*(3.05-2.2)+22*0.75*(3.05-2.2)+1*0.7*(3.05-2.2)+3*1.2*(3.05-2.2)+3*1*(3.05-2.2)+3*1*(3.05-2.2)+2*0.9*(3.05-2.2)+1*1.5*(3.05-2.2)+3*0.9*(3.05-2.2)+5*0.75*(3.05-2.2)+1*0.45*(3.05-2.2)+3*0.6*(3.05-2.2)+1*3*(3.05-2.2)+...
A101: B | B101: 200mm thick wall | C101: =TAKEOFF!$H$2026 -> 193.89003 | D101: m2 | E101: =RATES!$D$47 -> 265 | F101: =C101*E101 -> 51380.857 | G101: 55.3*3.05+(8*1*(3.05-2.2)+15*0.9*(3.05-2.2)+22*0.75*(3.05-2.2)+1*0.7*(3.05-2.2)+3*1.2*(3.05-2.2)+3*1*(3.05-2.2)+3*1*(3.05-2.2)+2*0.9*(3.05-2.2)+1*1.5*(3.05-2.2)+3*0.9*(3.05-2.2)+5*0.75*(3.05-2.2)+1*0.45*(3.05-2.2)+3*0.6*(3.05-2.2)+1*3*(3.05-2.2)+4...
B103: =B96 -> ELEMENT NO. 2: MASONRY | F103: =SUM(F98:F102) -> 385904.19
B104: Carried to Bill Summary
B107: ELEMENT NO. 4: WINDOWS/DOORS
B109: L20 DOORS - Supply and fix the following door assemblies complete with frames, ironmongery sets to steel doors and all accessories:
A110: A | B110: 1000mm x 2200mm 1-hour fire-rated galvanised steel single-leaf security door assembly (D2) | C110: =TAKEOFF!$H$2031 -> 8 | D110: nr | E110: =RATES!$D$75 -> 7800 | F110: =C110*E110 -> 62400 | G110: 8
A112: B | B112: 900mm x 2200mm single leaf timber panel door (D3) | C112: =TAKEOFF!$H$2034 -> 15 | D112: nr | E112: =RATES!$D$76 -> 3400 | F112: =C112*E112 -> 51000 | G112: 15
A114: C | B114: 750mm x 2200mm single leaf timber flush door (D6) | C114: =TAKEOFF!$H$2037 -> 22 | D114: nr | E114: =RATES!$D$79 -> 1900 | F114: =C114*E114 -> 41800 | G114: 22
A116: D | B116: 700mm x 2200mm single-leaf 2-hour fire-rated galvanised steel door (D7) | C116: =TAKEOFF!$H$2040 -> 1 | D116: nr | E116: =RATES!$D$80 -> 6800 | F116: =C116*E116 -> 6800 | G116: 1
A118: E | B118: 1200mm x 2200mm 1-hour fire-rated leaf-and-a-half galvanised steel security door assembly (D8) | C118: =TAKEOFF!$H$2043 -> 3 | D118: nr | E118: =RATES!$D$81 -> 9800 | F118: =C118*E118 -> 29400 | G118: 3
A120: F | B120: 1000mm x 2200mm 1-hour fire-rated galvanised steel single-leaf security door assembly - emergency stairs (ED1) | C120: =TAKEOFF!$H$2046 -> 3 | D120: nr | E120: =RATES!$D$82 -> 7200 | F120: =C120*E120 -> 21600 | G120: 3
A122: G | B122: 1000mm x 2200mm 1-hour fire-rated galvanised steel single-leaf security door with translucent glass panel (ED2) | C122: =TAKEOFF!$H$2049 -> 3 | D122: nr | E122: =RATES!$D$83 -> 8100 | F122: =C122*E122 -> 24300 | G122: 3
A124: H | B124: 900mm x 2200mm 1-hour fire-rated galvanised steel single-leaf security door assembly (D9) | C124: =TAKEOFF!$H$2052 -> 2 | D124: nr | E124: =RATES!$D$84 -> 6900 | F124: =C124*E124 -> 13800 | G124: 2
A126: J | B126: 1500mm x 2200mm timber bi-fold door (FD1) | C126: =TAKEOFF!$H$2055 -> 1 | D126: nr | E126: =RATES!$D$86 -> 4600 | F126: =C126*E126 -> 4600 | G126: 1
A128: K | B128: 900mm x 2200mm screw-fixed galvanised steel service access panel (M1) | C128: =TAKEOFF!$H$2058 -> 3 | D128: nr | E128: =RATES!$D$87 -> 2900 | F128: =C128*E128 -> 8700 | G128: 3
A130: L | B130: 750mm x 2200mm screw-fixed galvanised steel service access panel (M2) | C130: =TAKEOFF!$H$2061 -> 5 | D130: nr | E130: =RATES!$D$88 -> 2600 | F130: =C130*E130 -> 13000 | G130: 5
A132: M | B132: 450mm x 2200mm screw-fixed galvanised steel service access panel (M3) | C132: =TAKEOFF!$H$2064 -> 1 | D132: nr | E132: =RATES!$D$89 -> 1900 | F132: =C132*E132 -> 1900 | G132: 1
A134: N | B134: 600mm x 2200mm screw-fixed galvanised steel service access panel (M5) | C134: =TAKEOFF!$H$2067 -> 3 | D134: nr | E134: =RATES!$D$90 -> 2200 | F134: =C134*E134 -> 6600 | G134: 3
A136: P | B136: 3000mm x 2200mm 3-panel galvanised steel framed tempered glass sliding door (SD1) | C136: =TAKEOFF!$H$2070 -> 1 | D136: nr | E136: =RATES!$D$94 -> 14500 | F136: =C136*E136 -> 14500 | G136: 1
A138: Q | B138: 1600mm x 2200mm 2-panel galvanised steel framed tempered glass sliding door (SD2) | C138: =TAKEOFF!$H$2073 -> 4 | D138: nr | E138: =RATES!$D$95 -> 8800 | F138: =C138*E138 -> 35200 | G138: 4
A140: R | B140: 1300mm x 2200mm 2-panel galvanised steel framed tempered glass sliding door (SD3) | C140: =TAKEOFF!$H$2076 -> 2 | D140: nr | E140: =RATES!$D$96 -> 7600 | F140: =C140*E140 -> 15200 | G140: 2
A142: S | B142: 1800mm x 2200mm 2-panel galvanised steel framed tempered glass sliding door (SD4) | C142: =TAKEOFF!$H$2079 -> 4 | D142: nr | E142: =RATES!$D$97 -> 9300 | F142: =C142*E142 -> 37200 | G142: 4
A144: T | B144: 1200mm x 2200mm 2-panel galvanised steel framed tempered glass sliding door (SD5) | C144: =TAKEOFF!$H$2082 -> 1 | D144: nr | E144: =RATES!$D$98 -> 7200 | F144: =C144*E144 -> 7200 | G144: 1
A146: U | B146: 50mm x 150mm frames (to timber doors) | C146: =TAKEOFF!$H$2087 -> 198.7 | D146: m | E146: =RATES!$D$100 -> 125 | F146: =C146*E146 -> 24837.5 | G146: 15*(2*2.2+0.9)+22*(2*2.2+0.75)+1*(2*2.2+1.5)
A148: V | B148: 50mm x 12mm door stop | C148: =TAKEOFF!$H$2092 -> 198.7 | D148: m | E148: =RATES!$D$101 -> 28 | F148: =C148*E148 -> 5563.6 | G148: 15*(2*2.2+0.9)+22*(2*2.2+0.75)+1*(2*2.2+1.5)
B151: Ironmongery - Supply and fix the following approved ironmongery to hardwood with accompanying patented screws:
A152: W | B152: Pair 100mm brass butt hinges | C152: =TAKEOFF!$H$2096 -> 56 | D152: pr | E152: =RATES!$D$102 -> 125 | F152: =C152*E152 -> 7000 | G152: 56
A154: X | B154: Ordinary locks | C154: =TAKEOFF!$H$2099 -> 15 | D154: nr | E154: =RATES!$D$103 -> 480 | F154: =C154*E154 -> 7200 | G154: 15
A156: Y | B156: Approved high quality mortice indicator lock | C156: =TAKEOFF!$H$2102 -> 22 | D156: nr | E156: =RATES!$D$104 -> 560 | F156: =C156*E156 -> 12320 | G156: 22
B158: ALUMINIUM GLAZED WINDOWS - Supply and install Italian extruded aluminium glazed windows, ALCOA R50 series, powder coated aluminium profile, glazed with 6mm tinted reflective glass secured onto galvanized steel sub-frames, complete with all accessories as per Architect's detail:
A159: Z | B159: 2 bay alu. framed glass sliding window 1800mm x 1300mm (W2) | C159: =TAKEOFF!$H$2106 -> 6 | D159: nr | E159: =RATES!$D$109 -> 3603.6 | F159: =C159*E159 -> 21621.6 | G159: 6
A161: A | B161: 1 bay alu. framed glass awning window 900mm x 1300mm (W4) | C161: =TAKEOFF!$H$2109 -> 10 | D161: nr | E161: =RATES!$D$111 -> 1801.8 | F161: =C161*E161 -> 18018 | G161: 10
A163: B | B163: 2 bay alu. framed glass sliding window 1800mm x 1600mm (W7) | C163: =TAKEOFF!$H$2112 -> 2 | D163: nr | E163: =RATES!$D$114 -> 4435.2 | F163: =C163*E163 -> 8870.4 | G163: 2
A165: C | B165: 1 x 3 bay alu. framed glass awning window 1200mm x 1900mm (W8) | C165: =TAKEOFF!$H$2115 -> 3 | D165: nr | E165: =RATES!$D$115 -> 3511.2 | F165: =C165*E165 -> 10533.6 | G165: 3
A167: D | B167: 2 bay alu. framed glass sliding window 1200mm x 1150mm (W9) | C167: =TAKEOFF!$H$2118 -> 8 | D167: nr | E167: =RATES!$D$116 -> 2125.2 | F167: =C167*E167 -> 17001.6 | G167: 8
A169: E | B169: 2 bay alu. framed glass sliding window 1200mm x 1200mm (W10) | C169: =TAKEOFF!$H$2121 -> 1 | D169: nr | E169: =RATES!$D$117 -> 2217.6 | F169: =C169*E169 -> 2217.6 | G169: 1
A171: F | B171: 2 bay alu. framed glass sliding window 1500mm x 1300mm (W11) | C171: =TAKEOFF!$H$2124 -> 7 | D171: nr | E171: =RATES!$D$118 -> 3003 | F171: =C171*E171 -> 21021 | G171: 7
A173: G | B173: 2 bay alu. framed glass sliding window 1500mm x 1150mm (W12) | C173: =TAKEOFF!$H$2127 -> 4 | D173: nr | E173: =RATES!$D$119 -> 2656.5 | F173: =C173*E173 -> 10626 | G173: 4
A175: H | B175: 3 bay alu. framed glass awning window 2400mm x 1300mm (W13) | C175: =TAKEOFF!$H$2130 -> 1 | D175: nr | E175: =RATES!$D$120 -> 4804.8 | F175: =C175*E175 -> 4804.8 | G175: 1
A177: J | B177: 3 bay alu. framed glass sliding window 3000mm x 1600mm (W15) | C177: =TAKEOFF!$H$2133 -> 1 | D177: nr | E177: =RATES!$D$122 -> 7392 | F177: =C177*E177 -> 7392 | G177: 1
A179: K | B179: 2 x 3 alu. framed glass awning window 1800mm x 1900mm (W17) | C179: =TAKEOFF!$H$2136 -> 3 | D179: nr | E179: =RATES!$D$124 -> 5266.8 | F179: =C179*E179 -> 15800.4 | G179: 3
A181: L | B181: 1 bay alu. framed glass awning window 750mm x 1300mm (W18) | C181: =TAKEOFF!$H$2139 -> 1 | D181: nr | E181: =RATES!$D$125 -> 1501.5 | F181: =C181*E181 -> 1501.5 | G181: 1
A183: M | B183: 2 x 3 alu. framed glass awning window 1450mm x 1900mm (W20) | C183: =TAKEOFF!$H$2142 -> 1 | D183: nr | E183: =RATES!$D$127 -> 4242.7 | F183: =C183*E183 -> 4242.7 | G183: 1
A185: N | B185: 2 bay alu. framed glass sliding window 900mm x 600mm (HW1) | C185: =TAKEOFF!$H$2145 -> 13 | D185: nr | E185: =RATES!$D$128 -> 831.6 | F185: =C185*E185 -> 10810.8 | G185: 13
A187: P | B187: 2 bay alu. framed glass sliding window 750mm x 600mm (HW2) | C187: =TAKEOFF!$H$2148 -> 5 | D187: nr | E187: =RATES!$D$129 -> 693 | F187: =C187*E187 -> 3465 | G187: 5
A189: Q | B189: 2 bay alu. framed glass sliding window 600mm x 600mm (HW3) | C189: =TAKEOFF!$H$2151 -> 2 | D189: nr | E189: =RATES!$D$130 -> 554.4 | F189: =C189*E189 -> 1108.8 | G189: 2
...

Sheet 5TH FLR 
A1: ='PRELIMS & GEN. ITEMS'!A1 -> PROJECT: BLOCK N REDEVELOPMENT
A2: ='PRELIMS & GEN. ITEMS'!A2 -> LOCATION: KANESHIE
A3: ='PRELIMS & GEN. ITEMS'!A3 -> CLIENT: STATE HOUSING LIMITED
A4: ='PRELIMS & GEN. ITEMS'!A4 -> DATE:9/30/2026
A5: ITEM | B5: DESCRIPTION | C5: QTY | D5: UNIT | E5: RATE | F5: AMOUNT - GHC | G5: Measurement basis / calculation
B7: MAIN BUILDING
B9: FIFTH FLOOR
B11: BILL SUMMARY
A13: A | B13: ELEMENT NO. 1: IN SITU CONCRETE/LARGE PRECAST CONCRETE | F13: =F90 -> 2630642.9
A15: B | B15: ELEMENT NO. 2: MASONRY | F15: =F101 -> 378588.89
A17: C | B17: ELEMENT NO. 4: WINDOWS/DOORS | F17: =F193 -> 566821.1
A19: D | B19: ELEMENT NO. 5: FLOOR FINISHES | F19: =F213 -> 341125.34
A21: E | B21: ELEMENT NO. 6: WALL FINISHES | F21: =F230 -> 309236.25
A23: F | B23: ELEMENT NO. 7: PAINTING AND DECORATING | F23: =F251 -> 187552.29
B25: =B9 -> FIFTH FLOOR | E25: GHC | F25: =SUM(F13:F24) -> 4413966.8
B26: To Bill General Summary
B29: BILL NR. 8 - FIFTH FLOOR
B31: ELEMENT NO. 1: IN SITU CONCRETE/LARGE PRECAST CONCRETE
B33: Vibrated in-situ concrete C40 as described in:
A34: A | B34: Suspended slab 250mm thick | C34: =TAKEOFF!$H$2379 -> 283.65 | D34: m3 | E34: =RATES!$D$22 -> 2310 | F34: =C34*E34 -> 655231.5 | G34: 1134.6*0.25
A36: B | B36: Beams (downstands below slab) | C36: =TAKEOFF!$H$2383 -> 19.831 | D36: m3 | E36: =RATES!$D$23 -> 2310 | F36: =C36*E36 -> 45809.61 | G36: 166.8*0.3*0.35+33.1*0.2*0.35
A38: C | B38: Columns | C38: =TAKEOFF!$H$2394 -> 40.545937 | D38: m3 | E38: =RATES!$D$21 -> 2310 | F38: =C38*E38 -> 93661.116 | G38: 5*0.75*0.5*3.05+1*0.75*0.5*3.05+2*0.75*0.5*3.05+1*0.75*0.5*3.05+3*1.2*0.3*3.05+6*1.2*0.3*3.05+1*1.2*0.3*3.05+15*1.2*0.3*3.05+1*(2.85*0.25+0.825*0.25)*3.05
A40: D | B40: Concrete wall - shear walls to main & emergency stair cores, 250mm thick | C40: =TAKEOFF!$H$2398 -> 36.31025 | D40: m3 | E40: =RATES!$D$20 -> 2310 | F40: =C40*E40 -> 83876.677 | G40: 22.05*3.05*0.25+25.57*3.05*0.25
A42: E | B42: Concrete wall - lift walls, 250mm thick | C42: =TAKEOFF!$H$2401 -> 16.641562 | D42: m3 | E42: =RATES!$D$20 -> 2310 | F42: =C42*E42 -> 38442.009 | G42: 21.825*3.05*0.25
A44: F | B44: Stairs | C44: =TAKEOFF!$H$2407 -> 11.182 | D44: m3 | E44: =RATES!$D$24 -> 2310 | F44: =C44*E44 -> 25830.42 | G44: (2.966*3.3/3.3+2.625)+(2.966*3.3/3.3+2.625)
A46: G | B46: Lintels 150 x 225mm over door and window openings | C46: =TAKEOFF!$H$2444 -> 6.56775 | D46: m3 | E46: =RATES!$D$25 -> 1925 | F46: =C46*E46 -> 12642.919 | G46: (7*(1+0.3)+15*(0.9+0.3)+20*(0.75+0.3)+1*(0.7+0.3)+3*(1.2+0.3)+3*(1+0.3)+3*(1+0.3)+1*(0.9+0.3)+1*(1.5+0.3)+2*(0.9+0.3)+5*(0.75+0.3)+1*(0.45+0.3)+3*(0.6+0.3)+1*(3+0.3)+3*(1.6+0.3)+2*(1.3+0.3)+4*(1.8+0.3)+1*(1.2+0.3)+6*(1.8+0.3)+10*(0.9+0.3)+1*(1.8+0...
B48: E20 FORMWORK - Formwork as described to:
A49: H | B49: Soffits of suspended slab | C49: =TAKEOFF!$H$2448 -> 1134.6 | D49: m2 | E49: =RATES!$D$38 -> 165 | F49: =C49*E49 -> 187209 | G49: 1134.6
A51: J | B51: Edges of suspended slab 250mm high | C51: =TAKEOFF!$H$2451 -> 294.6 | D51: m | E51: =RATES!$D$40 -> 65 | F51: =C51*E51 -> 19149 | G51: 294.6
A53: K | B53: Sides and soffits of beams | C53: =TAKEOFF!$H$2455 -> 196.59 | D53: m2 | E53: =RATES!$D$39 -> 165 | F53: =C53*E53 -> 32437.35 | G53: 166.8*(2*0.35+0.3)+33.1*(2*0.35+0.2)
A55: L | B55: Columns | C55: =TAKEOFF!$H$2466 -> 321.3175 | D55: m2 | E55: =RATES!$D$37 -> 165 | F55: =C55*E55 -> 53017.387 | G55: 5*2*(0.75+0.5)*3.05+1*2*(0.75+0.5)*3.05+2*2*(0.75+0.5)*3.05+1*2*(0.75+0.5)*3.05+3*2*(1.2+0.3)*3.05+6*2*(1.2+0.3)*3.05+1*2*(1.2+0.3)*3.05+15*2*(1.2+0.3)*3.05+1*2*(2.85+1.075)*3.05
A57: M | B57: Concrete wall (both faces) | C57: =TAKEOFF!$H$2471 -> 423.6145 | D57: m2 | E57: =RATES!$D$36 -> 165 | F57: =C57*E57 -> 69896.393 | G57: 2*22.05*3.05+2*21.825*3.05+2*25.57*3.05
A59: N | B59: Soffits of stair flights, landings and risers | C59: =TAKEOFF!$H$2479 -> 66.5328 | D59: m2 | E59: =RATES!$D$42 -> 165 | F59: =C59*E59 -> 10977.912 | G59: (2*3.424*1.8+15.0+22*0.15*1.8)+(2*3.424*1.8+15.0+22*0.15*1.8)
A61: P | B61: Side and soffits of lintel / coping | C61: =TAKEOFF!$H$2516 -> 116.76 | D61: m2 | E61: =RATES!$D$43 -> 165 | F61: =C61*E61 -> 19265.4 | G61: (7*(1+0.3)+15*(0.9+0.3)+20*(0.75+0.3)+1*(0.7+0.3)+3*(1.2+0.3)+3*(1+0.3)+3*(1+0.3)+1*(0.9+0.3)+1*(1.5+0.3)+2*(0.9+0.3)+5*(0.75+0.3)+1*(0.45+0.3)+3*(0.6+0.3)+1*(3+0.3)+3*(1.6+0.3)+2*(1.3+0.3)+4*(1.8+0.3)+1*(1.2+0.3)+6*(1.8+0.3)+10*(0.9+0.3)+1*(1.8+0...
B63: E30 REINFORCEMENT - High tensile yield round bar reinforcement (standard) to BS 4449:
A64: Q | B64: 10mm diameter in columns | C64: =TAKEOFF!$H$2520 -> 4.551 | D64: t | E64: =RATES!$D$29 -> 14300 | F64: =C64*E64 -> 65079.3 | G64: 4.551
A66: R | B66: 20mm diameter in columns | C66: =TAKEOFF!$H$2523 -> 7.133 | D66: t | E66: =RATES!$D$32 -> 14300 | F66: =C66*E66 -> 102001.9 | G66: 7.133
A68: S | B68: 10mm diameter in beams (links) | C68: =TAKEOFF!$H$2526 -> 1.806 | D68: t | E68: =RATES!$D$29 -> 14300 | F68: =C68*E68 -> 25825.8 | G68: 1.806
A70: T | B70: 16mm diameter in beams | C70: =TAKEOFF!$H$2529 -> 1.248 | D70: t | E70: =RATES!$D$31 -> 14300 | F70: =C70*E70 -> 17846.4 | G70: 1.248
A72: U | B72: 20mm diameter in beams | C72: =TAKEOFF!$H$2532 -> 2.135 | D72: t | E72: =RATES!$D$32 -> 14300 | F72: =C72*E72 -> 30530.5 | G72: 2.135
A74: V | B74: 25mm diameter in beams | C74: =TAKEOFF!$H$2535 -> 5.507 | D74: t | E74: =RATES!$D$33 -> 14300 | F74: =C74*E74 -> 78750.1 | G74: 5.507
A76: W | B76: 10mm diameter in shear & lift walls (links) | C76: =TAKEOFF!$H$2539 -> 2.078 | D76: t | E76: =RATES!$D$29 -> 14300 | F76: =C76*E76 -> 29715.4 | G76: 1.442+0.636
A78: X | B78: 12mm diameter in shear, lift & ramp walls | C78: =TAKEOFF!$H$2543 -> 2.783 | D78: t | E78: =RATES!$D$30 -> 14300 | F78: =C78*E78 -> 39796.9 | G78: 1.917+0.866
A80: Y | B80: 20mm diameter in shear & lift walls | C80: =TAKEOFF!$H$2547 -> 10.224 | D80: t | E80: =RATES!$D$32 -> 14300 | F80: =C80*E80 -> 146203.2 | G80: 6.904+3.320
A82: Z | B82: 12mm diameter in stairs | C82: =TAKEOFF!$H$2550 -> 0.88 | D82: t | E82: =RATES!$D$30 -> 14300 | F82: =C82*E82 -> 12584 | G82: 0.880
A84: A | B84: 16mm diameter in stairs | C84: =TAKEOFF!$H$2553 -> 1.434 | D84: t | E84: =RATES!$D$31 -> 14300 | F84: =C84*E84 -> 20506.2 | G84: 1.434
A86: B | B86: 12mm diameter for suspended slab | C86: =TAKEOFF!$H$2556 -> 49.804 | D86: t | E86: =RATES!$D$30 -> 14300 | F86: =C86*E86 -> 712197.2 | G86: 49.804
A88: C | B88: 16mm diameter for suspended slab | C88: =TAKEOFF!$H$2559 -> 0.151 | D88: t | E88: =RATES!$D$31 -> 14300 | F88: =C88*E88 -> 2159.3 | G88: 0.151
B90: =B31 -> ELEMENT NO. 1: IN SITU CONCRETE/LARGE PRECAST CONCRETE | F90: =SUM(F33:F89) -> 2630642.9
B91: Carried to Bill Summary
B94: ELEMENT NO. 2: MASONRY
B96: F10 BRICK/BLOCK WALL - Solid sandcrete blockwork in cement and sand (1:4) mortar as described in:
A97: A | B97: 150mm thick wall | C97: =TAKEOFF!$H$2599 -> 1550.8207 | D97: m2 | E97: =RATES!$D$46 -> 215 | F97: =C97*E97 -> 333426.45 | G97: 447.7*3.05+(7*1*(3.05-2.2)+15*0.9*(3.05-2.2)+20*0.75*(3.05-2.2)+1*0.7*(3.05-2.2)+3*1.2*(3.05-2.2)+3*1*(3.05-2.2)+3*1*(3.05-2.2)+1*0.9*(3.05-2.2)+1*1.5*(3.05-2.2)+2*0.9*(3.05-2.2)+5*0.75*(3.05-2.2)+1*0.45*(3.05-2.2)+3*0.6*(3.05-2.2)+1*3*(3.05-2.2)+...
A99: B | B99: 200mm thick wall | C99: =TAKEOFF!$H$2637 -> 170.4243 | D99: m2 | E99: =RATES!$D$47 -> 265 | F99: =C99*E99 -> 45162.44 | G99: 49.2*3.05+(7*1*(3.05-2.2)+15*0.9*(3.05-2.2)+20*0.75*(3.05-2.2)+1*0.7*(3.05-2.2)+3*1.2*(3.05-2.2)+3*1*(3.05-2.2)+3*1*(3.05-2.2)+1*0.9*(3.05-2.2)+1*1.5*(3.05-2.2)+2*0.9*(3.05-2.2)+5*0.75*(3.05-2.2)+1*0.45*(3.05-2.2)+3*0.6*(3.05-2.2)+1*3*(3.05-2.2)+3...
B101: =B94 -> ELEMENT NO. 2: MASONRY | F101: =SUM(F96:F100) -> 378588.89
B102: Carried to Bill Summary
B104: ELEMENT NO. 4: WINDOWS/DOORS
B106: L20 DOORS - Supply and fix the following door assemblies complete with frames, ironmongery sets to steel doors and all accessories:
A107: A | B107: 1000mm x 2200mm 1-hour fire-rated galvanised steel single-leaf security door assembly (D2) | C107: =TAKEOFF!$H$2642 -> 7 | D107: nr | E107: =RATES!$D$75 -> 7800 | F107: =C107*E107 -> 54600 | G107: 7
A109: B | B109: 900mm x 2200mm single leaf timber panel door (D3) | C109: =TAKEOFF!$H$2645 -> 15 | D109: nr | E109: =RATES!$D$76 -> 3400 | F109: =C109*E109 -> 51000 | G109: 15
A111: C | B111: 750mm x 2200mm single leaf timber flush door (D6) | C111: =TAKEOFF!$H$2648 -> 20 | D111: nr | E111: =RATES!$D$79 -> 1900 | F111: =C111*E111 -> 38000 | G111: 20
A113: D | B113: 700mm x 2200mm single-leaf 2-hour fire-rated galvanised steel door (D7) | C113: =TAKEOFF!$H$2651 -> 1 | D113: nr | E113: =RATES!$D$80 -> 6800 | F113: =C113*E113 -> 6800 | G113: 1
A115: E | B115: 1200mm x 2200mm 1-hour fire-rated leaf-and-a-half galvanised steel security door assembly (D8) | C115: =TAKEOFF!$H$2654 -> 3 | D115: nr | E115: =RATES!$D$81 -> 9800 | F115: =C115*E115 -> 29400 | G115: 3
A117: F | B117: 1000mm x 2200mm 1-hour fire-rated galvanised steel single-leaf security door assembly - emergency stairs (ED1) | C117: =TAKEOFF!$H$2657 -> 3 | D117: nr | E117: =RATES!$D$82 -> 7200 | F117: =C117*E117 -> 21600 | G117: 3
A119: G | B119: 1000mm x 2200mm 1-hour fire-rated galvanised steel single-leaf security door with translucent glass panel (ED2) | C119: =TAKEOFF!$H$2660 -> 3 | D119: nr | E119: =RATES!$D$83 -> 8100 | F119: =C119*E119 -> 24300 | G119: 3
A121: H | B121: 900mm x 2200mm 1-hour fire-rated galvanised steel single-leaf security door assembly (D9) | C121: =TAKEOFF!$H$2663 -> 1 | D121: nr | E121: =RATES!$D$84 -> 6900 | F121: =C121*E121 -> 6900 | G121: 1
A123: J | B123: 1500mm x 2200mm timber bi-fold door (FD1) | C123: =TAKEOFF!$H$2666 -> 1 | D123: nr | E123: =RATES!$D$86 -> 4600 | F123: =C123*E123 -> 4600 | G123: 1
A125: K | B125: 900mm x 2200mm screw-fixed galvanised steel service access panel (M1) | C125: =TAKEOFF!$H$2669 -> 2 | D125: nr | E125: =RATES!$D$87 -> 2900 | F125: =C125*E125 -> 5800 | G125: 2
A127: L | B127: 750mm x 2200mm screw-fixed galvanised steel service access panel (M2) | C127: =TAKEOFF!$H$2672 -> 5 | D127: nr | E127: =RATES!$D$88 -> 2600 | F127: =C127*E127 -> 13000 | G127: 5
A129: M | B129: 450mm x 2200mm screw-fixed galvanised steel service access panel (M3) | C129: =TAKEOFF!$H$2675 -> 1 | D129: nr | E129: =RATES!$D$89 -> 1900 | F129: =C129*E129 -> 1900 | G129: 1
A131: N | B131: 600mm x 2200mm screw-fixed galvanised steel service access panel (M5) | C131: =TAKEOFF!$H$2678 -> 3 | D131: nr | E131: =RATES!$D$90 -> 2200 | F131: =C131*E131 -> 6600 | G131: 3
A133: P | B133: 3000mm x 2200mm 3-panel galvanised steel framed tempered glass sliding door (SD1) | C133: =TAKEOFF!$H$2681 -> 1 | D133: nr | E133: =RATES!$D$94 -> 14500 | F133: =C133*E133 -> 14500 | G133: 1
A135: Q | B135: 1600mm x 2200mm 2-panel galvanised steel framed tempered glass sliding door (SD2) | C135: =TAKEOFF!$H$2684 -> 3 | D135: nr | E135: =RATES!$D$95 -> 8800 | F135: =C135*E135 -> 26400 | G135: 3
A137: R | B137: 1300mm x 2200mm 2-panel galvanised steel framed tempered glass sliding door (SD3) | C137: =TAKEOFF!$H$2687 -> 2 | D137: nr | E137: =RATES!$D$96 -> 7600 | F137: =C137*E137 -> 15200 | G137: 2
A141: S | B141: 1800mm x 2200mm 2-panel galvanised steel framed tempered glass sliding door (SD4) | C141: =TAKEOFF!$H$2690 -> 4 | D141: nr | E141: =RATES!$D$97 -> 9300 | F141: =C141*E141 -> 37200 | G141: 4
A143: T | B143: 1200mm x 2200mm 2-panel galvanised steel framed tempered glass sliding door (SD5) | C143: =TAKEOFF!$H$2693 -> 1 | D143: nr | E143: =RATES!$D$98 -> 7200 | F143: =C143*E143 -> 7200 | G143: 1
A145: U | B145: 50mm x 150mm frames (to timber doors) | C145: =TAKEOFF!$H$2698 -> 188.4 | D145: m | E145: =RATES!$D$100 -> 125 | F145: =C145*E145 -> 23550 | G145: 15*(2*2.2+0.9)+20*(2*2.2+0.75)+1*(2*2.2+1.5)
A147: V | B147: 50mm x 12mm door stop | C147: =TAKEOFF!$H$2703 -> 188.4 | D147: m | E147: =RATES!$D$101 -> 28 | F147: =C147*E147 -> 5275.2 | G147: 15*(2*2.2+0.9)+20*(2*2.2+0.75)+1*(2*2.2+1.5)
B149: Ironmongery - Supply and fix the following approved ironmongery to hardwood with accompanying patented screws:
A150: W | B150: Pair 100mm brass butt hinges | C150: =TAKEOFF!$H$2707 -> 53 | D150: pr | E150: =RATES!$D$102 -> 125 | F150: =C150*E150 -> 6625 | G150: 53
A152: X | B152: Ordinary locks | C152: =TAKEOFF!$H$2710 -> 15 | D152: nr | E152: =RATES!$D$103 -> 480 | F152: =C152*E152 -> 7200 | G152: 15
A154: Y | B154: Approved high quality mortice indicator lock | C154: =TAKEOFF!$H$2713 -> 20 | D154: nr | E154: =RATES!$D$104 -> 560 | F154: =C154*E154 -> 11200 | G154: 20
B156: ALUMINIUM GLAZED WINDOWS - Supply and install Italian extruded aluminium glazed windows, ALCOA R50 series, powder coated aluminium profile, glazed with 6mm tinted reflective glass secured onto galvanized steel sub-frames, complete with all accessories as per Architect's detail:
A157: Z | B157: 2 bay alu. framed glass sliding window 1800mm x 1300mm (W2) | C157: =TAKEOFF!$H$2717 -> 6 | D157: nr | E157: =RATES!$D$109 -> 3603.6 | F157: =C157*E157 -> 21621.6 | G157: 6
A159: A | B159: 1 bay alu. framed glass awning window 900mm x 1300mm (W4) | C159: =TAKEOFF!$H$2720 -> 10 | D159: nr | E159: =RATES!$D$111 -> 1801.8 | F159: =C159*E159 -> 18018 | G159: 10
A161: B | B161: 2 bay alu. framed glass sliding window 1800mm x 1600mm (W7) | C161: =TAKEOFF!$H$2723 -> 1 | D161: nr | E161: =RATES!$D$114 -> 4435.2 | F161: =C161*E161 -> 4435.2 | G161: 1
A163: C | B163: 1 x 3 bay alu. framed glass awning window 1200mm x 1900mm (W8) | C163: =TAKEOFF!$H$2726 -> 3 | D163: nr | E163: =RATES!$D$115 -> 3511.2 | F163: =C163*E163 -> 10533.6 | G163: 3
A165: D | B165: 2 bay alu. framed glass sliding window 1200mm x 1150mm (W9) | C165: =TAKEOFF!$H$2729 -> 8 | D165: nr | E165: =RATES!$D$116 -> 2125.2 | F165: =C165*E165 -> 17001.6 | G165: 8
A167: E | B167: 2 bay alu. framed glass sliding window 1200mm x 1200mm (W10) | C167: =TAKEOFF!$H$2732 -> 1 | D167: nr | E167: =RATES!$D$117 -> 2217.6 | F167: =C167*E167 -> 2217.6 | G167: 1
A169: F | B169: 2 bay alu. framed glass sliding window 1500mm x 1300mm (W11) | C169: =TAKEOFF!$H$2735 -> 6 | D169: nr | E169: =RATES!$D$118 -> 3003 | F169: =C169*E169 -> 18018 | G169: 6
A171: G | B171: 2 bay alu. framed glass sliding window 1500mm x 1150mm (W12) | C171: =TAKEOFF!$H$2738 -> 3 | D171: nr | E171: =RATES!$D$119 -> 2656.5 | F171: =C171*E171 -> 7969.5 | G171: 3
A173: H | B173: 3 bay alu. framed glass awning window 2400mm x 1300mm (W13) | C173: =TAKEOFF!$H$2741 -> 1 | D173: nr | E173: =RATES!$D$120 -> 4804.8 | F173: =C173*E173 -> 4804.8 | G173: 1
A177: J | B177: 3 bay alu. framed glass sliding window 3000mm x 1600mm (W15) | C177: =TAKEOFF!$H$2744 -> 1 | D177: nr | E177: =RATES!$D$122 -> 7392 | F177: =C177*E177 -> 7392 | G177: 1
A179: K | B179: 2 x 3 alu. framed glass awning window 1800mm x 1900mm (W17) | C179: =TAKEOFF!$H$2747 -> 3 | D179: nr | E179: =RATES!$D$124 -> 5266.8 | F179: =C179*E179 -> 15800.4 | G179: 3
A181: L | B181: 1 bay alu. framed glass awning window 750mm x 1300mm (W18) | C181: =TAKEOFF!$H$2750 -> 1 | D181: nr | E181: =RATES!$D$125 -> 1501.5 | F181: =C181*E181 -> 1501.5 | G181: 1
A183: M | B183: 2 x 3 alu. framed glass awning window 1450mm x 1900mm (W20) | C183: =TAKEOFF!$H$2753 -> 1 | D183: nr | E183: =RATES!$D$127 -> 4242.7 | F183: =C183*E183 -> 4242.7 | G183: 1
A185: N | B185: 2 bay alu. framed glass sliding window 900mm x 600mm (HW1) | C185: =TAKEOFF!$H$2756 -> 12 | D185: nr | E185: =RATES!$D$128 -> 831.6 | F185: =C185*E185 -> 9979.2 | G185: 12
A187: P | B187: 2 bay alu. framed glass sliding window 750mm x 600mm (HW2) | C187: =TAKEOFF!$H$2759 -> 4 | D187: nr | E187: =RATES!$D$129 -> 693 | F187: =C187*E187 -> 2772 | G187: 4
A189: Q | B189: 2 bay alu. framed glass sliding window 600mm x 600mm (HW3) | C189: =TAKEOFF!$H$2762 -> 1 | D189: nr | E189: =RATES!$D$130 -> 554.4 | F189: =C189*E189 -> 554.4 | G189: 1
A191: R | B191: 2 bay alu. framed glass sliding window 1200mm x 600mm (HW4) | C191: =TAKEOFF!$H$2765 -> 1 | D191: nr | E191: =RATES!$D$131 -> 1108.8 | F191: =C191*E191 -> 1108.8 | G191: 1
...

Sheet 6TH FLR  
A1: ='PRELIMS & GEN. ITEMS'!A1 -> PROJECT: BLOCK N REDEVELOPMENT
A2: ='PRELIMS & GEN. ITEMS'!A2 -> LOCATION: KANESHIE
A3: ='PRELIMS & GEN. ITEMS'!A3 -> CLIENT: STATE HOUSING LIMITED
A4: ='PRELIMS & GEN. ITEMS'!A4 -> DATE:9/30/2026
A5: ITEM | B5: DESCRIPTION | C5: QTY | D5: UNIT | E5: RATE | F5: AMOUNT - GHC | G5: Measurement basis / calculation
B7: MAIN BUILDING
B9: SIXTH FLOOR
B11: BILL SUMMARY
A13: A | B13: ELEMENT NO. 1: IN SITU CONCRETE/LARGE PRECAST CONCRETE | F13: =F90 -> 2632741.7
A15: B | B15: ELEMENT NO. 2: MASONRY | F15: =F101 -> 394834.26
A17: C | B17: ELEMENT NO. 4: WINDOWS/DOORS | F17: =F191 -> 597073.55
A19: D | B19: ELEMENT NO. 5: FLOOR FINISHES | F19: =F211 -> 349083.24
A21: E | B21: ELEMENT NO. 6: WALL FINISHES | F21: =F227 -> 321670.38
A23: F | B23: ELEMENT NO. 7: PAINTING AND DECORATING | F23: =F247 -> 190908.58
B25: =B9 -> SIXTH FLOOR | E25: GHC | F25: =SUM(F13:F24) -> 4486311.7
B26: To Bill General Summary
B29: BILL NR. 9 - SIXTH FLOOR
B31: ELEMENT NO. 1: IN SITU CONCRETE/LARGE PRECAST CONCRETE
B33: Vibrated in-situ concrete C40 as described in:
A34: A | B34: Suspended slab 250mm thick | C34: =TAKEOFF!$H$2990 -> 283.65 | D34: m3 | E34: =RATES!$D$22 -> 2310 | F34: =C34*E34 -> 655231.5 | G34: 1134.6*0.25
A36: B | B36: Beams (downstands below slab) | C36: =TAKEOFF!$H$2994 -> 19.831 | D36: m3 | E36: =RATES!$D$23 -> 2310 | F36: =C36*E36 -> 45809.61 | G36: 166.8*0.3*0.35+33.1*0.2*0.35
A38: C | B38: Columns | C38: =TAKEOFF!$H$3005 -> 40.545937 | D38: m3 | E38: =RATES!$D$21 -> 2310 | F38: =C38*E38 -> 93661.116 | G38: 5*0.75*0.5*3.05+1*0.75*0.5*3.05+2*0.75*0.5*3.05+1*0.75*0.5*3.05+3*1.2*0.3*3.05+6*1.2*0.3*3.05+1*1.2*0.3*3.05+15*1.2*0.3*3.05+1*(2.85*0.25+0.825*0.25)*3.05
A40: D | B40: Concrete wall - shear walls to main & emergency stair cores, 250mm thick | C40: =TAKEOFF!$H$3009 -> 36.31025 | D40: m3 | E40: =RATES!$D$20 -> 2310 | F40: =C40*E40 -> 83876.677 | G40: 22.05*3.05*0.25+25.57*3.05*0.25
A42: E | B42: Concrete wall - lift walls, 250mm thick | C42: =TAKEOFF!$H$3012 -> 16.641562 | D42: m3 | E42: =RATES!$D$20 -> 2310 | F42: =C42*E42 -> 38442.009 | G42: 21.825*3.05*0.25
A44: F | B44: Stairs | C44: =TAKEOFF!$H$3018 -> 11.182 | D44: m3 | E44: =RATES!$D$24 -> 2310 | F44: =C44*E44 -> 25830.42 | G44: (2.966*3.3/3.3+2.625)+(2.966*3.3/3.3+2.625)
A46: G | B46: Lintels 150 x 225mm over door and window openings | C46: =TAKEOFF!$H$3055 -> 6.99975 | D46: m3 | E46: =RATES!$D$25 -> 1925 | F46: =C46*E46 -> 13474.519 | G46: (8*(1+0.3)+15*(0.9+0.3)+21*(0.75+0.3)+1*(0.7+0.3)+3*(1.2+0.3)+3*(1+0.3)+3*(1+0.3)+1*(0.9+0.3)+1*(1.5+0.3)+2*(0.9+0.3)+5*(0.75+0.3)+1*(0.45+0.3)+3*(0.6+0.3)+1*(3+0.3)+4*(1.6+0.3)+2*(1.3+0.3)+4*(1.8+0.3)+1*(1.2+0.3)+6*(1.8+0.3)+10*(0.9+0.3)+2*(1.8+0...
B48: E20 FORMWORK - Formwork as described to:
A49: H | B49: Soffits of suspended slab | C49: =TAKEOFF!$H$3059 -> 1134.6 | D49: m2 | E49: =RATES!$D$38 -> 165 | F49: =C49*E49 -> 187209 | G49: 1134.6
A51: J | B51: Edges of suspended slab 250mm high | C51: =TAKEOFF!$H$3062 -> 294.6 | D51: m | E51: =RATES!$D$40 -> 65 | F51: =C51*E51 -> 19149 | G51: 294.6
A53: K | B53: Sides and soffits of beams | C53: =TAKEOFF!$H$3066 -> 196.59 | D53: m2 | E53: =RATES!$D$39 -> 165 | F53: =C53*E53 -> 32437.35 | G53: 166.8*(2*0.35+0.3)+33.1*(2*0.35+0.2)
A55: L | B55: Columns | C55: =TAKEOFF!$H$3077 -> 321.3175 | D55: m2 | E55: =RATES!$D$37 -> 165 | F55: =C55*E55 -> 53017.387 | G55: 5*2*(0.75+0.5)*3.05+1*2*(0.75+0.5)*3.05+2*2*(0.75+0.5)*3.05+1*2*(0.75+0.5)*3.05+3*2*(1.2+0.3)*3.05+6*2*(1.2+0.3)*3.05+1*2*(1.2+0.3)*3.05+15*2*(1.2+0.3)*3.05+1*2*(2.85+1.075)*3.05
A57: M | B57: Concrete wall (both faces) | C57: =TAKEOFF!$H$3082 -> 423.6145 | D57: m2 | E57: =RATES!$D$36 -> 165 | F57: =C57*E57 -> 69896.393 | G57: 2*22.05*3.05+2*21.825*3.05+2*25.57*3.05
A59: N | B59: Soffits of stair flights, landings and risers | C59: =TAKEOFF!$H$3090 -> 66.5328 | D59: m2 | E59: =RATES!$D$42 -> 165 | F59: =C59*E59 -> 10977.912 | G59: (2*3.424*1.8+15.0+22*0.15*1.8)+(2*3.424*1.8+15.0+22*0.15*1.8)
A61: P | B61: Side and soffits of lintel / coping | C61: =TAKEOFF!$H$3127 -> 124.44 | D61: m2 | E61: =RATES!$D$43 -> 165 | F61: =C61*E61 -> 20532.6 | G61: (8*(1+0.3)+15*(0.9+0.3)+21*(0.75+0.3)+1*(0.7+0.3)+3*(1.2+0.3)+3*(1+0.3)+3*(1+0.3)+1*(0.9+0.3)+1*(1.5+0.3)+2*(0.9+0.3)+5*(0.75+0.3)+1*(0.45+0.3)+3*(0.6+0.3)+1*(3+0.3)+4*(1.6+0.3)+2*(1.3+0.3)+4*(1.8+0.3)+1*(1.2+0.3)+6*(1.8+0.3)+10*(0.9+0.3)+2*(1.8+0...
B63: E30 REINFORCEMENT - High tensile yield round bar reinforcement (standard) to BS 4449:
A64: Q | B64: 10mm diameter in columns | C64: =TAKEOFF!$H$3131 -> 4.551 | D64: t | E64: =RATES!$D$29 -> 14300 | F64: =C64*E64 -> 65079.3 | G64: 4.551
A66: R | B66: 20mm diameter in columns | C66: =TAKEOFF!$H$3134 -> 7.133 | D66: t | E66: =RATES!$D$32 -> 14300 | F66: =C66*E66 -> 102001.9 | G66: 7.133
A68: S | B68: 10mm diameter in beams (links) | C68: =TAKEOFF!$H$3137 -> 1.806 | D68: t | E68: =RATES!$D$29 -> 14300 | F68: =C68*E68 -> 25825.8 | G68: 1.806
A70: T | B70: 16mm diameter in beams | C70: =TAKEOFF!$H$3140 -> 1.248 | D70: t | E70: =RATES!$D$31 -> 14300 | F70: =C70*E70 -> 17846.4 | G70: 1.248
A72: U | B72: 20mm diameter in beams | C72: =TAKEOFF!$H$3143 -> 2.135 | D72: t | E72: =RATES!$D$32 -> 14300 | F72: =C72*E72 -> 30530.5 | G72: 2.135
A74: V | B74: 25mm diameter in beams | C74: =TAKEOFF!$H$3146 -> 5.507 | D74: t | E74: =RATES!$D$33 -> 14300 | F74: =C74*E74 -> 78750.1 | G74: 5.507
A76: W | B76: 10mm diameter in shear & lift walls (links) | C76: =TAKEOFF!$H$3150 -> 2.078 | D76: t | E76: =RATES!$D$29 -> 14300 | F76: =C76*E76 -> 29715.4 | G76: 1.442+0.636
A78: X | B78: 12mm diameter in shear, lift & ramp walls | C78: =TAKEOFF!$H$3154 -> 2.783 | D78: t | E78: =RATES!$D$30 -> 14300 | F78: =C78*E78 -> 39796.9 | G78: 1.917+0.866
A80: Y | B80: 20mm diameter in shear & lift walls | C80: =TAKEOFF!$H$3158 -> 10.224 | D80: t | E80: =RATES!$D$32 -> 14300 | F80: =C80*E80 -> 146203.2 | G80: 6.904+3.320
A82: Z | B82: 12mm diameter in stairs | C82: =TAKEOFF!$H$3161 -> 0.88 | D82: t | E82: =RATES!$D$30 -> 14300 | F82: =C82*E82 -> 12584 | G82: 0.880
A84: A | B84: 16mm diameter in stairs | C84: =TAKEOFF!$H$3164 -> 1.434 | D84: t | E84: =RATES!$D$31 -> 14300 | F84: =C84*E84 -> 20506.2 | G84: 1.434
A86: B | B86: 12mm diameter for suspended slab | C86: =TAKEOFF!$H$3167 -> 49.804 | D86: t | E86: =RATES!$D$30 -> 14300 | F86: =C86*E86 -> 712197.2 | G86: 49.804
A88: C | B88: 16mm diameter for suspended slab | C88: =TAKEOFF!$H$3170 -> 0.151 | D88: t | E88: =RATES!$D$31 -> 14300 | F88: =C88*E88 -> 2159.3 | G88: 0.151
B90: =B31 -> ELEMENT NO. 1: IN SITU CONCRETE/LARGE PRECAST CONCRETE | F90: =SUM(F33:F89) -> 2632741.7
B91: Carried to Bill Summary
B94: ELEMENT NO. 2: MASONRY
B96: F10 BRICK/BLOCK WALL - Solid sandcrete blockwork in cement and sand (1:4) mortar as described in:
A97: A | B97: 150mm thick wall | C97: =TAKEOFF!$H$3210 -> 1621.8764 | D97: m2 | E97: =RATES!$D$46 -> 215 | F97: =C97*E97 -> 348703.42 | G97: 465.9*3.05+(8*1*(3.05-2.2)+15*0.9*(3.05-2.2)+21*0.75*(3.05-2.2)+1*0.7*(3.05-2.2)+3*1.2*(3.05-2.2)+3*1*(3.05-2.2)+3*1*(3.05-2.2)+1*0.9*(3.05-2.2)+1*1.5*(3.05-2.2)+2*0.9*(3.05-2.2)+5*0.75*(3.05-2.2)+1*0.45*(3.05-2.2)+3*0.6*(3.05-2.2)+1*3*(3.05-2.2)+...
A99: B | B99: 200mm thick wall | C99: =TAKEOFF!$H$3248 -> 174.07862 | D99: m2 | E99: =RATES!$D$47 -> 265 | F99: =C99*E99 -> 46130.834 | G99: 50.0*3.05+(8*1*(3.05-2.2)+15*0.9*(3.05-2.2)+21*0.75*(3.05-2.2)+1*0.7*(3.05-2.2)+3*1.2*(3.05-2.2)+3*1*(3.05-2.2)+3*1*(3.05-2.2)+1*0.9*(3.05-2.2)+1*1.5*(3.05-2.2)+2*0.9*(3.05-2.2)+5*0.75*(3.05-2.2)+1*0.45*(3.05-2.2)+3*0.6*(3.05-2.2)+1*3*(3.05-2.2)+4...
B101: =B94 -> ELEMENT NO. 2: MASONRY | F101: =SUM(F96:F100) -> 394834.26
B102: Carried to Bill Summary
B105: ELEMENT NO. 4: WINDOWS/DOORS
B107: L20 DOORS - Supply and fix the following door assemblies complete with frames, ironmongery sets to steel doors and all accessories:
A108: A | B108: 1000mm x 2200mm 1-hour fire-rated galvanised steel single-leaf security door assembly (D2) | C108: =TAKEOFF!$H$3253 -> 8 | D108: nr | E108: =RATES!$D$75 -> 7800 | F108: =C108*E108 -> 62400 | G108: 8
A110: B | B110: 900mm x 2200mm single leaf timber panel door (D3) | C110: =TAKEOFF!$H$3256 -> 15 | D110: nr | E110: =RATES!$D$76 -> 3400 | F110: =C110*E110 -> 51000 | G110: 15
A112: C | B112: 750mm x 2200mm single leaf timber flush door (D6) | C112: =TAKEOFF!$H$3259 -> 21 | D112: nr | E112: =RATES!$D$79 -> 1900 | F112: =C112*E112 -> 39900 | G112: 21
A114: D | B114: 700mm x 2200mm single-leaf 2-hour fire-rated galvanised steel door (D7) | C114: =TAKEOFF!$H$3262 -> 1 | D114: nr | E114: =RATES!$D$80 -> 6800 | F114: =C114*E114 -> 6800 | G114: 1
A116: E | B116: 1200mm x 2200mm 1-hour fire-rated leaf-and-a-half galvanised steel security door assembly (D8) | C116: =TAKEOFF!$H$3265 -> 3 | D116: nr | E116: =RATES!$D$81 -> 9800 | F116: =C116*E116 -> 29400 | G116: 3
A118: F | B118: 1000mm x 2200mm 1-hour fire-rated galvanised steel single-leaf security door assembly - emergency stairs (ED1) | C118: =TAKEOFF!$H$3268 -> 3 | D118: nr | E118: =RATES!$D$82 -> 7200 | F118: =C118*E118 -> 21600 | G118: 3
A120: G | B120: 1000mm x 2200mm 1-hour fire-rated galvanised steel single-leaf security door with translucent glass panel (ED2) | C120: =TAKEOFF!$H$3271 -> 3 | D120: nr | E120: =RATES!$D$83 -> 8100 | F120: =C120*E120 -> 24300 | G120: 3
A122: H | B122: 900mm x 2200mm 1-hour fire-rated galvanised steel single-leaf security door assembly (D9) | C122: =TAKEOFF!$H$3274 -> 1 | D122: nr | E122: =RATES!$D$84 -> 6900 | F122: =C122*E122 -> 6900 | G122: 1
A124: J | B124: 1500mm x 2200mm timber bi-fold door (FD1) | C124: =TAKEOFF!$H$3277 -> 1 | D124: nr | E124: =RATES!$D$86 -> 4600 | F124: =C124*E124 -> 4600 | G124: 1
A126: K | B126: 900mm x 2200mm screw-fixed galvanised steel service access panel (M1) | C126: =TAKEOFF!$H$3280 -> 2 | D126: nr | E126: =RATES!$D$87 -> 2900 | F126: =C126*E126 -> 5800 | G126: 2
A128: L | B128: 750mm x 2200mm screw-fixed galvanised steel service access panel (M2) | C128: =TAKEOFF!$H$3283 -> 5 | D128: nr | E128: =RATES!$D$88 -> 2600 | F128: =C128*E128 -> 13000 | G128: 5
A130: M | B130: 450mm x 2200mm screw-fixed galvanised steel service access panel (M3) | C130: =TAKEOFF!$H$3286 -> 1 | D130: nr | E130: =RATES!$D$89 -> 1900 | F130: =C130*E130 -> 1900 | G130: 1
A132: N | B132: 600mm x 2200mm screw-fixed galvanised steel service access panel (M5) | C132: =TAKEOFF!$H$3289 -> 3 | D132: nr | E132: =RATES!$D$90 -> 2200 | F132: =C132*E132 -> 6600 | G132: 3
A134: P | B134: 3000mm x 2200mm 3-panel galvanised steel framed tempered glass sliding door (SD1) | C134: =TAKEOFF!$H$3292 -> 1 | D134: nr | E134: =RATES!$D$94 -> 14500 | F134: =C134*E134 -> 14500 | G134: 1
A136: Q | B136: 1600mm x 2200mm 2-panel galvanised steel framed tempered glass sliding door (SD2) | C136: =TAKEOFF!$H$3295 -> 4 | D136: nr | E136: =RATES!$D$95 -> 8800 | F136: =C136*E136 -> 35200 | G136: 4
A138: R | B138: 1300mm x 2200mm 2-panel galvanised steel framed tempered glass sliding door (SD3) | C138: =TAKEOFF!$H$3298 -> 2 | D138: nr | E138: =RATES!$D$96 -> 7600 | F138: =C138*E138 -> 15200 | G138: 2
A140: S | B140: 1800mm x 2200mm 2-panel galvanised steel framed tempered glass sliding door (SD4) | C140: =TAKEOFF!$H$3301 -> 4 | D140: nr | E140: =RATES!$D$97 -> 9300 | F140: =C140*E140 -> 37200 | G140: 4
A142: T | B142: 1200mm x 2200mm 2-panel galvanised steel framed tempered glass sliding door (SD5) | C142: =TAKEOFF!$H$3304 -> 1 | D142: nr | E142: =RATES!$D$98 -> 7200 | F142: =C142*E142 -> 7200 | G142: 1
A144: U | B144: 50mm x 150mm frames (to timber doors) | C144: =TAKEOFF!$H$3309 -> 193.55 | D144: m | E144: =RATES!$D$100 -> 125 | F144: =C144*E144 -> 24193.75 | G144: 15*(2*2.2+0.9)+21*(2*2.2+0.75)+1*(2*2.2+1.5)
A146: V | B146: 50mm x 12mm door stop | C146: =TAKEOFF!$H$3314 -> 193.55 | D146: m | E146: =RATES!$D$101 -> 28 | F146: =C146*E146 -> 5419.4 | G146: 15*(2*2.2+0.9)+21*(2*2.2+0.75)+1*(2*2.2+1.5)
B149: Ironmongery - Supply and fix the following approved ironmongery to hardwood with accompanying patented screws:
A150: W | B150: Pair 100mm brass butt hinges | C150: =TAKEOFF!$H$3318 -> 54 | D150: pr | E150: =RATES!$D$102 -> 125 | F150: =C150*E150 -> 6750 | G150: 54
A152: X | B152: Ordinary locks | C152: =TAKEOFF!$H$3321 -> 15 | D152: nr | E152: =RATES!$D$103 -> 480 | F152: =C152*E152 -> 7200 | G152: 15
A154: Y | B154: Approved high quality mortice indicator lock | C154: =TAKEOFF!$H$3324 -> 21 | D154: nr | E154: =RATES!$D$104 -> 560 | F154: =C154*E154 -> 11760 | G154: 21
B156: ALUMINIUM GLAZED WINDOWS - Supply and install Italian extruded aluminium glazed windows, ALCOA R50 series, powder coated aluminium profile, glazed with 6mm tinted reflective glass secured onto galvanized steel sub-frames, complete with all accessories as per Architect's detail:
A157: Z | B157: 2 bay alu. framed glass sliding window 1800mm x 1300mm (W2) | C157: =TAKEOFF!$H$3328 -> 6 | D157: nr | E157: =RATES!$D$109 -> 3603.6 | F157: =C157*E157 -> 21621.6 | G157: 6
A159: A | B159: 1 bay alu. framed glass awning window 900mm x 1300mm (W4) | C159: =TAKEOFF!$H$3331 -> 10 | D159: nr | E159: =RATES!$D$111 -> 1801.8 | F159: =C159*E159 -> 18018 | G159: 10
A161: B | B161: 2 bay alu. framed glass sliding window 1800mm x 1600mm (W7) | C161: =TAKEOFF!$H$3334 -> 2 | D161: nr | E161: =RATES!$D$114 -> 4435.2 | F161: =C161*E161 -> 8870.4 | G161: 2
A163: C | B163: 1 x 3 bay alu. framed glass awning window 1200mm x 1900mm (W8) | C163: =TAKEOFF!$H$3337 -> 3 | D163: nr | E163: =RATES!$D$115 -> 3511.2 | F163: =C163*E163 -> 10533.6 | G163: 3
A165: D | B165: 2 bay alu. framed glass sliding window 1200mm x 1150mm (W9) | C165: =TAKEOFF!$H$3340 -> 8 | D165: nr | E165: =RATES!$D$116 -> 2125.2 | F165: =C165*E165 -> 17001.6 | G165: 8
A167: E | B167: 2 bay alu. framed glass sliding window 1200mm x 1200mm (W10) | C167: =TAKEOFF!$H$3343 -> 1 | D167: nr | E167: =RATES!$D$117 -> 2217.6 | F167: =C167*E167 -> 2217.6 | G167: 1
A169: F | B169: 2 bay alu. framed glass sliding window 1500mm x 1300mm (W11) | C169: =TAKEOFF!$H$3346 -> 6 | D169: nr | E169: =RATES!$D$118 -> 3003 | F169: =C169*E169 -> 18018 | G169: 6
A171: G | B171: 2 bay alu. framed glass sliding window 1500mm x 1150mm (W12) | C171: =TAKEOFF!$H$3349 -> 4 | D171: nr | E171: =RATES!$D$119 -> 2656.5 | F171: =C171*E171 -> 10626 | G171: 4
A173: H | B173: 3 bay alu. framed glass awning window 2400mm x 1300mm (W13) | C173: =TAKEOFF!$H$3352 -> 1 | D173: nr | E173: =RATES!$D$120 -> 4804.8 | F173: =C173*E173 -> 4804.8 | G173: 1
A175: J | B175: 3 bay alu. framed glass sliding window 3000mm x 1600mm (W15) | C175: =TAKEOFF!$H$3355 -> 1 | D175: nr | E175: =RATES!$D$122 -> 7392 | F175: =C175*E175 -> 7392 | G175: 1
A177: K | B177: 2 x 3 alu. framed glass awning window 1800mm x 1900mm (W17) | C177: =TAKEOFF!$H$3358 -> 3 | D177: nr | E177: =RATES!$D$124 -> 5266.8 | F177: =C177*E177 -> 15800.4 | G177: 3
A179: L | B179: 1 bay alu. framed glass awning window 750mm x 1300mm (W18) | C179: =TAKEOFF!$H$3361 -> 1 | D179: nr | E179: =RATES!$D$125 -> 1501.5 | F179: =C179*E179 -> 1501.5 | G179: 1
A181: M | B181: 2 x 3 alu. framed glass awning window 1450mm x 1900mm (W20) | C181: =TAKEOFF!$H$3364 -> 1 | D181: nr | E181: =RATES!$D$127 -> 4242.7 | F181: =C181*E181 -> 4242.7 | G181: 1
A183: N | B183: 2 bay alu. framed glass sliding window 900mm x 600mm (HW1) | C183: =TAKEOFF!$H$3367 -> 13 | D183: nr | E183: =RATES!$D$128 -> 831.6 | F183: =C183*E183 -> 10810.8 | G183: 13
A185: P | B185: 2 bay alu. framed glass sliding window 750mm x 600mm (HW2) | C185: =TAKEOFF!$H$3370 -> 5 | D185: nr | E185: =RATES!$D$129 -> 693 | F185: =C185*E185 -> 3465 | G185: 5
A187: Q | B187: 2 bay alu. framed glass sliding window 600mm x 600mm (HW3) | C187: =TAKEOFF!$H$3373 -> 2 | D187: nr | E187: =RATES!$D$130 -> 554.4 | F187: =C187*E187 -> 1108.8 | G187: 2
A189: R | B189: 2 bay alu. framed glass sliding window 1200mm x 600mm (HW4) | C189: =TAKEOFF!$H$3376 -> 2 | D189: nr | E189: =RATES!$D$131 -> 1108.8 | F189: =C189*E189 -> 2217.6 | G189: 2
...

Sheet 7TH FLR   
A1: ='PRELIMS & GEN. ITEMS'!A1 -> PROJECT: BLOCK N REDEVELOPMENT
A2: ='PRELIMS & GEN. ITEMS'!A2 -> LOCATION: KANESHIE
A3: ='PRELIMS & GEN. ITEMS'!A3 -> CLIENT: STATE HOUSING LIMITED
A4: ='PRELIMS & GEN. ITEMS'!A4 -> DATE:9/30/2026
A5: ITEM | B5: DESCRIPTION | C5: QTY | D5: UNIT | E5: RATE | F5: AMOUNT - GHC | G5: Measurement basis / calculation
B7: MAIN BUILDING
B9: SEVENTH FLOOR
B11: BILL SUMMARY
A13: A | B13: ELEMENT NO. 1: IN SITU CONCRETE/LARGE PRECAST CONCRETE | F13: =F90 -> 2630954.4
A15: B | B15: ELEMENT NO. 2: MASONRY | F15: =F101 -> 381266.88
A17: C | B17: ELEMENT NO. 4: WINDOWS/DOORS | F17: =F191 -> 573414.1
A19: D | B19: ELEMENT NO. 5: FLOOR FINISHES | F19: =F211 -> 345672.24
A21: E | B21: ELEMENT NO. 6: WALL FINISHES | F21: =F227 -> 312099.76
A23: F | B23: ELEMENT NO. 7: PAINTING AND DECORATING | F23: =F248 -> 188326.49
B25: =B9 -> SEVENTH FLOOR | E25: GHC | F25: =SUM(F13:F24) -> 4431733.9
B26: To Bill General Summary
B29: BILL NR. 10 - SEVENTH FLOOR
B31: ELEMENT NO. 1: IN SITU CONCRETE/LARGE PRECAST CONCRETE
B33: Vibrated in-situ concrete C40 as described in:
A34: A | B34: Suspended slab 250mm thick | C34: =TAKEOFF!$H$3601 -> 283.65 | D34: m3 | E34: =RATES!$D$22 -> 2310 | F34: =C34*E34 -> 655231.5 | G34: 1134.6*0.25
A36: B | B36: Beams (downstands below slab) | C36: =TAKEOFF!$H$3605 -> 19.831 | D36: m3 | E36: =RATES!$D$23 -> 2310 | F36: =C36*E36 -> 45809.61 | G36: 166.8*0.3*0.35+33.1*0.2*0.35
A38: C | B38: Columns | C38: =TAKEOFF!$H$3616 -> 40.545937 | D38: m3 | E38: =RATES!$D$21 -> 2310 | F38: =C38*E38 -> 93661.116 | G38: 5*0.75*0.5*3.05+1*0.75*0.5*3.05+2*0.75*0.5*3.05+1*0.75*0.5*3.05+3*1.2*0.3*3.05+6*1.2*0.3*3.05+1*1.2*0.3*3.05+15*1.2*0.3*3.05+1*(2.85*0.25+0.825*0.25)*3.05
A40: D | B40: Concrete wall - shear walls to main & emergency stair cores, 250mm thick | C40: =TAKEOFF!$H$3620 -> 36.31025 | D40: m3 | E40: =RATES!$D$20 -> 2310 | F40: =C40*E40 -> 83876.677 | G40: 22.05*3.05*0.25+25.57*3.05*0.25
A42: E | B42: Concrete wall - lift walls, 250mm thick | C42: =TAKEOFF!$H$3623 -> 16.641562 | D42: m3 | E42: =RATES!$D$20 -> 2310 | F42: =C42*E42 -> 38442.009 | G42: 21.825*3.05*0.25
A44: F | B44: Stairs | C44: =TAKEOFF!$H$3629 -> 11.182 | D44: m3 | E44: =RATES!$D$24 -> 2310 | F44: =C44*E44 -> 25830.42 | G44: (2.966*3.3/3.3+2.625)+(2.966*3.3/3.3+2.625)
A46: G | B46: Lintels 150 x 225mm over door and window openings | C46: =TAKEOFF!$H$3666 -> 6.631875 | D46: m3 | E46: =RATES!$D$25 -> 1925 | F46: =C46*E46 -> 12766.359 | G46: (8*(1+0.3)+15*(0.9+0.3)+20*(0.75+0.3)+1*(0.7+0.3)+3*(1.2+0.3)+3*(1+0.3)+2*(1+0.3)+1*(0.9+0.3)+1*(1.5+0.3)+2*(0.9+0.3)+4*(0.75+0.3)+1*(0.45+0.3)+3*(0.6+0.3)+1*(3+0.3)+4*(1.6+0.3)+2*(1.3+0.3)+4*(1.8+0.3)+1*(1.2+0.3)+6*(1.8+0.3)+10*(0.9+0.3)+1*(1.8+0...
B48: E20 FORMWORK - Formwork as described to:
A49: H | B49: Soffits of suspended slab | C49: =TAKEOFF!$H$3670 -> 1134.6 | D49: m2 | E49: =RATES!$D$38 -> 165 | F49: =C49*E49 -> 187209 | G49: 1134.6
A51: J | B51: Edges of suspended slab 250mm high | C51: =TAKEOFF!$H$3673 -> 294.6 | D51: m | E51: =RATES!$D$40 -> 65 | F51: =C51*E51 -> 19149 | G51: 294.6
A53: K | B53: Sides and soffits of beams | C53: =TAKEOFF!$H$3677 -> 196.59 | D53: m2 | E53: =RATES!$D$39 -> 165 | F53: =C53*E53 -> 32437.35 | G53: 166.8*(2*0.35+0.3)+33.1*(2*0.35+0.2)
A55: L | B55: Columns | C55: =TAKEOFF!$H$3688 -> 321.3175 | D55: m2 | E55: =RATES!$D$37 -> 165 | F55: =C55*E55 -> 53017.387 | G55: 5*2*(0.75+0.5)*3.05+1*2*(0.75+0.5)*3.05+2*2*(0.75+0.5)*3.05+1*2*(0.75+0.5)*3.05+3*2*(1.2+0.3)*3.05+6*2*(1.2+0.3)*3.05+1*2*(1.2+0.3)*3.05+15*2*(1.2+0.3)*3.05+1*2*(2.85+1.075)*3.05
A57: M | B57: Concrete wall (both faces) | C57: =TAKEOFF!$H$3693 -> 423.6145 | D57: m2 | E57: =RATES!$D$36 -> 165 | F57: =C57*E57 -> 69896.393 | G57: 2*22.05*3.05+2*21.825*3.05+2*25.57*3.05
A59: N | B59: Soffits of stair flights, landings and risers | C59: =TAKEOFF!$H$3701 -> 66.5328 | D59: m2 | E59: =RATES!$D$42 -> 165 | F59: =C59*E59 -> 10977.912 | G59: (2*3.424*1.8+15.0+22*0.15*1.8)+(2*3.424*1.8+15.0+22*0.15*1.8)
A61: P | B61: Side and soffits of lintel / coping | C61: =TAKEOFF!$H$3738 -> 117.9 | D61: m2 | E61: =RATES!$D$43 -> 165 | F61: =C61*E61 -> 19453.5 | G61: (8*(1+0.3)+15*(0.9+0.3)+20*(0.75+0.3)+1*(0.7+0.3)+3*(1.2+0.3)+3*(1+0.3)+2*(1+0.3)+1*(0.9+0.3)+1*(1.5+0.3)+2*(0.9+0.3)+4*(0.75+0.3)+1*(0.45+0.3)+3*(0.6+0.3)+1*(3+0.3)+4*(1.6+0.3)+2*(1.3+0.3)+4*(1.8+0.3)+1*(1.2+0.3)+6*(1.8+0.3)+10*(0.9+0.3)+1*(1.8+0...
B63: E30 REINFORCEMENT - High tensile yield round bar reinforcement (standard) to BS 4449:
A64: Q | B64: 10mm diameter in columns | C64: =TAKEOFF!$H$3742 -> 4.551 | D64: t | E64: =RATES!$D$29 -> 14300 | F64: =C64*E64 -> 65079.3 | G64: 4.551
A66: R | B66: 20mm diameter in columns | C66: =TAKEOFF!$H$3745 -> 7.133 | D66: t | E66: =RATES!$D$32 -> 14300 | F66: =C66*E66 -> 102001.9 | G66: 7.133
A68: S | B68: 10mm diameter in beams (links) | C68: =TAKEOFF!$H$3748 -> 1.806 | D68: t | E68: =RATES!$D$29 -> 14300 | F68: =C68*E68 -> 25825.8 | G68: 1.806
A70: T | B70: 16mm diameter in beams | C70: =TAKEOFF!$H$3751 -> 1.248 | D70: t | E70: =RATES!$D$31 -> 14300 | F70: =C70*E70 -> 17846.4 | G70: 1.248
A72: U | B72: 20mm diameter in beams | C72: =TAKEOFF!$H$3754 -> 2.135 | D72: t | E72: =RATES!$D$32 -> 14300 | F72: =C72*E72 -> 30530.5 | G72: 2.135
A74: V | B74: 25mm diameter in beams | C74: =TAKEOFF!$H$3757 -> 5.507 | D74: t | E74: =RATES!$D$33 -> 14300 | F74: =C74*E74 -> 78750.1 | G74: 5.507
A76: W | B76: 10mm diameter in shear & lift walls (links) | C76: =TAKEOFF!$H$3761 -> 2.078 | D76: t | E76: =RATES!$D$29 -> 14300 | F76: =C76*E76 -> 29715.4 | G76: 1.442+0.636
A78: X | B78: 12mm diameter in shear, lift & ramp walls | C78: =TAKEOFF!$H$3765 -> 2.783 | D78: t | E78: =RATES!$D$30 -> 14300 | F78: =C78*E78 -> 39796.9 | G78: 1.917+0.866
A80: Y | B80: 20mm diameter in shear & lift walls | C80: =TAKEOFF!$H$3769 -> 10.224 | D80: t | E80: =RATES!$D$32 -> 14300 | F80: =C80*E80 -> 146203.2 | G80: 6.904+3.320
A82: Z | B82: 12mm diameter in stairs | C82: =TAKEOFF!$H$3772 -> 0.88 | D82: t | E82: =RATES!$D$30 -> 14300 | F82: =C82*E82 -> 12584 | G82: 0.880
A84: A | B84: 16mm diameter in stairs | C84: =TAKEOFF!$H$3775 -> 1.434 | D84: t | E84: =RATES!$D$31 -> 14300 | F84: =C84*E84 -> 20506.2 | G84: 1.434
A86: B | B86: 12mm diameter for suspended slab | C86: =TAKEOFF!$H$3778 -> 49.804 | D86: t | E86: =RATES!$D$30 -> 14300 | F86: =C86*E86 -> 712197.2 | G86: 49.804
A88: C | B88: 16mm diameter for suspended slab | C88: =TAKEOFF!$H$3781 -> 0.151 | D88: t | E88: =RATES!$D$31 -> 14300 | F88: =C88*E88 -> 2159.3 | G88: 0.151
B90: =B31 -> ELEMENT NO. 1: IN SITU CONCRETE/LARGE PRECAST CONCRETE | F90: =SUM(F33:F89) -> 2630954.4
B91: Carried to Bill Summary
B94: ELEMENT NO. 2: MASONRY
B96: F10 BRICK/BLOCK WALL - Solid sandcrete blockwork in cement and sand (1:4) mortar as described in:
A97: A | B97: 150mm thick wall | C97: =TAKEOFF!$H$3821 -> 1559.324 | D97: m2 | E97: =RATES!$D$46 -> 215 | F97: =C97*E97 -> 335254.66 | G97: 449.8*3.05+(8*1*(3.05-2.2)+15*0.9*(3.05-2.2)+20*0.75*(3.05-2.2)+1*0.7*(3.05-2.2)+3*1.2*(3.05-2.2)+3*1*(3.05-2.2)+2*1*(3.05-2.2)+1*0.9*(3.05-2.2)+1*1.5*(3.05-2.2)+2*0.9*(3.05-2.2)+4*0.75*(3.05-2.2)+1*0.45*(3.05-2.2)+3*0.6*(3.05-2.2)+1*3*(3.05-2.2)+...
A99: B | B99: 200mm thick wall | C99: =TAKEOFF!$H$3859 -> 173.631 | D99: m2 | E99: =RATES!$D$47 -> 265 | F99: =C99*E99 -> 46012.215 | G99: 50.1*3.05+(8*1*(3.05-2.2)+15*0.9*(3.05-2.2)+20*0.75*(3.05-2.2)+1*0.7*(3.05-2.2)+3*1.2*(3.05-2.2)+3*1*(3.05-2.2)+2*1*(3.05-2.2)+1*0.9*(3.05-2.2)+1*1.5*(3.05-2.2)+2*0.9*(3.05-2.2)+4*0.75*(3.05-2.2)+1*0.45*(3.05-2.2)+3*0.6*(3.05-2.2)+1*3*(3.05-2.2)+4...
B101: =B94 -> ELEMENT NO. 2: MASONRY | F101: =SUM(F96:F100) -> 381266.88
B102: Carried to Bill Summary
B105: ELEMENT NO. 4: WINDOWS/DOORS
B107: L20 DOORS - Supply and fix the following door assemblies complete with frames, ironmongery sets to steel doors and all accessories:
A108: A | B108: 1000mm x 2200mm 1-hour fire-rated galvanised steel single-leaf security door assembly (D2) | C108: =TAKEOFF!$H$3864 -> 8 | D108: nr | E108: =RATES!$D$75 -> 7800 | F108: =C108*E108 -> 62400 | G108: 8
A110: B | B110: 900mm x 2200mm single leaf timber panel door (D3) | C110: =TAKEOFF!$H$3867 -> 15 | D110: nr | E110: =RATES!$D$76 -> 3400 | F110: =C110*E110 -> 51000 | G110: 15
A112: C | B112: 750mm x 2200mm single leaf timber flush door (D6) | C112: =TAKEOFF!$H$3870 -> 20 | D112: nr | E112: =RATES!$D$79 -> 1900 | F112: =C112*E112 -> 38000 | G112: 20
A114: D | B114: 700mm x 2200mm single-leaf 2-hour fire-rated galvanised steel door (D7) | C114: =TAKEOFF!$H$3873 -> 1 | D114: nr | E114: =RATES!$D$80 -> 6800 | F114: =C114*E114 -> 6800 | G114: 1
A116: E | B116: 1200mm x 2200mm 1-hour fire-rated leaf-and-a-half galvanised steel security door assembly (D8) | C116: =TAKEOFF!$H$3876 -> 3 | D116: nr | E116: =RATES!$D$81 -> 9800 | F116: =C116*E116 -> 29400 | G116: 3
A118: F | B118: 1000mm x 2200mm 1-hour fire-rated galvanised steel single-leaf security door assembly - emergency stairs (ED1) | C118: =TAKEOFF!$H$3879 -> 3 | D118: nr | E118: =RATES!$D$82 -> 7200 | F118: =C118*E118 -> 21600 | G118: 3
A120: G | B120: 1000mm x 2200mm 1-hour fire-rated galvanised steel single-leaf security door with translucent glass panel (ED2) | C120: =TAKEOFF!$H$3882 -> 2 | D120: nr | E120: =RATES!$D$83 -> 8100 | F120: =C120*E120 -> 16200 | G120: 2
A122: H | B122: 900mm x 2200mm 1-hour fire-rated galvanised steel single-leaf security door assembly (D9) | C122: =TAKEOFF!$H$3885 -> 1 | D122: nr | E122: =RATES!$D$84 -> 6900 | F122: =C122*E122 -> 6900 | G122: 1
A124: J | B124: 1500mm x 2200mm timber bi-fold door (FD1) | C124: =TAKEOFF!$H$3888 -> 1 | D124: nr | E124: =RATES!$D$86 -> 4600 | F124: =C124*E124 -> 4600 | G124: 1
A126: K | B126: 900mm x 2200mm screw-fixed galvanised steel service access panel (M1) | C126: =TAKEOFF!$H$3891 -> 2 | D126: nr | E126: =RATES!$D$87 -> 2900 | F126: =C126*E126 -> 5800 | G126: 2
A128: L | B128: 750mm x 2200mm screw-fixed galvanised steel service access panel (M2) | C128: =TAKEOFF!$H$3894 -> 4 | D128: nr | E128: =RATES!$D$88 -> 2600 | F128: =C128*E128 -> 10400 | G128: 4
A130: M | B130: 450mm x 2200mm screw-fixed galvanised steel service access panel (M3) | C130: =TAKEOFF!$H$3897 -> 1 | D130: nr | E130: =RATES!$D$89 -> 1900 | F130: =C130*E130 -> 1900 | G130: 1
A132: N | B132: 600mm x 2200mm screw-fixed galvanised steel service access panel (M5) | C132: =TAKEOFF!$H$3900 -> 3 | D132: nr | E132: =RATES!$D$90 -> 2200 | F132: =C132*E132 -> 6600 | G132: 3
A134: P | B134: 3000mm x 2200mm 3-panel galvanised steel framed tempered glass sliding door (SD1) | C134: =TAKEOFF!$H$3903 -> 1 | D134: nr | E134: =RATES!$D$94 -> 14500 | F134: =C134*E134 -> 14500 | G134: 1
A136: Q | B136: 1600mm x 2200mm 2-panel galvanised steel framed tempered glass sliding door (SD2) | C136: =TAKEOFF!$H$3906 -> 4 | D136: nr | E136: =RATES!$D$95 -> 8800 | F136: =C136*E136 -> 35200 | G136: 4
A138: R | B138: 1300mm x 2200mm 2-panel galvanised steel framed tempered glass sliding door (SD3) | C138: =TAKEOFF!$H$3909 -> 2 | D138: nr | E138: =RATES!$D$96 -> 7600 | F138: =C138*E138 -> 15200 | G138: 2
A140: S | B140: 1800mm x 2200mm 2-panel galvanised steel framed tempered glass sliding door (SD4) | C140: =TAKEOFF!$H$3912 -> 4 | D140: nr | E140: =RATES!$D$97 -> 9300 | F140: =C140*E140 -> 37200 | G140: 4
A142: T | B142: 1200mm x 2200mm 2-panel galvanised steel framed tempered glass sliding door (SD5) | C142: =TAKEOFF!$H$3915 -> 1 | D142: nr | E142: =RATES!$D$98 -> 7200 | F142: =C142*E142 -> 7200 | G142: 1
A144: U | B144: 50mm x 150mm frames (to timber doors) | C144: =TAKEOFF!$H$3920 -> 188.4 | D144: m | E144: =RATES!$D$100 -> 125 | F144: =C144*E144 -> 23550 | G144: 15*(2*2.2+0.9)+20*(2*2.2+0.75)+1*(2*2.2+1.5)
A146: V | B146: 50mm x 12mm door stop | C146: =TAKEOFF!$H$3925 -> 188.4 | D146: m | E146: =RATES!$D$101 -> 28 | F146: =C146*E146 -> 5275.2 | G146: 15*(2*2.2+0.9)+20*(2*2.2+0.75)+1*(2*2.2+1.5)
B148: Ironmongery - Supply and fix the following approved ironmongery to hardwood with accompanying patented screws:
A149: W | B149: Pair 100mm brass butt hinges | C149: =TAKEOFF!$H$3929 -> 53 | D149: pr | E149: =RATES!$D$102 -> 125 | F149: =C149*E149 -> 6625 | G149: 53
A151: X | B151: Ordinary locks | C151: =TAKEOFF!$H$3932 -> 15 | D151: nr | E151: =RATES!$D$103 -> 480 | F151: =C151*E151 -> 7200 | G151: 15
A153: Y | B153: Approved high quality mortice indicator lock | C153: =TAKEOFF!$H$3935 -> 20 | D153: nr | E153: =RATES!$D$104 -> 560 | F153: =C153*E153 -> 11200 | G153: 20
B156: ALUMINIUM GLAZED WINDOWS - Supply and install Italian extruded aluminium glazed windows, ALCOA R50 series, powder coated aluminium profile, glazed with 6mm tinted reflective glass secured onto galvanized steel sub-frames, complete with all accessories as per Architect's detail:
A157: Z | B157: 2 bay alu. framed glass sliding window 1800mm x 1300mm (W2) | C157: =TAKEOFF!$H$3939 -> 6 | D157: nr | E157: =RATES!$D$109 -> 3603.6 | F157: =C157*E157 -> 21621.6 | G157: 6
A159: A | B159: 1 bay alu. framed glass awning window 900mm x 1300mm (W4) | C159: =TAKEOFF!$H$3942 -> 10 | D159: nr | E159: =RATES!$D$111 -> 1801.8 | F159: =C159*E159 -> 18018 | G159: 10
A161: B | B161: 2 bay alu. framed glass sliding window 1800mm x 1600mm (W7) | C161: =TAKEOFF!$H$3945 -> 1 | D161: nr | E161: =RATES!$D$114 -> 4435.2 | F161: =C161*E161 -> 4435.2 | G161: 1
A163: C | B163: 1 x 3 bay alu. framed glass awning window 1200mm x 1900mm (W8) | C163: =TAKEOFF!$H$3948 -> 3 | D163: nr | E163: =RATES!$D$115 -> 3511.2 | F163: =C163*E163 -> 10533.6 | G163: 3
A165: D | B165: 2 bay alu. framed glass sliding window 1200mm x 1150mm (W9) | C165: =TAKEOFF!$H$3951 -> 8 | D165: nr | E165: =RATES!$D$116 -> 2125.2 | F165: =C165*E165 -> 17001.6 | G165: 8
A167: E | B167: 2 bay alu. framed glass sliding window 1200mm x 1200mm (W10) | C167: =TAKEOFF!$H$3954 -> 1 | D167: nr | E167: =RATES!$D$117 -> 2217.6 | F167: =C167*E167 -> 2217.6 | G167: 1
A169: F | B169: 2 bay alu. framed glass sliding window 1500mm x 1300mm (W11) | C169: =TAKEOFF!$H$3957 -> 6 | D169: nr | E169: =RATES!$D$118 -> 3003 | F169: =C169*E169 -> 18018 | G169: 6
A171: G | B171: 2 bay alu. framed glass sliding window 1500mm x 1150mm (W12) | C171: =TAKEOFF!$H$3960 -> 3 | D171: nr | E171: =RATES!$D$119 -> 2656.5 | F171: =C171*E171 -> 7969.5 | G171: 3
A173: H | B173: 3 bay alu. framed glass awning window 2400mm x 1300mm (W13) | C173: =TAKEOFF!$H$3963 -> 1 | D173: nr | E173: =RATES!$D$120 -> 4804.8 | F173: =C173*E173 -> 4804.8 | G173: 1
A175: J | B175: 3 bay alu. framed glass sliding window 3000mm x 1600mm (W15) | C175: =TAKEOFF!$H$3966 -> 1 | D175: nr | E175: =RATES!$D$122 -> 7392 | F175: =C175*E175 -> 7392 | G175: 1
A177: K | B177: 2 x 3 alu. framed glass awning window 1800mm x 1900mm (W17) | C177: =TAKEOFF!$H$3969 -> 3 | D177: nr | E177: =RATES!$D$124 -> 5266.8 | F177: =C177*E177 -> 15800.4 | G177: 3
A179: L | B179: 1 bay alu. framed glass awning window 750mm x 1300mm (W18) | C179: =TAKEOFF!$H$3972 -> 1 | D179: nr | E179: =RATES!$D$125 -> 1501.5 | F179: =C179*E179 -> 1501.5 | G179: 1
A181: M | B181: 2 x 3 alu. framed glass awning window 1450mm x 1900mm (W20) | C181: =TAKEOFF!$H$3975 -> 1 | D181: nr | E181: =RATES!$D$127 -> 4242.7 | F181: =C181*E181 -> 4242.7 | G181: 1
A183: N | B183: 2 bay alu. framed glass sliding window 900mm x 600mm (HW1) | C183: =TAKEOFF!$H$3978 -> 12 | D183: nr | E183: =RATES!$D$128 -> 831.6 | F183: =C183*E183 -> 9979.2 | G183: 12
A185: P | B185: 2 bay alu. framed glass sliding window 750mm x 600mm (HW2) | C185: =TAKEOFF!$H$3981 -> 5 | D185: nr | E185: =RATES!$D$129 -> 693 | F185: =C185*E185 -> 3465 | G185: 5
A187: Q | B187: 2 bay alu. framed glass sliding window 600mm x 600mm (HW3) | C187: =TAKEOFF!$H$3984 -> 1 | D187: nr | E187: =RATES!$D$130 -> 554.4 | F187: =C187*E187 -> 554.4 | G187: 1
A189: R | B189: 2 bay alu. framed glass sliding window 1200mm x 600mm (HW4) | C189: =TAKEOFF!$H$3987 -> 1 | D189: nr | E189: =RATES!$D$131 -> 1108.8 | F189: =C189*E189 -> 1108.8 | G189: 1
...

Sheet 8TH FLR   
A1: ='PRELIMS & GEN. ITEMS'!A1 -> PROJECT: BLOCK N REDEVELOPMENT
A2: ='PRELIMS & GEN. ITEMS'!A2 -> LOCATION: KANESHIE
A3: ='PRELIMS & GEN. ITEMS'!A3 -> CLIENT: STATE HOUSING LIMITED
A4: ='PRELIMS & GEN. ITEMS'!A4 -> DATE:9/30/2026
A5: ITEM | B5: DESCRIPTION | C5: QTY | D5: UNIT | E5: RATE | F5: AMOUNT - GHC | G5: Measurement basis / calculation
B7: MAIN BUILDING
B9: EIGHTH FLOOR
B11: BILL SUMMARY
A13: A | B13: ELEMENT NO. 1: IN SITU CONCRETE/LARGE PRECAST CONCRETE | F13: =F94 -> 2628506.8
A15: B | B15: ELEMENT NO. 2: MASONRY | F15: =F105 -> 379547.96
A17: C | B17: ELEMENT NO. 4: WINDOWS/DOORS | F17: =F195 -> 576573.55
A19: D | B19: ELEMENT NO. 5: FLOOR FINISHES | F19: =F215 -> 345862.54
A21: E | B21: ELEMENT NO. 6: WALL FINISHES | F21: =F231 -> 311695.51
A23: F | B23: ELEMENT NO. 7: PAINTING AND DECORATING | F23: =F251 -> 185701.3
B25: =B9 -> EIGHTH FLOOR | E25: GHC | F25: =SUM(F13:F24) -> 4427887.7
B26: To Bill General Summary
B29: BILL NR. 11 - EIGHTH FLOOR
B31: ELEMENT NO. 1: IN SITU CONCRETE/LARGE PRECAST CONCRETE
B33: Vibrated in-situ concrete C40 as described in:
A34: A | B34: Suspended slab 250mm thick | C34: =TAKEOFF!$H$4212 -> 283.65 | D34: m3 | E34: =RATES!$D$22 -> 2310 | F34: =C34*E34 -> 655231.5 | G34: 1134.6*0.25
A36: B | B36: Beams (downstands below slab) | C36: =TAKEOFF!$H$4216 -> 19.831 | D36: m3 | E36: =RATES!$D$23 -> 2310 | F36: =C36*E36 -> 45809.61 | G36: 166.8*0.3*0.35+33.1*0.2*0.35
A38: C | B38: Columns | C38: =TAKEOFF!$H$4227 -> 40.545937 | D38: m3 | E38: =RATES!$D$21 -> 2310 | F38: =C38*E38 -> 93661.116 | G38: 5*0.75*0.5*3.05+1*0.75*0.5*3.05+2*0.75*0.5*3.05+1*0.75*0.5*3.05+3*1.2*0.3*3.05+6*1.2*0.3*3.05+1*1.2*0.3*3.05+15*1.2*0.3*3.05+1*(2.85*0.25+0.825*0.25)*3.05
A40: D | B40: Concrete wall - shear walls to main & emergency stair cores, 250mm thick | C40: =TAKEOFF!$H$4231 -> 36.31025 | D40: m3 | E40: =RATES!$D$20 -> 2310 | F40: =C40*E40 -> 83876.677 | G40: 22.05*3.05*0.25+25.57*3.05*0.25
A42: E | B42: Concrete wall - lift walls, 250mm thick | C42: =TAKEOFF!$H$4234 -> 16.641562 | D42: m3 | E42: =RATES!$D$20 -> 2310 | F42: =C42*E42 -> 38442.009 | G42: 21.825*3.05*0.25
A44: F | B44: Stairs | C44: =TAKEOFF!$H$4240 -> 11.182 | D44: m3 | E44: =RATES!$D$24 -> 2310 | F44: =C44*E44 -> 25830.42 | G44: (2.966*3.3/3.3+2.625)+(2.966*3.3/3.3+2.625)
A46: G | B46: Lintels 150 x 225mm over door and window openings | C46: =TAKEOFF!$H$4277 -> 6.8698125 | D46: m3 | E46: =RATES!$D$25 -> 1925 | F46: =C46*E46 -> 13224.389 | G46: (8*(1+0.3)+15*(0.9+0.3)+21*(0.75+0.3)+1*(0.7+0.3)+2*(1.2+0.3)+3*(1+0.3)+2*(1+0.3)+1*(0.9+0.3)+1*(1.5+0.3)+2*(0.9+0.3)+4*(0.75+0.3)+1*(0.45+0.3)+3*(0.6+0.3)+1*(3+0.3)+4*(1.6+0.3)+2*(1.3+0.3)+4*(1.8+0.3)+1*(1.2+0.3)+6*(1.8+0.3)+10*(0.9+0.3)+2*(1.8+0...
B48: E20 FORMWORK - Formwork as described to:
A49: H | B49: Soffits of suspended slab | C49: =TAKEOFF!$H$4281 -> 1134.6 | D49: m2 | E49: =RATES!$D$38 -> 165 | F49: =C49*E49 -> 187209 | G49: 1134.6
A51: J | B51: Edges of suspended slab 250mm high | C51: =TAKEOFF!$H$4284 -> 294.6 | D51: m | E51: =RATES!$D$40 -> 65 | F51: =C51*E51 -> 19149 | G51: 294.6
A53: K | B53: Sides and soffits of beams | C53: =TAKEOFF!$H$4288 -> 196.59 | D53: m2 | E53: =RATES!$D$39 -> 165 | F53: =C53*E53 -> 32437.35 | G53: 166.8*(2*0.35+0.3)+33.1*(2*0.35+0.2)
A55: L | B55: Columns | C55: =TAKEOFF!$H$4299 -> 321.3175 | D55: m2 | E55: =RATES!$D$37 -> 165 | F55: =C55*E55 -> 53017.387 | G55: 5*2*(0.75+0.5)*3.05+1*2*(0.75+0.5)*3.05+2*2*(0.75+0.5)*3.05+1*2*(0.75+0.5)*3.05+3*2*(1.2+0.3)*3.05+6*2*(1.2+0.3)*3.05+1*2*(1.2+0.3)*3.05+15*2*(1.2+0.3)*3.05+1*2*(2.85+1.075)*3.05
A57: M | B57: Concrete wall (both faces) | C57: =TAKEOFF!$H$4304 -> 423.6145 | D57: m2 | E57: =RATES!$D$36 -> 165 | F57: =C57*E57 -> 69896.393 | G57: 2*22.05*3.05+2*21.825*3.05+2*25.57*3.05
A59: N | B59: Soffits of stair flights, landings and risers | C59: =TAKEOFF!$H$4312 -> 66.5328 | D59: m2 | E59: =RATES!$D$42 -> 165 | F59: =C59*E59 -> 10977.912 | G59: (2*3.424*1.8+15.0+22*0.15*1.8)+(2*3.424*1.8+15.0+22*0.15*1.8)
A61: P | B61: Side and soffits of lintel / coping | C61: =TAKEOFF!$H$4349 -> 122.13 | D61: m2 | E61: =RATES!$D$43 -> 165 | F61: =C61*E61 -> 20151.45 | G61: (8*(1+0.3)+15*(0.9+0.3)+21*(0.75+0.3)+1*(0.7+0.3)+2*(1.2+0.3)+3*(1+0.3)+2*(1+0.3)+1*(0.9+0.3)+1*(1.5+0.3)+2*(0.9+0.3)+4*(0.75+0.3)+1*(0.45+0.3)+3*(0.6+0.3)+1*(3+0.3)+4*(1.6+0.3)+2*(1.3+0.3)+4*(1.8+0.3)+1*(1.2+0.3)+6*(1.8+0.3)+10*(0.9+0.3)+2*(1.8+0...
B65: E30 REINFORCEMENT - High tensile yield round bar reinforcement (standard) to BS 4449:
A66: Q | B66: 10mm diameter in columns | C66: =TAKEOFF!$H$4353 -> 4.509 | D66: t | E66: =RATES!$D$29 -> 14300 | F66: =C66*E66 -> 64478.7 | G66: 4.509
A68: R | B68: 20mm diameter in columns | C68: =TAKEOFF!$H$4356 -> 6.299 | D68: t | E68: =RATES!$D$32 -> 14300 | F68: =C68*E68 -> 90075.7 | G68: 6.299
A70: S | B70: 25mm diameter in columns | C70: =TAKEOFF!$H$4359 -> 0.624 | D70: t | E70: =RATES!$D$33 -> 14300 | F70: =C70*E70 -> 8923.2 | G70: 0.624
A72: T | B72: 10mm diameter in beams (links) | C72: =TAKEOFF!$H$4362 -> 1.806 | D72: t | E72: =RATES!$D$29 -> 14300 | F72: =C72*E72 -> 25825.8 | G72: 1.806
A74: U | B74: 16mm diameter in beams | C74: =TAKEOFF!$H$4365 -> 1.248 | D74: t | E74: =RATES!$D$31 -> 14300 | F74: =C74*E74 -> 17846.4 | G74: 1.248
A76: V | B76: 20mm diameter in beams | C76: =TAKEOFF!$H$4368 -> 2.135 | D76: t | E76: =RATES!$D$32 -> 14300 | F76: =C76*E76 -> 30530.5 | G76: 2.135
A78: W | B78: 25mm diameter in beams | C78: =TAKEOFF!$H$4371 -> 5.507 | D78: t | E78: =RATES!$D$33 -> 14300 | F78: =C78*E78 -> 78750.1 | G78: 5.507
A80: X | B80: 10mm diameter in shear & lift walls (links) | C80: =TAKEOFF!$H$4375 -> 2.078 | D80: t | E80: =RATES!$D$29 -> 14300 | F80: =C80*E80 -> 29715.4 | G80: 1.442+0.636
A82: Y | B82: 12mm diameter in shear, lift & ramp walls | C82: =TAKEOFF!$H$4379 -> 2.783 | D82: t | E82: =RATES!$D$30 -> 14300 | F82: =C82*E82 -> 39796.9 | G82: 1.917+0.866
A84: Z | B84: 20mm diameter in shear & lift walls | C84: =TAKEOFF!$H$4383 -> 10.224 | D84: t | E84: =RATES!$D$32 -> 14300 | F84: =C84*E84 -> 146203.2 | G84: 6.904+3.320
A86: A | B86: 12mm diameter in stairs | C86: =TAKEOFF!$H$4386 -> 0.88 | D86: t | E86: =RATES!$D$30 -> 14300 | F86: =C86*E86 -> 12584 | G86: 0.880
A88: B | B88: 16mm diameter in stairs | C88: =TAKEOFF!$H$4389 -> 1.434 | D88: t | E88: =RATES!$D$31 -> 14300 | F88: =C88*E88 -> 20506.2 | G88: 1.434
A90: C | B90: 12mm diameter for suspended slab | C90: =TAKEOFF!$H$4392 -> 49.804 | D90: t | E90: =RATES!$D$30 -> 14300 | F90: =C90*E90 -> 712197.2 | G90: 49.804
A92: D | B92: 16mm diameter for suspended slab | C92: =TAKEOFF!$H$4395 -> 0.151 | D92: t | E92: =RATES!$D$31 -> 14300 | F92: =C92*E92 -> 2159.3 | G92: 0.151
B94: =B31 -> ELEMENT NO. 1: IN SITU CONCRETE/LARGE PRECAST CONCRETE | F94: =SUM(F33:F93) -> 2628506.8
B95: Carried to Bill Summary
B98: ELEMENT NO. 2: MASONRY
B100: F10 BRICK/BLOCK WALL - Solid sandcrete blockwork in cement and sand (1:4) mortar as described in:
A101: A | B101: 150mm thick wall | C101: =TAKEOFF!$H$4435 -> 1542.5175 | D101: m2 | E101: =RATES!$D$46 -> 215 | F101: =C101*E101 -> 331641.26 | G101: 441.2*3.05+(8*1*(3.05-2.2)+15*0.9*(3.05-2.2)+21*0.75*(3.05-2.2)+1*0.7*(3.05-2.2)+2*1.2*(3.05-2.2)+3*1*(3.05-2.2)+2*1*(3.05-2.2)+1*0.9*(3.05-2.2)+1*1.5*(3.05-2.2)+2*0.9*(3.05-2.2)+4*0.75*(3.05-2.2)+1*0.45*(3.05-2.2)+3*0.6*(3.05-2.2)+1*3*(3.05-2.2)+...
A103: B | B103: 200mm thick wall | C103: =TAKEOFF!$H$4473 -> 180.78001 | D103: m2 | E103: =RATES!$D$47 -> 265 | F103: =C103*E103 -> 47906.703 | G103: 51.7*3.05+(8*1*(3.05-2.2)+15*0.9*(3.05-2.2)+21*0.75*(3.05-2.2)+1*0.7*(3.05-2.2)+2*1.2*(3.05-2.2)+3*1*(3.05-2.2)+2*1*(3.05-2.2)+1*0.9*(3.05-2.2)+1*1.5*(3.05-2.2)+2*0.9*(3.05-2.2)+4*0.75*(3.05-2.2)+1*0.45*(3.05-2.2)+3*0.6*(3.05-2.2)+1*3*(3.05-2.2)+4...
B105: =B98 -> ELEMENT NO. 2: MASONRY | F105: =SUM(F100:F104) -> 379547.96
B106: Carried to Bill Summary
B108: ELEMENT NO. 4: WINDOWS/DOORS
B110: L20 DOORS - Supply and fix the following door assemblies complete with frames, ironmongery sets to steel doors and all accessories:
A111: A | B111: 1000mm x 2200mm 1-hour fire-rated galvanised steel single-leaf security door assembly (D2) | C111: =TAKEOFF!$H$4478 -> 8 | D111: nr | E111: =RATES!$D$75 -> 7800 | F111: =C111*E111 -> 62400 | G111: 8
A113: B | B113: 900mm x 2200mm single leaf timber panel door (D3) | C113: =TAKEOFF!$H$4481 -> 15 | D113: nr | E113: =RATES!$D$76 -> 3400 | F113: =C113*E113 -> 51000 | G113: 15
A115: C | B115: 750mm x 2200mm single leaf timber flush door (D6) | C115: =TAKEOFF!$H$4484 -> 21 | D115: nr | E115: =RATES!$D$79 -> 1900 | F115: =C115*E115 -> 39900 | G115: 21
A117: D | B117: 700mm x 2200mm single-leaf 2-hour fire-rated galvanised steel door (D7) | C117: =TAKEOFF!$H$4487 -> 1 | D117: nr | E117: =RATES!$D$80 -> 6800 | F117: =C117*E117 -> 6800 | G117: 1
A119: E | B119: 1200mm x 2200mm 1-hour fire-rated leaf-and-a-half galvanised steel security door assembly (D8) | C119: =TAKEOFF!$H$4490 -> 2 | D119: nr | E119: =RATES!$D$81 -> 9800 | F119: =C119*E119 -> 19600 | G119: 2
A121: F | B121: 1000mm x 2200mm 1-hour fire-rated galvanised steel single-leaf security door assembly - emergency stairs (ED1) | C121: =TAKEOFF!$H$4493 -> 3 | D121: nr | E121: =RATES!$D$82 -> 7200 | F121: =C121*E121 -> 21600 | G121: 3
A123: G | B123: 1000mm x 2200mm 1-hour fire-rated galvanised steel single-leaf security door with translucent glass panel (ED2) | C123: =TAKEOFF!$H$4496 -> 2 | D123: nr | E123: =RATES!$D$83 -> 8100 | F123: =C123*E123 -> 16200 | G123: 2
A125: H | B125: 900mm x 2200mm 1-hour fire-rated galvanised steel single-leaf security door assembly (D9) | C125: =TAKEOFF!$H$4499 -> 1 | D125: nr | E125: =RATES!$D$84 -> 6900 | F125: =C125*E125 -> 6900 | G125: 1
A127: J | B127: 1500mm x 2200mm timber bi-fold door (FD1) | C127: =TAKEOFF!$H$4502 -> 1 | D127: nr | E127: =RATES!$D$86 -> 4600 | F127: =C127*E127 -> 4600 | G127: 1
A129: K | B129: 900mm x 2200mm screw-fixed galvanised steel service access panel (M1) | C129: =TAKEOFF!$H$4505 -> 2 | D129: nr | E129: =RATES!$D$87 -> 2900 | F129: =C129*E129 -> 5800 | G129: 2
A131: L | B131: 750mm x 2200mm screw-fixed galvanised steel service access panel (M2) | C131: =TAKEOFF!$H$4508 -> 4 | D131: nr | E131: =RATES!$D$88 -> 2600 | F131: =C131*E131 -> 10400 | G131: 4
A133: M | B133: 450mm x 2200mm screw-fixed galvanised steel service access panel (M3) | C133: =TAKEOFF!$H$4511 -> 1 | D133: nr | E133: =RATES!$D$89 -> 1900 | F133: =C133*E133 -> 1900 | G133: 1
A135: N | B135: 600mm x 2200mm screw-fixed galvanised steel service access panel (M5) | C135: =TAKEOFF!$H$4514 -> 3 | D135: nr | E135: =RATES!$D$90 -> 2200 | F135: =C135*E135 -> 6600 | G135: 3
A137: P | B137: 3000mm x 2200mm 3-panel galvanised steel framed tempered glass sliding door (SD1) | C137: =TAKEOFF!$H$4517 -> 1 | D137: nr | E137: =RATES!$D$94 -> 14500 | F137: =C137*E137 -> 14500 | G137: 1
A139: Q | B139: 1600mm x 2200mm 2-panel galvanised steel framed tempered glass sliding door (SD2) | C139: =TAKEOFF!$H$4520 -> 4 | D139: nr | E139: =RATES!$D$95 -> 8800 | F139: =C139*E139 -> 35200 | G139: 4
A141: R | B141: 1300mm x 2200mm 2-panel galvanised steel framed tempered glass sliding door (SD3) | C141: =TAKEOFF!$H$4523 -> 2 | D141: nr | E141: =RATES!$D$96 -> 7600 | F141: =C141*E141 -> 15200 | G141: 2
A143: S | B143: 1800mm x 2200mm 2-panel galvanised steel framed tempered glass sliding door (SD4) | C143: =TAKEOFF!$H$4526 -> 4 | D143: nr | E143: =RATES!$D$97 -> 9300 | F143: =C143*E143 -> 37200 | G143: 4
A145: T | B145: 1200mm x 2200mm 2-panel galvanised steel framed tempered glass sliding door (SD5) | C145: =TAKEOFF!$H$4529 -> 1 | D145: nr | E145: =RATES!$D$98 -> 7200 | F145: =C145*E145 -> 7200 | G145: 1
A147: U | B147: 50mm x 150mm frames (to timber doors) | C147: =TAKEOFF!$H$4534 -> 193.55 | D147: m | E147: =RATES!$D$100 -> 125 | F147: =C147*E147 -> 24193.75 | G147: 15*(2*2.2+0.9)+21*(2*2.2+0.75)+1*(2*2.2+1.5)
A149: V | B149: 50mm x 12mm door stop | C149: =TAKEOFF!$H$4539 -> 193.55 | D149: m | E149: =RATES!$D$101 -> 28 | F149: =C149*E149 -> 5419.4 | G149: 15*(2*2.2+0.9)+21*(2*2.2+0.75)+1*(2*2.2+1.5)
B151: Ironmongery - Supply and fix the following approved ironmongery to hardwood with accompanying patented screws:
A152: W | B152: Pair 100mm brass butt hinges | C152: =TAKEOFF!$H$4543 -> 54 | D152: pr | E152: =RATES!$D$102 -> 125 | F152: =C152*E152 -> 6750 | G152: 54
A154: X | B154: Ordinary locks | C154: =TAKEOFF!$H$4546 -> 15 | D154: nr | E154: =RATES!$D$103 -> 480 | F154: =C154*E154 -> 7200 | G154: 15
A156: Y | B156: Approved high quality mortice indicator lock | C156: =TAKEOFF!$H$4549 -> 21 | D156: nr | E156: =RATES!$D$104 -> 560 | F156: =C156*E156 -> 11760 | G156: 21
B160: ALUMINIUM GLAZED WINDOWS - Supply and install Italian extruded aluminium glazed windows, ALCOA R50 series, powder coated aluminium profile, glazed with 6mm tinted reflective glass secured onto galvanized steel sub-frames, complete with all accessories as per Architect's detail:
A161: Z | B161: 2 bay alu. framed glass sliding window 1800mm x 1300mm (W2) | C161: =TAKEOFF!$H$4553 -> 6 | D161: nr | E161: =RATES!$D$109 -> 3603.6 | F161: =C161*E161 -> 21621.6 | G161: 6
A163: A | B163: 1 bay alu. framed glass awning window 900mm x 1300mm (W4) | C163: =TAKEOFF!$H$4556 -> 10 | D163: nr | E163: =RATES!$D$111 -> 1801.8 | F163: =C163*E163 -> 18018 | G163: 10
A165: B | B165: 2 bay alu. framed glass sliding window 1800mm x 1600mm (W7) | C165: =TAKEOFF!$H$4559 -> 2 | D165: nr | E165: =RATES!$D$114 -> 4435.2 | F165: =C165*E165 -> 8870.4 | G165: 2
A167: C | B167: 1 x 3 bay alu. framed glass awning window 1200mm x 1900mm (W8) | C167: =TAKEOFF!$H$4562 -> 3 | D167: nr | E167: =RATES!$D$115 -> 3511.2 | F167: =C167*E167 -> 10533.6 | G167: 3
A169: D | B169: 2 bay alu. framed glass sliding window 1200mm x 1150mm (W9) | C169: =TAKEOFF!$H$4565 -> 8 | D169: nr | E169: =RATES!$D$116 -> 2125.2 | F169: =C169*E169 -> 17001.6 | G169: 8
A171: E | B171: 2 bay alu. framed glass sliding window 1200mm x 1200mm (W10) | C171: =TAKEOFF!$H$4568 -> 1 | D171: nr | E171: =RATES!$D$117 -> 2217.6 | F171: =C171*E171 -> 2217.6 | G171: 1
A173: F | B173: 2 bay alu. framed glass sliding window 1500mm x 1300mm (W11) | C173: =TAKEOFF!$H$4571 -> 6 | D173: nr | E173: =RATES!$D$118 -> 3003 | F173: =C173*E173 -> 18018 | G173: 6
A175: G | B175: 2 bay alu. framed glass sliding window 1500mm x 1150mm (W12) | C175: =TAKEOFF!$H$4574 -> 4 | D175: nr | E175: =RATES!$D$119 -> 2656.5 | F175: =C175*E175 -> 10626 | G175: 4
A177: H | B177: 3 bay alu. framed glass awning window 2400mm x 1300mm (W13) | C177: =TAKEOFF!$H$4577 -> 1 | D177: nr | E177: =RATES!$D$120 -> 4804.8 | F177: =C177*E177 -> 4804.8 | G177: 1
A179: J | B179: 3 bay alu. framed glass sliding window 3000mm x 1600mm (W15) | C179: =TAKEOFF!$H$4580 -> 1 | D179: nr | E179: =RATES!$D$122 -> 7392 | F179: =C179*E179 -> 7392 | G179: 1
A181: K | B181: 2 x 3 alu. framed glass awning window 1800mm x 1900mm (W17) | C181: =TAKEOFF!$H$4583 -> 3 | D181: nr | E181: =RATES!$D$124 -> 5266.8 | F181: =C181*E181 -> 15800.4 | G181: 3
A183: L | B183: 1 bay alu. framed glass awning window 750mm x 1300mm (W18) | C183: =TAKEOFF!$H$4586 -> 1 | D183: nr | E183: =RATES!$D$125 -> 1501.5 | F183: =C183*E183 -> 1501.5 | G183: 1
A185: M | B185: 2 x 3 alu. framed glass awning window 1450mm x 1900mm (W20) | C185: =TAKEOFF!$H$4589 -> 1 | D185: nr | E185: =RATES!$D$127 -> 4242.7 | F185: =C185*E185 -> 4242.7 | G185: 1
A187: N | B187: 2 bay alu. framed glass sliding window 900mm x 600mm (HW1) | C187: =TAKEOFF!$H$4592 -> 13 | D187: nr | E187: =RATES!$D$128 -> 831.6 | F187: =C187*E187 -> 10810.8 | G187: 13
A189: P | B189: 2 bay alu. framed glass sliding window 750mm x 600mm (HW2) | C189: =TAKEOFF!$H$4595 -> 5 | D189: nr | E189: =RATES!$D$129 -> 693 | F189: =C189*E189 -> 3465 | G189: 5
A191: Q | B191: 2 bay alu. framed glass sliding window 600mm x 600mm (HW3) | C191: =TAKEOFF!$H$4598 -> 2 | D191: nr | E191: =RATES!$D$130 -> 554.4 | F191: =C191*E191 -> 1108.8 | G191: 2
...

Sheet 9TH FLR    
A1: ='PRELIMS & GEN. ITEMS'!A1 -> PROJECT: BLOCK N REDEVELOPMENT
A2: ='PRELIMS & GEN. ITEMS'!A2 -> LOCATION: KANESHIE
A3: ='PRELIMS & GEN. ITEMS'!A3 -> CLIENT: STATE HOUSING LIMITED
A4: ='PRELIMS & GEN. ITEMS'!A4 -> DATE:9/30/2026
A5: ITEM | B5: DESCRIPTION | C5: QTY | D5: UNIT | E5: RATE | F5: AMOUNT - GHC | G5: Measurement basis / calculation
B7: MAIN BUILDING
B9: NINTH FLOOR
B11: BILL SUMMARY
A13: A | B13: ELEMENT NO. 1: IN SITU CONCRETE/LARGE PRECAST CONCRETE | F13: =F92 -> 2564952.1
A15: B | B15: ELEMENT NO. 2: MASONRY | F15: =F102 -> 310127.3
A17: C | B17: ELEMENT NO. 3: WATERPROOFING | F17: =F112 -> 79963.8
A19: D | B19: ELEMENT NO. 4: WINDOWS/DOORS | F19: =F193 -> 357735.95
A21: E | B21: ELEMENT NO. 5: FLOOR FINISHES | F21: =F216 -> 357394.34
A23: F | B23: ELEMENT NO. 6: WALL FINISHES | F23: =F233 -> 272188.02
A25: G | B25: ELEMENT NO. 7: PAINTING AND DECORATING | F25: =F254 -> 154620.02
B27: =B9 -> NINTH FLOOR | E27: GHC | F27: =SUM(F13:F26) -> 4096981.5
B28: To Bill General Summary
B31: BILL NR. 12 - NINTH FLOOR
B33: ELEMENT NO. 1: IN SITU CONCRETE/LARGE PRECAST CONCRETE
B35: Vibrated in-situ concrete C40 as described in:
A36: A | B36: Suspended slab 250mm thick | C36: =TAKEOFF!$H$4826 -> 283.6 | D36: m3 | E36: =RATES!$D$22 -> 2310 | F36: =C36*E36 -> 655116 | G36: 1134.4*0.25
A38: B | B38: Beams (downstands below slab) | C38: =TAKEOFF!$H$4830 -> 21.8995 | D38: m3 | E38: =RATES!$D$23 -> 2310 | F38: =C38*E38 -> 50587.845 | G38: 186.5*0.3*0.35+33.1*0.2*0.35
A40: C | B40: Columns | C40: =TAKEOFF!$H$4838 -> 28.731 | D40: m3 | E40: =RATES!$D$21 -> 2310 | F40: =C40*E40 -> 66368.61 | G40: 1*0.75*0.5*3.05+2*0.75*0.5*3.05+1*0.75*0.5*3.05+6*1.2*0.3*3.05+1*1.2*0.3*3.05+15*1.2*0.3*3.05
A42: D | B42: Concrete wall - shear walls to main & emergency stair cores, 250mm thick | C42: =TAKEOFF!$H$4842 -> 36.31025 | D42: m3 | E42: =RATES!$D$20 -> 2310 | F42: =C42*E42 -> 83876.677 | G42: 22.05*3.05*0.25+25.57*3.05*0.25
A44: E | B44: Concrete wall - lift walls, 250mm thick | C44: =TAKEOFF!$H$4845 -> 16.641562 | D44: m3 | E44: =RATES!$D$20 -> 2310 | F44: =C44*E44 -> 38442.009 | G44: 21.825*3.05*0.25
A46: F | B46: Stairs | C46: =TAKEOFF!$H$4851 -> 11.182 | D46: m3 | E46: =RATES!$D$24 -> 2310 | F46: =C46*E46 -> 25830.42 | G46: (2.966*3.3/3.3+2.625)+(2.966*3.3/3.3+2.625)
A48: G | B48: Lintels 150 x 225mm over door and window openings | C48: =TAKEOFF!$H$4883 -> 4.222125 | D48: m3 | E48: =RATES!$D$25 -> 1925 | F48: =C48*E48 -> 8127.5906 | G48: (4*(1+0.3)+8*(0.9+0.3)+17*(0.75+0.3)+1*(0.7+0.3)+2*(1.2+0.3)+2*(1+0.3)+2*(1+0.3)+1*(0.9+0.3)+2*(0.9+0.3)+4*(0.75+0.3)+1*(0.45+0.3)+3*(0.6+0.3)+1*(3+0.3)+2*(1.6+0.3)+1*(1.3+0.3)+2*(1.8+0.3)+3*(1.8+0.3)+6*(0.9+0.3)+1*(1.8+0.3)+1*(1.2+0.3)+5*(1.2+0.3...
B50: E20 FORMWORK - Formwork as described to:
A51: H | B51: Soffits of suspended slab | C51: =TAKEOFF!$H$4887 -> 1134.4 | D51: m2 | E51: =RATES!$D$38 -> 165 | F51: =C51*E51 -> 187176 | G51: 1134.4
A53: J | B53: Edges of suspended slab 250mm high | C53: =TAKEOFF!$H$4890 -> 294.5 | D53: m | E53: =RATES!$D$40 -> 65 | F53: =C53*E53 -> 19142.5 | G53: 294.5
A55: K | B55: Sides and soffits of beams | C55: =TAKEOFF!$H$4894 -> 216.29 | D55: m2 | E55: =RATES!$D$39 -> 165 | F55: =C55*E55 -> 35687.85 | G55: 186.5*(2*0.35+0.3)+33.1*(2*0.35+0.2)
A57: L | B57: Columns | C57: =TAKEOFF!$H$4902 -> 231.8 | D57: m2 | E57: =RATES!$D$37 -> 165 | F57: =C57*E57 -> 38247 | G57: 1*2*(0.75+0.5)*3.05+2*2*(0.75+0.5)*3.05+1*2*(0.75+0.5)*3.05+6*2*(1.2+0.3)*3.05+1*2*(1.2+0.3)*3.05+15*2*(1.2+0.3)*3.05
A59: M | B59: Concrete wall (both faces) | C59: =TAKEOFF!$H$4907 -> 423.6145 | D59: m2 | E59: =RATES!$D$36 -> 165 | F59: =C59*E59 -> 69896.393 | G59: 2*22.05*3.05+2*21.825*3.05+2*25.57*3.05
A61: N | B61: Soffits of stair flights, landings and risers | C61: =TAKEOFF!$H$4915 -> 66.5328 | D61: m2 | E61: =RATES!$D$42 -> 165 | F61: =C61*E61 -> 10977.912 | G61: (2*3.424*1.8+15.0+22*0.15*1.8)+(2*3.424*1.8+15.0+22*0.15*1.8)
A63: P | B63: Side and soffits of lintel / coping | C63: =TAKEOFF!$H$4947 -> 75.06 | D63: m2 | E63: =RATES!$D$43 -> 165 | F63: =C63*E63 -> 12384.9 | G63: (4*(1+0.3)+8*(0.9+0.3)+17*(0.75+0.3)+1*(0.7+0.3)+2*(1.2+0.3)+2*(1+0.3)+2*(1+0.3)+1*(0.9+0.3)+2*(0.9+0.3)+4*(0.75+0.3)+1*(0.45+0.3)+3*(0.6+0.3)+1*(3+0.3)+2*(1.6+0.3)+1*(1.3+0.3)+2*(1.8+0.3)+3*(1.8+0.3)+6*(0.9+0.3)+1*(1.8+0.3)+1*(1.2+0.3)+5*(1.2+0.3...
B65: E30 REINFORCEMENT - High tensile yield round bar reinforcement (standard) to BS 4449:
A66: Q | B66: 10mm diameter in columns | C66: =TAKEOFF!$H$4951 -> 3.235 | D66: t | E66: =RATES!$D$29 -> 14300 | F66: =C66*E66 -> 46260.5 | G66: 3.235
A68: R | B68: 20mm diameter in columns | C68: =TAKEOFF!$H$4954 -> 5.111 | D68: t | E68: =RATES!$D$32 -> 14300 | F68: =C68*E68 -> 73087.3 | G68: 5.111
A70: S | B70: 10mm diameter in beams (links) | C70: =TAKEOFF!$H$4957 -> 2.032 | D70: t | E70: =RATES!$D$29 -> 14300 | F70: =C70*E70 -> 29057.6 | G70: 2.032
A72: T | B72: 16mm diameter in beams | C72: =TAKEOFF!$H$4960 -> 1.163 | D72: t | E72: =RATES!$D$31 -> 14300 | F72: =C72*E72 -> 16630.9 | G72: 1.163
A74: U | B74: 20mm diameter in beams | C74: =TAKEOFF!$H$4963 -> 2.461 | D74: t | E74: =RATES!$D$32 -> 14300 | F74: =C74*E74 -> 35192.3 | G74: 2.461
A76: V | B76: 25mm diameter in beams | C76: =TAKEOFF!$H$4966 -> 6.491 | D76: t | E76: =RATES!$D$33 -> 14300 | F76: =C76*E76 -> 92821.3 | G76: 6.491
A78: W | B78: 10mm diameter in shear & lift walls (links) | C78: =TAKEOFF!$H$4970 -> 2.078 | D78: t | E78: =RATES!$D$29 -> 14300 | F78: =C78*E78 -> 29715.4 | G78: 1.442+0.636
A80: X | B80: 12mm diameter in shear, lift & ramp walls | C80: =TAKEOFF!$H$4974 -> 3.061 | D80: t | E80: =RATES!$D$30 -> 14300 | F80: =C80*E80 -> 43772.3 | G80: 2.109+0.952
A82: Y | B82: 20mm diameter in shear & lift walls | C82: =TAKEOFF!$H$4978 -> 10.224 | D82: t | E82: =RATES!$D$32 -> 14300 | F82: =C82*E82 -> 146203.2 | G82: 6.904+3.320
A84: Z | B84: 12mm diameter in stairs | C84: =TAKEOFF!$H$4981 -> 0.88 | D84: t | E84: =RATES!$D$30 -> 14300 | F84: =C84*E84 -> 12584 | G84: 0.880
A86: A | B86: 16mm diameter in stairs | C86: =TAKEOFF!$H$4984 -> 1.434 | D86: t | E86: =RATES!$D$31 -> 14300 | F86: =C86*E86 -> 20506.2 | G86: 1.434
A88: B | B88: 12mm diameter for suspended slab | C88: =TAKEOFF!$H$4987 -> 50.007 | D88: t | E88: =RATES!$D$30 -> 14300 | F88: =C88*E88 -> 715100.1 | G88: 50.007
A90: C | B90: 16mm diameter for suspended slab | C90: =TAKEOFF!$H$4990 -> 0.151 | D90: t | E90: =RATES!$D$31 -> 14300 | F90: =C90*E90 -> 2159.3 | G90: 0.151
B92: =B33 -> ELEMENT NO. 1: IN SITU CONCRETE/LARGE PRECAST CONCRETE | F92: =SUM(F35:F91) -> 2564952.1
B93: Carried to Bill Summary
B95: ELEMENT NO. 2: MASONRY
B97: F10 BRICK/BLOCK WALL - Solid sandcrete blockwork in cement and sand (1:4) mortar as described in:
A98: A | B98: 150mm thick wall | C98: =TAKEOFF!$H$5025 -> 1336.386 | D98: m2 | E98: =RATES!$D$46 -> 215 | F98: =C98*E98 -> 287322.99 | G98: 397.2*3.05+(4*1*(3.05-2.2)+8*0.9*(3.05-2.2)+17*0.75*(3.05-2.2)+1*0.7*(3.05-2.2)+2*1.2*(3.05-2.2)+2*1*(3.05-2.2)+2*1*(3.05-2.2)+1*0.9*(3.05-2.2)+2*0.9*(3.05-2.2)+4*0.75*(3.05-2.2)+1*0.45*(3.05-2.2)+3*0.6*(3.05-2.2)+1*3*(3.05-2.2)+2*1.6*(3.05-2.2)+1...
A100: B | B100: 200mm thick wall | C100: =TAKEOFF!$H$5058 -> 86.054 | D100: m2 | E100: =RATES!$D$47 -> 265 | F100: =C100*E100 -> 22804.31 | G100: 25.6*3.05+(4*1*(3.05-2.2)+8*0.9*(3.05-2.2)+17*0.75*(3.05-2.2)+1*0.7*(3.05-2.2)+2*1.2*(3.05-2.2)+2*1*(3.05-2.2)+2*1*(3.05-2.2)+1*0.9*(3.05-2.2)+2*0.9*(3.05-2.2)+4*0.75*(3.05-2.2)+1*0.45*(3.05-2.2)+3*0.6*(3.05-2.2)+1*3*(3.05-2.2)+2*1.6*(3.05-2.2)+1*...
B102: =B95 -> ELEMENT NO. 2: MASONRY | F102: =SUM(F97:F101) -> 310127.3
B103: Carried to Bill Summary
B105: ELEMENT NO. 3: WATERPROOFING
B107: WATERPROOFING
A108: A | B108: Liquid/applied waterproofing to roofs, terraces and wet external areas | C108: =TAKEOFF!$H$5063 -> 337.4 | D108: m2 | E108: =RATES!$D$68 -> 165 | F108: =C108*E108 -> 55671 | G108: 337.4
A110: B | B110: Protective cement-sand screed over waterproofing | C110: =TAKEOFF!$H$5066 -> 337.4 | D110: m2 | E110: =RATES!$D$69 -> 72 | F110: =C110*E110 -> 24292.8 | G110: 337.4
B112: =B105 -> ELEMENT NO. 3: WATERPROOFING | F112: =SUM(F107:F111) -> 79963.8
B113: Carried to Bill Summary
B116: ELEMENT NO. 4: WINDOWS/DOORS
B118: L20 DOORS - Supply and fix the following door assemblies complete with frames, ironmongery sets to steel doors and all accessories:
A119: A | B119: 1000mm x 2200mm 1-hour fire-rated galvanised steel single-leaf security door assembly (D2) | C119: =TAKEOFF!$H$5071 -> 4 | D119: nr | E119: =RATES!$D$75 -> 7800 | F119: =C119*E119 -> 31200 | G119: 4
A121: B | B121: 900mm x 2200mm single leaf timber panel door (D3) | C121: =TAKEOFF!$H$5074 -> 8 | D121: nr | E121: =RATES!$D$76 -> 3400 | F121: =C121*E121 -> 27200 | G121: 8
A123: C | B123: 750mm x 2200mm single leaf timber flush door (D6) | C123: =TAKEOFF!$H$5077 -> 17 | D123: nr | E123: =RATES!$D$79 -> 1900 | F123: =C123*E123 -> 32300 | G123: 17
A125: D | B125: 700mm x 2200mm single-leaf 2-hour fire-rated galvanised steel door (D7) | C125: =TAKEOFF!$H$5080 -> 1 | D125: nr | E125: =RATES!$D$80 -> 6800 | F125: =C125*E125 -> 6800 | G125: 1
A127: E | B127: 1200mm x 2200mm 1-hour fire-rated leaf-and-a-half galvanised steel security door assembly (D8) | C127: =TAKEOFF!$H$5083 -> 2 | D127: nr | E127: =RATES!$D$81 -> 9800 | F127: =C127*E127 -> 19600 | G127: 2
A129: F | B129: 1000mm x 2200mm 1-hour fire-rated galvanised steel single-leaf security door assembly - emergency stairs (ED1) | C129: =TAKEOFF!$H$5086 -> 2 | D129: nr | E129: =RATES!$D$82 -> 7200 | F129: =C129*E129 -> 14400 | G129: 2
A131: G | B131: 1000mm x 2200mm 1-hour fire-rated galvanised steel single-leaf security door with translucent glass panel (ED2) | C131: =TAKEOFF!$H$5089 -> 2 | D131: nr | E131: =RATES!$D$83 -> 8100 | F131: =C131*E131 -> 16200 | G131: 2
A133: H | B133: 900mm x 2200mm 1-hour fire-rated galvanised steel single-leaf security door assembly (D9) | C133: =TAKEOFF!$H$5092 -> 1 | D133: nr | E133: =RATES!$D$84 -> 6900 | F133: =C133*E133 -> 6900 | G133: 1
A135: J | B135: 900mm x 2200mm screw-fixed galvanised steel service access panel (M1) | C135: =TAKEOFF!$H$5095 -> 2 | D135: nr | E135: =RATES!$D$87 -> 2900 | F135: =C135*E135 -> 5800 | G135: 2
A137: K | B137: 750mm x 2200mm screw-fixed galvanised steel service access panel (M2) | C137: =TAKEOFF!$H$5098 -> 4 | D137: nr | E137: =RATES!$D$88 -> 2600 | F137: =C137*E137 -> 10400 | G137: 4
A139: L | B139: 450mm x 2200mm screw-fixed galvanised steel service access panel (M3) | C139: =TAKEOFF!$H$5101 -> 1 | D139: nr | E139: =RATES!$D$89 -> 1900 | F139: =C139*E139 -> 1900 | G139: 1
A141: M | B141: 600mm x 2200mm screw-fixed galvanised steel service access panel (M5) | C141: =TAKEOFF!$H$5104 -> 3 | D141: nr | E141: =RATES!$D$90 -> 2200 | F141: =C141*E141 -> 6600 | G141: 3
A143: N | B143: 3000mm x 2200mm 3-panel galvanised steel framed tempered glass sliding door (SD1) | C143: =TAKEOFF!$H$5107 -> 1 | D143: nr | E143: =RATES!$D$94 -> 14500 | F143: =C143*E143 -> 14500 | G143: 1
A145: P | B145: 1600mm x 2200mm 2-panel galvanised steel framed tempered glass sliding door (SD2) | C145: =TAKEOFF!$H$5110 -> 2 | D145: nr | E145: =RATES!$D$95 -> 8800 | F145: =C145*E145 -> 17600 | G145: 2
A147: Q | B147: 1300mm x 2200mm 2-panel galvanised steel framed tempered glass sliding door (SD3) | C147: =TAKEOFF!$H$5113 -> 1 | D147: nr | E147: =RATES!$D$96 -> 7600 | F147: =C147*E147 -> 7600 | G147: 1
A149: R | B149: 1800mm x 2200mm 2-panel galvanised steel framed tempered glass sliding door (SD4) | C149: =TAKEOFF!$H$5116 -> 2 | D149: nr | E149: =RATES!$D$97 -> 9300 | F149: =C149*E149 -> 18600 | G149: 2
A151: S | B151: 50mm x 150mm frames (to timber doors) | C151: =TAKEOFF!$H$5120 -> 129.95 | D151: m | E151: =RATES!$D$100 -> 125 | F151: =C151*E151 -> 16243.75 | G151: 8*(2*2.2+0.9)+17*(2*2.2+0.75)
A153: T | B153: 50mm x 12mm door stop | C153: =TAKEOFF!$H$5124 -> 129.95 | D153: m | E153: =RATES!$D$101 -> 28 | F153: =C153*E153 -> 3638.6 | G153: 8*(2*2.2+0.9)+17*(2*2.2+0.75)
B157: Ironmongery - Supply and fix the following approved ironmongery to hardwood with accompanying patented screws:
A158: U | B158: Pair 100mm brass butt hinges | C158: =TAKEOFF!$H$5128 -> 38 | D158: pr | E158: =RATES!$D$102 -> 125 | F158: =C158*E158 -> 4750 | G158: 38
A160: V | B160: Ordinary locks | C160: =TAKEOFF!$H$5131 -> 8 | D160: nr | E160: =RATES!$D$103 -> 480 | F160: =C160*E160 -> 3840 | G160: 8
A162: W | B162: Approved high quality mortice indicator lock | C162: =TAKEOFF!$H$5134 -> 17 | D162: nr | E162: =RATES!$D$104 -> 560 | F162: =C162*E162 -> 9520 | G162: 17
B164: ALUMINIUM GLAZED WINDOWS - Supply and install Italian extruded aluminium glazed windows, ALCOA R50 series, powder coated aluminium profile, glazed with 6mm tinted reflective glass secured onto galvanized steel sub-frames, complete with all accessories as per Architect's detail:
A165: X | B165: 2 bay alu. framed glass sliding window 1800mm x 1300mm (W2) | C165: =TAKEOFF!$H$5138 -> 3 | D165: nr | E165: =RATES!$D$109 -> 3603.6 | F165: =C165*E165 -> 10810.8 | G165: 3
A167: Y | B167: 1 bay alu. framed glass awning window 900mm x 1300mm (W4) | C167: =TAKEOFF!$H$5141 -> 6 | D167: nr | E167: =RATES!$D$111 -> 1801.8 | F167: =C167*E167 -> 10810.8 | G167: 6
A169: Z | B169: 2 bay alu. framed glass sliding window 1800mm x 1600mm (W7) | C169: =TAKEOFF!$H$5144 -> 1 | D169: nr | E169: =RATES!$D$114 -> 4435.2 | F169: =C169*E169 -> 4435.2 | G169: 1
A171: A | B171: 1 x 3 bay alu. framed glass awning window 1200mm x 1900mm (W8) | C171: =TAKEOFF!$H$5147 -> 1 | D171: nr | E171: =RATES!$D$115 -> 3511.2 | F171: =C171*E171 -> 3511.2 | G171: 1
A173: B | B173: 2 bay alu. framed glass sliding window 1200mm x 1150mm (W9) | C173: =TAKEOFF!$H$5150 -> 5 | D173: nr | E173: =RATES!$D$116 -> 2125.2 | F173: =C173*E173 -> 10626 | G173: 5
A175: C | B175: 2 bay alu. framed glass sliding window 1200mm x 1200mm (W10) | C175: =TAKEOFF!$H$5153 -> 1 | D175: nr | E175: =RATES!$D$117 -> 2217.6 | F175: =C175*E175 -> 2217.6 | G175: 1
A177: D | B177: 2 bay alu. framed glass sliding window 1500mm x 1300mm (W11) | C177: =TAKEOFF!$H$5156 -> 3 | D177: nr | E177: =RATES!$D$118 -> 3003 | F177: =C177*E177 -> 9009 | G177: 3
A179: E | B179: 2 bay alu. framed glass sliding window 1500mm x 1150mm (W12) | C179: =TAKEOFF!$H$5159 -> 2 | D179: nr | E179: =RATES!$D$119 -> 2656.5 | F179: =C179*E179 -> 5313 | G179: 2
A181: F | B181: 3 bay alu. framed glass sliding window 3000mm x 1600mm (W15) | C181: =TAKEOFF!$H$5162 -> 1 | D181: nr | E181: =RATES!$D$122 -> 7392 | F181: =C181*E181 -> 7392 | G181: 1
A183: G | B183: 2 x 3 alu. framed glass awning window 1800mm x 1900mm (W17) | C183: =TAKEOFF!$H$5165 -> 1 | D183: nr | E183: =RATES!$D$124 -> 5266.8 | F183: =C183*E183 -> 5266.8 | G183: 1
A185: H | B185: 2 bay alu. framed glass sliding window 900mm x 600mm (HW1) | C185: =TAKEOFF!$H$5168 -> 10 | D185: nr | E185: =RATES!$D$128 -> 831.6 | F185: =C185*E185 -> 8316 | G185: 10
A187: J | B187: 2 bay alu. framed glass sliding window 750mm x 600mm (HW2) | C187: =TAKEOFF!$H$5171 -> 4 | D187: nr | E187: =RATES!$D$129 -> 693 | F187: =C187*E187 -> 2772 | G187: 4
...

Sheet 10TH FLR   
A1: ='PRELIMS & GEN. ITEMS'!A1 -> PROJECT: BLOCK N REDEVELOPMENT
A2: ='PRELIMS & GEN. ITEMS'!A2 -> LOCATION: KANESHIE
A3: ='PRELIMS & GEN. ITEMS'!A3 -> CLIENT: STATE HOUSING LIMITED
A4: ='PRELIMS & GEN. ITEMS'!A4 -> DATE:9/30/2026
A5: ITEM | B5: DESCRIPTION | C5: QTY | D5: UNIT | E5: RATE | F5: AMOUNT - GHC | G5: Measurement basis / calculation
B7: MAIN BUILDING
B9: TENTH FLOOR
B11: BILL SUMMARY
A13: A | B13: ELEMENT NO. 1: IN SITU CONCRETE/LARGE PRECAST CONCRETE | F13: =F89 -> 2042424.5
A15: B | B15: ELEMENT NO. 2: MASONRY | F15: =F100 -> 293194.08
A17: C | B17: ELEMENT NO. 4: WINDOWS/DOORS | F17: =F187 -> 451212.8
A19: D | B19: ELEMENT NO. 5: FLOOR FINISHES | F19: =F208 -> 264471.94
A21: E | B21: ELEMENT NO. 6: WALL FINISHES | F21: =F225 -> 235040.25
A23: F | B23: ELEMENT NO. 7: PAINTING AND DECORATING | F23: =F246 -> 140426.27
B25: =B9 -> TENTH FLOOR | E25: GHC | F25: =SUM(F13:F24) -> 3426769.9
B26: To Bill General Summary
B28: BILL NR. 13 - TENTH FLOOR
B30: ELEMENT NO. 1: IN SITU CONCRETE/LARGE PRECAST CONCRETE
B32: Vibrated in-situ concrete C40 as described in:
A33: A | B33: Suspended slab 250mm thick | C33: =TAKEOFF!$H$5384 -> 217.1 | D33: m3 | E33: =RATES!$D$22 -> 2310 | F33: =C33*E33 -> 501501 | G33: 868.4*0.25
A35: B | B35: Beams (downstands below slab) | C35: =TAKEOFF!$H$5388 -> 13.825 | D35: m3 | E35: =RATES!$D$23 -> 2310 | F35: =C35*E35 -> 31935.75 | G35: 122.2*0.3*0.35+14.2*0.2*0.35
A37: C | B37: Columns | C37: =TAKEOFF!$H$5396 -> 28.731 | D37: m3 | E37: =RATES!$D$21 -> 2310 | F37: =C37*E37 -> 66368.61 | G37: 1*0.75*0.5*3.05+2*0.75*0.5*3.05+1*0.75*0.5*3.05+6*1.2*0.3*3.05+1*1.2*0.3*3.05+15*1.2*0.3*3.05
A39: D | B39: Concrete wall - shear walls to main & emergency stair cores, 250mm thick | C39: =TAKEOFF!$H$5400 -> 36.31025 | D39: m3 | E39: =RATES!$D$20 -> 2310 | F39: =C39*E39 -> 83876.677 | G39: 22.05*3.05*0.25+25.57*3.05*0.25
A41: E | B41: Concrete wall - lift walls, 250mm thick | C41: =TAKEOFF!$H$5403 -> 16.641562 | D41: m3 | E41: =RATES!$D$20 -> 2310 | F41: =C41*E41 -> 38442.009 | G41: 21.825*3.05*0.25
A43: F | B43: Stairs | C43: =TAKEOFF!$H$5409 -> 11.182 | D43: m3 | E43: =RATES!$D$24 -> 2310 | F43: =C43*E43 -> 25830.42 | G43: (2.966*3.3/3.3+2.625)+(2.966*3.3/3.3+2.625)
A45: G | B45: Lintels 150 x 225mm over door and window openings | C45: =TAKEOFF!$H$5444 -> 5.238 | D45: m3 | E45: =RATES!$D$25 -> 1925 | F45: =C45*E45 -> 10083.15 | G45: (6*(1+0.3)+11*(0.9+0.3)+16*(0.75+0.3)+1*(0.7+0.3)+2*(1.2+0.3)+2*(1+0.3)+2*(1+0.3)+1*(0.9+0.3)+1*(1.5+0.3)+2*(0.9+0.3)+4*(0.75+0.3)+1*(0.45+0.3)+3*(0.6+0.3)+1*(3+0.3)+3*(1.6+0.3)+2*(1.3+0.3)+3*(1.8+0.3)+1*(1.2+0.3)+4*(1.8+0.3)+8*(0.9+0.3)+1*(1.8+0....
B47: E20 FORMWORK - Formwork as described to:
A48: H | B48: Soffits of suspended slab | C48: =TAKEOFF!$H$5448 -> 868.4 | D48: m2 | E48: =RATES!$D$38 -> 165 | F48: =C48*E48 -> 143286 | G48: 868.4
A50: J | B50: Edges of suspended slab 250mm high | C50: =TAKEOFF!$H$5451 -> 252.6 | D50: m | E50: =RATES!$D$40 -> 65 | F50: =C50*E50 -> 16419 | G50: 252.6
A52: K | B52: Sides and soffits of beams | C52: =TAKEOFF!$H$5455 -> 134.98 | D52: m2 | E52: =RATES!$D$39 -> 165 | F52: =C52*E52 -> 22271.7 | G52: 122.2*(2*0.35+0.3)+14.2*(2*0.35+0.2)
A54: L | B54: Columns | C54: =TAKEOFF!$H$5463 -> 231.8 | D54: m2 | E54: =RATES!$D$37 -> 165 | F54: =C54*E54 -> 38247 | G54: 1*2*(0.75+0.5)*3.05+2*2*(0.75+0.5)*3.05+1*2*(0.75+0.5)*3.05+6*2*(1.2+0.3)*3.05+1*2*(1.2+0.3)*3.05+15*2*(1.2+0.3)*3.05
A56: M | B56: Concrete wall (both faces) | C56: =TAKEOFF!$H$5468 -> 423.6145 | D56: m2 | E56: =RATES!$D$36 -> 165 | F56: =C56*E56 -> 69896.393 | G56: 2*22.05*3.05+2*21.825*3.05+2*25.57*3.05
A58: N | B58: Soffits of stair flights, landings and risers | C58: =TAKEOFF!$H$5476 -> 66.5328 | D58: m2 | E58: =RATES!$D$42 -> 165 | F58: =C58*E58 -> 10977.912 | G58: (2*3.424*1.8+15.0+22*0.15*1.8)+(2*3.424*1.8+15.0+22*0.15*1.8)
A60: P | B60: Side and soffits of lintel / coping | C60: =TAKEOFF!$H$5511 -> 93.12 | D60: m2 | E60: =RATES!$D$43 -> 165 | F60: =C60*E60 -> 15364.8 | G60: (6*(1+0.3)+11*(0.9+0.3)+16*(0.75+0.3)+1*(0.7+0.3)+2*(1.2+0.3)+2*(1+0.3)+2*(1+0.3)+1*(0.9+0.3)+1*(1.5+0.3)+2*(0.9+0.3)+4*(0.75+0.3)+1*(0.45+0.3)+3*(0.6+0.3)+1*(3+0.3)+3*(1.6+0.3)+2*(1.3+0.3)+3*(1.8+0.3)+1*(1.2+0.3)+4*(1.8+0.3)+8*(0.9+0.3)+1*(1.8+0....
B62: E30 REINFORCEMENT - High tensile yield round bar reinforcement (standard) to BS 4449:
A63: Q | B63: 10mm diameter in columns | C63: =TAKEOFF!$H$5515 -> 2.468 | D63: t | E63: =RATES!$D$29 -> 14300 | F63: =C63*E63 -> 35292.4 | G63: 2.468
A65: R | B65: 20mm diameter in columns | C65: =TAKEOFF!$H$5518 -> 4.084 | D65: t | E65: =RATES!$D$32 -> 14300 | F65: =C65*E65 -> 58401.2 | G65: 4.084
A67: S | B67: 10mm diameter in beams (links) | C67: =TAKEOFF!$H$5521 -> 1.226 | D67: t | E67: =RATES!$D$29 -> 14300 | F67: =C67*E67 -> 17531.8 | G67: 1.226
A69: T | B69: 16mm diameter in beams | C69: =TAKEOFF!$H$5524 -> 1.219 | D69: t | E69: =RATES!$D$31 -> 14300 | F69: =C69*E69 -> 17431.7 | G69: 1.219
A71: U | B71: 20mm diameter in beams | C71: =TAKEOFF!$H$5527 -> 0.81 | D71: t | E71: =RATES!$D$32 -> 14300 | F71: =C71*E71 -> 11583 | G71: 0.810
A73: V | B73: 25mm diameter in beams | C73: =TAKEOFF!$H$5530 -> 4.057 | D73: t | E73: =RATES!$D$33 -> 14300 | F73: =C73*E73 -> 58015.1 | G73: 4.057
A75: W | B75: 10mm diameter in shear & lift walls (links) | C75: =TAKEOFF!$H$5534 -> 2.078 | D75: t | E75: =RATES!$D$29 -> 14300 | F75: =C75*E75 -> 29715.4 | G75: 1.442+0.636
A77: X | B77: 12mm diameter in shear, lift & ramp walls | C77: =TAKEOFF!$H$5538 -> 2.783 | D77: t | E77: =RATES!$D$30 -> 14300 | F77: =C77*E77 -> 39796.9 | G77: 1.917+0.866
A79: Y | B79: 20mm diameter in shear & lift walls | C79: =TAKEOFF!$H$5542 -> 10.224 | D79: t | E79: =RATES!$D$32 -> 14300 | F79: =C79*E79 -> 146203.2 | G79: 6.904+3.320
A81: Z | B81: 12mm diameter in stairs | C81: =TAKEOFF!$H$5545 -> 0.88 | D81: t | E81: =RATES!$D$30 -> 14300 | F81: =C81*E81 -> 12584 | G81: 0.880
A83: A | B83: 16mm diameter in stairs | C83: =TAKEOFF!$H$5548 -> 1.434 | D83: t | E83: =RATES!$D$31 -> 14300 | F83: =C83*E83 -> 20506.2 | G83: 1.434
A85: B | B85: 12mm diameter for suspended slab | C85: =TAKEOFF!$H$5551 -> 36.276 | D85: t | E85: =RATES!$D$30 -> 14300 | F85: =C85*E85 -> 518746.8 | G85: 36.276
A87: C | B87: 16mm diameter for suspended slab | C87: =TAKEOFF!$H$5554 -> 0.148 | D87: t | E87: =RATES!$D$31 -> 14300 | F87: =C87*E87 -> 2116.4 | G87: 0.148
B89: =B30 -> ELEMENT NO. 1: IN SITU CONCRETE/LARGE PRECAST CONCRETE | F89: =SUM(F32:F88) -> 2042424.5
B90: Carried to Bill Summary
B93: ELEMENT NO. 2: MASONRY
B95: F10 BRICK/BLOCK WALL - Solid sandcrete blockwork in cement and sand (1:4) mortar as described in:
A96: A | B96: 150mm thick wall | C96: =TAKEOFF!$H$5592 -> 1230.4068 | D96: m2 | E96: =RATES!$D$46 -> 215 | F96: =C96*E96 -> 264537.46 | G96: 354.0*3.05+(6*1*(3.05-2.2)+11*0.9*(3.05-2.2)+16*0.75*(3.05-2.2)+1*0.7*(3.05-2.2)+2*1.2*(3.05-2.2)+2*1*(3.05-2.2)+2*1*(3.05-2.2)+1*0.9*(3.05-2.2)+1*1.5*(3.05-2.2)+2*0.9*(3.05-2.2)+4*0.75*(3.05-2.2)+1*0.45*(3.05-2.2)+3*0.6*(3.05-2.2)+1*3*(3.05-2.2)+...
A98: B | B98: 200mm thick wall | C98: =TAKEOFF!$H$5628 -> 108.13819 | D98: m2 | E98: =RATES!$D$47 -> 265 | F98: =C98*E98 -> 28656.62 | G98: 31.1*3.05+(6*1*(3.05-2.2)+11*0.9*(3.05-2.2)+16*0.75*(3.05-2.2)+1*0.7*(3.05-2.2)+2*1.2*(3.05-2.2)+2*1*(3.05-2.2)+2*1*(3.05-2.2)+1*0.9*(3.05-2.2)+1*1.5*(3.05-2.2)+2*0.9*(3.05-2.2)+4*0.75*(3.05-2.2)+1*0.45*(3.05-2.2)+3*0.6*(3.05-2.2)+1*3*(3.05-2.2)+3...
B100: =B93 -> ELEMENT NO. 2: MASONRY | F100: =SUM(F95:F99) -> 293194.08
B101: Carried to Bill Summary
B104: ELEMENT NO. 4: WINDOWS/DOORS
B106: L20 DOORS - Supply and fix the following door assemblies complete with frames, ironmongery sets to steel doors and all accessories:
A107: A | B107: 1000mm x 2200mm 1-hour fire-rated galvanised steel single-leaf security door assembly (D2) | C107: =TAKEOFF!$H$5633 -> 6 | D107: nr | E107: =RATES!$D$75 -> 7800 | F107: =C107*E107 -> 46800 | G107: 6
A109: B | B109: 900mm x 2200mm single leaf timber panel door (D3) | C109: =TAKEOFF!$H$5636 -> 11 | D109: nr | E109: =RATES!$D$76 -> 3400 | F109: =C109*E109 -> 37400 | G109: 11
A111: C | B111: 750mm x 2200mm single leaf timber flush door (D6) | C111: =TAKEOFF!$H$5639 -> 16 | D111: nr | E111: =RATES!$D$79 -> 1900 | F111: =C111*E111 -> 30400 | G111: 16
A113: D | B113: 700mm x 2200mm single-leaf 2-hour fire-rated galvanised steel door (D7) | C113: =TAKEOFF!$H$5642 -> 1 | D113: nr | E113: =RATES!$D$80 -> 6800 | F113: =C113*E113 -> 6800 | G113: 1
A115: E | B115: 1200mm x 2200mm 1-hour fire-rated leaf-and-a-half galvanised steel security door assembly (D8) | C115: =TAKEOFF!$H$5645 -> 2 | D115: nr | E115: =RATES!$D$81 -> 9800 | F115: =C115*E115 -> 19600 | G115: 2
A117: F | B117: 1000mm x 2200mm 1-hour fire-rated galvanised steel single-leaf security door assembly - emergency stairs (ED1) | C117: =TAKEOFF!$H$5648 -> 2 | D117: nr | E117: =RATES!$D$82 -> 7200 | F117: =C117*E117 -> 14400 | G117: 2
A119: G | B119: 1000mm x 2200mm 1-hour fire-rated galvanised steel single-leaf security door with translucent glass panel (ED2) | C119: =TAKEOFF!$H$5651 -> 2 | D119: nr | E119: =RATES!$D$83 -> 8100 | F119: =C119*E119 -> 16200 | G119: 2
A121: H | B121: 900mm x 2200mm 1-hour fire-rated galvanised steel single-leaf security door assembly (D9) | C121: =TAKEOFF!$H$5654 -> 1 | D121: nr | E121: =RATES!$D$84 -> 6900 | F121: =C121*E121 -> 6900 | G121: 1
A123: J | B123: 1500mm x 2200mm timber bi-fold door (FD1) | C123: =TAKEOFF!$H$5657 -> 1 | D123: nr | E123: =RATES!$D$86 -> 4600 | F123: =C123*E123 -> 4600 | G123: 1
A125: K | B125: 900mm x 2200mm screw-fixed galvanised steel service access panel (M1) | C125: =TAKEOFF!$H$5660 -> 2 | D125: nr | E125: =RATES!$D$87 -> 2900 | F125: =C125*E125 -> 5800 | G125: 2
A127: L | B127: 750mm x 2200mm screw-fixed galvanised steel service access panel (M2) | C127: =TAKEOFF!$H$5663 -> 4 | D127: nr | E127: =RATES!$D$88 -> 2600 | F127: =C127*E127 -> 10400 | G127: 4
A129: M | B129: 450mm x 2200mm screw-fixed galvanised steel service access panel (M3) | C129: =TAKEOFF!$H$5666 -> 1 | D129: nr | E129: =RATES!$D$89 -> 1900 | F129: =C129*E129 -> 1900 | G129: 1
A131: N | B131: 600mm x 2200mm screw-fixed galvanised steel service access panel (M5) | C131: =TAKEOFF!$H$5669 -> 3 | D131: nr | E131: =RATES!$D$90 -> 2200 | F131: =C131*E131 -> 6600 | G131: 3
A133: P | B133: 3000mm x 2200mm 3-panel galvanised steel framed tempered glass sliding door (SD1) | C133: =TAKEOFF!$H$5672 -> 1 | D133: nr | E133: =RATES!$D$94 -> 14500 | F133: =C133*E133 -> 14500 | G133: 1
A135: Q | B135: 1600mm x 2200mm 2-panel galvanised steel framed tempered glass sliding door (SD2) | C135: =TAKEOFF!$H$5675 -> 3 | D135: nr | E135: =RATES!$D$95 -> 8800 | F135: =C135*E135 -> 26400 | G135: 3
A137: R | B137: 1300mm x 2200mm 2-panel galvanised steel framed tempered glass sliding door (SD3) | C137: =TAKEOFF!$H$5678 -> 2 | D137: nr | E137: =RATES!$D$96 -> 7600 | F137: =C137*E137 -> 15200 | G137: 2
A139: S | B139: 1800mm x 2200mm 2-panel galvanised steel framed tempered glass sliding door (SD4) | C139: =TAKEOFF!$H$5681 -> 3 | D139: nr | E139: =RATES!$D$97 -> 9300 | F139: =C139*E139 -> 27900 | G139: 3
A141: T | B141: 1200mm x 2200mm 2-panel galvanised steel framed tempered glass sliding door (SD5) | C141: =TAKEOFF!$H$5684 -> 1 | D141: nr | E141: =RATES!$D$98 -> 7200 | F141: =C141*E141 -> 7200 | G141: 1
A143: U | B143: 50mm x 150mm frames (to timber doors) | C143: =TAKEOFF!$H$5689 -> 146.6 | D143: m | E143: =RATES!$D$100 -> 125 | F143: =C143*E143 -> 18325 | G143: 11*(2*2.2+0.9)+16*(2*2.2+0.75)+1*(2*2.2+1.5)
A145: V | B145: 50mm x 12mm door stop | C145: =TAKEOFF!$H$5694 -> 146.6 | D145: m | E145: =RATES!$D$101 -> 28 | F145: =C145*E145 -> 4104.8 | G145: 11*(2*2.2+0.9)+16*(2*2.2+0.75)+1*(2*2.2+1.5)
B149: Ironmongery - Supply and fix the following approved ironmongery to hardwood with accompanying patented screws:
A150: W | B150: Pair 100mm brass butt hinges | C150: =TAKEOFF!$H$5698 -> 41 | D150: pr | E150: =RATES!$D$102 -> 125 | F150: =C150*E150 -> 5125 | G150: 41
A152: X | B152: Ordinary locks | C152: =TAKEOFF!$H$5701 -> 11 | D152: nr | E152: =RATES!$D$103 -> 480 | F152: =C152*E152 -> 5280 | G152: 11
A154: Y | B154: Approved high quality mortice indicator lock | C154: =TAKEOFF!$H$5704 -> 16 | D154: nr | E154: =RATES!$D$104 -> 560 | F154: =C154*E154 -> 8960 | G154: 16
B156: ALUMINIUM GLAZED WINDOWS - Supply and install Italian extruded aluminium glazed windows, ALCOA R50 series, powder coated aluminium profile, glazed with 6mm tinted reflective glass secured onto galvanized steel sub-frames, complete with all accessories as per Architect's detail:
A157: Z | B157: 2 bay alu. framed glass sliding window 1800mm x 1300mm (W2) | C157: =TAKEOFF!$H$5708 -> 4 | D157: nr | E157: =RATES!$D$109 -> 3603.6 | F157: =C157*E157 -> 14414.4 | G157: 4
A159: A | B159: 1 bay alu. framed glass awning window 900mm x 1300mm (W4) | C159: =TAKEOFF!$H$5711 -> 8 | D159: nr | E159: =RATES!$D$111 -> 1801.8 | F159: =C159*E159 -> 14414.4 | G159: 8
A161: B | B161: 2 bay alu. framed glass sliding window 1800mm x 1600mm (W7) | C161: =TAKEOFF!$H$5714 -> 1 | D161: nr | E161: =RATES!$D$114 -> 4435.2 | F161: =C161*E161 -> 4435.2 | G161: 1
A163: C | B163: 1 x 3 bay alu. framed glass awning window 1200mm x 1900mm (W8) | C163: =TAKEOFF!$H$5717 -> 2 | D163: nr | E163: =RATES!$D$115 -> 3511.2 | F163: =C163*E163 -> 7022.4 | G163: 2
A165: D | B165: 2 bay alu. framed glass sliding window 1200mm x 1150mm (W9) | C165: =TAKEOFF!$H$5720 -> 6 | D165: nr | E165: =RATES!$D$116 -> 2125.2 | F165: =C165*E165 -> 12751.2 | G165: 6
A167: E | B167: 2 bay alu. framed glass sliding window 1200mm x 1200mm (W10) | C167: =TAKEOFF!$H$5723 -> 1 | D167: nr | E167: =RATES!$D$117 -> 2217.6 | F167: =C167*E167 -> 2217.6 | G167: 1
A169: F | B169: 2 bay alu. framed glass sliding window 1500mm x 1300mm (W11) | C169: =TAKEOFF!$H$5726 -> 5 | D169: nr | E169: =RATES!$D$118 -> 3003 | F169: =C169*E169 -> 15015 | G169: 5
A171: G | B171: 2 bay alu. framed glass sliding window 1500mm x 1150mm (W12) | C171: =TAKEOFF!$H$5729 -> 3 | D171: nr | E171: =RATES!$D$119 -> 2656.5 | F171: =C171*E171 -> 7969.5 | G171: 3
A173: H | B173: 3 bay alu. framed glass sliding window 3000mm x 1600mm (W15) | C173: =TAKEOFF!$H$5732 -> 1 | D173: nr | E173: =RATES!$D$122 -> 7392 | F173: =C173*E173 -> 7392 | G173: 1
A175: J | B175: 2 x 3 alu. framed glass awning window 1800mm x 1900mm (W17) | C175: =TAKEOFF!$H$5735 -> 2 | D175: nr | E175: =RATES!$D$124 -> 5266.8 | F175: =C175*E175 -> 10533.6 | G175: 2
A177: K | B177: 1 bay alu. framed glass awning window 750mm x 1300mm (W18) | C177: =TAKEOFF!$H$5738 -> 1 | D177: nr | E177: =RATES!$D$125 -> 1501.5 | F177: =C177*E177 -> 1501.5 | G177: 1
A179: L | B179: 2 bay alu. framed glass sliding window 900mm x 600mm (HW1) | C179: =TAKEOFF!$H$5741 -> 10 | D179: nr | E179: =RATES!$D$128 -> 831.6 | F179: =C179*E179 -> 8316 | G179: 10
A181: M | B181: 2 bay alu. framed glass sliding window 750mm x 600mm (HW2) | C181: =TAKEOFF!$H$5744 -> 4 | D181: nr | E181: =RATES!$D$129 -> 693 | F181: =C181*E181 -> 2772 | G181: 4
A183: N | B183: 2 bay alu. framed glass sliding window 600mm x 600mm (HW3) | C183: =TAKEOFF!$H$5747 -> 1 | D183: nr | E183: =RATES!$D$130 -> 554.4 | F183: =C183*E183 -> 554.4 | G183: 1
A185: P | B185: 2 bay alu. framed glass sliding window 1200mm x 600mm (HW4) | C185: =TAKEOFF!$H$5750 -> 1 | D185: nr | E185: =RATES!$D$131 -> 1108.8 | F185: =C185*E185 -> 1108.8 | G185: 1
B187: =B104 -> ELEMENT NO. 4: WINDOWS/DOORS | F187: =SUM(F106:F186) -> 451212.8
B188: Carried to Bill Summary
...

Sheet 11TH FLR
A1: ='PRELIMS & GEN. ITEMS'!A1 -> PROJECT: BLOCK N REDEVELOPMENT
A2: ='PRELIMS & GEN. ITEMS'!A2 -> LOCATION: KANESHIE
A3: ='PRELIMS & GEN. ITEMS'!A3 -> CLIENT: STATE HOUSING LIMITED
A4: ='PRELIMS & GEN. ITEMS'!A4 -> DATE:9/30/2026
A5: ITEM | B5: DESCRIPTION | C5: QTY | D5: UNIT | E5: RATE | F5: AMOUNT - GHC | G5: Measurement basis / calculation
B7: MAIN BUILDING
B9: ELEVENTH LEVEL - ROOF TOP TERRACE
B11: BILL SUMMARY
A13: A | B13: ELEMENT NO. 1: IN SITU CONCRETE/LARGE PRECAST CONCRETE | F13: =F85 -> 1875874.2
A15: B | B15: ELEMENT NO. 2: MASONRY | F15: =F95 -> 66159.512
A17: C | B17: ELEMENT NO. 3: WATERPROOFING | F17: =F109 -> 165192.7
A19: D | B19: ELEMENT NO. 4: WINDOWS/DOORS | F19: =F146 -> 97002.1
A21: E | B21: ELEMENT NO. 5: FLOOR FINISHES | F21: =F167 -> 269854.9
A23: F | B23: ELEMENT NO. 6: WALL FINISHES | F23: =F183 -> 92272.672
A25: G | B25: ELEMENT NO. 7: PAINTING AND DECORATING | F25: =F203 -> 56411.264
B27: =B9 -> ELEVENTH LEVEL - ROOF TOP TERRACE | E27: GHC | F27: =SUM(F13:F26) -> 2622767.4
B28: To Bill General Summary
B30: BILL NR. 14 - ROOF TOP TERRACE
B32: ELEMENT NO. 1: IN SITU CONCRETE/LARGE PRECAST CONCRETE
B34: Vibrated in-situ concrete C40 as described in:
A35: A | B35: Suspended slab 250mm thick | C35: =TAKEOFF!$H$5965 -> 217.025 | D35: m3 | E35: =RATES!$D$22 -> 2310 | F35: =C35*E35 -> 501327.75 | G35: 868.1*0.25
A37: B | B37: Beams (downstands below slab) | C37: =TAKEOFF!$H$5969 -> 14.1925 | D37: m3 | E37: =RATES!$D$23 -> 2310 | F37: =C37*E37 -> 32784.675 | G37: 125.7*0.3*0.35+14.2*0.2*0.35
A39: C | B39: Columns | C39: =TAKEOFF!$H$5973 -> 3.219 | D39: m3 | E39: =RATES!$D$21 -> 2310 | F39: =C39*E39 -> 7435.89 | G39: 2*0.75*0.5*2.9+1*1.2*0.3*2.9
A41: D | B41: Concrete wall - shear walls to main & emergency stair cores, 250mm thick | C41: =TAKEOFF!$H$5977 -> 34.5245 | D41: m3 | E41: =RATES!$D$20 -> 2310 | F41: =C41*E41 -> 79751.595 | G41: 22.05*2.9*0.25+25.57*2.9*0.25
A43: E | B43: Concrete wall - lift walls, 250mm thick | C43: =TAKEOFF!$H$5980 -> 15.823125 | D43: m3 | E43: =RATES!$D$20 -> 2310 | F43: =C43*E43 -> 36551.419 | G43: 21.825*2.9*0.25
A45: F | B45: Lintels 150 x 225mm over door and window openings | C45: =TAKEOFF!$H$5991 -> 1.083375 | D45: m3 | E45: =RATES!$D$25 -> 1925 | F45: =C45*E45 -> 2085.4969 | G45: (7*(0.9+0.3)+8*(0.75+0.3)+1*(0.7+0.3)+2*(1+0.3)+1*(0.9+0.3)+5*(0.9+0.3)+2*(0.75+0.3)+1*(0.6+0.3)+1*(1.2+0.3))*0.15*0.225
A47: G | B47: Copings 300 x 150mm to parapets | C47: =TAKEOFF!$H$5994 -> 8.2125 | D47: m3 | E47: =RATES!$D$26 -> 1925 | F47: =C47*E47 -> 15809.063 | G47: 182.5*0.3*0.15
B49: E20 FORMWORK - Formwork as described to:
A50: H | B50: Soffits of suspended slab | C50: =TAKEOFF!$H$5998 -> 868.1 | D50: m2 | E50: =RATES!$D$38 -> 165 | F50: =C50*E50 -> 143236.5 | G50: 868.1
A52: J | B52: Edges of suspended slab 250mm high | C52: =TAKEOFF!$H$6001 -> 252.9 | D52: m | E52: =RATES!$D$40 -> 65 | F52: =C52*E52 -> 16438.5 | G52: 252.9
A54: K | B54: Sides and soffits of beams | C54: =TAKEOFF!$H$6005 -> 138.48 | D54: m2 | E54: =RATES!$D$39 -> 165 | F54: =C54*E54 -> 22849.2 | G54: 125.7*(2*0.35+0.3)+14.2*(2*0.35+0.2)
A56: L | B56: Columns | C56: =TAKEOFF!$H$6009 -> 23.2 | D56: m2 | E56: =RATES!$D$37 -> 165 | F56: =C56*E56 -> 3828 | G56: 2*2*(0.75+0.5)*2.9+1*2*(1.2+0.3)*2.9
A58: M | B58: Concrete wall (both faces) | C58: =TAKEOFF!$H$6014 -> 402.781 | D58: m2 | E58: =RATES!$D$36 -> 165 | F58: =C58*E58 -> 66458.865 | G58: 2*22.05*2.9+2*21.825*2.9+2*25.57*2.9
A60: N | B60: Side and soffits of lintel / coping | C60: =TAKEOFF!$H$6026 -> 74.01 | D60: m2 | E60: =RATES!$D$43 -> 165 | F60: =C60*E60 -> 12211.65 | G60: (7*(0.9+0.3)+8*(0.75+0.3)+1*(0.7+0.3)+2*(1+0.3)+1*(0.9+0.3)+5*(0.9+0.3)+2*(0.75+0.3)+1*(0.6+0.3)+1*(1.2+0.3))*(2*0.225+0.15)+182.5*2*0.15
B62: E30 REINFORCEMENT - High tensile yield round bar reinforcement (standard) to BS 4449:
A63: P | B63: 10mm diameter in columns | C63: =TAKEOFF!$H$6030 -> 0.21 | D63: t | E63: =RATES!$D$29 -> 14300 | F63: =C63*E63 -> 3003 | G63: 0.210
A65: Q | B65: 20mm diameter in columns | C65: =TAKEOFF!$H$6033 -> 0.426 | D65: t | E65: =RATES!$D$32 -> 14300 | F65: =C65*E65 -> 6091.8 | G65: 0.426
A67: R | B67: 10mm diameter in beams (links) | C67: =TAKEOFF!$H$6036 -> 1.311 | D67: t | E67: =RATES!$D$29 -> 14300 | F67: =C67*E67 -> 18747.3 | G67: 1.311
A69: S | B69: 16mm diameter in beams | C69: =TAKEOFF!$H$6039 -> 1.256 | D69: t | E69: =RATES!$D$31 -> 14300 | F69: =C69*E69 -> 17960.8 | G69: 1.256
A71: T | B71: 20mm diameter in beams | C71: =TAKEOFF!$H$6042 -> 1.064 | D71: t | E71: =RATES!$D$32 -> 14300 | F71: =C71*E71 -> 15215.2 | G71: 1.064
A73: U | B73: 25mm diameter in beams | C73: =TAKEOFF!$H$6045 -> 3.622 | D73: t | E73: =RATES!$D$33 -> 14300 | F73: =C73*E73 -> 51794.6 | G73: 3.622
A75: V | B75: 10mm diameter in shear & lift walls (links) | C75: =TAKEOFF!$H$6049 -> 1.984 | D75: t | E75: =RATES!$D$29 -> 14300 | F75: =C75*E75 -> 28371.2 | G75: 1.377+0.607
A77: W | B77: 12mm diameter in shear, lift & ramp walls | C77: =TAKEOFF!$H$6053 -> 2.643 | D77: t | E77: =RATES!$D$30 -> 14300 | F77: =C77*E77 -> 37794.9 | G77: 1.821+0.822
A79: X | B79: 20mm diameter in shear & lift walls | C79: =TAKEOFF!$H$6057 -> 9.851 | D79: t | E79: =RATES!$D$32 -> 14300 | F79: =C79*E79 -> 140869.3 | G79: 6.652+3.199
A81: Y | B81: 12mm diameter for suspended slab | C81: =TAKEOFF!$H$6060 -> 42.841 | D81: t | E81: =RATES!$D$30 -> 14300 | F81: =C81*E81 -> 612626.3 | G81: 42.841
A83: Z | B83: 16mm diameter for suspended slab | C83: =TAKEOFF!$H$6063 -> 0.184 | D83: t | E83: =RATES!$D$31 -> 14300 | F83: =C83*E83 -> 2631.2 | G83: 0.184
B85: =B32 -> ELEMENT NO. 1: IN SITU CONCRETE/LARGE PRECAST CONCRETE | F85: =SUM(F34:F84) -> 1875874.2
B86: Carried to Bill Summary
B88: ELEMENT NO. 2: MASONRY
B90: F10 BRICK/BLOCK WALL - Solid sandcrete blockwork in cement and sand (1:4) mortar as described in:
A91: A | B91: 150mm thick wall | C91: =TAKEOFF!$H$6077 -> 266.83625 | D91: m2 | E91: =RATES!$D$46 -> 215 | F91: =C91*E91 -> 57369.794 | G91: 82.0*2.9+(7*0.9*(3.05-2.2)+8*0.75*(3.05-2.2)+1*0.7*(3.05-2.2)+2*1*(3.05-2.2)+1*0.9*(3.05-2.2)+5*0.9*(3.05-0.6)+2*0.75*(3.05-0.6)+1*0.6*(3.05-0.6)+1*1.2*(3.05-0.6))*0.890
A93: B | B93: 200mm thick wall | C93: =TAKEOFF!$H$6089 -> 33.16875 | D93: m2 | E93: =RATES!$D$47 -> 265 | F93: =C93*E93 -> 8789.7187 | G93: 10.2*2.9+(7*0.9*(3.05-2.2)+8*0.75*(3.05-2.2)+1*0.7*(3.05-2.2)+2*1*(3.05-2.2)+1*0.9*(3.05-2.2)+5*0.9*(3.05-0.6)+2*0.75*(3.05-0.6)+1*0.6*(3.05-0.6)+1*1.2*(3.05-0.6))*0.110
B95: =B88 -> ELEMENT NO. 2: MASONRY | F95: =SUM(F90:F94) -> 66159.512
B96: Carried to Bill Summary
B98: ELEMENT NO. 3: WATERPROOFING
B100: WATERPROOFING
A101: A | B101: Liquid/applied waterproofing to roofs, terraces and wet external areas | C101: =TAKEOFF!$H$6094 -> 412.1 | D101: m2 | E101: =RATES!$D$68 -> 165 | F101: =C101*E101 -> 67996.5 | G101: 412.1
A103: B | B103: Protective cement-sand screed over waterproofing | C103: =TAKEOFF!$H$6097 -> 412.1 | D103: m2 | E103: =RATES!$D$69 -> 72 | F103: =C103*E103 -> 29671.2 | G103: 412.1
A105: C | B105: Metal/aluminium flashings, upstands and counterflashings | C105: =TAKEOFF!$H$6100 -> 182.5 | D105: m | E105: =RATES!$D$70 -> 185 | F105: =C105*E105 -> 33762.5 | G105: 182.5
A107: D | B107: Roof/terrace gutters and concealed drainage channels | C107: =TAKEOFF!$H$6103 -> 182.5 | D107: m | E107: =RATES!$D$71 -> 185 | F107: =C107*E107 -> 33762.5 | G107: 182.5
B109: =B98 -> ELEMENT NO. 3: WATERPROOFING | F109: =SUM(F100:F108) -> 165192.7
B110: Carried to Bill Summary
B113: ELEMENT NO. 4: WINDOWS/DOORS
B115: L20 DOORS - Supply and fix the following door assemblies complete with frames, ironmongery sets to steel doors and all accessories:
A116: A | B116: 900mm x 2200mm single leaf timber panel door (D3) | C116: =TAKEOFF!$H$6108 -> 7 | D116: nr | E116: =RATES!$D$76 -> 3400 | F116: =C116*E116 -> 23800 | G116: 7
A118: B | B118: 750mm x 2200mm single leaf timber flush door (D6) | C118: =TAKEOFF!$H$6111 -> 8 | D118: nr | E118: =RATES!$D$79 -> 1900 | F118: =C118*E118 -> 15200 | G118: 8
A120: C | B120: 700mm x 2200mm single-leaf 2-hour fire-rated galvanised steel door (D7) | C120: =TAKEOFF!$H$6114 -> 1 | D120: nr | E120: =RATES!$D$80 -> 6800 | F120: =C120*E120 -> 6800 | G120: 1
A122: D | B122: 1000mm x 2200mm 1-hour fire-rated galvanised steel single-leaf security door assembly - emergency stairs (ED1) | C122: =TAKEOFF!$H$6117 -> 2 | D122: nr | E122: =RATES!$D$82 -> 7200 | F122: =C122*E122 -> 14400 | G122: 2
A124: E | B124: 900mm x 2200mm 1-hour fire-rated galvanised steel single-leaf security door assembly (D9) | C124: =TAKEOFF!$H$6120 -> 1 | D124: nr | E124: =RATES!$D$84 -> 6900 | F124: =C124*E124 -> 6900 | G124: 1
A126: F | B126: 50mm x 150mm frames (to timber doors) | C126: =TAKEOFF!$H$6124 -> 78.3 | D126: m | E126: =RATES!$D$100 -> 125 | F126: =C126*E126 -> 9787.5 | G126: 7*(2*2.2+0.9)+8*(2*2.2+0.75)
A128: G | B128: 50mm x 12mm door stop | C128: =TAKEOFF!$H$6128 -> 78.3 | D128: m | E128: =RATES!$D$101 -> 28 | F128: =C128*E128 -> 2192.4 | G128: 7*(2*2.2+0.9)+8*(2*2.2+0.75)
B130: Ironmongery - Supply and fix the following approved ironmongery to hardwood with accompanying patented screws:
A131: H | B131: Pair 100mm brass butt hinges | C131: =TAKEOFF!$H$6132 -> 23 | D131: pr | E131: =RATES!$D$102 -> 125 | F131: =C131*E131 -> 2875 | G131: 23
A133: J | B133: Ordinary locks | C133: =TAKEOFF!$H$6135 -> 7 | D133: nr | E133: =RATES!$D$103 -> 480 | F133: =C133*E133 -> 3360 | G133: 7
A135: K | B135: Approved high quality mortice indicator lock | C135: =TAKEOFF!$H$6138 -> 8 | D135: nr | E135: =RATES!$D$104 -> 560 | F135: =C135*E135 -> 4480 | G135: 8
B137: ALUMINIUM GLAZED WINDOWS - Supply and install Italian extruded aluminium glazed windows, ALCOA R50 series, powder coated aluminium profile, glazed with 6mm tinted reflective glass secured onto galvanized steel sub-frames, complete with all accessories as per Architect's detail:
A138: L | B138: 2 bay alu. framed glass sliding window 900mm x 600mm (HW1) | C138: =TAKEOFF!$H$6142 -> 5 | D138: nr | E138: =RATES!$D$128 -> 831.6 | F138: =C138*E138 -> 4158 | G138: 5
A140: M | B140: 2 bay alu. framed glass sliding window 750mm x 600mm (HW2) | C140: =TAKEOFF!$H$6145 -> 2 | D140: nr | E140: =RATES!$D$129 -> 693 | F140: =C140*E140 -> 1386 | G140: 2
A142: N | B142: 2 bay alu. framed glass sliding window 600mm x 600mm (HW3) | C142: =TAKEOFF!$H$6148 -> 1 | D142: nr | E142: =RATES!$D$130 -> 554.4 | F142: =C142*E142 -> 554.4 | G142: 1
A144: P | B144: 2 bay alu. framed glass sliding window 1200mm x 600mm (HW4) | C144: =TAKEOFF!$H$6151 -> 1 | D144: nr | E144: =RATES!$D$131 -> 1108.8 | F144: =C144*E144 -> 1108.8 | G144: 1
B146: =B113 -> ELEMENT NO. 4: WINDOWS/DOORS | F146: =SUM(F115:F145) -> 97002.1
B147: Carried to Bill Summary
B150: ELEMENT NO. 5: FLOOR FINISHES
B152: M10/M40 FLOOR FINISHES
A153: A | B153: 25mm cement and sand (1:3) screeded finish laid level on concrete and finished smooth with steel trowel | C153: =TAKEOFF!$H$6156 -> 319.4 | D153: m2 | E153: =RATES!$D$50 -> 68 | F153: =C153*E153 -> 21719.2 | G153: 319.4
A155: B | B155: 12mm cement and sand (1:4) screeded bed laid level on concrete floor to receive floor tiles | C155: =TAKEOFF!$H$6159 -> 319.4 | D155: m2 | E155: =RATES!$D$51 -> 48 | F155: =C155*E155 -> 15331.2 | G155: 319.4
A157: C | B157: 400x400mm non-slip porcelain floor tiles to washrooms & WCs, adhesive, grout and cutting | C157: =TAKEOFF!$H$6162 -> 24.2 | D157: m2 | E157: =RATES!$D$53 -> 230 | F157: =C157*E157 -> 5566 | G157: 24.2
A159: D | B159: 600x600mm semi-polished porcelain floor tiles to habitable rooms, shops & offices | C159: =TAKEOFF!$H$6165 -> 235.9 | D159: m2 | E159: =RATES!$D$55 -> 265 | F159: =C159*E159 -> 62513.5 | G159: 235.9
A161: E | B161: 600x1200mm semi-polished porcelain floor tiles to stair/lift lobbies & reception | C161: =TAKEOFF!$H$6168 -> 19.3 | D161: m2 | E161: =RATES!$D$56 -> 330 | F161: =C161*E161 -> 6369 | G161: 19.3
A163: F | B163: 600x600mm non-slip R11 porcelain tiles to corridors, terraces, verandah & service areas | C163: =TAKEOFF!$H$6171 -> 40 | D163: m2 | E163: =RATES!$D$57 -> 250 | F163: =C163*E163 -> 10000 | G163: 40.0
A165: G | B165: Interlocking composite tiles to roof-top outdoor sitting & play areas | C165: =TAKEOFF!$H$6174 -> 412.1 | D165: m2 | E165: =RATES!$D$58 -> 360 | F165: =C165*E165 -> 148356 | G165: 412.1
B167: =B150 -> ELEMENT NO. 5: FLOOR FINISHES | F167: =SUM(F152:F166) -> 269854.9
B168: Carried to Bill Summary
B170: ELEMENT NO. 6: WALL FINISHES
B172: M20 PLASTERED/RENDERED COATINGS - 12.5mm cement and sand (1:3) rendering as described on blockwork or concrete to:
A173: A | B173: Interior walls | C173: =TAKEOFF!$H$6192 -> -20.257368 | D173: m2 | E173: =RATES!$D$48 -> 78 | F173: =C173*E173 -> -1580.0747 | G173: (2*(82.0+10.2)+2*42.3-16.8-182.5)*2.9-24.2/3.8*8.0*2.9-2*(7*0.9*2.2+8*0.75*2.2+1*0.7*2.2+2*1*2.2+1*0.9*2.2)-(5*0.9*0.6+2*0.75*0.6+1*0.6*0.6+1*1.2*0.6)
A175: B | B175: Interior partitions and washrooms | C175: =TAKEOFF!$H$6196 -> 137.23947 | D175: m2 | E175: =RATES!$D$48 -> 78 | F175: =C175*E175 -> 10704.679 | G175: 24.2/3.8*8.0*2.9-24.2/3.8*0.75*2.2
A177: C | B177: External walls | C177: =TAKEOFF!$H$6203 -> 570.195 | D177: m2 | E177: =RATES!$D$49 -> 88 | F177: =C177*E177 -> 50177.16 | G177: 182.5*3.15-(5*0.9*0.6+2*0.75*0.6+1*0.6*0.6+1*1.2*0.6)
A179: D | B179: 12mm cement and sand (1:4) screeded backing to receive wall tiles | C179: =TAKEOFF!$H$6207 -> 111.76579 | D179: m2 | E179: =RATES!$D$52 -> 55 | F179: =C179*E179 -> 6147.1184 | G179: 24.2/3.8*8.0*2.4-24.2/3.8*0.75*2.2
A181: E | B181: Ceramic/porcelain wall tiles to washrooms to 2.4m high, adhesive & grout (type TBC) | C181: =TAKEOFF!$H$6211 -> 111.76579 | D181: m2 | E181: =RATES!$D$60 -> 240 | F181: =C181*E181 -> 26823.789 | G181: 24.2/3.8*8.0*2.4-24.2/3.8*0.75*2.2
...

Sheet 12TH FLR 
A1: ='PRELIMS & GEN. ITEMS'!A1 -> PROJECT: BLOCK N REDEVELOPMENT
A2: ='PRELIMS & GEN. ITEMS'!A2 -> LOCATION: KANESHIE
A3: ='PRELIMS & GEN. ITEMS'!A3 -> CLIENT: STATE HOUSING LIMITED
A4: ='PRELIMS & GEN. ITEMS'!A4 -> DATE:9/30/2026
A5: ITEM | B5: DESCRIPTION | C5: QTY | D5: UNIT | E5: RATE | F5: AMOUNT - GHC | G5: Measurement basis / calculation
B7: MAIN BUILDING
B9: TWELFTH LEVEL - ROOF LEVEL & TOP OF LIFT CORE
B11: BILL SUMMARY
A13: A | B13: ELEMENT NO. 1: IN SITU CONCRETE/LARGE PRECAST CONCRETE | F13: =F64 -> 418563.87
A15: B | B15: ELEMENT NO. 2: MASONRY | F15: =F75 -> 22569.6
A17: C | B17: ELEMENT NO. 3: WATERPROOFING | F17: =F90 -> 90897.2
