Workbook

Sheet Cover Page 
A1: aq
B11: PROPOSED BILLS OF QUANTITIES FOR KANESHIE BLOCK N REDEVELOPMENT
F23: DATE:9/30/2026

Sheet GEN SUMMARY
A1: PROJECT: BLOCK N REDEVELOPMENT
A2: LOCATION: KANESHIE
A3: CLIENT: STATE HOUSING LIMITED
A4: ='Cover Page '!F23 -> DATE:9/30/2026
A5: ITEM | B5: GENERAL SUMMARY | D5: GHC
A7: A | B7: PRELIMINARIES AND GENERAL ITEMS | D7: ='PRELIMS & GEN. ITEMS'!F41 -> 6123000
A9: B | B9: SUBSTRUCTURE (ALL PROVISIONAL) | D9: =SUBSTRUCTURE!F19 -> 13010013
A11: C | B11: GROUND FLOOR (INCL. M1 PARKING LEVEL) | D11: ='GROUND FLR '!F25 -> 4201917.1
A13: D | B13: FIRST FLOOR (INCL. M2 PARKING LEVEL) | D13: ='1ST FLR '!F25 -> 4073182.1
A15: E | B15: SECOND FLOOR (INCL. MEZZANINE PARKING LEVEL) | D15: ='2ND FLR'!F25 -> 4870821.8
A17: F | B17: THIRD FLOOR | D17: ='3RD FLR'!F25 -> 5599162.8
A19: G | B19: FOURTH FLOOR | D19: ='4TH FLR '!F25 -> 5197425.6
A21: H | B21: FIFTH FLOOR | D21: ='5TH FLR '!F25 -> 5106769.7
A23: J | B23: SIXTH FLOOR | D23: ='6TH FLR '!F25 -> 5180255.7
A25: K | B25: SEVENTH FLOOR | D25: ='7TH FLR '!F25 -> 5124646.8
A27: L | B27: EIGHTH FLOOR | D27: ='8TH FLR '!F25 -> 5120461.9
A29: M | B29: NINTH FLOOR | D29: ='9TH FLR '!F27 -> 4768520
A31: N | B31: TENTH FLOOR | D31: ='10TH FLR '!F25 -> 3957995
A33: P | B33: ELEVENTH LEVEL - ROOF TOP TERRACE | D33: ='11TH FLR'!F27 -> 3142285.2
A35: Q | B35: TWELFTH LEVEL - ROOF LEVEL & LIFT CORE | D35: ='12TH FLR '!F19 -> 656113.1
A37: R | B37: LIFTS AND PROVISIONAL SUMS | D37: ='LIFTS & PS'!F17 -> 8770000
B38: SUB - TOTAL (1) | C38: GHC | D38: =SUM(D6:D37) -> 84902569
B41: ADD: STATUTORY LEVIES AND TAXES | C41: 0.2 | D41: =D38*C41 -> 16980514
B43: TOTAL COST OF THE WORKS | C43: GHC | D43: =D41+D38 -> 1.0188308e+08

Sheet PRELIMS & GEN. ITEMS
A2: ='GEN SUMMARY'!A1 -> PROJECT: BLOCK N REDEVELOPMENT
A3: ='GEN SUMMARY'!A2 -> LOCATION: KANESHIE
A4: ='GEN SUMMARY'!A3 -> CLIENT: STATE HOUSING LIMITED
A5: ='GEN SUMMARY'!A4 -> DATE:9/30/2026
B7: BILL NO.1- PRELIMINARIES BILL AND GENERAL CONDITIONS
A8: ITEM | B8: DESCRIPTION | C8: QTY | D8: UNIT | E8: RATE | F8: AMOUNT GHS
B10: SUMMARY
B12: COLLECTION
B13: Page 2 | F13: =F74 -> 0
B15: Page 3 | F15: =F106 -> 0
B17: Page 4 | F17: =F137 -> 910000
B19: Page 5 | F19: =F163 -> 245000
B21: Page 6 | F21: =F186 -> 0
B23: Page 7 | F23: =F216 -> 3000000
B25: Page 8 | F25: =F241 -> 801000
B27: Page 9 | F27: =F268 -> 650000
B29: Page 10 | F29: =F295 -> 60000
B31: Page 11 | F31: =F325 -> 282000
B33: Page 12 | F33: =F355 -> 90000
B35: Page 13 | F35: =F370 -> 25000
B37: Page 14 | F37: =F379 -> 60000
B41: PRELIMINARIES AND GENERAL ITEMS | F41: =SUM(F13:F39) -> 6123000
B42: TOTAL CARRIED TO GENERAL SUMMARY
A43: A | B43: Generally
B44: The contractor shall be deemed to have allowed against each item a rate which complies with all the requirements of the “Preliminaries”. All unpriced preliminaries items shall be deemed to have been included in the general pricing of the works. All item containing “Preliminaries” shall apply to the whole of the works The contractor shall be deemed to have allowed against each item or in his rates of complying with all the requirements of the “Preliminaries”. All item containing “Preliminaries” shall apply to the whole of the works
A46: B | B46: Names of Parties
B47: The names of parties referred to in these Bills of Quantities and in the Conditions of Contract are as follows:-
B48: ENTERPRISE LIFE COMPANY LIMITED
A50: C | B50: ALL DRAWINGS
B51: The drawings used for the preparation of the bills of quantities are scheduled at the Appendix
A53: D | B53: Format of Bills of Quantities
B54: Major portions of this Bills of Quantities have been prepared in accordance with the "Standard Method of Measurement of Building Works", Seventh (7th) Edition (metric) Revised SMM7R (metric) dated July 1998 issued by the Royal Institution of Chartered Surveyors (R.I.C.S.) and the building Employers Confederation (B.E.C.) both of the United Kingdom. However, departures from this method of measurement (see General Notes on Method of Measurement) have been effected to reduce the number of measured Labour items and also to simplify certain other measured items. The Contractor must allow for this departures in his/her pricing so that his/her tender figure shall represent the total cost of all items of works involved in the project. No claim for extra payment will be entertained on the ground that method of the measurement adopted does not comply with the said Standard Method of Measurement.
A56: E | B56: Prohibition of Use
B57: The quantities given in the Bills of Quantities are not intended for ordering of materials/components. Quantities for use in ordering materials/components must be calculated by the Contractor by measurement on site or from contract drawings.
A59: F | B59: Site Location
B60: The Site is located at: Accra in the Greater Accra Region The Contractor is to visit and examine the site and satisfy himself as to the site conditions and facilities for obtaining special materials and shall obtain generally his own information on all matters affecting the execution of the Works.
A62: G | B62: Overtime
B63: The Contractor shall be held to have made all enquiries as to the source of his labour and to have made all provisions in his tender for every cost to him of providing and maintaining the labour force necessary to complete the contract including all extra and additional works in the contract Time, including all overtime and weekend working which he considers he shall require and supervisory cost associated therewith. No extra will be allowed on the contract Sum for this Clause.
A65: H | B65: Definition of Abbreviations
B66: Abbreviations have been used in the Bills of Quantities for the units of measurement and the Contractor should take due notice of the under-mentioned:
B67: m3/ m3/cu. m. - Cubic Metre
B68: m2/ m2/sq. m. - Square Metre
B69: lm - Linear Metre
B70: mm - Millimetre
B71: kg - Kilogramme
B72: T/ton - Tonne
B73: No./Nr. - Number
B74: TO COLLECTION | F74: =SUM(F43:F73) -> 0
A75: A | B75: Alterations to the Bills of Quantities
B76: No alterations or qualifications of any kind whatsoever shall be made by the Contractor to the text of the Bills of Quantities unless authorised or directed in writing by the Engineer or Quantity Surveyor. If any unauthorised alteration or qualification is made by the Contractor, it will be ignored and the text prepared text will be rigidly adhered to.
A78: B | B78: Preamble References
B79: To avoid long descriptions and repetitions, certain description of measured items contain only brief details of materials and/or workmanship and reference to a preamble clause. Whether specifically referred to or not, items in the preambles section in these Bills of Quantities are deemed to qualify and be part of every description of measured work to which they refer and shall be deemed to have been taken into consideration in pricing the whole of these Bills of Quantities.
A81: C | B81: Priced Bills of Quantities
B82: Should there be a difference between a Contractor's Tender Sum and the arithmetically corrected Tender Figure of the "measured works" (after a complete technical and arithmetical check) an adjustment will be made to the rates by agreement. Conversely, a percentage adjustment shall be calculated by using the total amount of the errors in relation to the value of the "measured works" and thus leaving the original Tender Sum unaltered. Variations to the "measured works" in both approaches shall be subject to the same rate amendments or percentage adjustments respectively.
A84: D | B84: Provisional Sum
B85: The Provisional Sum in these Bills of Quantities are used solely to indicate a gross amount inclusive of Contractor's profit and all other elements of loss. These sums will be expended or deducted in whole or in part as required by the Engineer and no claim for loss of profit will be entertained in this respect. The Contractor must not order expenditure against any work covered by Provisional Sums unless receipt of order in writing from the Engineer.
A87: E | B87: Prime Cost (PC) Sums
B88: Prime Cost (PC) Sums included in these Bills of Quantities are for goods to be supplied by a Supplier or work to be executed by a Contractor both to be nominated by the Engineer, P.C. Sums shall be understood to mean the NET amount expended in favour of such persons after deducting all discounts and shall include all taxes (where applicable) and the cost of packing, carriage/freight and delivery as specified. All such PC Sums are at the complete disposal of the Engineer who may direct how they are expended, deducted in whole or in part from the Contract Sum. Following a PC Sum, provision has been made for the Contractor to insert an element of profit and attendance. The Contractor shall express the element of profit as a percentage of the PC Sum and that of attendance as a lump sum.
A90: F | B90: Price Adjustment
B91: There shall be no adjustment for fluctuations
A93: G | B93: Description of the Works
B94: The works shall comprise the construction the following facilities including external services and works. Included in this document are the following:
B95: PRELIMINARIES AND GENERAL CONDITIONS
B96: DEMOLITION / ALTERATIONS/RENOVATIONS
B97: CONCRETE WORKS
B98: MASONRY
B99: STURCTURAL / CARCASING METAL / TIMBER CLADDING/COVERING LININGS/SHEATHING/DRY PARTITIONING
B100: WINDOWS/DOORS/STAIRS
B101: SURFACE FINISHES
B102: FURNITURE/EQUIPMENT
B103: ELECTRICAL/FIRE
B104: PLUMBING INSTALLATION
B105: VENTILATION /AIR CONDITIONING SYSTEMS ELEVATOR INSALLATION EXTERNAL WORKS
B106: TO COLLECTION | F106: =SUM(F75:F105) -> 0
A107: A | B107: Assistance to Consultant, Etc.
B108: Allow a sum for providing all reasonable information, labour and facilities required by the Supervising Consultant (Resident Clerk of works, Engineer, Architect, Etc) in carrying out their duties in connection with this contract per specification.
A110: B | B110: Performance Guarantee | F110: =RATES!$D$142 -> 250000
B111: The Contractor shall be required within twenty eight (28) days of receiving the acceptance letter to enter into a written, signed and witnessed guarantee to guarantee the due performance of the works in the sum of ten percent (10%) of the total amount of the contract for performance guarantee .
B112: The acceptance of a Performance Guarantee obtained by the Contractor with a Bank Company shall be at the sole discretion of the Employer. The guarantee will remain in force until such time as the Contractor has made good the defects notified to him/her by the Engineer in accordance with the Conditions of Contract.
A114: C | B114: Advance Payment Guarantee | F114: =RATES!$D$143 -> 150000
B115: Should any advance be given, the Contractor shall provide as a condition precedent, an acceptable advance guarantee from a Bank covering the amount of the advance until its repayment in full.
B117: All Risks Insurance
A118: D | B118: Provide and maintain All Risks Insurance for the Works, plant, materials, and temporary works including third-party liability, in accordance with the Conditions of Contract. | F118: =RATES!$D$144 -> 450000
A121: E | B121: Direct Payments
B122: The Direct Payment are for works, materials/components to be provided either by the Employer or by persons directly contracted to/or directly engaged by him/her. The sums will not be paid to or through the Contractor. They will be deducted in full from the contract sum as and when the works and materials/components are delivered.
A124: F | B124: Setting Out the Works | F124: =RATES!$D$145 -> 60000
B125: At commencement of the contract and during progress of the works, the Contractor shall set out the whole of the works in accordance with the drawings and in conjunction with levels and measurements taken on the site and shall be responsible for the accuracy thereof, and if inaccurate, for making alterations as required by the Engineer.
B126: The Contractor shall perform all setting out by a method to be approved by the Engineer and provide all instruments, templates, rods and setting out boards etc. as may be necessary for this purpose and where required maintain these for reference during the progress of the works.
B127: The Contractor shall protect and preserve all bench marks, site rails, pegs and other items used for setting out the works.
A129: G | B129: Existing Materials on Site
B130: Sand, gravel, vegetable soil, turf and other materials obtained from the site shall remain the property of the Employer until removed from the site in accordance with the contract. Excavations shall not be made or enlarged for the purpose of obtaining such materials. These materials shall not be used for any purpose other than for the execution of the works.
A132: H | B132: Maintenance of Services
B133: The Contractor shall protect, uphold, temporarily direct and maintain all pipes, ducts, drains, sewers, service mains, overhead cables and the like during the execution of the works. The Contractor shall make good damage to any cause within its control at its own expense or pay any costs and charges in connection therewith. Approval shall be obtained at least two (2) weeks in advance if any services have to be interrupted.
A135: H | B135: Temporary Accommodation for the Employer
B136: The Contractor shall at his/her own expense provide and erect suitable offices of not less than fifty (50) square metres in floor area for the exclusive use of the Client's consultants complete with plan chest, tables and chairs, other furniture and equipment including the supply of electricity.(N/A) | G136: =F136*70% -> 0
B137: TO COLLECTION | F137: =SUM(F107:F136) -> 910000
A138: A | B138: Semi-Permanent Name/Project Display Board | F138: =RATES!$D$146 -> 25000
B139: The Contractor shall provide a steel framed and steel sheet notice board at the entrance of the site bearing the names of the Project, Contractor, 3-D architects impression of the project and all Consultants. The size, design and colour of the notice board shall be subject to the approval of the Engineer.
A141: B | B141: Advertising Right
B142: The Contractor shall not display any other notice or advertisement in any form on any part of the site, works, hoardings or adjoining ground without the prior approval in writing of the Engineer.
...

Sheet SUBSTRUCTURE
A1: ='PRELIMS & GEN. ITEMS'!A2 -> PROJECT: BLOCK N REDEVELOPMENT
A2: ='PRELIMS & GEN. ITEMS'!A3 -> LOCATION: KANESHIE
A3: ='PRELIMS & GEN. ITEMS'!A4 -> CLIENT: STATE HOUSING LIMITED
A4: ='PRELIMS & GEN. ITEMS'!A5 -> DATE:9/30/2026
A5: ITEM | B5: DESCRIPTION | C5: QTY | D5: UNIT | E5: RATE | F5: AMOUNT - GHC | G5: Measurement basis / calculation
B7: MAIN BUILDING
B9: SUBSTRUCTURE (ALL PROVISIONAL)
B11: BILL SUMMARY
A13: A | B13: D GROUNDWORK (D20 EXCAVATION AND FILLING) | F13: =F44 -> 3070047
A15: B | B15: E IN SITU CONCRETE | F15: =F84 -> 9896922.7
A17: C | B17: BLOCK WORK | F17: =F93 -> 43043
B19: =B9 -> SUBSTRUCTURE (ALL PROVISIONAL) | E19: GHC | F19: =SUM(F13:F18) -> 13010013
B20: To Bill General Summary
B23: BILL NR. 2 - SUBSTRUCTURE
B25: D GROUNDWORK (D20 EXCAVATION AND FILLING)
B27: Site Preparation
A28: A | B28: Clear site of all vegetation, grub up their roots and dispose-off (Block N plot and Parking-22 forecourt) | C28: =40.85*38.27+35.2*20.9 -> 2299.0095 | D28: m2 | E28: =RATES!$D$7 -> 15 | F28: =C28*E28 -> 34485.143 | G28: 40.85*38.27+35.2*20.9
A30: B | B30: Excavate oversite to remove vegetable soil average 150mm deep and deposit on site for re-use average 50m from excavation | C30: =(41.0+2*2.0)*(36.0+2*2.0) -> 1800 | D30: m2 | E30: =RATES!$D$8 -> 28 | F30: =C30*E30 -> 50400 | G30: (41.0+2*2.0)*(36.0+2*2.0)
A32: C | B32: Excavate raft foundation to reduce levels maximum depth 4.00m | C32: =(45.0*40.0)*4.0 -> 7200 | D32: m3 | E32: =RATES!$D$9 -> 85 | F32: =C32*E32 -> 612000 | G32: (45.0*40.0)*4.0
A34: D | B34: Fill to make up levels over raft average 1000mm thick with waterproof external membrane and high strength biaxial geogrid; compacted | C34: =41.0*36.0*1.0-(69.445*0.25*1.0)-(13.294*1.0) -> 1445.3447 | D34: m3 | E34: =RATES!$D$10 -> 220 | F34: =C34*E34 -> 317975.84 | G34: 41.0*36.0*1.0-(69.445*0.25*1.0)-(13.294*1.0)
A36: E | B36: Fill to make up levels below raft 1700mm thick with 300mm thick compacted crushed rock layers between geogrid layers until formation level is reached | C36: =(45.0*40.0)*1.7 -> 3060 | D36: m3 | E36: =RATES!$D$11 -> 480 | F36: =C36*E36 -> 1468800 | G36: (45.0*40.0)*1.7
A38: F | B38: Backfill and compact selected excavated material around foundations | C38: =((45.0*40.0)-(41.0*36.0))*(4.0-1.7) -> 745.2 | D38: m3 | E38: =RATES!$D$12 -> 60 | F38: =C38*E38 -> 44712 | G38: ((45.0*40.0)-(41.0*36.0))*(4.0-1.7)
A40: G | B40: Load up surplus excavated material and remove from site | C40: =(45.0*40.0)*4.0-((45.0*40.0)-(41.0*36.0))*(4.0-1.7) -> 6454.8 | D40: m3 | E40: =RATES!$D$13 -> 75 | F40: =C40*E40 -> 484110 | G40: (45.0*40.0)*4.0-((45.0*40.0)-(41.0*36.0))*(4.0-1.7)
A42: H | B42: Approved imported granular material hardcore filling to make up levels: depositing and compacting in layers 150mm maximum thickness | C42: =41.0*36.0*0.15 -> 221.4 | D42: m3 | E42: =RATES!$D$14 -> 260 | F42: =C42*E42 -> 57564 | G42: 41.0*36.0*0.15
B44: =B25 -> D GROUNDWORK (D20 EXCAVATION AND FILLING) | F44: =SUM(F27:F43) -> 3070047
B45: Carried to Bill Summary
B48: E IN SITU CONCRETE
B50: E10 Plain in-situ concrete (1:4:8 - 38mm aggregate) as described in:
A51: A | B51: Blinding 100mm thick under raft | C51: =41.0*36.0*0.10 -> 147.6 | D51: m3 | E51: =RATES!$D$15 -> 1650 | F51: =C51*E51 -> 243540 | G51: 41.0*36.0*0.10
A53: B | B53: 150mm thick bed | C53: =41.0*36.0*0.15 -> 221.4 | D53: m3 | E53: =RATES!$D$16 -> 2150 | F53: =C53*E53 -> 476010 | G53: 41.0*36.0*0.15
B55: Vibrated in-situ concrete C40 as described in:
A56: C | B56: Concrete walls (raft to ground floor) | C56: =(22.05+21.825+25.57)*0.25*1.3 -> 22.569625 | D56: m3 | E56: =RATES!$D$20 -> 2750 | F56: =C56*E56 -> 62066.469 | G56: (22.05+21.825+25.57)*0.25*1.3
A58: D | B58: Concrete in raft 1300mm thick | C58: =41.0*36.0*1.3 -> 1918.8 | D58: m3 | E58: =RATES!$D$19 -> 2550 | F58: =C58*E58 -> 4892940 | G58: 41.0*36.0*1.3
A60: E | B60: Concrete in columns (raft to ground floor) | C60: =5*0.75*0.5*1.3+1*0.75*0.5*1.3+2*0.75*0.5*1.3+1*0.75*0.5*1.3+3*1.2*0.3*1.3+6*1.2*0.3*1.3+1*1.2*0.3*1.3+15*1.2*0.3*1.3+1*(2.85*0.25+0.825*0.25)*1.3 -> 17.281875 | D60: m3 | E60: =RATES!$D$21 -> 2800 | F60: =C60*E60 -> 48389.25 | G60: 5*0.75*0.5*1.3+1*0.75*0.5*1.3+2*0.75*0.5*1.3+1*0.75*0.5*1.3+3*1.2*0.3*1.3+6*1.2*0.3*1.3+1*1.2*0.3*1.3+15*1.2*0.3*1.3+1*(2.85*0.25+0.825*0.25)*1.3
B62: E30 REINFORCEMENT - High tensile yield round bar reinforcement (standard):
A63: F | B63: 20mm diameter in raft | C63: =2.466 -> 2.466 | D63: t | E63: =RATES!$D$32 -> 19000 | F63: =C63*E63 -> 46854 | G63: 2.466
A65: G | B65: 25mm diameter in raft | C65: =184.672 -> 184.672 | D65: t | E65: =RATES!$D$33 -> 19000 | F65: =C65*E65 -> 3508768 | G65: 184.672
A67: H | B67: 10mm diameter links to columns & walls (raft to ground floor) | C67: =3.252+0.517+0.260 -> 4.029 | D67: t | E67: =RATES!$D$29 -> 20500 | F67: =C67*E67 -> 82594.5 | G67: 3.252+0.517+0.260
A69: J | B69: 12mm diameter to walls (raft to ground floor) | C69: =0.863+0.390 -> 1.253 | D69: t | E69: =RATES!$D$30 -> 20000 | F69: =C69*E69 -> 25060 | G69: 0.863+0.390
A71: K | B71: 25mm diameter to columns & walls (raft to ground floor) | C71: =6.531+9.840+4.935 -> 21.306 | D71: t | E71: =RATES!$D$33 -> 19000 | F71: =C71*E71 -> 404814 | G71: 6.531+9.840+4.935
A73: L | B73: 20mm diameter in columns (raft to ground floor) | C73: =0.338 -> 0.338 | D73: t | E73: =RATES!$D$32 -> 19000 | F73: =C73*E73 -> 6422 | G73: 0.338
B75: E20 FORMWORK
A76: M | B76: Concrete walls (both faces) | C76: =2*(22.05+21.825+25.57)*1.3 -> 180.557 | D76: m2 | E76: =RATES!$D$36 -> 185 | F76: =C76*E76 -> 33403.045 | G76: 2*(22.05+21.825+25.57)*1.3
A78: N | B78: Edges of bed 150mm high | C78: =2*(41.0+36.0) -> 154 | D78: m | E78: =RATES!$D$40 -> 65 | F78: =C78*E78 -> 10010 | G78: 2*(41.0+36.0)
A80: P | B80: Edges of raft 1300mm high | C80: =2*(41.0+36.0)*1.3 -> 200.2 | D80: m2 | E80: =RATES!$D$41 -> 150 | F80: =C80*E80 -> 30030 | G80: 2*(41.0+36.0)*1.3
A82: Q | B82: Sides of columns (raft to ground floor) | C82: =5*2*(0.75+0.5)*1.3+1*2*(0.75+0.5)*1.3+2*2*(0.75+0.5)*1.3+1*2*(0.75+0.5)*1.3+3*2*(1.2+0.3)*1.3+6*2*(1.2+0.3)*1.3+1*2*(1.2+0.3)*1.3+15*2*(1.2+0.3)*1.3+1*2*(2.85+1.075)*1.3 -> 136.955 | D82: m2 | E82: =RATES!$D$37 -> 190 | F82: =C82*E82 -> 26021.45 | G82: 5*2*(0.75+0.5)*1.3+1*2*(0.75+0.5)*1.3+2*2*(0.75+0.5)*1.3+1*2*(0.75+0.5)*1.3+3*2*(1.2+0.3)*1.3+6*2*(1.2+0.3)*1.3+1*2*(1.2+0.3)*1.3+15*2*(1.2+0.3)*1.3+1*2*(2.85+1.075)*1.3
B84: =B48 -> E IN SITU CONCRETE | F84: =SUM(F50:F83) -> 9896922.7
B85: Carried to Bill Summary
B88: BLOCK WORK
B90: Solid sandcrete blockwork in cement and sand (1:4) mortar:
A91: A | B91: 150mm walls to plinth | C91: =2*(41.0+36.0)*1.3 -> 200.2 | D91: m2 | E91: =RATES!$D$46 -> 215 | F91: =C91*E91 -> 43043 | G91: 2*(41.0+36.0)*1.3
B93: =B88 -> BLOCK WORK | F93: =SUM(F90:F92) -> 43043
B94: Carried to Bill Summary
B97: Raft top SSL -1.000; formation -4.000 (STR-001). Raft 41.0 x 36.0m measured on STR-001/STR-002.

Sheet GROUND FLR 
A1: ='PRELIMS & GEN. ITEMS'!A2 -> PROJECT: BLOCK N REDEVELOPMENT
A2: ='PRELIMS & GEN. ITEMS'!A3 -> LOCATION: KANESHIE
A3: ='PRELIMS & GEN. ITEMS'!A4 -> CLIENT: STATE HOUSING LIMITED
A4: ='PRELIMS & GEN. ITEMS'!A5 -> DATE:9/30/2026
A5: ITEM | B5: DESCRIPTION | C5: QTY | D5: UNIT | E5: RATE | F5: AMOUNT - GHC | G5: Measurement basis / calculation
B7: MAIN BUILDING
B9: GROUND FLOOR (INCL. M1 PARKING LEVEL 1B)
B11: BILL SUMMARY
A13: A | B13: ELEMENT NO. 1: IN SITU CONCRETE/LARGE PRECAST CONCRETE | F13: =F92 -> 2969324.3
A15: B | B15: ELEMENT NO. 2: MASONRY | F15: =F103 -> 209940.8
A17: C | B17: ELEMENT NO. 4: WINDOWS/DOORS | F17: =F166 -> 412711.9
A19: D | B19: ELEMENT NO. 5: FLOOR FINISHES | F19: =F189 -> 311872.36
A21: E | B21: ELEMENT NO. 6: WALL FINISHES | F21: =F206 -> 157798.45
A23: F | B23: ELEMENT NO. 7: PAINTING AND DECORATING | F23: =F229 -> 140269.25
B25: =B9 -> GROUND FLOOR (INCL. M1 PARKING LEVEL 1B) | E25: GHC | F25: =SUM(F13:F24) -> 4201917.1
B26: To Bill General Summary
B29: BILL NR. 3 - GROUND FLOOR
B31: ELEMENT NO. 1: IN SITU CONCRETE/LARGE PRECAST CONCRETE
B33: Vibrated in-situ concrete C40 as described in:
A34: A | B34: Suspended slab 250mm thick | C34: =689.1*0.25 -> 172.275 | D34: m3 | E34: =RATES!$D$22 -> 2650 | F34: =C34*E34 -> 456528.75 | G34: 689.1*0.25
A36: B | B36: Beams (downstands below slab) | C36: =67.8*0.3*0.35 -> 7.119 | D36: m3 | E36: =RATES!$D$23 -> 2700 | F36: =C36*E36 -> 19221.3 | G36: 67.8*0.3*0.35
A38: C | B38: Columns | C38: =5*0.75*0.5*3.6+1*0.75*0.5*3.6+2*0.75*0.5*3.6+1*0.75*0.5*1.95+1*0.75*0.5*2.45+3*1.2*0.3*3.6+6*1.2*0.3*3.6+1*1.2*0.3*3.6+15*1.2*0.3*1.95+15*1.2*0.3*2.45+1*(2.85*0.25+0.825*0.25)*3.6 -> 52.4775 | D38: m3 | E38: =RATES!$D$21 -> 2800 | F38: =C38*E38 -> 146937 | G38: 5*0.75*0.5*3.6+1*0.75*0.5*3.6+2*0.75*0.5*3.6+1*0.75*0.5*1.95+1*0.75*0.5*2.45+3*1.2*0.3*3.6+6*1.2*0.3*3.6+1*1.2*0.3*3.6+15*1.2*0.3*1.95+15*1.2*0.3*2.45+1*(2.85*0.25+0.825*0.25)*3.6
A40: D | B40: Concrete wall - shear walls to main & emergency stair cores, 250mm thick | C40: =22.05*3.6*0.25+25.57*2.25*0.25+25.57*2.45*0.25 -> 49.88975 | D40: m3 | E40: =RATES!$D$20 -> 2750 | F40: =C40*E40 -> 137196.81 | G40: 22.05*3.6*0.25+25.57*2.25*0.25+25.57*2.45*0.25
A42: E | B42: Concrete wall - lift walls, 250mm thick | C42: =21.825*3.6*0.25 -> 19.6425 | D42: m3 | E42: =RATES!$D$20 -> 2750 | F42: =C42*E42 -> 54016.875 | G42: 21.825*3.6*0.25
A44: F | B44: Stairs | C44: =(2.966*3.85/3.3+2.625)+(2.966*2.5/3.3+2.625)+(2.966*2.7/3.3+2.625) -> 16.00903 | D44: m3 | E44: =RATES!$D$24 -> 2850 | F44: =C44*E44 -> 45625.736 | G44: (2.966*3.85/3.3+2.625)+(2.966*2.5/3.3+2.625)+(2.966*2.7/3.3+2.625)
A46: G | B46: Lintels 150 x 225mm over door and window openings | C46: =(1*(1.8+0.3)+6*(0.9+0.3)+1*(0.9+0.3)+1*(3.2+0.3)+6*(0.75+0.3)+2*(0.7+0.3)+3*(1+0.3)+2*(0.9+0.3)+3*(1.8+0.3)+2*(1.8+0.3)+2*(2.4+0.3)+1*(5.05+0.3)+2*(4.2+0.3)+1*(3.6+0.3)+1*(1.8+0.3)+1*(1.8+0.3)+1*(3.5+0.3)+3*(3.6+0.3)+2*(2.4+0.3)+2*(2.1+0.3)+4*(0.9+0.3)+1*(0.75+0.3))*0.15*0.225 -> 3.324375 | D46: m3 | E46: =RATES!$D$25 -> 2600 | F46: =C46*E46 -> 8643.375 | G46: (1*(1.8+0.3)+6*(0.9+0.3)+1*(0.9+0.3)+1*(3.2+0.3)+6*(0.75+0.3)+2*(0.7+0.3)+3*(1+0.3)+2*(0.9+0.3)+3*(1.8+0.3)+2*(1.8+0.3)+2*(2.4+0.3)+1*(5.05+0.3)+2*(4.2+0.3)+1*(3.6+0.3)+1*(1.8+0.3)+1*(1.8+0.3)+1*(3.5+0.3)+3*(3.6+0.3)+2*(2.4+0.3)+2*(2.1+0.3)+4*(0.9...
B48: E20 FORMWORK - Formwork as described to:
A49: H | B49: Soffits of suspended slab | C49: =689.1 -> 689.1 | D49: m2 | E49: =RATES!$D$38 -> 170 | F49: =C49*E49 -> 117147 | G49: 689.1
A51: J | B51: Edges of suspended slab 250mm high | C51: =238.4 -> 238.4 | D51: m | E51: =RATES!$D$40 -> 65 | F51: =C51*E51 -> 15496 | G51: 238.4
A53: K | B53: Sides and soffits of beams | C53: =67.8*(2*0.35+0.3) -> 67.8 | D53: m2 | E53: =RATES!$D$39 -> 200 | F53: =C53*E53 -> 13560 | G53: 67.8*(2*0.35+0.3)
A55: L | B55: Columns | C55: =5*2*(0.75+0.5)*3.6+1*2*(0.75+0.5)*3.6+2*2*(0.75+0.5)*3.6+1*2*(0.75+0.5)*1.95+1*2*(0.75+0.5)*2.45+3*2*(1.2+0.3)*3.6+6*2*(1.2+0.3)*3.6+1*2*(1.2+0.3)*3.6+15*2*(1.2+0.3)*1.95+15*2*(1.2+0.3)*2.45+1*2*(2.85+1.075)*3.6 -> 417.26 | D55: m2 | E55: =RATES!$D$37 -> 190 | F55: =C55*E55 -> 79279.4 | G55: 5*2*(0.75+0.5)*3.6+1*2*(0.75+0.5)*3.6+2*2*(0.75+0.5)*3.6+1*2*(0.75+0.5)*1.95+1*2*(0.75+0.5)*2.45+3*2*(1.2+0.3)*3.6+6*2*(1.2+0.3)*3.6+1*2*(1.2+0.3)*3.6+15*2*(1.2+0.3)*1.95+15*2*(1.2+0.3)*2.45+1*2*(2.85+1.075)*3.6
A57: M | B57: Concrete wall (both faces) | C57: =2*22.05*3.6+2*21.825*3.6+2*25.57*2.25+2*25.57*2.45 -> 556.258 | D57: m2 | E57: =RATES!$D$36 -> 185 | F57: =C57*E57 -> 102907.73 | G57: 2*22.05*3.6+2*21.825*3.6+2*25.57*2.25+2*25.57*2.45
A59: N | B59: Soffits of stair flights, landings and risers | C59: =(2*3.424*1.8+15.0+22*0.15*1.8)+(2*3.424*1.8+15.0+22*0.15*1.8)+(2*3.424*1.8+15.0+22*0.15*1.8) -> 99.7992 | D59: m2 | E59: =RATES!$D$42 -> 230 | F59: =C59*E59 -> 22953.816 | G59: (2*3.424*1.8+15.0+22*0.15*1.8)+(2*3.424*1.8+15.0+22*0.15*1.8)+(2*3.424*1.8+15.0+22*0.15*1.8)
A61: P | B61: Side and soffits of lintel / coping | C61: =(1*(1.8+0.3)+6*(0.9+0.3)+1*(0.9+0.3)+1*(3.2+0.3)+6*(0.75+0.3)+2*(0.7+0.3)+3*(1+0.3)+2*(0.9+0.3)+3*(1.8+0.3)+2*(1.8+0.3)+2*(2.4+0.3)+1*(5.05+0.3)+2*(4.2+0.3)+1*(3.6+0.3)+1*(1.8+0.3)+1*(1.8+0.3)+1*(3.5+0.3)+3*(3.6+0.3)+2*(2.4+0.3)+2*(2.1+0.3)+4*(0.9+0.3)+1*(0.75+0.3))*(2*0.225+0.15) -> 59.1 | D61: m2 | E61: =RATES!$D$43 -> 180 | F61: =C61*E61 -> 10638 | G61: (1*(1.8+0.3)+6*(0.9+0.3)+1*(0.9+0.3)+1*(3.2+0.3)+6*(0.75+0.3)+2*(0.7+0.3)+3*(1+0.3)+2*(0.9+0.3)+3*(1.8+0.3)+2*(1.8+0.3)+2*(2.4+0.3)+1*(5.05+0.3)+2*(4.2+0.3)+1*(3.6+0.3)+1*(1.8+0.3)+1*(1.8+0.3)+1*(3.5+0.3)+3*(3.6+0.3)+2*(2.4+0.3)+2*(2.1+0.3)+4*(0.9...
B63: E30 REINFORCEMENT - High tensile yield round bar reinforcement (standard) to BS 4449:
A64: Q | B64: 10mm diameter in columns | C64: =4.372+1.656 -> 6.028 | D64: t | E64: =RATES!$D$29 -> 20500 | F64: =C64*E64 -> 123574 | G64: 4.372+1.656
A66: R | B66: 20mm diameter in columns | C66: =0.599 -> 0.599 | D66: t | E66: =RATES!$D$32 -> 19000 | F66: =C66*E66 -> 11381 | G66: 0.599
A68: S | B68: 25mm diameter in columns | C68: =10.083+4.303 -> 14.386 | D68: t | E68: =RATES!$D$33 -> 19000 | F68: =C68*E68 -> 273334 | G68: 10.083+4.303
A70: T | B70: 10mm diameter in beams (links) | C70: =1.126 -> 1.126 | D70: t | E70: =RATES!$D$29 -> 20500 | F70: =C70*E70 -> 23083 | G70: 1.126
A72: U | B72: 16mm diameter in beams | C72: =0.576 -> 0.576 | D72: t | E72: =RATES!$D$31 -> 19500 | F72: =C72*E72 -> 11232 | G72: 0.576
A74: V | B74: 20mm diameter in beams | C74: =0.814 -> 0.814 | D74: t | E74: =RATES!$D$32 -> 19000 | F74: =C74*E74 -> 15466 | G74: 0.814
A76: W | B76: 25mm diameter in beams | C76: =2.438 -> 2.438 | D76: t | E76: =RATES!$D$33 -> 19000 | F76: =C76*E76 -> 46322 | G76: 2.438
A78: X | B78: 10mm diameter in shear & lift walls (links) | C78: =1.374+0.751+0.660 -> 2.785 | D78: t | E78: =RATES!$D$29 -> 20500 | F78: =C78*E78 -> 57092.5 | G78: 1.374+0.751+0.660
A80: Y | B80: 12mm diameter in shear, lift & ramp walls | C80: =2.268+1.472+0.840+0.835 -> 5.415 | D80: t | E80: =RATES!$D$30 -> 20000 | F80: =C80*E80 -> 108300 | G80: 2.268+1.472+0.840+0.835
A82: Z | B82: 25mm diameter in shear & lift walls | C82: =10.865+6.137+5.196 -> 22.198 | D82: t | E82: =RATES!$D$33 -> 19000 | F82: =C82*E82 -> 421762 | G82: 10.865+6.137+5.196
A84: A | B84: 12mm diameter in stairs | C84: =0.880+0.440 -> 1.32 | D84: t | E84: =RATES!$D$30 -> 20000 | F84: =C84*E84 -> 26400 | G84: 0.880+0.440
A86: B | B86: 16mm diameter in stairs | C86: =1.192+0.694 -> 1.886 | D86: t | E86: =RATES!$D$31 -> 19500 | F86: =C86*E86 -> 36777 | G86: 1.192+0.694
A88: C | B88: 12mm diameter for suspended slab | C88: =25.574 -> 25.574 | D88: t | E88: =RATES!$D$30 -> 20000 | F88: =C88*E88 -> 511480 | G88: 25.574
A90: D | B90: 16mm diameter for suspended slab | C90: =3.742 -> 3.742 | D90: t | E90: =RATES!$D$31 -> 19500 | F90: =C90*E90 -> 72969 | G90: 3.742
B92: =B31 -> ELEMENT NO. 1: IN SITU CONCRETE/LARGE PRECAST CONCRETE | F92: =SUM(F33:F91) -> 2969324.3
B93: Carried to Bill Summary
B96: ELEMENT NO. 2: MASONRY
B98: F10 BRICK/BLOCK WALL - Solid sandcrete blockwork in cement and sand (1:4) mortar as described in:
A99: A | B99: 150mm thick wall | C99: =203.6*3.6+(1*1.8*(3.05-2.4)+6*0.9*(3.05-2.2)+1*0.9*(3.05-2.35)+1*3.2*(3.05-2.2)+6*0.75*(3.05-2.2)+2*0.7*(3.05-2.2)+3*1*(3.05-2.2)+2*0.9*(3.05-2.2)+3*1.8*(3.05-2.2)+2*1.8*(3.05-2.2)+2*2.4*(3.05-2.2)+1*5.05*(3.05-2.2)+2*4.2*(3.05-2.157)+1*3.6*(3.05-1.9)+1*1.8*(3.05-1.5)+1*1.8*(3.05-1.9)+1*3.5*(3.05-1.5)+3*3.6*(3.05-2.2)+2*2.4*(3.05-1.9)+2*2.1*(3.05-0.9)+4*0.9*(3.05-0.6)+1*0.75*(3.05-0.6))*0.858 -> 810.64435 | D99: m2 | E99: =RATES!$D$46 -> 215 | F99: =C99*E99 -> 174288.54 | G99: 203.6*3.6+(1*1.8*(3.05-2.4)+6*0.9*(3.05-2.2)+1*0.9*(3.05-2.35)+1*3.2*(3.05-2.2)+6*0.75*(3.05-2.2)+2*0.7*(3.05-2.2)+3*1*(3.05-2.2)+2*0.9*(3.05-2.2)+3*1.8*(3.05-2.2)+2*1.8*(3.05-2.2)+2*2.4*(3.05-2.2)+1*5.05*(3.05-2.2)+2*4.2*(3.05-2.157)+1*3.6*(3.05-...
A101: B | B101: 200mm thick wall | C101: =33.8*3.6+(1*1.8*(3.05-2.4)+6*0.9*(3.05-2.2)+1*0.9*(3.05-2.35)+1*3.2*(3.05-2.2)+6*0.75*(3.05-2.2)+2*0.7*(3.05-2.2)+3*1*(3.05-2.2)+2*0.9*(3.05-2.2)+3*1.8*(3.05-2.2)+2*1.8*(3.05-2.2)+2*2.4*(3.05-2.2)+1*5.05*(3.05-2.2)+2*4.2*(3.05-2.157)+1*3.6*(3.05-1.9)+1*1.8*(3.05-1.5)+1*1.8*(3.05-1.9)+1*3.5*(3.05-1.5)+3*3.6*(3.05-2.2)+2*2.4*(3.05-1.9)+2*2.1*(3.05-0.9)+4*0.9*(3.05-0.6)+1*0.75*(3.05-0.6))*0.142 -> 134.53685 | D101: m2 | E101: =RATES!$D$47 -> 265 | F101: =C101*E101 -> 35652.265 | G101: 33.8*3.6+(1*1.8*(3.05-2.4)+6*0.9*(3.05-2.2)+1*0.9*(3.05-2.35)+1*3.2*(3.05-2.2)+6*0.75*(3.05-2.2)+2*0.7*(3.05-2.2)+3*1*(3.05-2.2)+2*0.9*(3.05-2.2)+3*1.8*(3.05-2.2)+2*1.8*(3.05-2.2)+2*2.4*(3.05-2.2)+1*5.05*(3.05-2.2)+2*4.2*(3.05-2.157)+1*3.6*(3.05-1...
B103: =B96 -> ELEMENT NO. 2: MASONRY | F103: =SUM(F98:F102) -> 209940.8
B104: Carried to Bill Summary
B107: ELEMENT NO. 4: WINDOWS/DOORS
B109: L20 DOORS - Supply and fix the following door assemblies complete with frames, ironmongery sets to steel doors and all accessories:
A110: A | B110: 1800mm x 2400mm 2-hour fire-rated double-leaf galvanised steel door (D1) | C110: =1 -> 1 | D110: nr | E110: =RATES!$D$74 -> 18500 | F110: =C110*E110 -> 18500 | G110: 1
A112: B | B112: 900mm x 2200mm single leaf timber panel door (D3) | C112: =6 -> 6 | D112: nr | E112: =RATES!$D$76 -> 3400 | F112: =C112*E112 -> 20400 | G112: 6
A114: C | B114: 900mm x 2350mm single leaf timber panel door with fanlight (D4) | C114: =1 -> 1 | D114: nr | E114: =RATES!$D$77 -> 3900 | F114: =C114*E114 -> 3900 | G114: 1
A116: D | B116: 3200mm x 2200mm 4-panel galvanised steel framed tempered glass sliding door assembly (D5) | C116: =1 -> 1 | D116: nr | E116: =RATES!$D$78 -> 16500 | F116: =C116*E116 -> 16500 | G116: 1
A118: E | B118: 750mm x 2200mm single leaf timber flush door (D6) | C118: =6 -> 6 | D118: nr | E118: =RATES!$D$79 -> 1900 | F118: =C118*E118 -> 11400 | G118: 6
A120: F | B120: 700mm x 2200mm single-leaf 2-hour fire-rated galvanised steel door (D7) | C120: =2 -> 2 | D120: nr | E120: =RATES!$D$80 -> 6800 | F120: =C120*E120 -> 13600 | G120: 2
A122: G | B122: 1000mm x 2200mm 1-hour fire-rated galvanised steel single-leaf security door assembly - emergency stairs (ED1) | C122: =3 -> 3 | D122: nr | E122: =RATES!$D$82 -> 7200 | F122: =C122*E122 -> 21600 | G122: 3
A124: H | B124: 900mm x 2200mm 1-hour fire-rated galvanised steel single-leaf security door assembly (D9) | C124: =2 -> 2 | D124: nr | E124: =RATES!$D$84 -> 6900 | F124: =C124*E124 -> 13800 | G124: 2
A126: J | B126: 1800mm x 2200mm double-leaf 2-hour fire-rated galvanised steel refuse room door (MD1) | C126: =3 -> 3 | D126: nr | E126: =RATES!$D$85 -> 14500 | F126: =C126*E126 -> 43500 | G126: 3
A128: K | B128: 1800mm x 2200mm double-leaf double-swing galvanised steel framed tempered glass door (GD1) | C128: =2 -> 2 | D128: nr | E128: =RATES!$D$91 -> 12500 | F128: =C128*E128 -> 25000 | G128: 2
A130: L | B130: 2400mm x 2200mm double-leaf double-swing galvanised steel framed tempered glass door (DW1) | C130: =2 -> 2 | D130: nr | E130: =RATES!$D$92 -> 15500 | F130: =C130*E130 -> 31000 | G130: 2
A132: M | B132: 5050mm x 2200mm double-leaf double-swing galvanised steel framed tempered glass door with fanlight and fixed side windows (DW2) | C132: =1 -> 1 | D132: nr | E132: =RATES!$D$93 -> 33000 | F132: =C132*E132 -> 33000 | G132: 1
A134: N | B134: Metal roller shutter door 4200mm x 2157mm (RD1) | C134: =2 -> 2 | D134: nr | E134: =RATES!$D$99 -> 23000 | F134: =C134*E134 -> 46000 | G134: 2
A136: P | B136: 50mm x 150mm frames (to timber doors) | C136: =6*(2*2.2+0.9)+1*(2*2.35+0.9)+6*(2*2.2+0.75) -> 68.3 | D136: m | E136: =RATES!$D$100 -> 125 | F136: =C136*E136 -> 8537.5 | G136: 6*(2*2.2+0.9)+1*(2*2.35+0.9)+6*(2*2.2+0.75)
A138: Q | B138: 50mm x 12mm door stop | C138: =6*(2*2.2+0.9)+1*(2*2.35+0.9)+6*(2*2.2+0.75) -> 68.3 | D138: m | E138: =RATES!$D$101 -> 28 | F138: =C138*E138 -> 1912.4 | G138: 6*(2*2.2+0.9)+1*(2*2.35+0.9)+6*(2*2.2+0.75)
B140: Ironmongery - Supply and fix the following approved ironmongery to hardwood with accompanying patented screws:
A141: R | B141: Pair 100mm brass butt hinges | C141: =20 -> 20 | D141: pr | E141: =RATES!$D$102 -> 125 | F141: =C141*E141 -> 2500 | G141: 20
A143: S | B143: Ordinary locks | C143: =7 -> 7 | D143: nr | E143: =RATES!$D$103 -> 480 | F143: =C143*E143 -> 3360 | G143: 7
A145: T | B145: Approved high quality mortice indicator lock | C145: =6 -> 6 | D145: nr | E145: =RATES!$D$104 -> 560 | F145: =C145*E145 -> 3360 | G145: 6
B147: ALUMINIUM GLAZED WINDOWS - Supply and install Italian extruded aluminium glazed windows, ALCOA R50 series, powder coated aluminium profile, glazed with 6mm tinted reflective glass secured onto galvanized steel sub-frames, complete with all accessories as per Architect's detail:
A148: U | B148: 4 x 2 bay alu. framed glass awning window 3600mm x 1900mm (W1) | C148: =1 -> 1 | D148: nr | E148: =RATES!$D$108 -> 11286 | F148: =C148*E148 -> 11286 | G148: 1
A150: V | B150: 2 bay alu. framed glass sliding window 1800mm x 1500mm (W3) | C150: =1 -> 1 | D150: nr | E150: =RATES!$D$110 -> 4455 | F150: =C150*E150 -> 4455 | G150: 1
A152: W | B152: 2 bay alu. framed glass sliding window 1800mm x 1900mm (W5) | C152: =1 -> 1 | D152: nr | E152: =RATES!$D$112 -> 5643 | F152: =C152*E152 -> 5643 | G152: 1
A154: X | B154: L-shaped alu. framed fixed glass window 1750mm x 1750mm x 1500mm (W6) | C154: =1 -> 1 | D154: nr | E154: =RATES!$D$113 -> 8662.5 | F154: =C154*E154 -> 8662.5 | G154: 1
A156: Y | B156: 3 bay alu. framed glass sliding window 3600mm x 2200mm (W14) | C156: =3 -> 3 | D156: nr | E156: =RATES!$D$121 -> 13068 | F156: =C156*E156 -> 39204 | G156: 3
A158: Z | B158: 3 x 2 alu. framed glass awning window 2400mm x 1900mm (W16) | C158: =2 -> 2 | D158: nr | E158: =RATES!$D$123 -> 7524 | F158: =C158*E158 -> 15048 | G158: 2
A160: A | B160: 3 bay alu. framed glass sliding window 2100mm x 900mm (W19) | C160: =2 -> 2 | D160: nr | E160: =RATES!$D$126 -> 3118.5 | F160: =C160*E160 -> 6237 | G160: 2
A162: B | B162: 2 bay alu. framed glass sliding window 900mm x 600mm (HW1) | C162: =4 -> 4 | D162: nr | E162: =RATES!$D$128 -> 891 | F162: =C162*E162 -> 3564 | G162: 4
A164: C | B164: 2 bay alu. framed glass sliding window 750mm x 600mm (HW2) | C164: =1 -> 1 | D164: nr | E164: =RATES!$D$129 -> 742.5 | F164: =C164*E164 -> 742.5 | G164: 1
B166: =B107 -> ELEMENT NO. 4: WINDOWS/DOORS | F166: =SUM(F109:F165) -> 412711.9
B167: Carried to Bill Summary
B170: ELEMENT NO. 5: FLOOR FINISHES
B172: M10/M40 FLOOR FINISHES
A173: A | B173: 25mm cement and sand (1:3) screeded finish laid level on concrete and finished smooth with steel trowel | C173: =749.4 -> 749.4 | D173: m2 | E173: =RATES!$D$50 -> 68 | F173: =C173*E173 -> 50959.2 | G173: 749.4
A175: B | B175: 12mm cement and sand (1:4) screeded bed laid level on concrete floor to receive floor tiles | C175: =749.4+(2*1.8*3.0+22*0.15*1.8+2.2*3.75+1.8*3.75)+(2*1.8*3.0+22*0.15*1.8+2.2*3.75+1.8*3.75)+(2*1.8*3.0+22*0.15*1.8+2.2*3.75+1.8*3.75) -> 844.62 | D175: m2 | E175: =RATES!$D$51 -> 48 | F175: =C175*E175 -> 40541.76 | G175: 749.4+(2*1.8*3.0+22*0.15*1.8+2.2*3.75+1.8*3.75)+(2*1.8*3.0+22*0.15*1.8+2.2*3.75+1.8*3.75)+(2*1.8*3.0+22*0.15*1.8+2.2*3.75+1.8*3.75)
A177: C | B177: 400x400mm non-slip porcelain floor tiles to washrooms & WCs, adhesive, grout and cutting | C177: =18.1 -> 18.1 | D177: m2 | E177: =RATES!$D$53 -> 230 | F177: =C177*E177 -> 4163 | G177: 18.1
A179: D | B179: 500x500mm matte R11 porcelain tiles to staircases (treads, risers and landings) | C179: =(2*1.8*3.0+22*0.15*1.8+2.2*3.75+1.8*3.75)+(2*1.8*3.0+22*0.15*1.8+2.2*3.75+1.8*3.75)+(2*1.8*3.0+22*0.15*1.8+2.2*3.75+1.8*3.75) -> 95.22 | D179: m2 | E179: =RATES!$D$54 -> 270 | F179: =C179*E179 -> 25709.4 | G179: (2*1.8*3.0+22*0.15*1.8+2.2*3.75+1.8*3.75)+(2*1.8*3.0+22*0.15*1.8+2.2*3.75+1.8*3.75)+(2*1.8*3.0+22*0.15*1.8+2.2*3.75+1.8*3.75)
A181: E | B181: 600x600mm semi-polished porcelain floor tiles to habitable rooms, shops & offices | C181: =208.6 -> 208.6 | D181: m2 | E181: =RATES!$D$55 -> 265 | F181: =C181*E181 -> 55279 | G181: 208.6
A183: F | B183: 600x1200mm semi-polished porcelain floor tiles to stair/lift lobbies & reception | C183: =52.0 -> 52 | D183: m2 | E183: =RATES!$D$56 -> 330 | F183: =C183*E183 -> 17160 | G183: 52.0
A185: G | B185: 600x600mm non-slip R11 porcelain tiles to corridors, terraces, verandah & service areas | C185: =470.8 -> 470.8 | D185: m2 | E185: =RATES!$D$57 -> 250 | F185: =C185*E185 -> 117700 | G185: 470.8
A187: H | B187: Interlocking composite tiles to roof-top outdoor sitting & play areas | C187: =1.0 -> 1 | D187: m2 | E187: =RATES!$D$58 -> 360 | F187: =C187*E187 -> 360 | G187: 1.0
...

Sheet 1ST FLR 
A1: ='PRELIMS & GEN. ITEMS'!A2 -> PROJECT: BLOCK N REDEVELOPMENT
A2: ='PRELIMS & GEN. ITEMS'!A3 -> LOCATION: KANESHIE
A3: ='PRELIMS & GEN. ITEMS'!A4 -> CLIENT: STATE HOUSING LIMITED
A4: ='PRELIMS & GEN. ITEMS'!A5 -> DATE:9/30/2026
A5: ITEM | B5: DESCRIPTION | C5: QTY | D5: UNIT | E5: RATE | F5: AMOUNT - GHC | G5: Measurement basis / calculation
B7: MAIN BUILDING
B9: FIRST FLOOR - LEVEL 2A PARKING (INCL. M2 LEVEL 2B)
B11: BILL SUMMARY
A13: A | B13: ELEMENT NO. 1: IN SITU CONCRETE/LARGE PRECAST CONCRETE | F13: =F92 -> 3630370.6
A15: B | B15: ELEMENT NO. 2: MASONRY | F15: =F103 -> 76177.553
A17: C | B17: ELEMENT NO. 4: WINDOWS/DOORS | F17: =F112 -> 21600
A19: D | B19: ELEMENT NO. 5: FLOOR FINISHES | F19: =F131 -> 227701.44
A21: E | B21: ELEMENT NO. 6: WALL FINISHES | F21: =F142 -> 63462.63
A23: F | B23: ELEMENT NO. 7: PAINTING AND DECORATING | F23: =F157 -> 53869.883
B25: =B9 -> FIRST FLOOR - LEVEL 2A PARKING (INCL. M2 LEVEL 2B) | E25: GHC | F25: =SUM(F13:F24) -> 4073182.1
B26: To Bill General Summary
B29: BILL NR. 4 - FIRST FLOOR
B31: ELEMENT NO. 1: IN SITU CONCRETE/LARGE PRECAST CONCRETE
B33: Vibrated in-situ concrete C40 as described in:
A34: A | B34: Suspended slab 250mm thick | C34: =737.6*0.25+650.6*0.25 -> 347.05 | D34: m3 | E34: =RATES!$D$22 -> 2650 | F34: =C34*E34 -> 919682.5 | G34: 737.6*0.25+650.6*0.25
A36: B | B36: Beams (downstands below slab) | C36: =81.1*0.3*0.35+43.5*0.2*0.35+63.6*0.3*0.35 -> 18.2385 | D36: m3 | E36: =RATES!$D$23 -> 2700 | F36: =C36*E36 -> 49243.95 | G36: 81.1*0.3*0.35+43.5*0.2*0.35+63.6*0.3*0.35
A38: C | B38: Columns | C38: =5*0.75*0.5*2.45+1*0.75*0.5*2.45+2*0.75*0.5*2.45+1*0.75*0.5*2.45+3*1.2*0.3*2.45+6*1.2*0.3*2.45+1*1.2*0.3*2.45+15*1.2*0.3*2.45+1*(2.85*0.25+0.825*0.25)*2.45 -> 32.569688 | D38: m3 | E38: =RATES!$D$21 -> 2800 | F38: =C38*E38 -> 91195.125 | G38: 5*0.75*0.5*2.45+1*0.75*0.5*2.45+2*0.75*0.5*2.45+1*0.75*0.5*2.45+3*1.2*0.3*2.45+6*1.2*0.3*2.45+1*1.2*0.3*2.45+15*1.2*0.3*2.45+1*(2.85*0.25+0.825*0.25)*2.45
A40: D | B40: Concrete wall - shear walls to main & emergency stair cores, 250mm thick | C40: =22.05*2.45*0.25+25.57*2.45*0.25 -> 29.16725 | D40: m3 | E40: =RATES!$D$20 -> 2750 | F40: =C40*E40 -> 80209.938 | G40: 22.05*2.45*0.25+25.57*2.45*0.25
A42: E | B42: Concrete wall - lift walls, 250mm thick | C42: =21.825*2.45*0.25 -> 13.367813 | D42: m3 | E42: =RATES!$D$20 -> 2750 | F42: =C42*E42 -> 36761.484 | G42: 21.825*2.45*0.25
A44: F | B44: Stairs | C44: =(2.966*2.7/3.3+2.625)+(2.966*2.7/3.3+2.625) -> 10.103455 | D44: m3 | E44: =RATES!$D$24 -> 2850 | F44: =C44*E44 -> 28794.845 | G44: (2.966*2.7/3.3+2.625)+(2.966*2.7/3.3+2.625)
A46: G | B46: Lintels 150 x 225mm over door and window openings | C46: =(3*(1+0.3))*0.15*0.225 -> 0.131625 | D46: m3 | E46: =RATES!$D$25 -> 2600 | F46: =C46*E46 -> 342.225 | G46: (3*(1+0.3))*0.15*0.225
B48: E20 FORMWORK - Formwork as described to:
A49: H | B49: Soffits of suspended slab | C49: =737.6+650.6 -> 1388.2 | D49: m2 | E49: =RATES!$D$38 -> 170 | F49: =C49*E49 -> 235994 | G49: 737.6+650.6
A51: J | B51: Edges of suspended slab 250mm high | C51: =185.9+224.9 -> 410.8 | D51: m | E51: =RATES!$D$40 -> 65 | F51: =C51*E51 -> 26702 | G51: 185.9+224.9
A53: K | B53: Sides and soffits of beams | C53: =81.1*(2*0.35+0.3)+43.5*(2*0.35+0.2)+63.6*(2*0.35+0.3) -> 183.85 | D53: m2 | E53: =RATES!$D$39 -> 200 | F53: =C53*E53 -> 36770 | G53: 81.1*(2*0.35+0.3)+43.5*(2*0.35+0.2)+63.6*(2*0.35+0.3)
A55: L | B55: Columns | C55: =5*2*(0.75+0.5)*2.45+1*2*(0.75+0.5)*2.45+2*2*(0.75+0.5)*2.45+1*2*(0.75+0.5)*2.45+3*2*(1.2+0.3)*2.45+6*2*(1.2+0.3)*2.45+1*2*(1.2+0.3)*2.45+15*2*(1.2+0.3)*2.45+1*2*(2.85+1.075)*2.45 -> 258.1075 | D55: m2 | E55: =RATES!$D$37 -> 190 | F55: =C55*E55 -> 49040.425 | G55: 5*2*(0.75+0.5)*2.45+1*2*(0.75+0.5)*2.45+2*2*(0.75+0.5)*2.45+1*2*(0.75+0.5)*2.45+3*2*(1.2+0.3)*2.45+6*2*(1.2+0.3)*2.45+1*2*(1.2+0.3)*2.45+15*2*(1.2+0.3)*2.45+1*2*(2.85+1.075)*2.45
A57: M | B57: Concrete wall (both faces) | C57: =2*22.05*2.45+2*21.825*2.45+2*25.57*2.45 -> 340.2805 | D57: m2 | E57: =RATES!$D$36 -> 185 | F57: =C57*E57 -> 62951.893 | G57: 2*22.05*2.45+2*21.825*2.45+2*25.57*2.45
A59: N | B59: Soffits of stair flights, landings and risers | C59: =(2*3.424*1.8+15.0+22*0.15*1.8)+(2*3.424*1.8+15.0+22*0.15*1.8) -> 66.5328 | D59: m2 | E59: =RATES!$D$42 -> 230 | F59: =C59*E59 -> 15302.544 | G59: (2*3.424*1.8+15.0+22*0.15*1.8)+(2*3.424*1.8+15.0+22*0.15*1.8)
A61: P | B61: Side and soffits of lintel / coping | C61: =(3*(1+0.3))*(2*0.225+0.15) -> 2.34 | D61: m2 | E61: =RATES!$D$43 -> 180 | F61: =C61*E61 -> 421.2 | G61: (3*(1+0.3))*(2*0.225+0.15)
B63: E30 REINFORCEMENT - High tensile yield round bar reinforcement (standard) to BS 4449:
A64: Q | B64: 10mm diameter in columns | C64: =2.717+1.656 -> 4.373 | D64: t | E64: =RATES!$D$29 -> 20500 | F64: =C64*E64 -> 89646.5 | G64: 2.717+1.656
A66: R | B66: 20mm diameter in columns | C66: =0.462+0.154 -> 0.616 | D66: t | E66: =RATES!$D$32 -> 19000 | F66: =C66*E66 -> 11704 | G66: 0.462+0.154
A68: S | B68: 25mm diameter in columns | C68: =4.634+4.062 -> 8.696 | D68: t | E68: =RATES!$D$33 -> 19000 | F68: =C68*E68 -> 165224 | G68: 4.634+4.062
A70: T | B70: 10mm diameter in beams (links) | C70: =0.977+0.644 -> 1.621 | D70: t | E70: =RATES!$D$29 -> 20500 | F70: =C70*E70 -> 33230.5 | G70: 0.977+0.644
A72: U | B72: 16mm diameter in beams | C72: =0.763+0.460 -> 1.223 | D72: t | E72: =RATES!$D$31 -> 19500 | F72: =C72*E72 -> 23848.5 | G72: 0.763+0.460
A74: V | B74: 20mm diameter in beams | C74: =0.797+0.802 -> 1.599 | D74: t | E74: =RATES!$D$32 -> 19000 | F74: =C74*E74 -> 30381 | G74: 0.797+0.802
A76: W | B76: 25mm diameter in beams | C76: =2.973+1.624 -> 4.597 | D76: t | E76: =RATES!$D$33 -> 19000 | F76: =C76*E76 -> 87343 | G76: 2.973+1.624
A78: X | B78: 10mm diameter in shear & lift walls (links) | C78: =0.520+0.520+0.660 -> 1.7 | D78: t | E78: =RATES!$D$29 -> 20500 | F78: =C78*E78 -> 34850 | G78: 0.520+0.520+0.660
A80: Y | B80: 12mm diameter in shear, lift & ramp walls | C80: =0.699+0.692+0.835 -> 2.226 | D80: t | E80: =RATES!$D$30 -> 20000 | F80: =C80*E80 -> 44520 | G80: 0.699+0.692+0.835
A82: Z | B82: 25mm diameter in shear & lift walls | C82: =4.539+4.682+5.196 -> 14.417 | D82: t | E82: =RATES!$D$33 -> 19000 | F82: =C82*E82 -> 273923 | G82: 4.539+4.682+5.196
A84: A | B84: 12mm diameter in stairs | C84: =0.440+0.440 -> 0.88 | D84: t | E84: =RATES!$D$30 -> 20000 | F84: =C84*E84 -> 17600 | G84: 0.440+0.440
A86: B | B86: 16mm diameter in stairs | C86: =0.740+0.694 -> 1.434 | D86: t | E86: =RATES!$D$31 -> 19500 | F86: =C86*E86 -> 27963 | G86: 0.740+0.694
A88: C | B88: 12mm diameter for suspended slab | C88: =27.947+23.776 -> 51.723 | D88: t | E88: =RATES!$D$30 -> 20000 | F88: =C88*E88 -> 1034460 | G88: 27.947+23.776
A90: D | B90: 16mm diameter for suspended slab | C90: =2.528+3.742 -> 6.27 | D90: t | E90: =RATES!$D$31 -> 19500 | F90: =C90*E90 -> 122265 | G90: 2.528+3.742
B92: =B31 -> ELEMENT NO. 1: IN SITU CONCRETE/LARGE PRECAST CONCRETE | F92: =SUM(F33:F91) -> 3630370.6
B93: Carried to Bill Summary
B96: ELEMENT NO. 2: MASONRY
B98: F10 BRICK/BLOCK WALL - Solid sandcrete blockwork in cement and sand (1:4) mortar as described in:
A99: A | B99: 150mm thick wall | C99: =98.4*2.45+(3*1*(3.05-2.2))*0.729 -> 242.93895 | D99: m2 | E99: =RATES!$D$46 -> 215 | F99: =C99*E99 -> 52231.874 | G99: 98.4*2.45+(3*1*(3.05-2.2))*0.729
A101: B | B101: 200mm thick wall | C101: =36.6*2.45+(3*1*(3.05-2.2))*0.271 -> 90.36105 | D101: m2 | E101: =RATES!$D$47 -> 265 | F101: =C101*E101 -> 23945.678 | G101: 36.6*2.45+(3*1*(3.05-2.2))*0.271
B103: =B96 -> ELEMENT NO. 2: MASONRY | F103: =SUM(F98:F102) -> 76177.553
B104: Carried to Bill Summary
B107: ELEMENT NO. 4: WINDOWS/DOORS
B109: L20 DOORS - Supply and fix the following door assemblies complete with frames, ironmongery sets to steel doors and all accessories:
A110: A | B110: 1000mm x 2200mm 1-hour fire-rated galvanised steel single-leaf security door assembly - emergency stairs (ED1) | C110: =3 -> 3 | D110: nr | E110: =RATES!$D$82 -> 7200 | F110: =C110*E110 -> 21600 | G110: 3
B112: =B107 -> ELEMENT NO. 4: WINDOWS/DOORS | F112: =SUM(F109:F111) -> 21600
B113: Carried to Bill Summary
B116: ELEMENT NO. 5: FLOOR FINISHES
B118: M10/M40 FLOOR FINISHES
A119: A | B119: 25mm cement and sand (1:3) screeded finish laid level on concrete and finished smooth with steel trowel | C119: =54.8 -> 54.8 | D119: m2 | E119: =RATES!$D$50 -> 68 | F119: =C119*E119 -> 3726.4 | G119: 54.8
A121: B | B121: 12mm cement and sand (1:4) screeded bed laid level on concrete floor to receive floor tiles | C121: =54.8+(2*1.8*3.0+22*0.15*1.8+2.2*3.75+1.8*3.75)+(2*1.8*3.0+22*0.15*1.8+2.2*3.75+1.8*3.75) -> 118.28 | D121: m2 | E121: =RATES!$D$51 -> 48 | F121: =C121*E121 -> 5677.44 | G121: 54.8+(2*1.8*3.0+22*0.15*1.8+2.2*3.75+1.8*3.75)+(2*1.8*3.0+22*0.15*1.8+2.2*3.75+1.8*3.75)
A123: C | B123: 500x500mm matte R11 porcelain tiles to staircases (treads, risers and landings) | C123: =(2*1.8*3.0+22*0.15*1.8+2.2*3.75+1.8*3.75)+(2*1.8*3.0+22*0.15*1.8+2.2*3.75+1.8*3.75) -> 63.48 | D123: m2 | E123: =RATES!$D$54 -> 270 | F123: =C123*E123 -> 17139.6 | G123: (2*1.8*3.0+22*0.15*1.8+2.2*3.75+1.8*3.75)+(2*1.8*3.0+22*0.15*1.8+2.2*3.75+1.8*3.75)
A125: D | B125: 600x1200mm semi-polished porcelain floor tiles to stair/lift lobbies & reception | C125: =32.7 -> 32.7 | D125: m2 | E125: =RATES!$D$56 -> 330 | F125: =C125*E125 -> 10791 | G125: 32.7
A127: E | B127: 600x600mm non-slip R11 porcelain tiles to corridors, terraces, verandah & service areas | C127: =22.2 -> 22.2 | D127: m2 | E127: =RATES!$D$57 -> 250 | F127: =C127*E127 -> 5550 | G127: 22.2
A129: F | B129: Seamless polyurethane (PU) resin screed / PU coating to parking decks & ramps | C129: =637.3 -> 637.3 | D129: m2 | E129: =RATES!$D$59 -> 290 | F129: =C129*E129 -> 184817 | G129: 637.3
B131: =B116 -> ELEMENT NO. 5: FLOOR FINISHES | F131: =SUM(F118:F130) -> 227701.44
B132: Carried to Bill Summary
B135: ELEMENT NO. 6: WALL FINISHES
B137: M20 PLASTERED/RENDERED COATINGS - 12.5mm cement and sand (1:3) rendering as described on blockwork or concrete to:
A138: A | B138: Interior walls | C138: =(2*(98.4+36.6)+2*25.8-16.8-134.3)*2.45-0-2*(3*1*2.2)-(0) -> 404.525 | D138: m2 | E138: =RATES!$D$48 -> 78 | F138: =C138*E138 -> 31552.95 | G138: (2*(98.4+36.6)+2*25.8-16.8-134.3)*2.45-0-2*(3*1*2.2)-(0)
A140: B | B140: External walls | C140: =134.3*2.7-(0) -> 362.61 | D140: m2 | E140: =RATES!$D$49 -> 88 | F140: =C140*E140 -> 31909.68 | G140: 134.3*2.7-(0)
B142: =B135 -> ELEMENT NO. 6: WALL FINISHES | F142: =SUM(F137:F141) -> 63462.63
B143: Carried to Bill Summary
B146: ELEMENT NO. 7: PAINTING AND DECORATING
B148: M60 PAINTING - Prepare and apply two undercoats and finishing coat of emulsion paint on:
A149: A | B149: Interior walls | C149: =(2*(98.4+36.6)+2*25.8-16.8-134.3)*2.45-0-2*(3*1*2.2)-(0) -> 404.525 | D149: m2 | E149: =RATES!$D$61 -> 45 | F149: =C149*E149 -> 18203.625 | G149: (2*(98.4+36.6)+2*25.8-16.8-134.3)*2.45-0-2*(3*1*2.2)-(0)
A151: B | B151: Exterior walls | C151: =134.3*2.7-(0) -> 362.61 | D151: m2 | E151: =RATES!$D$62 -> 62 | F151: =C151*E151 -> 22481.82 | G151: 134.3*2.7-(0)
A153: C | B153: Columns and walls; girth exceeding 300mm (exposed faces, ground & parking levels) | C153: =5*2*(0.75+0.5)*2.45+1*2*(0.75+0.5)*2.45+2*2*(0.75+0.5)*2.45+1*2*(0.75+0.5)*2.45+3*2*(1.2+0.3)*2.45+6*2*(1.2+0.3)*2.45+1*2*(1.2+0.3)*2.45+15*2*(1.2+0.3)*2.45+1*2*(2.85+1.075)*2.45 -> 258.1075 | D153: m2 | E153: =RATES!$D$61 -> 45 | F153: =C153*E153 -> 11614.838 | G153: 5*2*(0.75+0.5)*2.45+1*2*(0.75+0.5)*2.45+2*2*(0.75+0.5)*2.45+1*2*(0.75+0.5)*2.45+3*2*(1.2+0.3)*2.45+6*2*(1.2+0.3)*2.45+1*2*(1.2+0.3)*2.45+15*2*(1.2+0.3)*2.45+1*2*(2.85+1.075)*2.45
A155: D | B155: Soffit of plaster board ceilings | C155: =32.7 -> 32.7 | D155: m2 | E155: =RATES!$D$63 -> 48 | F155: =C155*E155 -> 1569.6 | G155: 32.7
B157: =B146 -> ELEMENT NO. 7: PAINTING AND DECORATING | F157: =SUM(F148:F156) -> 53869.883
B158: Carried to Bill Summary
B161: Doors and windows: schedules ARCH-501/502 give building totals only (no tags on plans); quantities are allocated to floors pro-rata to measured habitable / washroom areas. Building totals equal the schedules.

Sheet 2ND FLR
A1: ='PRELIMS & GEN. ITEMS'!A2 -> PROJECT: BLOCK N REDEVELOPMENT
A2: ='PRELIMS & GEN. ITEMS'!A3 -> LOCATION: KANESHIE
A3: ='PRELIMS & GEN. ITEMS'!A4 -> CLIENT: STATE HOUSING LIMITED
A4: ='PRELIMS & GEN. ITEMS'!A5 -> DATE:9/30/2026
A5: ITEM | B5: DESCRIPTION | C5: QTY | D5: UNIT | E5: RATE | F5: AMOUNT - GHC | G5: Measurement basis / calculation
B7: MAIN BUILDING
B9: SECOND FLOOR - LEVEL 3A PARKING (INCL. MEZZANINE LEVEL 3B)
B11: BILL SUMMARY
A13: A | B13: ELEMENT NO. 1: IN SITU CONCRETE/LARGE PRECAST CONCRETE | F13: =F92 -> 4005497.4
A15: B | B15: ELEMENT NO. 2: MASONRY | F15: =F103 -> 175769.91
A17: C | B17: ELEMENT NO. 4: WINDOWS/DOORS | F17: =F112 -> 43200
A19: D | B19: ELEMENT NO. 5: FLOOR FINISHES | F19: =F131 -> 370064.94
A21: E | B21: ELEMENT NO. 6: WALL FINISHES | F21: =F142 -> 158847.63
A23: F | B23: ELEMENT NO. 7: PAINTING AND DECORATING | F23: =F157 -> 117441.9
B25: =B9 -> SECOND FLOOR - LEVEL 3A PARKING (INCL. MEZZANINE LEVEL 3B) | E25: GHC | F25: =SUM(F13:F24) -> 4870821.8
B26: To Bill General Summary
B29: BILL NR. 5 - SECOND FLOOR
B31: ELEMENT NO. 1: IN SITU CONCRETE/LARGE PRECAST CONCRETE
B33: Vibrated in-situ concrete C40 as described in:
A34: A | B34: Suspended slab 250mm thick | C34: =737.5*0.25+554.9*0.25 -> 323.1 | D34: m3 | E34: =RATES!$D$22 -> 2650 | F34: =C34*E34 -> 856215 | G34: 737.5*0.25+554.9*0.25
A36: B | B36: Beams (downstands below slab) | C36: =79.9*0.3*0.35+43*0.2*0.35+64.3*0.3*0.35 -> 18.151 | D36: m3 | E36: =RATES!$D$23 -> 2700 | F36: =C36*E36 -> 49007.7 | G36: 79.9*0.3*0.35+43*0.2*0.35+64.3*0.3*0.35
A38: C | B38: Columns | C38: =5*0.75*0.5*3.8+1*0.75*0.5*3.8+2*0.75*0.5*3.8+1*0.75*0.5*2.75+3*1.2*0.3*3.8+6*1.2*0.3*3.8+1*1.2*0.3*3.8+15*1.2*0.3*2.75+1*(2.85*0.25+0.825*0.25)*3.8 -> 44.4525 | D38: m3 | E38: =RATES!$D$21 -> 2800 | F38: =C38*E38 -> 124467 | G38: 5*0.75*0.5*3.8+1*0.75*0.5*3.8+2*0.75*0.5*3.8+1*0.75*0.5*2.75+3*1.2*0.3*3.8+6*1.2*0.3*3.8+1*1.2*0.3*3.8+15*1.2*0.3*2.75+1*(2.85*0.25+0.825*0.25)*3.8
A40: D | B40: Concrete wall - shear walls to main & emergency stair cores, 250mm thick | C40: =22.05*3.8*0.25+25.57*2.75*0.25 -> 38.526875 | D40: m3 | E40: =RATES!$D$20 -> 2750 | F40: =C40*E40 -> 105948.91 | G40: 22.05*3.8*0.25+25.57*2.75*0.25
A42: E | B42: Concrete wall - lift walls, 250mm thick | C42: =21.825*3.8*0.25 -> 20.73375 | D42: m3 | E42: =RATES!$D$20 -> 2750 | F42: =C42*E42 -> 57017.812 | G42: 21.825*3.8*0.25
A44: F | B44: Stairs | C44: =(2.966*4.05/3.3+2.625)+(2.966*3/3.3+2.625) -> 11.586455 | D44: m3 | E44: =RATES!$D$24 -> 2850 | F44: =C44*E44 -> 33021.395 | G44: (2.966*4.05/3.3+2.625)+(2.966*3/3.3+2.625)
A46: G | B46: Lintels 150 x 225mm over door and window openings | C46: =(3*(1+0.3))*0.15*0.225+(3*(1+0.3))*0.15*0.225 -> 0.26325 | D46: m3 | E46: =RATES!$D$25 -> 2600 | F46: =C46*E46 -> 684.45 | G46: (3*(1+0.3))*0.15*0.225+(3*(1+0.3))*0.15*0.225
B48: E20 FORMWORK - Formwork as described to:
A49: H | B49: Soffits of suspended slab | C49: =737.5+554.9 -> 1292.4 | D49: m2 | E49: =RATES!$D$38 -> 170 | F49: =C49*E49 -> 219708 | G49: 737.5+554.9
A51: J | B51: Edges of suspended slab 250mm high | C51: =186.5+216.4 -> 402.9 | D51: m | E51: =RATES!$D$40 -> 65 | F51: =C51*E51 -> 26188.5 | G51: 186.5+216.4
A53: K | B53: Sides and soffits of beams | C53: =79.9*(2*0.35+0.3)+43*(2*0.35+0.2)+64.3*(2*0.35+0.3) -> 182.9 | D53: m2 | E53: =RATES!$D$39 -> 200 | F53: =C53*E53 -> 36580 | G53: 79.9*(2*0.35+0.3)+43*(2*0.35+0.2)+64.3*(2*0.35+0.3)
A55: L | B55: Columns | C55: =5*2*(0.75+0.5)*3.8+1*2*(0.75+0.5)*3.8+2*2*(0.75+0.5)*3.8+1*2*(0.75+0.5)*2.75+3*2*(1.2+0.3)*3.8+6*2*(1.2+0.3)*3.8+1*2*(1.2+0.3)*3.8+15*2*(1.2+0.3)*2.75+1*2*(2.85+1.075)*3.8 -> 350.455 | D55: m2 | E55: =RATES!$D$37 -> 190 | F55: =C55*E55 -> 66586.45 | G55: 5*2*(0.75+0.5)*3.8+1*2*(0.75+0.5)*3.8+2*2*(0.75+0.5)*3.8+1*2*(0.75+0.5)*2.75+3*2*(1.2+0.3)*3.8+6*2*(1.2+0.3)*3.8+1*2*(1.2+0.3)*3.8+15*2*(1.2+0.3)*2.75+1*2*(2.85+1.075)*3.8
A57: M | B57: Concrete wall (both faces) | C57: =2*22.05*3.8+2*21.825*3.8+2*25.57*2.75 -> 474.085 | D57: m2 | E57: =RATES!$D$36 -> 185 | F57: =C57*E57 -> 87705.725 | G57: 2*22.05*3.8+2*21.825*3.8+2*25.57*2.75
A59: N | B59: Soffits of stair flights, landings and risers | C59: =(2*3.424*1.8+15.0+22*0.15*1.8)+(2*3.424*1.8+15.0+22*0.15*1.8) -> 66.5328 | D59: m2 | E59: =RATES!$D$42 -> 230 | F59: =C59*E59 -> 15302.544 | G59: (2*3.424*1.8+15.0+22*0.15*1.8)+(2*3.424*1.8+15.0+22*0.15*1.8)
A61: P | B61: Side and soffits of lintel / coping | C61: =(3*(1+0.3))*(2*0.225+0.15)+(3*(1+0.3))*(2*0.225+0.15) -> 4.68 | D61: m2 | E61: =RATES!$D$43 -> 180 | F61: =C61*E61 -> 842.4 | G61: (3*(1+0.3))*(2*0.225+0.15)+(3*(1+0.3))*(2*0.225+0.15)
B63: E30 REINFORCEMENT - High tensile yield round bar reinforcement (standard) to BS 4449:
A64: Q | B64: 10mm diameter in columns | C64: =3.239+1.656 -> 4.895 | D64: t | E64: =RATES!$D$29 -> 20500 | F64: =C64*E64 -> 100347.5 | G64: 3.239+1.656
A66: R | B66: 20mm diameter in columns | C66: =0.622+3.166 -> 3.788 | D66: t | E66: =RATES!$D$32 -> 19000 | F66: =C66*E66 -> 71972 | G66: 0.622+3.166
A68: S | B68: 25mm diameter in columns | C68: =6.238 -> 6.238 | D68: t | E68: =RATES!$D$33 -> 19000 | F68: =C68*E68 -> 118522 | G68: 6.238
A70: T | B70: 10mm diameter in beams (links) | C70: =0.902+0.579 -> 1.481 | D70: t | E70: =RATES!$D$29 -> 20500 | F70: =C70*E70 -> 30360.5 | G70: 0.902+0.579
A72: U | B72: 16mm diameter in beams | C72: =0.740+0.406 -> 1.146 | D72: t | E72: =RATES!$D$31 -> 19500 | F72: =C72*E72 -> 22347 | G72: 0.740+0.406
A74: V | B74: 20mm diameter in beams | C74: =0.797+1.171 -> 1.968 | D74: t | E74: =RATES!$D$32 -> 19000 | F74: =C74*E74 -> 37392 | G74: 0.797+1.171
A76: W | B76: 25mm diameter in beams | C76: =2.427+0.885 -> 3.312 | D76: t | E76: =RATES!$D$33 -> 19000 | F76: =C76*E76 -> 62928 | G76: 2.427+0.885
A78: X | B78: 10mm diameter in shear & lift walls (links) | C78: =0.780+0.780+0.733 -> 2.293 | D78: t | E78: =RATES!$D$29 -> 20500 | F78: =C78*E78 -> 47006.5 | G78: 0.780+0.780+0.733
A80: Y | B80: 12mm diameter in shear, lift & ramp walls | C80: =1.092+1.082+0.939 -> 3.113 | D80: t | E80: =RATES!$D$30 -> 20000 | F80: =C80*E80 -> 62260 | G80: 1.092+1.082+0.939
A82: Z | B82: 25mm diameter in shear & lift walls | C82: =6.196+6.390+5.617 -> 18.203 | D82: t | E82: =RATES!$D$33 -> 19000 | F82: =C82*E82 -> 345857 | G82: 6.196+6.390+5.617
A84: A | B84: 12mm diameter in stairs | C84: =0.440+0.440 -> 0.88 | D84: t | E84: =RATES!$D$30 -> 20000 | F84: =C84*E84 -> 17600 | G84: 0.440+0.440
A86: B | B86: 16mm diameter in stairs | C86: =0.740+0.694 -> 1.434 | D86: t | E86: =RATES!$D$31 -> 19500 | F86: =C86*E86 -> 27963 | G86: 0.740+0.694
A88: C | B88: 12mm diameter for suspended slab | C88: =35.127+33.929 -> 69.056 | D88: t | E88: =RATES!$D$30 -> 20000 | F88: =C88*E88 -> 1381120 | G88: 35.127+33.929
A90: D | B90: 16mm diameter for suspended slab | C90: =0.028 -> 0.028 | D90: t | E90: =RATES!$D$31 -> 19500 | F90: =C90*E90 -> 546 | G90: 0.028
B92: =B31 -> ELEMENT NO. 1: IN SITU CONCRETE/LARGE PRECAST CONCRETE | F92: =SUM(F33:F91) -> 4005497.4
B93: Carried to Bill Summary
B96: ELEMENT NO. 2: MASONRY
B98: F10 BRICK/BLOCK WALL - Solid sandcrete blockwork in cement and sand (1:4) mortar as described in:
A99: A | B99: 150mm thick wall | C99: =144.5*2.45+(3*1*(3.05-2.2))*0.896+127.5*2.45+(3*1*(3.05-2.2))*0.801 -> 670.72735 | D99: m2 | E99: =RATES!$D$46 -> 215 | F99: =C99*E99 -> 144206.38 | G99: 144.5*2.45+(3*1*(3.05-2.2))*0.896+127.5*2.45+(3*1*(3.05-2.2))*0.801
A101: B | B101: 200mm thick wall | C101: =16.7*2.45+(3*1*(3.05-2.2))*0.104+31.6*2.45+(3*1*(3.05-2.2))*0.199 -> 119.10765 | D101: m2 | E101: =RATES!$D$47 -> 265 | F101: =C101*E101 -> 31563.527 | G101: 16.7*2.45+(3*1*(3.05-2.2))*0.104+31.6*2.45+(3*1*(3.05-2.2))*0.199
B103: =B96 -> ELEMENT NO. 2: MASONRY | F103: =SUM(F98:F102) -> 175769.91
B104: Carried to Bill Summary
B107: ELEMENT NO. 4: WINDOWS/DOORS
B109: L20 DOORS - Supply and fix the following door assemblies complete with frames, ironmongery sets to steel doors and all accessories:
A110: A | B110: 1000mm x 2200mm 1-hour fire-rated galvanised steel single-leaf security door assembly - emergency stairs (ED1) | C110: =3+3 -> 6 | D110: nr | E110: =RATES!$D$82 -> 7200 | F110: =C110*E110 -> 43200 | G110: 3+3
B112: =B107 -> ELEMENT NO. 4: WINDOWS/DOORS | F112: =SUM(F109:F111) -> 43200
B113: Carried to Bill Summary
B116: ELEMENT NO. 5: FLOOR FINISHES
B118: M10/M40 FLOOR FINISHES
A119: A | B119: 25mm cement and sand (1:3) screeded finish laid level on concrete and finished smooth with steel trowel | C119: =3.3+20.0 -> 23.3 | D119: m2 | E119: =RATES!$D$50 -> 68 | F119: =C119*E119 -> 1584.4 | G119: 3.3+20.0
A121: B | B121: 12mm cement and sand (1:4) screeded bed laid level on concrete floor to receive floor tiles | C121: =3.3+20.0+(2*1.8*3.0+22*0.15*1.8+2.2*3.75+1.8*3.75)+(2*1.8*3.0+22*0.15*1.8+2.2*3.75+1.8*3.75) -> 86.78 | D121: m2 | E121: =RATES!$D$51 -> 48 | F121: =C121*E121 -> 4165.44 | G121: 3.3+20.0+(2*1.8*3.0+22*0.15*1.8+2.2*3.75+1.8*3.75)+(2*1.8*3.0+22*0.15*1.8+2.2*3.75+1.8*3.75)
A123: C | B123: 500x500mm matte R11 porcelain tiles to staircases (treads, risers and landings) | C123: =(2*1.8*3.0+22*0.15*1.8+2.2*3.75+1.8*3.75)+(2*1.8*3.0+22*0.15*1.8+2.2*3.75+1.8*3.75) -> 63.48 | D123: m2 | E123: =RATES!$D$54 -> 270 | F123: =C123*E123 -> 17139.6 | G123: (2*1.8*3.0+22*0.15*1.8+2.2*3.75+1.8*3.75)+(2*1.8*3.0+22*0.15*1.8+2.2*3.75+1.8*3.75)
A125: D | B125: 600x600mm semi-polished porcelain floor tiles to habitable rooms, shops & offices | C125: =3.3 -> 3.3 | D125: m2 | E125: =RATES!$D$55 -> 265 | F125: =C125*E125 -> 874.5 | G125: 3.3
A127: E | B127: 600x600mm non-slip R11 porcelain tiles to corridors, terraces, verandah & service areas | C127: =20.0 -> 20 | D127: m2 | E127: =RATES!$D$57 -> 250 | F127: =C127*E127 -> 5000 | G127: 20.0
A129: F | B129: Seamless polyurethane (PU) resin screed / PU coating to parking decks & ramps | C129: =685.4+491.5 -> 1176.9 | D129: m2 | E129: =RATES!$D$59 -> 290 | F129: =C129*E129 -> 341301 | G129: 685.4+491.5
B131: =B116 -> ELEMENT NO. 5: FLOOR FINISHES | F131: =SUM(F118:F130) -> 370064.94
B132: Carried to Bill Summary
B135: ELEMENT NO. 6: WALL FINISHES
B137: M20 PLASTERED/RENDERED COATINGS - 12.5mm cement and sand (1:3) rendering as described on blockwork or concrete to:
A138: A | B138: Interior walls | C138: =(2*(144.5+16.7)+2*35.1-16.8-134.0)*2.45-0-2*(3*1*2.2)-(0)+(2*(127.5+31.6)+2*42.8-16.8-191.5)*2.45-0-2*(3*1*2.2)-(0) -> 1044.985 | D138: m2 | E138: =RATES!$D$48 -> 78 | F138: =C138*E138 -> 81508.83 | G138: (2*(144.5+16.7)+2*35.1-16.8-134.0)*2.45-0-2*(3*1*2.2)-(0)+(2*(127.5+31.6)+2*42.8-16.8-191.5)*2.45-0-2*(3*1*2.2)-(0)
A140: B | B140: External walls | C140: =134.0*2.7-(0)+191.5*2.7-(0) -> 878.85 | D140: m2 | E140: =RATES!$D$49 -> 88 | F140: =C140*E140 -> 77338.8 | G140: 134.0*2.7-(0)+191.5*2.7-(0)
B142: =B135 -> ELEMENT NO. 6: WALL FINISHES | F142: =SUM(F137:F141) -> 158847.63
B143: Carried to Bill Summary
B146: ELEMENT NO. 7: PAINTING AND DECORATING
B148: M60 PAINTING - Prepare and apply two undercoats and finishing coat of emulsion paint on:
A149: A | B149: Interior walls | C149: =(2*(144.5+16.7)+2*35.1-16.8-134.0)*2.45-0-2*(3*1*2.2)-(0)+(2*(127.5+31.6)+2*42.8-16.8-191.5)*2.45-0-2*(3*1*2.2)-(0) -> 1044.985 | D149: m2 | E149: =RATES!$D$61 -> 45 | F149: =C149*E149 -> 47024.325 | G149: (2*(144.5+16.7)+2*35.1-16.8-134.0)*2.45-0-2*(3*1*2.2)-(0)+(2*(127.5+31.6)+2*42.8-16.8-191.5)*2.45-0-2*(3*1*2.2)-(0)
A151: B | B151: Exterior walls | C151: =134.0*2.7-(0)+191.5*2.7-(0) -> 878.85 | D151: m2 | E151: =RATES!$D$62 -> 62 | F151: =C151*E151 -> 54488.7 | G151: 134.0*2.7-(0)+191.5*2.7-(0)
A153: C | B153: Columns and walls; girth exceeding 300mm (exposed faces, ground & parking levels) | C153: =5*2*(0.75+0.5)*3.8+1*2*(0.75+0.5)*3.8+2*2*(0.75+0.5)*3.8+1*2*(0.75+0.5)*2.75+3*2*(1.2+0.3)*3.8+6*2*(1.2+0.3)*3.8+1*2*(1.2+0.3)*3.8+15*2*(1.2+0.3)*2.75+1*2*(2.85+1.075)*3.8 -> 350.455 | D153: m2 | E153: =RATES!$D$61 -> 45 | F153: =C153*E153 -> 15770.475 | G153: 5*2*(0.75+0.5)*3.8+1*2*(0.75+0.5)*3.8+2*2*(0.75+0.5)*3.8+1*2*(0.75+0.5)*2.75+3*2*(1.2+0.3)*3.8+6*2*(1.2+0.3)*3.8+1*2*(1.2+0.3)*3.8+15*2*(1.2+0.3)*2.75+1*2*(2.85+1.075)*3.8
A155: D | B155: Soffit of plaster board ceilings | C155: =3.3 -> 3.3 | D155: m2 | E155: =RATES!$D$63 -> 48 | F155: =C155*E155 -> 158.4 | G155: 3.3
B157: =B146 -> ELEMENT NO. 7: PAINTING AND DECORATING | F157: =SUM(F148:F156) -> 117441.9
B158: Carried to Bill Summary
B161: Doors and windows: schedules ARCH-501/502 give building totals only (no tags on plans); quantities are allocated to floors pro-rata to measured habitable / washroom areas. Building totals equal the schedules.

Sheet 3RD FLR
A1: ='PRELIMS & GEN. ITEMS'!A2 -> PROJECT: BLOCK N REDEVELOPMENT
A2: ='PRELIMS & GEN. ITEMS'!A3 -> LOCATION: KANESHIE
A3: ='PRELIMS & GEN. ITEMS'!A4 -> CLIENT: STATE HOUSING LIMITED
A4: ='PRELIMS & GEN. ITEMS'!A5 -> DATE:9/30/2026
A5: ITEM | B5: DESCRIPTION | C5: QTY | D5: UNIT | E5: RATE | F5: AMOUNT - GHC | G5: Measurement basis / calculation
B7: MAIN BUILDING
B9: THIRD FLOOR
B11: BILL SUMMARY
A13: A | B13: ELEMENT NO. 1: IN SITU CONCRETE/LARGE PRECAST CONCRETE | F13: =F90 -> 3579714.6
A15: B | B15: ELEMENT NO. 2: MASONRY | F15: =F101 -> 420081.85
A17: C | B17: ELEMENT NO. 4: WINDOWS/DOORS | F17: =F190 -> 704364.25
A19: D | B19: ELEMENT NO. 5: FLOOR FINISHES | F19: =F211 -> 385700.14
A21: E | B21: ELEMENT NO. 6: WALL FINISHES | F21: =F228 -> 315809.63
A23: F | B23: ELEMENT NO. 7: PAINTING AND DECORATING | F23: =F249 -> 193492.32
B25: =B9 -> THIRD FLOOR | E25: GHC | F25: =SUM(F13:F24) -> 5599162.8
B26: To Bill General Summary
B29: BILL NR. 6 - THIRD FLOOR
B31: ELEMENT NO. 1: IN SITU CONCRETE/LARGE PRECAST CONCRETE
B33: Vibrated in-situ concrete C40 as described in:
A34: A | B34: Suspended slab 250mm thick | C34: =1273.9*0.25 -> 318.475 | D34: m3 | E34: =RATES!$D$22 -> 2650 | F34: =C34*E34 -> 843958.75 | G34: 1273.9*0.25
A36: B | B36: Beams (downstands below slab) | C36: =97.4*0.3*0.35+33.1*0.2*0.35 -> 12.544 | D36: m3 | E36: =RATES!$D$23 -> 2700 | F36: =C36*E36 -> 33868.8 | G36: 97.4*0.3*0.35+33.1*0.2*0.35
A38: C | B38: Columns | C38: =5*0.75*0.5*3.05+1*0.75*0.5*3.05+2*0.75*0.5*3.05+1*0.75*0.5*3.05+3*1.2*0.3*3.05+6*1.2*0.3*3.05+1*1.2*0.3*3.05+15*1.2*0.3*3.05+1*(2.85*0.25+0.825*0.25)*3.05 -> 40.545937 | D38: m3 | E38: =RATES!$D$21 -> 2800 | F38: =C38*E38 -> 113528.62 | G38: 5*0.75*0.5*3.05+1*0.75*0.5*3.05+2*0.75*0.5*3.05+1*0.75*0.5*3.05+3*1.2*0.3*3.05+6*1.2*0.3*3.05+1*1.2*0.3*3.05+15*1.2*0.3*3.05+1*(2.85*0.25+0.825*0.25)*3.05
A40: D | B40: Concrete wall - shear walls to main & emergency stair cores, 250mm thick | C40: =22.05*3.05*0.25+25.57*3.05*0.25 -> 36.31025 | D40: m3 | E40: =RATES!$D$20 -> 2750 | F40: =C40*E40 -> 99853.187 | G40: 22.05*3.05*0.25+25.57*3.05*0.25
A42: E | B42: Concrete wall - lift walls, 250mm thick | C42: =21.825*3.05*0.25 -> 16.641562 | D42: m3 | E42: =RATES!$D$20 -> 2750 | F42: =C42*E42 -> 45764.297 | G42: 21.825*3.05*0.25
A44: F | B44: Stairs | C44: =(2.966*3.3/3.3+2.625)+(2.966*3.3/3.3+2.625) -> 11.182 | D44: m3 | E44: =RATES!$D$24 -> 2850 | F44: =C44*E44 -> 31868.7 | G44: (2.966*3.3/3.3+2.625)+(2.966*3.3/3.3+2.625)
A46: G | B46: Lintels 150 x 225mm over door and window openings | C46: =(10*(1+0.3)+19*(0.9+0.3)+21*(0.75+0.3)+2*(0.7+0.3)+3*(1.2+0.3)+3*(1+0.3)+3*(1+0.3)+2*(0.9+0.3)+1*(1.5+0.3)+3*(0.9+0.3)+5*(0.75+0.3)+1*(0.45+0.3)+3*(0.6+0.3)+1*(3+0.3)+4*(1.6+0.3)+3*(1.3+0.3)+5*(1.8+0.3)+1*(1.2+0.3)+7*(1.8+0.3)+13*(0.9+0.3)+2*(1.8+0.3)+4*(1.2+0.3)+10*(1.2+0.3)+1*(1.2+0.3)+8*(1.5+0.3)+4*(1.5+0.3)+1*(2.4+0.3)+1*(3+0.3)+4*(1.8+0.3)+1*(0.75+0.3)+1*(1.45+0.3)+12*(0.9+0.3)+5*(0.75+0.3)+1*(0.6+0.3)+1*(1.2+0.3))*0.15*0.225 -> 7.90425 | D46: m3 | E46: =RATES!$D$25 -> 2600 | F46: =C46*E46 -> 20551.05 | G46: (10*(1+0.3)+19*(0.9+0.3)+21*(0.75+0.3)+2*(0.7+0.3)+3*(1.2+0.3)+3*(1+0.3)+3*(1+0.3)+2*(0.9+0.3)+1*(1.5+0.3)+3*(0.9+0.3)+5*(0.75+0.3)+1*(0.45+0.3)+3*(0.6+0.3)+1*(3+0.3)+4*(1.6+0.3)+3*(1.3+0.3)+5*(1.8+0.3)+1*(1.2+0.3)+7*(1.8+0.3)+13*(0.9+0.3)+2*(1.8+...
B48: E20 FORMWORK - Formwork as described to:
A49: H | B49: Soffits of suspended slab | C49: =1273.9 -> 1273.9 | D49: m2 | E49: =RATES!$D$38 -> 170 | F49: =C49*E49 -> 216563 | G49: 1273.9
A51: J | B51: Edges of suspended slab 250mm high | C51: =232.4 -> 232.4 | D51: m | E51: =RATES!$D$40 -> 65 | F51: =C51*E51 -> 15106 | G51: 232.4
A53: K | B53: Sides and soffits of beams | C53: =97.4*(2*0.35+0.3)+33.1*(2*0.35+0.2) -> 127.19 | D53: m2 | E53: =RATES!$D$39 -> 200 | F53: =C53*E53 -> 25438 | G53: 97.4*(2*0.35+0.3)+33.1*(2*0.35+0.2)
A55: L | B55: Columns | C55: =5*2*(0.75+0.5)*3.05+1*2*(0.75+0.5)*3.05+2*2*(0.75+0.5)*3.05+1*2*(0.75+0.5)*3.05+3*2*(1.2+0.3)*3.05+6*2*(1.2+0.3)*3.05+1*2*(1.2+0.3)*3.05+15*2*(1.2+0.3)*3.05+1*2*(2.85+1.075)*3.05 -> 321.3175 | D55: m2 | E55: =RATES!$D$37 -> 190 | F55: =C55*E55 -> 61050.325 | G55: 5*2*(0.75+0.5)*3.05+1*2*(0.75+0.5)*3.05+2*2*(0.75+0.5)*3.05+1*2*(0.75+0.5)*3.05+3*2*(1.2+0.3)*3.05+6*2*(1.2+0.3)*3.05+1*2*(1.2+0.3)*3.05+15*2*(1.2+0.3)*3.05+1*2*(2.85+1.075)*3.05
A57: M | B57: Concrete wall (both faces) | C57: =2*22.05*3.05+2*21.825*3.05+2*25.57*3.05 -> 423.6145 | D57: m2 | E57: =RATES!$D$36 -> 185 | F57: =C57*E57 -> 78368.683 | G57: 2*22.05*3.05+2*21.825*3.05+2*25.57*3.05
A59: N | B59: Soffits of stair flights, landings and risers | C59: =(2*3.424*1.8+15.0+22*0.15*1.8)+(2*3.424*1.8+15.0+22*0.15*1.8) -> 66.5328 | D59: m2 | E59: =RATES!$D$42 -> 230 | F59: =C59*E59 -> 15302.544 | G59: (2*3.424*1.8+15.0+22*0.15*1.8)+(2*3.424*1.8+15.0+22*0.15*1.8)
A61: P | B61: Side and soffits of lintel / coping | C61: =(10*(1+0.3)+19*(0.9+0.3)+21*(0.75+0.3)+2*(0.7+0.3)+3*(1.2+0.3)+3*(1+0.3)+3*(1+0.3)+2*(0.9+0.3)+1*(1.5+0.3)+3*(0.9+0.3)+5*(0.75+0.3)+1*(0.45+0.3)+3*(0.6+0.3)+1*(3+0.3)+4*(1.6+0.3)+3*(1.3+0.3)+5*(1.8+0.3)+1*(1.2+0.3)+7*(1.8+0.3)+13*(0.9+0.3)+2*(1.8+0.3)+4*(1.2+0.3)+10*(1.2+0.3)+1*(1.2+0.3)+8*(1.5+0.3)+4*(1.5+0.3)+1*(2.4+0.3)+1*(3+0.3)+4*(1.8+0.3)+1*(0.75+0.3)+1*(1.45+0.3)+12*(0.9+0.3)+5*(0.75+0.3)+1*(0.6+0.3)+1*(1.2+0.3))*(2*0.225+0.15) -> 140.52 | D61: m2 | E61: =RATES!$D$43 -> 180 | F61: =C61*E61 -> 25293.6 | G61: (10*(1+0.3)+19*(0.9+0.3)+21*(0.75+0.3)+2*(0.7+0.3)+3*(1.2+0.3)+3*(1+0.3)+3*(1+0.3)+2*(0.9+0.3)+1*(1.5+0.3)+3*(0.9+0.3)+5*(0.75+0.3)+1*(0.45+0.3)+3*(0.6+0.3)+1*(3+0.3)+4*(1.6+0.3)+3*(1.3+0.3)+5*(1.8+0.3)+1*(1.2+0.3)+7*(1.8+0.3)+13*(0.9+0.3)+2*(1.8+...
B63: E30 REINFORCEMENT - High tensile yield round bar reinforcement (standard) to BS 4449:
A64: Q | B64: 10mm diameter in columns | C64: =4.551 -> 4.551 | D64: t | E64: =RATES!$D$29 -> 20500 | F64: =C64*E64 -> 93295.5 | G64: 4.551
A66: R | B66: 20mm diameter in columns | C66: =7.133 -> 7.133 | D66: t | E66: =RATES!$D$32 -> 19000 | F66: =C66*E66 -> 135527 | G66: 7.133
A68: S | B68: 10mm diameter in beams (links) | C68: =1.164 -> 1.164 | D68: t | E68: =RATES!$D$29 -> 20500 | F68: =C68*E68 -> 23862 | G68: 1.164
A70: T | B70: 16mm diameter in beams | C70: =1.003 -> 1.003 | D70: t | E70: =RATES!$D$31 -> 19500 | F70: =C70*E70 -> 19558.5 | G70: 1.003
A72: U | B72: 20mm diameter in beams | C72: =2.162 -> 2.162 | D72: t | E72: =RATES!$D$32 -> 19000 | F72: =C72*E72 -> 41078 | G72: 2.162
A74: V | B74: 25mm diameter in beams | C74: =2.016 -> 2.016 | D74: t | E74: =RATES!$D$33 -> 19000 | F74: =C74*E74 -> 38304 | G74: 2.016
A76: W | B76: 10mm diameter in shear & lift walls (links) | C76: =1.442+0.636 -> 2.078 | D76: t | E76: =RATES!$D$29 -> 20500 | F76: =C76*E76 -> 42599 | G76: 1.442+0.636
A78: X | B78: 12mm diameter in shear, lift & ramp walls | C78: =1.917+0.866 -> 2.783 | D78: t | E78: =RATES!$D$30 -> 20000 | F78: =C78*E78 -> 55660 | G78: 1.917+0.866
A80: Y | B80: 25mm diameter in shear & lift walls | C80: =11.314+5.441 -> 16.755 | D80: t | E80: =RATES!$D$33 -> 19000 | F80: =C80*E80 -> 318345 | G80: 11.314+5.441
A82: Z | B82: 12mm diameter in stairs | C82: =0.880 -> 0.88 | D82: t | E82: =RATES!$D$30 -> 20000 | F82: =C82*E82 -> 17600 | G82: 0.880
A84: A | B84: 16mm diameter in stairs | C84: =1.434 -> 1.434 | D84: t | E84: =RATES!$D$31 -> 19500 | F84: =C84*E84 -> 27963 | G84: 1.434
A86: B | B86: 12mm diameter for suspended slab | C86: =56.828 -> 56.828 | D86: t | E86: =RATES!$D$30 -> 20000 | F86: =C86*E86 -> 1136560 | G86: 56.828
A88: C | B88: 16mm diameter for suspended slab | C88: =0.146 -> 0.146 | D88: t | E88: =RATES!$D$31 -> 19500 | F88: =C88*E88 -> 2847 | G88: 0.146
B90: =B31 -> ELEMENT NO. 1: IN SITU CONCRETE/LARGE PRECAST CONCRETE | F90: =SUM(F33:F89) -> 3579714.6
B91: Carried to Bill Summary
B94: ELEMENT NO. 2: MASONRY
B96: F10 BRICK/BLOCK WALL - Solid sandcrete blockwork in cement and sand (1:4) mortar as described in:
A97: A | B97: 150mm thick wall | C97: =500.0*3.05+(10*1*(3.05-2.2)+19*0.9*(3.05-2.2)+21*0.75*(3.05-2.2)+2*0.7*(3.05-2.2)+3*1.2*(3.05-2.2)+3*1*(3.05-2.2)+3*1*(3.05-2.2)+2*0.9*(3.05-2.2)+1*1.5*(3.05-2.2)+3*0.9*(3.05-2.2)+5*0.75*(3.05-2.2)+1*0.45*(3.05-2.2)+3*0.6*(3.05-2.2)+1*3*(3.05-2.2)+4*1.6*(3.05-2.2)+3*1.3*(3.05-2.2)+5*1.8*(3.05-2.2)+1*1.2*(3.05-2.2)+7*1.8*(3.05-1.3)+13*0.9*(3.05-1.3)+2*1.8*(3.05-1.6)+4*1.2*(3.05-1.9)+10*1.2*(3.05-1.15)+1*1.2*(3.05-1.2)+8*1.5*(3.05-1.3)+4*1.5*(3.05-1.15)+1*2.4*(3.05-1.3)+1*3*(3.05-1.6)+4*1.8*(3.05-1.9)+1*0.75*(3.05-1.3)+1*1.45*(3.05-1.9)+12*0.9*(3.05-0.6)+5*0.75*(3.05-0.6)+1*0.6*(3.05-0.6)+1*1.2*(3.05-0.6))*0.914 -> 1750.301 | D97: m2 | E97: =RATES!$D$46 -> 215 | F97: =C97*E97 -> 376314.71 | G97: 500.0*3.05+(10*1*(3.05-2.2)+19*0.9*(3.05-2.2)+21*0.75*(3.05-2.2)+2*0.7*(3.05-2.2)+3*1.2*(3.05-2.2)+3*1*(3.05-2.2)+3*1*(3.05-2.2)+2*0.9*(3.05-2.2)+1*1.5*(3.05-2.2)+3*0.9*(3.05-2.2)+5*0.75*(3.05-2.2)+1*0.45*(3.05-2.2)+3*0.6*(3.05-2.2)+1*3*(3.05-2.2)...
A99: B | B99: 200mm thick wall | C99: =47.2*3.05+(10*1*(3.05-2.2)+19*0.9*(3.05-2.2)+21*0.75*(3.05-2.2)+2*0.7*(3.05-2.2)+3*1.2*(3.05-2.2)+3*1*(3.05-2.2)+3*1*(3.05-2.2)+2*0.9*(3.05-2.2)+1*1.5*(3.05-2.2)+3*0.9*(3.05-2.2)+5*0.75*(3.05-2.2)+1*0.45*(3.05-2.2)+3*0.6*(3.05-2.2)+1*3*(3.05-2.2)+4*1.6*(3.05-2.2)+3*1.3*(3.05-2.2)+5*1.8*(3.05-2.2)+1*1.2*(3.05-2.2)+7*1.8*(3.05-1.3)+13*0.9*(3.05-1.3)+2*1.8*(3.05-1.6)+4*1.2*(3.05-1.9)+10*1.2*(3.05-1.15)+1*1.2*(3.05-1.2)+8*1.5*(3.05-1.3)+4*1.5*(3.05-1.15)+1*2.4*(3.05-1.3)+1*3*(3.05-1.6)+4*1.8*(3.05-1.9)+1*0.75*(3.05-1.3)+1*1.45*(3.05-1.9)+12*0.9*(3.05-0.6)+5*0.75*(3.05-0.6)+1*0.6*(3.05-0.6)+1*1.2*(3.05-0.6))*0.086 -> 165.159 | D99: m2 | E99: =RATES!$D$47 -> 265 | F99: =C99*E99 -> 43767.135 | G99: 47.2*3.05+(10*1*(3.05-2.2)+19*0.9*(3.05-2.2)+21*0.75*(3.05-2.2)+2*0.7*(3.05-2.2)+3*1.2*(3.05-2.2)+3*1*(3.05-2.2)+3*1*(3.05-2.2)+2*0.9*(3.05-2.2)+1*1.5*(3.05-2.2)+3*0.9*(3.05-2.2)+5*0.75*(3.05-2.2)+1*0.45*(3.05-2.2)+3*0.6*(3.05-2.2)+1*3*(3.05-2.2)+...
B101: =B94 -> ELEMENT NO. 2: MASONRY | F101: =SUM(F96:F100) -> 420081.85
B102: Carried to Bill Summary
B105: ELEMENT NO. 4: WINDOWS/DOORS
B107: L20 DOORS - Supply and fix the following door assemblies complete with frames, ironmongery sets to steel doors and all accessories:
A108: A | B108: 1000mm x 2200mm 1-hour fire-rated galvanised steel single-leaf security door assembly (D2) | C108: =10 -> 10 | D108: nr | E108: =RATES!$D$75 -> 7800 | F108: =C108*E108 -> 78000 | G108: 10
A110: B | B110: 900mm x 2200mm single leaf timber panel door (D3) | C110: =19 -> 19 | D110: nr | E110: =RATES!$D$76 -> 3400 | F110: =C110*E110 -> 64600 | G110: 19
A112: C | B112: 750mm x 2200mm single leaf timber flush door (D6) | C112: =21 -> 21 | D112: nr | E112: =RATES!$D$79 -> 1900 | F112: =C112*E112 -> 39900 | G112: 21
A114: D | B114: 700mm x 2200mm single-leaf 2-hour fire-rated galvanised steel door (D7) | C114: =2 -> 2 | D114: nr | E114: =RATES!$D$80 -> 6800 | F114: =C114*E114 -> 13600 | G114: 2
A116: E | B116: 1200mm x 2200mm 1-hour fire-rated leaf-and-a-half galvanised steel security door assembly (D8) | C116: =3 -> 3 | D116: nr | E116: =RATES!$D$81 -> 9800 | F116: =C116*E116 -> 29400 | G116: 3
A118: F | B118: 1000mm x 2200mm 1-hour fire-rated galvanised steel single-leaf security door assembly - emergency stairs (ED1) | C118: =3 -> 3 | D118: nr | E118: =RATES!$D$82 -> 7200 | F118: =C118*E118 -> 21600 | G118: 3
A120: G | B120: 1000mm x 2200mm 1-hour fire-rated galvanised steel single-leaf security door with translucent glass panel (ED2) | C120: =3 -> 3 | D120: nr | E120: =RATES!$D$83 -> 8100 | F120: =C120*E120 -> 24300 | G120: 3
A122: H | B122: 900mm x 2200mm 1-hour fire-rated galvanised steel single-leaf security door assembly (D9) | C122: =2 -> 2 | D122: nr | E122: =RATES!$D$84 -> 6900 | F122: =C122*E122 -> 13800 | G122: 2
A124: J | B124: 1500mm x 2200mm timber bi-fold door (FD1) | C124: =1 -> 1 | D124: nr | E124: =RATES!$D$86 -> 4600 | F124: =C124*E124 -> 4600 | G124: 1
A126: K | B126: 900mm x 2200mm screw-fixed galvanised steel service access panel (M1) | C126: =3 -> 3 | D126: nr | E126: =RATES!$D$87 -> 2900 | F126: =C126*E126 -> 8700 | G126: 3
A128: L | B128: 750mm x 2200mm screw-fixed galvanised steel service access panel (M2) | C128: =5 -> 5 | D128: nr | E128: =RATES!$D$88 -> 2600 | F128: =C128*E128 -> 13000 | G128: 5
A130: M | B130: 450mm x 2200mm screw-fixed galvanised steel service access panel (M3) | C130: =1 -> 1 | D130: nr | E130: =RATES!$D$89 -> 1900 | F130: =C130*E130 -> 1900 | G130: 1
A132: N | B132: 600mm x 2200mm screw-fixed galvanised steel service access panel (M5) | C132: =3 -> 3 | D132: nr | E132: =RATES!$D$90 -> 2200 | F132: =C132*E132 -> 6600 | G132: 3
A134: P | B134: 3000mm x 2200mm 3-panel galvanised steel framed tempered glass sliding door (SD1) | C134: =1 -> 1 | D134: nr | E134: =RATES!$D$94 -> 14500 | F134: =C134*E134 -> 14500 | G134: 1
A136: Q | B136: 1600mm x 2200mm 2-panel galvanised steel framed tempered glass sliding door (SD2) | C136: =4 -> 4 | D136: nr | E136: =RATES!$D$95 -> 8800 | F136: =C136*E136 -> 35200 | G136: 4
A138: R | B138: 1300mm x 2200mm 2-panel galvanised steel framed tempered glass sliding door (SD3) | C138: =3 -> 3 | D138: nr | E138: =RATES!$D$96 -> 7600 | F138: =C138*E138 -> 22800 | G138: 3
A140: S | B140: 1800mm x 2200mm 2-panel galvanised steel framed tempered glass sliding door (SD4) | C140: =5 -> 5 | D140: nr | E140: =RATES!$D$97 -> 9300 | F140: =C140*E140 -> 46500 | G140: 5
A142: T | B142: 1200mm x 2200mm 2-panel galvanised steel framed tempered glass sliding door (SD5) | C142: =1 -> 1 | D142: nr | E142: =RATES!$D$98 -> 7200 | F142: =C142*E142 -> 7200 | G142: 1
A144: U | B144: 50mm x 150mm frames (to timber doors) | C144: =19*(2*2.2+0.9)+21*(2*2.2+0.75)+1*(2*2.2+1.5) -> 214.75 | D144: m | E144: =RATES!$D$100 -> 125 | F144: =C144*E144 -> 26843.75 | G144: 19*(2*2.2+0.9)+21*(2*2.2+0.75)+1*(2*2.2+1.5)
A146: V | B146: 50mm x 12mm door stop | C146: =19*(2*2.2+0.9)+21*(2*2.2+0.75)+1*(2*2.2+1.5) -> 214.75 | D146: m | E146: =RATES!$D$101 -> 28 | F146: =C146*E146 -> 6013 | G146: 19*(2*2.2+0.9)+21*(2*2.2+0.75)+1*(2*2.2+1.5)
B148: Ironmongery - Supply and fix the following approved ironmongery to hardwood with accompanying patented screws:
A149: W | B149: Pair 100mm brass butt hinges | C149: =60 -> 60 | D149: pr | E149: =RATES!$D$102 -> 125 | F149: =C149*E149 -> 7500 | G149: 60
A151: X | B151: Ordinary locks | C151: =19 -> 19 | D151: nr | E151: =RATES!$D$103 -> 480 | F151: =C151*E151 -> 9120 | G151: 19
A153: Y | B153: Approved high quality mortice indicator lock | C153: =21 -> 21 | D153: nr | E153: =RATES!$D$104 -> 560 | F153: =C153*E153 -> 11760 | G153: 21
B155: ALUMINIUM GLAZED WINDOWS - Supply and install Italian extruded aluminium glazed windows, ALCOA R50 series, powder coated aluminium profile, glazed with 6mm tinted reflective glass secured onto galvanized steel sub-frames, complete with all accessories as per Architect's detail:
A156: Z | B156: 2 bay alu. framed glass sliding window 1800mm x 1300mm (W2) | C156: =7 -> 7 | D156: nr | E156: =RATES!$D$109 -> 3861 | F156: =C156*E156 -> 27027 | G156: 7
A158: A | B158: 1 bay alu. framed glass awning window 900mm x 1300mm (W4) | C158: =13 -> 13 | D158: nr | E158: =RATES!$D$111 -> 1930.5 | F158: =C158*E158 -> 25096.5 | G158: 13
A160: B | B160: 2 bay alu. framed glass sliding window 1800mm x 1600mm (W7) | C160: =2 -> 2 | D160: nr | E160: =RATES!$D$114 -> 4752 | F160: =C160*E160 -> 9504 | G160: 2
A162: C | B162: 1 x 3 bay alu. framed glass awning window 1200mm x 1900mm (W8) | C162: =4 -> 4 | D162: nr | E162: =RATES!$D$115 -> 3762 | F162: =C162*E162 -> 15048 | G162: 4
A164: D | B164: 2 bay alu. framed glass sliding window 1200mm x 1150mm (W9) | C164: =10 -> 10 | D164: nr | E164: =RATES!$D$116 -> 2277 | F164: =C164*E164 -> 22770 | G164: 10
A166: E | B166: 2 bay alu. framed glass sliding window 1200mm x 1200mm (W10) | C166: =1 -> 1 | D166: nr | E166: =RATES!$D$117 -> 2376 | F166: =C166*E166 -> 2376 | G166: 1
A168: F | B168: 2 bay alu. framed glass sliding window 1500mm x 1300mm (W11) | C168: =8 -> 8 | D168: nr | E168: =RATES!$D$118 -> 3217.5 | F168: =C168*E168 -> 25740 | G168: 8
A170: G | B170: 2 bay alu. framed glass sliding window 1500mm x 1150mm (W12) | C170: =4 -> 4 | D170: nr | E170: =RATES!$D$119 -> 2846.25 | F170: =C170*E170 -> 11385 | G170: 4
A172: H | B172: 3 bay alu. framed glass awning window 2400mm x 1300mm (W13) | C172: =1 -> 1 | D172: nr | E172: =RATES!$D$120 -> 5148 | F172: =C172*E172 -> 5148 | G172: 1
A174: J | B174: 3 bay alu. framed glass sliding window 3000mm x 1600mm (W15) | C174: =1 -> 1 | D174: nr | E174: =RATES!$D$122 -> 7920 | F174: =C174*E174 -> 7920 | G174: 1
A176: K | B176: 2 x 3 alu. framed glass awning window 1800mm x 1900mm (W17) | C176: =4 -> 4 | D176: nr | E176: =RATES!$D$124 -> 5643 | F176: =C176*E176 -> 22572 | G176: 4
A178: L | B178: 1 bay alu. framed glass awning window 750mm x 1300mm (W18) | C178: =1 -> 1 | D178: nr | E178: =RATES!$D$125 -> 1608.75 | F178: =C178*E178 -> 1608.75 | G178: 1
A180: M | B180: 2 x 3 alu. framed glass awning window 1450mm x 1900mm (W20) | C180: =1 -> 1 | D180: nr | E180: =RATES!$D$127 -> 4545.75 | F180: =C180*E180 -> 4545.75 | G180: 1
A182: N | B182: 2 bay alu. framed glass sliding window 900mm x 600mm (HW1) | C182: =12 -> 12 | D182: nr | E182: =RATES!$D$128 -> 891 | F182: =C182*E182 -> 10692 | G182: 12
A184: P | B184: 2 bay alu. framed glass sliding window 750mm x 600mm (HW2) | C184: =5 -> 5 | D184: nr | E184: =RATES!$D$129 -> 742.5 | F184: =C184*E184 -> 3712.5 | G184: 5
A186: Q | B186: 2 bay alu. framed glass sliding window 600mm x 600mm (HW3) | C186: =1 -> 1 | D186: nr | E186: =RATES!$D$130 -> 594 | F186: =C186*E186 -> 594 | G186: 1
A188: R | B188: 2 bay alu. framed glass sliding window 1200mm x 600mm (HW4) | C188: =1 -> 1 | D188: nr | E188: =RATES!$D$131 -> 1188 | F188: =C188*E188 -> 1188 | G188: 1
...

Sheet 4TH FLR 
A1: ='PRELIMS & GEN. ITEMS'!A2 -> PROJECT: BLOCK N REDEVELOPMENT
A2: ='PRELIMS & GEN. ITEMS'!A3 -> LOCATION: KANESHIE
A3: ='PRELIMS & GEN. ITEMS'!A4 -> CLIENT: STATE HOUSING LIMITED
A4: ='PRELIMS & GEN. ITEMS'!A5 -> DATE:9/30/2026
A5: ITEM | B5: DESCRIPTION | C5: QTY | D5: UNIT | E5: RATE | F5: AMOUNT - GHC | G5: Measurement basis / calculation
B7: MAIN BUILDING
B9: FOURTH FLOOR
B11: BILL SUMMARY
A13: A | B13: ELEMENT NO. 1: IN SITU CONCRETE/LARGE PRECAST CONCRETE | F13: =F92 -> 3356708.8
A15: B | B15: ELEMENT NO. 2: MASONRY | F15: =F103 -> 385904.19
A17: C | B17: ELEMENT NO. 4: WINDOWS/DOORS | F17: =F192 -> 624892.6
A19: D | B19: ELEMENT NO. 5: FLOOR FINISHES | F19: =F213 -> 344765.54
A21: E | B21: ELEMENT NO. 6: WALL FINISHES | F21: =F230 -> 304843.68
A23: F | B23: ELEMENT NO. 7: PAINTING AND DECORATING | F23: =F251 -> 180310.77
B25: =B9 -> FOURTH FLOOR | E25: GHC | F25: =SUM(F13:F24) -> 5197425.6
B26: To Bill General Summary
B29: BILL NR. 7 - FOURTH FLOOR
B31: ELEMENT NO. 1: IN SITU CONCRETE/LARGE PRECAST CONCRETE
B33: Vibrated in-situ concrete C40 as described in:
A34: A | B34: Suspended slab 250mm thick | C34: =1134.6*0.25 -> 283.65 | D34: m3 | E34: =RATES!$D$22 -> 2650 | F34: =C34*E34 -> 751672.5 | G34: 1134.6*0.25
A36: B | B36: Beams (downstands below slab) | C36: =166.8*0.3*0.35+33.1*0.2*0.35 -> 19.831 | D36: m3 | E36: =RATES!$D$23 -> 2700 | F36: =C36*E36 -> 53543.7 | G36: 166.8*0.3*0.35+33.1*0.2*0.35
A38: C | B38: Columns | C38: =5*0.75*0.5*3.05+1*0.75*0.5*3.05+2*0.75*0.5*3.05+1*0.75*0.5*3.05+3*1.2*0.3*3.05+6*1.2*0.3*3.05+1*1.2*0.3*3.05+15*1.2*0.3*3.05+1*(2.85*0.25+0.825*0.25)*3.05 -> 40.545937 | D38: m3 | E38: =RATES!$D$21 -> 2800 | F38: =C38*E38 -> 113528.62 | G38: 5*0.75*0.5*3.05+1*0.75*0.5*3.05+2*0.75*0.5*3.05+1*0.75*0.5*3.05+3*1.2*0.3*3.05+6*1.2*0.3*3.05+1*1.2*0.3*3.05+15*1.2*0.3*3.05+1*(2.85*0.25+0.825*0.25)*3.05
A40: D | B40: Concrete wall - shear walls to main & emergency stair cores, 250mm thick | C40: =22.05*3.05*0.25+25.57*3.05*0.25 -> 36.31025 | D40: m3 | E40: =RATES!$D$20 -> 2750 | F40: =C40*E40 -> 99853.187 | G40: 22.05*3.05*0.25+25.57*3.05*0.25
A42: E | B42: Concrete wall - lift walls, 250mm thick | C42: =21.825*3.05*0.25 -> 16.641562 | D42: m3 | E42: =RATES!$D$20 -> 2750 | F42: =C42*E42 -> 45764.297 | G42: 21.825*3.05*0.25
A44: F | B44: Stairs | C44: =(2.966*3.3/3.3+2.625)+(2.966*3.3/3.3+2.625) -> 11.182 | D44: m3 | E44: =RATES!$D$24 -> 2850 | F44: =C44*E44 -> 31868.7 | G44: (2.966*3.3/3.3+2.625)+(2.966*3.3/3.3+2.625)
A46: G | B46: Lintels 150 x 225mm over door and window openings | C46: =(8*(1+0.3)+15*(0.9+0.3)+22*(0.75+0.3)+1*(0.7+0.3)+3*(1.2+0.3)+3*(1+0.3)+3*(1+0.3)+2*(0.9+0.3)+1*(1.5+0.3)+3*(0.9+0.3)+5*(0.75+0.3)+1*(0.45+0.3)+3*(0.6+0.3)+1*(3+0.3)+4*(1.6+0.3)+2*(1.3+0.3)+4*(1.8+0.3)+1*(1.2+0.3)+6*(1.8+0.3)+10*(0.9+0.3)+2*(1.8+0.3)+3*(1.2+0.3)+8*(1.2+0.3)+1*(1.2+0.3)+7*(1.5+0.3)+4*(1.5+0.3)+1*(2.4+0.3)+1*(3+0.3)+3*(1.8+0.3)+1*(0.75+0.3)+1*(1.45+0.3)+13*(0.9+0.3)+5*(0.75+0.3)+2*(0.6+0.3)+2*(1.2+0.3))*0.15*0.225 -> 7.1769375 | D46: m3 | E46: =RATES!$D$25 -> 2600 | F46: =C46*E46 -> 18660.038 | G46: (8*(1+0.3)+15*(0.9+0.3)+22*(0.75+0.3)+1*(0.7+0.3)+3*(1.2+0.3)+3*(1+0.3)+3*(1+0.3)+2*(0.9+0.3)+1*(1.5+0.3)+3*(0.9+0.3)+5*(0.75+0.3)+1*(0.45+0.3)+3*(0.6+0.3)+1*(3+0.3)+4*(1.6+0.3)+2*(1.3+0.3)+4*(1.8+0.3)+1*(1.2+0.3)+6*(1.8+0.3)+10*(0.9+0.3)+2*(1.8+0...
B48: E20 FORMWORK - Formwork as described to:
A49: H | B49: Soffits of suspended slab | C49: =1134.6 -> 1134.6 | D49: m2 | E49: =RATES!$D$38 -> 170 | F49: =C49*E49 -> 192882 | G49: 1134.6
A51: J | B51: Edges of suspended slab 250mm high | C51: =294.6 -> 294.6 | D51: m | E51: =RATES!$D$40 -> 65 | F51: =C51*E51 -> 19149 | G51: 294.6
A53: K | B53: Sides and soffits of beams | C53: =166.8*(2*0.35+0.3)+33.1*(2*0.35+0.2) -> 196.59 | D53: m2 | E53: =RATES!$D$39 -> 200 | F53: =C53*E53 -> 39318 | G53: 166.8*(2*0.35+0.3)+33.1*(2*0.35+0.2)
A55: L | B55: Columns | C55: =5*2*(0.75+0.5)*3.05+1*2*(0.75+0.5)*3.05+2*2*(0.75+0.5)*3.05+1*2*(0.75+0.5)*3.05+3*2*(1.2+0.3)*3.05+6*2*(1.2+0.3)*3.05+1*2*(1.2+0.3)*3.05+15*2*(1.2+0.3)*3.05+1*2*(2.85+1.075)*3.05 -> 321.3175 | D55: m2 | E55: =RATES!$D$37 -> 190 | F55: =C55*E55 -> 61050.325 | G55: 5*2*(0.75+0.5)*3.05+1*2*(0.75+0.5)*3.05+2*2*(0.75+0.5)*3.05+1*2*(0.75+0.5)*3.05+3*2*(1.2+0.3)*3.05+6*2*(1.2+0.3)*3.05+1*2*(1.2+0.3)*3.05+15*2*(1.2+0.3)*3.05+1*2*(2.85+1.075)*3.05
A57: M | B57: Concrete wall (both faces) | C57: =2*22.05*3.05+2*21.825*3.05+2*25.57*3.05 -> 423.6145 | D57: m2 | E57: =RATES!$D$36 -> 185 | F57: =C57*E57 -> 78368.683 | G57: 2*22.05*3.05+2*21.825*3.05+2*25.57*3.05
A59: N | B59: Soffits of stair flights, landings and risers | C59: =(2*3.424*1.8+15.0+22*0.15*1.8)+(2*3.424*1.8+15.0+22*0.15*1.8) -> 66.5328 | D59: m2 | E59: =RATES!$D$42 -> 230 | F59: =C59*E59 -> 15302.544 | G59: (2*3.424*1.8+15.0+22*0.15*1.8)+(2*3.424*1.8+15.0+22*0.15*1.8)
A61: P | B61: Side and soffits of lintel / coping | C61: =(8*(1+0.3)+15*(0.9+0.3)+22*(0.75+0.3)+1*(0.7+0.3)+3*(1.2+0.3)+3*(1+0.3)+3*(1+0.3)+2*(0.9+0.3)+1*(1.5+0.3)+3*(0.9+0.3)+5*(0.75+0.3)+1*(0.45+0.3)+3*(0.6+0.3)+1*(3+0.3)+4*(1.6+0.3)+2*(1.3+0.3)+4*(1.8+0.3)+1*(1.2+0.3)+6*(1.8+0.3)+10*(0.9+0.3)+2*(1.8+0.3)+3*(1.2+0.3)+8*(1.2+0.3)+1*(1.2+0.3)+7*(1.5+0.3)+4*(1.5+0.3)+1*(2.4+0.3)+1*(3+0.3)+3*(1.8+0.3)+1*(0.75+0.3)+1*(1.45+0.3)+13*(0.9+0.3)+5*(0.75+0.3)+2*(0.6+0.3)+2*(1.2+0.3))*(2*0.225+0.15) -> 127.59 | D61: m2 | E61: =RATES!$D$43 -> 180 | F61: =C61*E61 -> 22966.2 | G61: (8*(1+0.3)+15*(0.9+0.3)+22*(0.75+0.3)+1*(0.7+0.3)+3*(1.2+0.3)+3*(1+0.3)+3*(1+0.3)+2*(0.9+0.3)+1*(1.5+0.3)+3*(0.9+0.3)+5*(0.75+0.3)+1*(0.45+0.3)+3*(0.6+0.3)+1*(3+0.3)+4*(1.6+0.3)+2*(1.3+0.3)+4*(1.8+0.3)+1*(1.2+0.3)+6*(1.8+0.3)+10*(0.9+0.3)+2*(1.8+0...
B63: E30 REINFORCEMENT - High tensile yield round bar reinforcement (standard) to BS 4449:
A64: Q | B64: 10mm diameter in columns | C64: =4.551 -> 4.551 | D64: t | E64: =RATES!$D$29 -> 20500 | F64: =C64*E64 -> 93295.5 | G64: 4.551
A66: R | B66: 20mm diameter in columns | C66: =7.133 -> 7.133 | D66: t | E66: =RATES!$D$32 -> 19000 | F66: =C66*E66 -> 135527 | G66: 7.133
A68: S | B68: 10mm diameter in beams (links) | C68: =1.806 -> 1.806 | D68: t | E68: =RATES!$D$29 -> 20500 | F68: =C68*E68 -> 37023 | G68: 1.806
A70: T | B70: 16mm diameter in beams | C70: =1.248 -> 1.248 | D70: t | E70: =RATES!$D$31 -> 19500 | F70: =C70*E70 -> 24336 | G70: 1.248
A72: U | B72: 20mm diameter in beams | C72: =2.135 -> 2.135 | D72: t | E72: =RATES!$D$32 -> 19000 | F72: =C72*E72 -> 40565 | G72: 2.135
A74: V | B74: 25mm diameter in beams | C74: =5.507 -> 5.507 | D74: t | E74: =RATES!$D$33 -> 19000 | F74: =C74*E74 -> 104633 | G74: 5.507
A76: W | B76: 10mm diameter in shear & lift walls (links) | C76: =1.442+0.636 -> 2.078 | D76: t | E76: =RATES!$D$29 -> 20500 | F76: =C76*E76 -> 42599 | G76: 1.442+0.636
A78: X | B78: 12mm diameter in shear, lift & ramp walls | C78: =1.917+0.866 -> 2.783 | D78: t | E78: =RATES!$D$30 -> 20000 | F78: =C78*E78 -> 55660 | G78: 1.917+0.866
A80: Y | B80: 20mm diameter in shear & lift walls | C80: =6.904 -> 6.904 | D80: t | E80: =RATES!$D$32 -> 19000 | F80: =C80*E80 -> 131176 | G80: 6.904
A82: Z | B82: 25mm diameter in shear & lift walls | C82: =5.441 -> 5.441 | D82: t | E82: =RATES!$D$33 -> 19000 | F82: =C82*E82 -> 103379 | G82: 5.441
A84: A | B84: 12mm diameter in stairs | C84: =0.880 -> 0.88 | D84: t | E84: =RATES!$D$30 -> 20000 | F84: =C84*E84 -> 17600 | G84: 0.880
A86: B | B86: 16mm diameter in stairs | C86: =1.434 -> 1.434 | D86: t | E86: =RATES!$D$31 -> 19500 | F86: =C86*E86 -> 27963 | G86: 1.434
A88: C | B88: 12mm diameter for suspended slab | C88: =49.804 -> 49.804 | D88: t | E88: =RATES!$D$30 -> 20000 | F88: =C88*E88 -> 996080 | G88: 49.804
A90: D | B90: 16mm diameter for suspended slab | C90: =0.151 -> 0.151 | D90: t | E90: =RATES!$D$31 -> 19500 | F90: =C90*E90 -> 2944.5 | G90: 0.151
B92: =B31 -> ELEMENT NO. 1: IN SITU CONCRETE/LARGE PRECAST CONCRETE | F92: =SUM(F33:F91) -> 3356708.8
B93: Carried to Bill Summary
B96: ELEMENT NO. 2: MASONRY
B98: F10 BRICK/BLOCK WALL - Solid sandcrete blockwork in cement and sand (1:4) mortar as described in:
A99: A | B99: 150mm thick wall | C99: =443.9*3.05+(8*1*(3.05-2.2)+15*0.9*(3.05-2.2)+22*0.75*(3.05-2.2)+1*0.7*(3.05-2.2)+3*1.2*(3.05-2.2)+3*1*(3.05-2.2)+3*1*(3.05-2.2)+2*0.9*(3.05-2.2)+1*1.5*(3.05-2.2)+3*0.9*(3.05-2.2)+5*0.75*(3.05-2.2)+1*0.45*(3.05-2.2)+3*0.6*(3.05-2.2)+1*3*(3.05-2.2)+4*1.6*(3.05-2.2)+2*1.3*(3.05-2.2)+4*1.8*(3.05-2.2)+1*1.2*(3.05-2.2)+6*1.8*(3.05-1.3)+10*0.9*(3.05-1.3)+2*1.8*(3.05-1.6)+3*1.2*(3.05-1.9)+8*1.2*(3.05-1.15)+1*1.2*(3.05-1.2)+7*1.5*(3.05-1.3)+4*1.5*(3.05-1.15)+1*2.4*(3.05-1.3)+1*3*(3.05-1.6)+3*1.8*(3.05-1.9)+1*0.75*(3.05-1.3)+1*1.45*(3.05-1.9)+13*0.9*(3.05-0.6)+5*0.75*(3.05-0.6)+2*0.6*(3.05-0.6)+2*1.2*(3.05-0.6))*0.889 -> 1555.9225 | D99: m2 | E99: =RATES!$D$46 -> 215 | F99: =C99*E99 -> 334523.33 | G99: 443.9*3.05+(8*1*(3.05-2.2)+15*0.9*(3.05-2.2)+22*0.75*(3.05-2.2)+1*0.7*(3.05-2.2)+3*1.2*(3.05-2.2)+3*1*(3.05-2.2)+3*1*(3.05-2.2)+2*0.9*(3.05-2.2)+1*1.5*(3.05-2.2)+3*0.9*(3.05-2.2)+5*0.75*(3.05-2.2)+1*0.45*(3.05-2.2)+3*0.6*(3.05-2.2)+1*3*(3.05-2.2)+...
A101: B | B101: 200mm thick wall | C101: =55.3*3.05+(8*1*(3.05-2.2)+15*0.9*(3.05-2.2)+22*0.75*(3.05-2.2)+1*0.7*(3.05-2.2)+3*1.2*(3.05-2.2)+3*1*(3.05-2.2)+3*1*(3.05-2.2)+2*0.9*(3.05-2.2)+1*1.5*(3.05-2.2)+3*0.9*(3.05-2.2)+5*0.75*(3.05-2.2)+1*0.45*(3.05-2.2)+3*0.6*(3.05-2.2)+1*3*(3.05-2.2)+4*1.6*(3.05-2.2)+2*1.3*(3.05-2.2)+4*1.8*(3.05-2.2)+1*1.2*(3.05-2.2)+6*1.8*(3.05-1.3)+10*0.9*(3.05-1.3)+2*1.8*(3.05-1.6)+3*1.2*(3.05-1.9)+8*1.2*(3.05-1.15)+1*1.2*(3.05-1.2)+7*1.5*(3.05-1.3)+4*1.5*(3.05-1.15)+1*2.4*(3.05-1.3)+1*3*(3.05-1.6)+3*1.8*(3.05-1.9)+1*0.75*(3.05-1.3)+1*1.45*(3.05-1.9)+13*0.9*(3.05-0.6)+5*0.75*(3.05-0.6)+2*0.6*(3.05-0.6)+2*1.2*(3.05-0.6))*0.111 -> 193.89003 | D101: m2 | E101: =RATES!$D$47 -> 265 | F101: =C101*E101 -> 51380.857 | G101: 55.3*3.05+(8*1*(3.05-2.2)+15*0.9*(3.05-2.2)+22*0.75*(3.05-2.2)+1*0.7*(3.05-2.2)+3*1.2*(3.05-2.2)+3*1*(3.05-2.2)+3*1*(3.05-2.2)+2*0.9*(3.05-2.2)+1*1.5*(3.05-2.2)+3*0.9*(3.05-2.2)+5*0.75*(3.05-2.2)+1*0.45*(3.05-2.2)+3*0.6*(3.05-2.2)+1*3*(3.05-2.2)+4...
B103: =B96 -> ELEMENT NO. 2: MASONRY | F103: =SUM(F98:F102) -> 385904.19
B104: Carried to Bill Summary
B107: ELEMENT NO. 4: WINDOWS/DOORS
B109: L20 DOORS - Supply and fix the following door assemblies complete with frames, ironmongery sets to steel doors and all accessories:
A110: A | B110: 1000mm x 2200mm 1-hour fire-rated galvanised steel single-leaf security door assembly (D2) | C110: =8 -> 8 | D110: nr | E110: =RATES!$D$75 -> 7800 | F110: =C110*E110 -> 62400 | G110: 8
A112: B | B112: 900mm x 2200mm single leaf timber panel door (D3) | C112: =15 -> 15 | D112: nr | E112: =RATES!$D$76 -> 3400 | F112: =C112*E112 -> 51000 | G112: 15
A114: C | B114: 750mm x 2200mm single leaf timber flush door (D6) | C114: =22 -> 22 | D114: nr | E114: =RATES!$D$79 -> 1900 | F114: =C114*E114 -> 41800 | G114: 22
A116: D | B116: 700mm x 2200mm single-leaf 2-hour fire-rated galvanised steel door (D7) | C116: =1 -> 1 | D116: nr | E116: =RATES!$D$80 -> 6800 | F116: =C116*E116 -> 6800 | G116: 1
A118: E | B118: 1200mm x 2200mm 1-hour fire-rated leaf-and-a-half galvanised steel security door assembly (D8) | C118: =3 -> 3 | D118: nr | E118: =RATES!$D$81 -> 9800 | F118: =C118*E118 -> 29400 | G118: 3
A120: F | B120: 1000mm x 2200mm 1-hour fire-rated galvanised steel single-leaf security door assembly - emergency stairs (ED1) | C120: =3 -> 3 | D120: nr | E120: =RATES!$D$82 -> 7200 | F120: =C120*E120 -> 21600 | G120: 3
A122: G | B122: 1000mm x 2200mm 1-hour fire-rated galvanised steel single-leaf security door with translucent glass panel (ED2) | C122: =3 -> 3 | D122: nr | E122: =RATES!$D$83 -> 8100 | F122: =C122*E122 -> 24300 | G122: 3
A124: H | B124: 900mm x 2200mm 1-hour fire-rated galvanised steel single-leaf security door assembly (D9) | C124: =2 -> 2 | D124: nr | E124: =RATES!$D$84 -> 6900 | F124: =C124*E124 -> 13800 | G124: 2
A126: J | B126: 1500mm x 2200mm timber bi-fold door (FD1) | C126: =1 -> 1 | D126: nr | E126: =RATES!$D$86 -> 4600 | F126: =C126*E126 -> 4600 | G126: 1
A128: K | B128: 900mm x 2200mm screw-fixed galvanised steel service access panel (M1) | C128: =3 -> 3 | D128: nr | E128: =RATES!$D$87 -> 2900 | F128: =C128*E128 -> 8700 | G128: 3
A130: L | B130: 750mm x 2200mm screw-fixed galvanised steel service access panel (M2) | C130: =5 -> 5 | D130: nr | E130: =RATES!$D$88 -> 2600 | F130: =C130*E130 -> 13000 | G130: 5
A132: M | B132: 450mm x 2200mm screw-fixed galvanised steel service access panel (M3) | C132: =1 -> 1 | D132: nr | E132: =RATES!$D$89 -> 1900 | F132: =C132*E132 -> 1900 | G132: 1
A134: N | B134: 600mm x 2200mm screw-fixed galvanised steel service access panel (M5) | C134: =3 -> 3 | D134: nr | E134: =RATES!$D$90 -> 2200 | F134: =C134*E134 -> 6600 | G134: 3
A136: P | B136: 3000mm x 2200mm 3-panel galvanised steel framed tempered glass sliding door (SD1) | C136: =1 -> 1 | D136: nr | E136: =RATES!$D$94 -> 14500 | F136: =C136*E136 -> 14500 | G136: 1
A138: Q | B138: 1600mm x 2200mm 2-panel galvanised steel framed tempered glass sliding door (SD2) | C138: =4 -> 4 | D138: nr | E138: =RATES!$D$95 -> 8800 | F138: =C138*E138 -> 35200 | G138: 4
A140: R | B140: 1300mm x 2200mm 2-panel galvanised steel framed tempered glass sliding door (SD3) | C140: =2 -> 2 | D140: nr | E140: =RATES!$D$96 -> 7600 | F140: =C140*E140 -> 15200 | G140: 2
A142: S | B142: 1800mm x 2200mm 2-panel galvanised steel framed tempered glass sliding door (SD4) | C142: =4 -> 4 | D142: nr | E142: =RATES!$D$97 -> 9300 | F142: =C142*E142 -> 37200 | G142: 4
A144: T | B144: 1200mm x 2200mm 2-panel galvanised steel framed tempered glass sliding door (SD5) | C144: =1 -> 1 | D144: nr | E144: =RATES!$D$98 -> 7200 | F144: =C144*E144 -> 7200 | G144: 1
A146: U | B146: 50mm x 150mm frames (to timber doors) | C146: =15*(2*2.2+0.9)+22*(2*2.2+0.75)+1*(2*2.2+1.5) -> 198.7 | D146: m | E146: =RATES!$D$100 -> 125 | F146: =C146*E146 -> 24837.5 | G146: 15*(2*2.2+0.9)+22*(2*2.2+0.75)+1*(2*2.2+1.5)
A148: V | B148: 50mm x 12mm door stop | C148: =15*(2*2.2+0.9)+22*(2*2.2+0.75)+1*(2*2.2+1.5) -> 198.7 | D148: m | E148: =RATES!$D$101 -> 28 | F148: =C148*E148 -> 5563.6 | G148: 15*(2*2.2+0.9)+22*(2*2.2+0.75)+1*(2*2.2+1.5)
B150: Ironmongery - Supply and fix the following approved ironmongery to hardwood with accompanying patented screws:
A151: W | B151: Pair 100mm brass butt hinges | C151: =56 -> 56 | D151: pr | E151: =RATES!$D$102 -> 125 | F151: =C151*E151 -> 7000 | G151: 56
A153: X | B153: Ordinary locks | C153: =15 -> 15 | D153: nr | E153: =RATES!$D$103 -> 480 | F153: =C153*E153 -> 7200 | G153: 15
A155: Y | B155: Approved high quality mortice indicator lock | C155: =22 -> 22 | D155: nr | E155: =RATES!$D$104 -> 560 | F155: =C155*E155 -> 12320 | G155: 22
B157: ALUMINIUM GLAZED WINDOWS - Supply and install Italian extruded aluminium glazed windows, ALCOA R50 series, powder coated aluminium profile, glazed with 6mm tinted reflective glass secured onto galvanized steel sub-frames, complete with all accessories as per Architect's detail:
A158: Z | B158: 2 bay alu. framed glass sliding window 1800mm x 1300mm (W2) | C158: =6 -> 6 | D158: nr | E158: =RATES!$D$109 -> 3861 | F158: =C158*E158 -> 23166 | G158: 6
A160: A | B160: 1 bay alu. framed glass awning window 900mm x 1300mm (W4) | C160: =10 -> 10 | D160: nr | E160: =RATES!$D$111 -> 1930.5 | F160: =C160*E160 -> 19305 | G160: 10
A162: B | B162: 2 bay alu. framed glass sliding window 1800mm x 1600mm (W7) | C162: =2 -> 2 | D162: nr | E162: =RATES!$D$114 -> 4752 | F162: =C162*E162 -> 9504 | G162: 2
A164: C | B164: 1 x 3 bay alu. framed glass awning window 1200mm x 1900mm (W8) | C164: =3 -> 3 | D164: nr | E164: =RATES!$D$115 -> 3762 | F164: =C164*E164 -> 11286 | G164: 3
A166: D | B166: 2 bay alu. framed glass sliding window 1200mm x 1150mm (W9) | C166: =8 -> 8 | D166: nr | E166: =RATES!$D$116 -> 2277 | F166: =C166*E166 -> 18216 | G166: 8
A168: E | B168: 2 bay alu. framed glass sliding window 1200mm x 1200mm (W10) | C168: =1 -> 1 | D168: nr | E168: =RATES!$D$117 -> 2376 | F168: =C168*E168 -> 2376 | G168: 1
A170: F | B170: 2 bay alu. framed glass sliding window 1500mm x 1300mm (W11) | C170: =7 -> 7 | D170: nr | E170: =RATES!$D$118 -> 3217.5 | F170: =C170*E170 -> 22522.5 | G170: 7
A172: G | B172: 2 bay alu. framed glass sliding window 1500mm x 1150mm (W12) | C172: =4 -> 4 | D172: nr | E172: =RATES!$D$119 -> 2846.25 | F172: =C172*E172 -> 11385 | G172: 4
A174: H | B174: 3 bay alu. framed glass awning window 2400mm x 1300mm (W13) | C174: =1 -> 1 | D174: nr | E174: =RATES!$D$120 -> 5148 | F174: =C174*E174 -> 5148 | G174: 1
A176: J | B176: 3 bay alu. framed glass sliding window 3000mm x 1600mm (W15) | C176: =1 -> 1 | D176: nr | E176: =RATES!$D$122 -> 7920 | F176: =C176*E176 -> 7920 | G176: 1
A178: K | B178: 2 x 3 alu. framed glass awning window 1800mm x 1900mm (W17) | C178: =3 -> 3 | D178: nr | E178: =RATES!$D$124 -> 5643 | F178: =C178*E178 -> 16929 | G178: 3
A180: L | B180: 1 bay alu. framed glass awning window 750mm x 1300mm (W18) | C180: =1 -> 1 | D180: nr | E180: =RATES!$D$125 -> 1608.75 | F180: =C180*E180 -> 1608.75 | G180: 1
A182: M | B182: 2 x 3 alu. framed glass awning window 1450mm x 1900mm (W20) | C182: =1 -> 1 | D182: nr | E182: =RATES!$D$127 -> 4545.75 | F182: =C182*E182 -> 4545.75 | G182: 1
A184: N | B184: 2 bay alu. framed glass sliding window 900mm x 600mm (HW1) | C184: =13 -> 13 | D184: nr | E184: =RATES!$D$128 -> 891 | F184: =C184*E184 -> 11583 | G184: 13
A186: P | B186: 2 bay alu. framed glass sliding window 750mm x 600mm (HW2) | C186: =5 -> 5 | D186: nr | E186: =RATES!$D$129 -> 742.5 | F186: =C186*E186 -> 3712.5 | G186: 5
A188: Q | B188: 2 bay alu. framed glass sliding window 600mm x 600mm (HW3) | C188: =2 -> 2 | D188: nr | E188: =RATES!$D$130 -> 594 | F188: =C188*E188 -> 1188 | G188: 2
...

Sheet 5TH FLR 
A1: ='PRELIMS & GEN. ITEMS'!A2 -> PROJECT: BLOCK N REDEVELOPMENT
A2: ='PRELIMS & GEN. ITEMS'!A3 -> LOCATION: KANESHIE
A3: ='PRELIMS & GEN. ITEMS'!A4 -> CLIENT: STATE HOUSING LIMITED
A4: ='PRELIMS & GEN. ITEMS'!A5 -> DATE:9/30/2026
A5: ITEM | B5: DESCRIPTION | C5: QTY | D5: UNIT | E5: RATE | F5: AMOUNT - GHC | G5: Measurement basis / calculation
B7: MAIN BUILDING
B9: FIFTH FLOOR
B11: BILL SUMMARY
A13: A | B13: ELEMENT NO. 1: IN SITU CONCRETE/LARGE PRECAST CONCRETE | F13: =F90 -> 3312876.5
A15: B | B15: ELEMENT NO. 2: MASONRY | F15: =F101 -> 378588.89
A17: C | B17: ELEMENT NO. 4: WINDOWS/DOORS | F17: =F190 -> 577390.45
A19: D | B19: ELEMENT NO. 5: FLOOR FINISHES | F19: =F211 -> 341125.34
A21: E | B21: ELEMENT NO. 6: WALL FINISHES | F21: =F228 -> 309236.25
A23: F | B23: ELEMENT NO. 7: PAINTING AND DECORATING | F23: =F249 -> 187552.29
B25: =B9 -> FIFTH FLOOR | E25: GHC | F25: =SUM(F13:F24) -> 5106769.7
B26: To Bill General Summary
B29: BILL NR. 8 - FIFTH FLOOR
B31: ELEMENT NO. 1: IN SITU CONCRETE/LARGE PRECAST CONCRETE
B33: Vibrated in-situ concrete C40 as described in:
A34: A | B34: Suspended slab 250mm thick | C34: =1134.6*0.25 -> 283.65 | D34: m3 | E34: =RATES!$D$22 -> 2650 | F34: =C34*E34 -> 751672.5 | G34: 1134.6*0.25
A36: B | B36: Beams (downstands below slab) | C36: =166.8*0.3*0.35+33.1*0.2*0.35 -> 19.831 | D36: m3 | E36: =RATES!$D$23 -> 2700 | F36: =C36*E36 -> 53543.7 | G36: 166.8*0.3*0.35+33.1*0.2*0.35
A38: C | B38: Columns | C38: =5*0.75*0.5*3.05+1*0.75*0.5*3.05+2*0.75*0.5*3.05+1*0.75*0.5*3.05+3*1.2*0.3*3.05+6*1.2*0.3*3.05+1*1.2*0.3*3.05+15*1.2*0.3*3.05+1*(2.85*0.25+0.825*0.25)*3.05 -> 40.545937 | D38: m3 | E38: =RATES!$D$21 -> 2800 | F38: =C38*E38 -> 113528.62 | G38: 5*0.75*0.5*3.05+1*0.75*0.5*3.05+2*0.75*0.5*3.05+1*0.75*0.5*3.05+3*1.2*0.3*3.05+6*1.2*0.3*3.05+1*1.2*0.3*3.05+15*1.2*0.3*3.05+1*(2.85*0.25+0.825*0.25)*3.05
A40: D | B40: Concrete wall - shear walls to main & emergency stair cores, 250mm thick | C40: =22.05*3.05*0.25+25.57*3.05*0.25 -> 36.31025 | D40: m3 | E40: =RATES!$D$20 -> 2750 | F40: =C40*E40 -> 99853.187 | G40: 22.05*3.05*0.25+25.57*3.05*0.25
A42: E | B42: Concrete wall - lift walls, 250mm thick | C42: =21.825*3.05*0.25 -> 16.641562 | D42: m3 | E42: =RATES!$D$20 -> 2750 | F42: =C42*E42 -> 45764.297 | G42: 21.825*3.05*0.25
A44: F | B44: Stairs | C44: =(2.966*3.3/3.3+2.625)+(2.966*3.3/3.3+2.625) -> 11.182 | D44: m3 | E44: =RATES!$D$24 -> 2850 | F44: =C44*E44 -> 31868.7 | G44: (2.966*3.3/3.3+2.625)+(2.966*3.3/3.3+2.625)
A46: G | B46: Lintels 150 x 225mm over door and window openings | C46: =(7*(1+0.3)+15*(0.9+0.3)+20*(0.75+0.3)+1*(0.7+0.3)+3*(1.2+0.3)+3*(1+0.3)+3*(1+0.3)+1*(0.9+0.3)+1*(1.5+0.3)+2*(0.9+0.3)+5*(0.75+0.3)+1*(0.45+0.3)+3*(0.6+0.3)+1*(3+0.3)+3*(1.6+0.3)+2*(1.3+0.3)+4*(1.8+0.3)+1*(1.2+0.3)+6*(1.8+0.3)+10*(0.9+0.3)+1*(1.8+0.3)+3*(1.2+0.3)+8*(1.2+0.3)+1*(1.2+0.3)+6*(1.5+0.3)+3*(1.5+0.3)+1*(2.4+0.3)+1*(3+0.3)+3*(1.8+0.3)+1*(0.75+0.3)+1*(1.45+0.3)+12*(0.9+0.3)+4*(0.75+0.3)+1*(0.6+0.3)+1*(1.2+0.3))*0.15*0.225 -> 6.56775 | D46: m3 | E46: =RATES!$D$25 -> 2600 | F46: =C46*E46 -> 17076.15 | G46: (7*(1+0.3)+15*(0.9+0.3)+20*(0.75+0.3)+1*(0.7+0.3)+3*(1.2+0.3)+3*(1+0.3)+3*(1+0.3)+1*(0.9+0.3)+1*(1.5+0.3)+2*(0.9+0.3)+5*(0.75+0.3)+1*(0.45+0.3)+3*(0.6+0.3)+1*(3+0.3)+3*(1.6+0.3)+2*(1.3+0.3)+4*(1.8+0.3)+1*(1.2+0.3)+6*(1.8+0.3)+10*(0.9+0.3)+1*(1.8+0...
B48: E20 FORMWORK - Formwork as described to:
A49: H | B49: Soffits of suspended slab | C49: =1134.6 -> 1134.6 | D49: m2 | E49: =RATES!$D$38 -> 170 | F49: =C49*E49 -> 192882 | G49: 1134.6
A51: J | B51: Edges of suspended slab 250mm high | C51: =294.6 -> 294.6 | D51: m | E51: =RATES!$D$40 -> 65 | F51: =C51*E51 -> 19149 | G51: 294.6
A53: K | B53: Sides and soffits of beams | C53: =166.8*(2*0.35+0.3)+33.1*(2*0.35+0.2) -> 196.59 | D53: m2 | E53: =RATES!$D$39 -> 200 | F53: =C53*E53 -> 39318 | G53: 166.8*(2*0.35+0.3)+33.1*(2*0.35+0.2)
A55: L | B55: Columns | C55: =5*2*(0.75+0.5)*3.05+1*2*(0.75+0.5)*3.05+2*2*(0.75+0.5)*3.05+1*2*(0.75+0.5)*3.05+3*2*(1.2+0.3)*3.05+6*2*(1.2+0.3)*3.05+1*2*(1.2+0.3)*3.05+15*2*(1.2+0.3)*3.05+1*2*(2.85+1.075)*3.05 -> 321.3175 | D55: m2 | E55: =RATES!$D$37 -> 190 | F55: =C55*E55 -> 61050.325 | G55: 5*2*(0.75+0.5)*3.05+1*2*(0.75+0.5)*3.05+2*2*(0.75+0.5)*3.05+1*2*(0.75+0.5)*3.05+3*2*(1.2+0.3)*3.05+6*2*(1.2+0.3)*3.05+1*2*(1.2+0.3)*3.05+15*2*(1.2+0.3)*3.05+1*2*(2.85+1.075)*3.05
A57: M | B57: Concrete wall (both faces) | C57: =2*22.05*3.05+2*21.825*3.05+2*25.57*3.05 -> 423.6145 | D57: m2 | E57: =RATES!$D$36 -> 185 | F57: =C57*E57 -> 78368.683 | G57: 2*22.05*3.05+2*21.825*3.05+2*25.57*3.05
A59: N | B59: Soffits of stair flights, landings and risers | C59: =(2*3.424*1.8+15.0+22*0.15*1.8)+(2*3.424*1.8+15.0+22*0.15*1.8) -> 66.5328 | D59: m2 | E59: =RATES!$D$42 -> 230 | F59: =C59*E59 -> 15302.544 | G59: (2*3.424*1.8+15.0+22*0.15*1.8)+(2*3.424*1.8+15.0+22*0.15*1.8)
A61: P | B61: Side and soffits of lintel / coping | C61: =(7*(1+0.3)+15*(0.9+0.3)+20*(0.75+0.3)+1*(0.7+0.3)+3*(1.2+0.3)+3*(1+0.3)+3*(1+0.3)+1*(0.9+0.3)+1*(1.5+0.3)+2*(0.9+0.3)+5*(0.75+0.3)+1*(0.45+0.3)+3*(0.6+0.3)+1*(3+0.3)+3*(1.6+0.3)+2*(1.3+0.3)+4*(1.8+0.3)+1*(1.2+0.3)+6*(1.8+0.3)+10*(0.9+0.3)+1*(1.8+0.3)+3*(1.2+0.3)+8*(1.2+0.3)+1*(1.2+0.3)+6*(1.5+0.3)+3*(1.5+0.3)+1*(2.4+0.3)+1*(3+0.3)+3*(1.8+0.3)+1*(0.75+0.3)+1*(1.45+0.3)+12*(0.9+0.3)+4*(0.75+0.3)+1*(0.6+0.3)+1*(1.2+0.3))*(2*0.225+0.15) -> 116.76 | D61: m2 | E61: =RATES!$D$43 -> 180 | F61: =C61*E61 -> 21016.8 | G61: (7*(1+0.3)+15*(0.9+0.3)+20*(0.75+0.3)+1*(0.7+0.3)+3*(1.2+0.3)+3*(1+0.3)+3*(1+0.3)+1*(0.9+0.3)+1*(1.5+0.3)+2*(0.9+0.3)+5*(0.75+0.3)+1*(0.45+0.3)+3*(0.6+0.3)+1*(3+0.3)+3*(1.6+0.3)+2*(1.3+0.3)+4*(1.8+0.3)+1*(1.2+0.3)+6*(1.8+0.3)+10*(0.9+0.3)+1*(1.8+0...
B63: E30 REINFORCEMENT - High tensile yield round bar reinforcement (standard) to BS 4449:
A64: Q | B64: 10mm diameter in columns | C64: =4.551 -> 4.551 | D64: t | E64: =RATES!$D$29 -> 20500 | F64: =C64*E64 -> 93295.5 | G64: 4.551
A66: R | B66: 20mm diameter in columns | C66: =7.133 -> 7.133 | D66: t | E66: =RATES!$D$32 -> 19000 | F66: =C66*E66 -> 135527 | G66: 7.133
A68: S | B68: 10mm diameter in beams (links) | C68: =1.806 -> 1.806 | D68: t | E68: =RATES!$D$29 -> 20500 | F68: =C68*E68 -> 37023 | G68: 1.806
A70: T | B70: 16mm diameter in beams | C70: =1.248 -> 1.248 | D70: t | E70: =RATES!$D$31 -> 19500 | F70: =C70*E70 -> 24336 | G70: 1.248
A72: U | B72: 20mm diameter in beams | C72: =2.135 -> 2.135 | D72: t | E72: =RATES!$D$32 -> 19000 | F72: =C72*E72 -> 40565 | G72: 2.135
A74: V | B74: 25mm diameter in beams | C74: =5.507 -> 5.507 | D74: t | E74: =RATES!$D$33 -> 19000 | F74: =C74*E74 -> 104633 | G74: 5.507
A76: W | B76: 10mm diameter in shear & lift walls (links) | C76: =1.442+0.636 -> 2.078 | D76: t | E76: =RATES!$D$29 -> 20500 | F76: =C76*E76 -> 42599 | G76: 1.442+0.636
A78: X | B78: 12mm diameter in shear, lift & ramp walls | C78: =1.917+0.866 -> 2.783 | D78: t | E78: =RATES!$D$30 -> 20000 | F78: =C78*E78 -> 55660 | G78: 1.917+0.866
A80: Y | B80: 20mm diameter in shear & lift walls | C80: =6.904+3.320 -> 10.224 | D80: t | E80: =RATES!$D$32 -> 19000 | F80: =C80*E80 -> 194256 | G80: 6.904+3.320
A82: Z | B82: 12mm diameter in stairs | C82: =0.880 -> 0.88 | D82: t | E82: =RATES!$D$30 -> 20000 | F82: =C82*E82 -> 17600 | G82: 0.880
A84: A | B84: 16mm diameter in stairs | C84: =1.434 -> 1.434 | D84: t | E84: =RATES!$D$31 -> 19500 | F84: =C84*E84 -> 27963 | G84: 1.434
A86: B | B86: 12mm diameter for suspended slab | C86: =49.804 -> 49.804 | D86: t | E86: =RATES!$D$30 -> 20000 | F86: =C86*E86 -> 996080 | G86: 49.804
A88: C | B88: 16mm diameter for suspended slab | C88: =0.151 -> 0.151 | D88: t | E88: =RATES!$D$31 -> 19500 | F88: =C88*E88 -> 2944.5 | G88: 0.151
B90: =B31 -> ELEMENT NO. 1: IN SITU CONCRETE/LARGE PRECAST CONCRETE | F90: =SUM(F33:F89) -> 3312876.5
B91: Carried to Bill Summary
B94: ELEMENT NO. 2: MASONRY
B96: F10 BRICK/BLOCK WALL - Solid sandcrete blockwork in cement and sand (1:4) mortar as described in:
A97: A | B97: 150mm thick wall | C97: =447.7*3.05+(7*1*(3.05-2.2)+15*0.9*(3.05-2.2)+20*0.75*(3.05-2.2)+1*0.7*(3.05-2.2)+3*1.2*(3.05-2.2)+3*1*(3.05-2.2)+3*1*(3.05-2.2)+1*0.9*(3.05-2.2)+1*1.5*(3.05-2.2)+2*0.9*(3.05-2.2)+5*0.75*(3.05-2.2)+1*0.45*(3.05-2.2)+3*0.6*(3.05-2.2)+1*3*(3.05-2.2)+3*1.6*(3.05-2.2)+2*1.3*(3.05-2.2)+4*1.8*(3.05-2.2)+1*1.2*(3.05-2.2)+6*1.8*(3.05-1.3)+10*0.9*(3.05-1.3)+1*1.8*(3.05-1.6)+3*1.2*(3.05-1.9)+8*1.2*(3.05-1.15)+1*1.2*(3.05-1.2)+6*1.5*(3.05-1.3)+3*1.5*(3.05-1.15)+1*2.4*(3.05-1.3)+1*3*(3.05-1.6)+3*1.8*(3.05-1.9)+1*0.75*(3.05-1.3)+1*1.45*(3.05-1.9)+12*0.9*(3.05-0.6)+4*0.75*(3.05-0.6)+1*0.6*(3.05-0.6)+1*1.2*(3.05-0.6))*0.901 -> 1550.8207 | D97: m2 | E97: =RATES!$D$46 -> 215 | F97: =C97*E97 -> 333426.45 | G97: 447.7*3.05+(7*1*(3.05-2.2)+15*0.9*(3.05-2.2)+20*0.75*(3.05-2.2)+1*0.7*(3.05-2.2)+3*1.2*(3.05-2.2)+3*1*(3.05-2.2)+3*1*(3.05-2.2)+1*0.9*(3.05-2.2)+1*1.5*(3.05-2.2)+2*0.9*(3.05-2.2)+5*0.75*(3.05-2.2)+1*0.45*(3.05-2.2)+3*0.6*(3.05-2.2)+1*3*(3.05-2.2)+...
A99: B | B99: 200mm thick wall | C99: =49.2*3.05+(7*1*(3.05-2.2)+15*0.9*(3.05-2.2)+20*0.75*(3.05-2.2)+1*0.7*(3.05-2.2)+3*1.2*(3.05-2.2)+3*1*(3.05-2.2)+3*1*(3.05-2.2)+1*0.9*(3.05-2.2)+1*1.5*(3.05-2.2)+2*0.9*(3.05-2.2)+5*0.75*(3.05-2.2)+1*0.45*(3.05-2.2)+3*0.6*(3.05-2.2)+1*3*(3.05-2.2)+3*1.6*(3.05-2.2)+2*1.3*(3.05-2.2)+4*1.8*(3.05-2.2)+1*1.2*(3.05-2.2)+6*1.8*(3.05-1.3)+10*0.9*(3.05-1.3)+1*1.8*(3.05-1.6)+3*1.2*(3.05-1.9)+8*1.2*(3.05-1.15)+1*1.2*(3.05-1.2)+6*1.5*(3.05-1.3)+3*1.5*(3.05-1.15)+1*2.4*(3.05-1.3)+1*3*(3.05-1.6)+3*1.8*(3.05-1.9)+1*0.75*(3.05-1.3)+1*1.45*(3.05-1.9)+12*0.9*(3.05-0.6)+4*0.75*(3.05-0.6)+1*0.6*(3.05-0.6)+1*1.2*(3.05-0.6))*0.099 -> 170.4243 | D99: m2 | E99: =RATES!$D$47 -> 265 | F99: =C99*E99 -> 45162.44 | G99: 49.2*3.05+(7*1*(3.05-2.2)+15*0.9*(3.05-2.2)+20*0.75*(3.05-2.2)+1*0.7*(3.05-2.2)+3*1.2*(3.05-2.2)+3*1*(3.05-2.2)+3*1*(3.05-2.2)+1*0.9*(3.05-2.2)+1*1.5*(3.05-2.2)+2*0.9*(3.05-2.2)+5*0.75*(3.05-2.2)+1*0.45*(3.05-2.2)+3*0.6*(3.05-2.2)+1*3*(3.05-2.2)+3...
B101: =B94 -> ELEMENT NO. 2: MASONRY | F101: =SUM(F96:F100) -> 378588.89
B102: Carried to Bill Summary
B105: ELEMENT NO. 4: WINDOWS/DOORS
B107: L20 DOORS - Supply and fix the following door assemblies complete with frames, ironmongery sets to steel doors and all accessories:
A108: A | B108: 1000mm x 2200mm 1-hour fire-rated galvanised steel single-leaf security door assembly (D2) | C108: =7 -> 7 | D108: nr | E108: =RATES!$D$75 -> 7800 | F108: =C108*E108 -> 54600 | G108: 7
A110: B | B110: 900mm x 2200mm single leaf timber panel door (D3) | C110: =15 -> 15 | D110: nr | E110: =RATES!$D$76 -> 3400 | F110: =C110*E110 -> 51000 | G110: 15
A112: C | B112: 750mm x 2200mm single leaf timber flush door (D6) | C112: =20 -> 20 | D112: nr | E112: =RATES!$D$79 -> 1900 | F112: =C112*E112 -> 38000 | G112: 20
A114: D | B114: 700mm x 2200mm single-leaf 2-hour fire-rated galvanised steel door (D7) | C114: =1 -> 1 | D114: nr | E114: =RATES!$D$80 -> 6800 | F114: =C114*E114 -> 6800 | G114: 1
A116: E | B116: 1200mm x 2200mm 1-hour fire-rated leaf-and-a-half galvanised steel security door assembly (D8) | C116: =3 -> 3 | D116: nr | E116: =RATES!$D$81 -> 9800 | F116: =C116*E116 -> 29400 | G116: 3
A118: F | B118: 1000mm x 2200mm 1-hour fire-rated galvanised steel single-leaf security door assembly - emergency stairs (ED1) | C118: =3 -> 3 | D118: nr | E118: =RATES!$D$82 -> 7200 | F118: =C118*E118 -> 21600 | G118: 3
A120: G | B120: 1000mm x 2200mm 1-hour fire-rated galvanised steel single-leaf security door with translucent glass panel (ED2) | C120: =3 -> 3 | D120: nr | E120: =RATES!$D$83 -> 8100 | F120: =C120*E120 -> 24300 | G120: 3
A122: H | B122: 900mm x 2200mm 1-hour fire-rated galvanised steel single-leaf security door assembly (D9) | C122: =1 -> 1 | D122: nr | E122: =RATES!$D$84 -> 6900 | F122: =C122*E122 -> 6900 | G122: 1
A124: J | B124: 1500mm x 2200mm timber bi-fold door (FD1) | C124: =1 -> 1 | D124: nr | E124: =RATES!$D$86 -> 4600 | F124: =C124*E124 -> 4600 | G124: 1
A126: K | B126: 900mm x 2200mm screw-fixed galvanised steel service access panel (M1) | C126: =2 -> 2 | D126: nr | E126: =RATES!$D$87 -> 2900 | F126: =C126*E126 -> 5800 | G126: 2
A128: L | B128: 750mm x 2200mm screw-fixed galvanised steel service access panel (M2) | C128: =5 -> 5 | D128: nr | E128: =RATES!$D$88 -> 2600 | F128: =C128*E128 -> 13000 | G128: 5
A130: M | B130: 450mm x 2200mm screw-fixed galvanised steel service access panel (M3) | C130: =1 -> 1 | D130: nr | E130: =RATES!$D$89 -> 1900 | F130: =C130*E130 -> 1900 | G130: 1
A132: N | B132: 600mm x 2200mm screw-fixed galvanised steel service access panel (M5) | C132: =3 -> 3 | D132: nr | E132: =RATES!$D$90 -> 2200 | F132: =C132*E132 -> 6600 | G132: 3
A134: P | B134: 3000mm x 2200mm 3-panel galvanised steel framed tempered glass sliding door (SD1) | C134: =1 -> 1 | D134: nr | E134: =RATES!$D$94 -> 14500 | F134: =C134*E134 -> 14500 | G134: 1
A136: Q | B136: 1600mm x 2200mm 2-panel galvanised steel framed tempered glass sliding door (SD2) | C136: =3 -> 3 | D136: nr | E136: =RATES!$D$95 -> 8800 | F136: =C136*E136 -> 26400 | G136: 3
A138: R | B138: 1300mm x 2200mm 2-panel galvanised steel framed tempered glass sliding door (SD3) | C138: =2 -> 2 | D138: nr | E138: =RATES!$D$96 -> 7600 | F138: =C138*E138 -> 15200 | G138: 2
A140: S | B140: 1800mm x 2200mm 2-panel galvanised steel framed tempered glass sliding door (SD4) | C140: =4 -> 4 | D140: nr | E140: =RATES!$D$97 -> 9300 | F140: =C140*E140 -> 37200 | G140: 4
A142: T | B142: 1200mm x 2200mm 2-panel galvanised steel framed tempered glass sliding door (SD5) | C142: =1 -> 1 | D142: nr | E142: =RATES!$D$98 -> 7200 | F142: =C142*E142 -> 7200 | G142: 1
A144: U | B144: 50mm x 150mm frames (to timber doors) | C144: =15*(2*2.2+0.9)+20*(2*2.2+0.75)+1*(2*2.2+1.5) -> 188.4 | D144: m | E144: =RATES!$D$100 -> 125 | F144: =C144*E144 -> 23550 | G144: 15*(2*2.2+0.9)+20*(2*2.2+0.75)+1*(2*2.2+1.5)
A146: V | B146: 50mm x 12mm door stop | C146: =15*(2*2.2+0.9)+20*(2*2.2+0.75)+1*(2*2.2+1.5) -> 188.4 | D146: m | E146: =RATES!$D$101 -> 28 | F146: =C146*E146 -> 5275.2 | G146: 15*(2*2.2+0.9)+20*(2*2.2+0.75)+1*(2*2.2+1.5)
B148: Ironmongery - Supply and fix the following approved ironmongery to hardwood with accompanying patented screws:
A149: W | B149: Pair 100mm brass butt hinges | C149: =53 -> 53 | D149: pr | E149: =RATES!$D$102 -> 125 | F149: =C149*E149 -> 6625 | G149: 53
A151: X | B151: Ordinary locks | C151: =15 -> 15 | D151: nr | E151: =RATES!$D$103 -> 480 | F151: =C151*E151 -> 7200 | G151: 15
A153: Y | B153: Approved high quality mortice indicator lock | C153: =20 -> 20 | D153: nr | E153: =RATES!$D$104 -> 560 | F153: =C153*E153 -> 11200 | G153: 20
B155: ALUMINIUM GLAZED WINDOWS - Supply and install Italian extruded aluminium glazed windows, ALCOA R50 series, powder coated aluminium profile, glazed with 6mm tinted reflective glass secured onto galvanized steel sub-frames, complete with all accessories as per Architect's detail:
A156: Z | B156: 2 bay alu. framed glass sliding window 1800mm x 1300mm (W2) | C156: =6 -> 6 | D156: nr | E156: =RATES!$D$109 -> 3861 | F156: =C156*E156 -> 23166 | G156: 6
A158: A | B158: 1 bay alu. framed glass awning window 900mm x 1300mm (W4) | C158: =10 -> 10 | D158: nr | E158: =RATES!$D$111 -> 1930.5 | F158: =C158*E158 -> 19305 | G158: 10
A160: B | B160: 2 bay alu. framed glass sliding window 1800mm x 1600mm (W7) | C160: =1 -> 1 | D160: nr | E160: =RATES!$D$114 -> 4752 | F160: =C160*E160 -> 4752 | G160: 1
A162: C | B162: 1 x 3 bay alu. framed glass awning window 1200mm x 1900mm (W8) | C162: =3 -> 3 | D162: nr | E162: =RATES!$D$115 -> 3762 | F162: =C162*E162 -> 11286 | G162: 3
A164: D | B164: 2 bay alu. framed glass sliding window 1200mm x 1150mm (W9) | C164: =8 -> 8 | D164: nr | E164: =RATES!$D$116 -> 2277 | F164: =C164*E164 -> 18216 | G164: 8
A166: E | B166: 2 bay alu. framed glass sliding window 1200mm x 1200mm (W10) | C166: =1 -> 1 | D166: nr | E166: =RATES!$D$117 -> 2376 | F166: =C166*E166 -> 2376 | G166: 1
A168: F | B168: 2 bay alu. framed glass sliding window 1500mm x 1300mm (W11) | C168: =6 -> 6 | D168: nr | E168: =RATES!$D$118 -> 3217.5 | F168: =C168*E168 -> 19305 | G168: 6
A170: G | B170: 2 bay alu. framed glass sliding window 1500mm x 1150mm (W12) | C170: =3 -> 3 | D170: nr | E170: =RATES!$D$119 -> 2846.25 | F170: =C170*E170 -> 8538.75 | G170: 3
A172: H | B172: 3 bay alu. framed glass awning window 2400mm x 1300mm (W13) | C172: =1 -> 1 | D172: nr | E172: =RATES!$D$120 -> 5148 | F172: =C172*E172 -> 5148 | G172: 1
A174: J | B174: 3 bay alu. framed glass sliding window 3000mm x 1600mm (W15) | C174: =1 -> 1 | D174: nr | E174: =RATES!$D$122 -> 7920 | F174: =C174*E174 -> 7920 | G174: 1
A176: K | B176: 2 x 3 alu. framed glass awning window 1800mm x 1900mm (W17) | C176: =3 -> 3 | D176: nr | E176: =RATES!$D$124 -> 5643 | F176: =C176*E176 -> 16929 | G176: 3
A178: L | B178: 1 bay alu. framed glass awning window 750mm x 1300mm (W18) | C178: =1 -> 1 | D178: nr | E178: =RATES!$D$125 -> 1608.75 | F178: =C178*E178 -> 1608.75 | G178: 1
A180: M | B180: 2 x 3 alu. framed glass awning window 1450mm x 1900mm (W20) | C180: =1 -> 1 | D180: nr | E180: =RATES!$D$127 -> 4545.75 | F180: =C180*E180 -> 4545.75 | G180: 1
A182: N | B182: 2 bay alu. framed glass sliding window 900mm x 600mm (HW1) | C182: =12 -> 12 | D182: nr | E182: =RATES!$D$128 -> 891 | F182: =C182*E182 -> 10692 | G182: 12
A184: P | B184: 2 bay alu. framed glass sliding window 750mm x 600mm (HW2) | C184: =4 -> 4 | D184: nr | E184: =RATES!$D$129 -> 742.5 | F184: =C184*E184 -> 2970 | G184: 4
A186: Q | B186: 2 bay alu. framed glass sliding window 600mm x 600mm (HW3) | C186: =1 -> 1 | D186: nr | E186: =RATES!$D$130 -> 594 | F186: =C186*E186 -> 594 | G186: 1
A188: R | B188: 2 bay alu. framed glass sliding window 1200mm x 600mm (HW4) | C188: =1 -> 1 | D188: nr | E188: =RATES!$D$131 -> 1188 | F188: =C188*E188 -> 1188 | G188: 1
...

Sheet 6TH FLR  
A1: ='PRELIMS & GEN. ITEMS'!A2 -> PROJECT: BLOCK N REDEVELOPMENT
A2: ='PRELIMS & GEN. ITEMS'!A3 -> LOCATION: KANESHIE
A3: ='PRELIMS & GEN. ITEMS'!A4 -> CLIENT: STATE HOUSING LIMITED
A4: ='PRELIMS & GEN. ITEMS'!A5 -> DATE:9/30/2026
A5: ITEM | B5: DESCRIPTION | C5: QTY | D5: UNIT | E5: RATE | F5: AMOUNT - GHC | G5: Measurement basis / calculation
B7: MAIN BUILDING
B9: SIXTH FLOOR
B11: BILL SUMMARY
A13: A | B13: ELEMENT NO. 1: IN SITU CONCRETE/LARGE PRECAST CONCRETE | F13: =F90 -> 3315382.1
A15: B | B15: ELEMENT NO. 2: MASONRY | F15: =F101 -> 394834.26
A17: C | B17: ELEMENT NO. 4: WINDOWS/DOORS | F17: =F190 -> 608377.15
A19: D | B19: ELEMENT NO. 5: FLOOR FINISHES | F19: =F211 -> 349083.24
A21: E | B21: ELEMENT NO. 6: WALL FINISHES | F21: =F228 -> 321670.38
A23: F | B23: ELEMENT NO. 7: PAINTING AND DECORATING | F23: =F249 -> 190908.58
B25: =B9 -> SIXTH FLOOR | E25: GHC | F25: =SUM(F13:F24) -> 5180255.7
B26: To Bill General Summary
B29: BILL NR. 9 - SIXTH FLOOR
B31: ELEMENT NO. 1: IN SITU CONCRETE/LARGE PRECAST CONCRETE
B33: Vibrated in-situ concrete C40 as described in:
A34: A | B34: Suspended slab 250mm thick | C34: =1134.6*0.25 -> 283.65 | D34: m3 | E34: =RATES!$D$22 -> 2650 | F34: =C34*E34 -> 751672.5 | G34: 1134.6*0.25
A36: B | B36: Beams (downstands below slab) | C36: =166.8*0.3*0.35+33.1*0.2*0.35 -> 19.831 | D36: m3 | E36: =RATES!$D$23 -> 2700 | F36: =C36*E36 -> 53543.7 | G36: 166.8*0.3*0.35+33.1*0.2*0.35
A38: C | B38: Columns | C38: =5*0.75*0.5*3.05+1*0.75*0.5*3.05+2*0.75*0.5*3.05+1*0.75*0.5*3.05+3*1.2*0.3*3.05+6*1.2*0.3*3.05+1*1.2*0.3*3.05+15*1.2*0.3*3.05+1*(2.85*0.25+0.825*0.25)*3.05 -> 40.545937 | D38: m3 | E38: =RATES!$D$21 -> 2800 | F38: =C38*E38 -> 113528.62 | G38: 5*0.75*0.5*3.05+1*0.75*0.5*3.05+2*0.75*0.5*3.05+1*0.75*0.5*3.05+3*1.2*0.3*3.05+6*1.2*0.3*3.05+1*1.2*0.3*3.05+15*1.2*0.3*3.05+1*(2.85*0.25+0.825*0.25)*3.05
A40: D | B40: Concrete wall - shear walls to main & emergency stair cores, 250mm thick | C40: =22.05*3.05*0.25+25.57*3.05*0.25 -> 36.31025 | D40: m3 | E40: =RATES!$D$20 -> 2750 | F40: =C40*E40 -> 99853.187 | G40: 22.05*3.05*0.25+25.57*3.05*0.25
A42: E | B42: Concrete wall - lift walls, 250mm thick | C42: =21.825*3.05*0.25 -> 16.641562 | D42: m3 | E42: =RATES!$D$20 -> 2750 | F42: =C42*E42 -> 45764.297 | G42: 21.825*3.05*0.25
A44: F | B44: Stairs | C44: =(2.966*3.3/3.3+2.625)+(2.966*3.3/3.3+2.625) -> 11.182 | D44: m3 | E44: =RATES!$D$24 -> 2850 | F44: =C44*E44 -> 31868.7 | G44: (2.966*3.3/3.3+2.625)+(2.966*3.3/3.3+2.625)
A46: G | B46: Lintels 150 x 225mm over door and window openings | C46: =(8*(1+0.3)+15*(0.9+0.3)+21*(0.75+0.3)+1*(0.7+0.3)+3*(1.2+0.3)+3*(1+0.3)+3*(1+0.3)+1*(0.9+0.3)+1*(1.5+0.3)+2*(0.9+0.3)+5*(0.75+0.3)+1*(0.45+0.3)+3*(0.6+0.3)+1*(3+0.3)+4*(1.6+0.3)+2*(1.3+0.3)+4*(1.8+0.3)+1*(1.2+0.3)+6*(1.8+0.3)+10*(0.9+0.3)+2*(1.8+0.3)+3*(1.2+0.3)+8*(1.2+0.3)+1*(1.2+0.3)+6*(1.5+0.3)+4*(1.5+0.3)+1*(2.4+0.3)+1*(3+0.3)+3*(1.8+0.3)+1*(0.75+0.3)+1*(1.45+0.3)+13*(0.9+0.3)+5*(0.75+0.3)+2*(0.6+0.3)+2*(1.2+0.3))*0.15*0.225 -> 6.99975 | D46: m3 | E46: =RATES!$D$25 -> 2600 | F46: =C46*E46 -> 18199.35 | G46: (8*(1+0.3)+15*(0.9+0.3)+21*(0.75+0.3)+1*(0.7+0.3)+3*(1.2+0.3)+3*(1+0.3)+3*(1+0.3)+1*(0.9+0.3)+1*(1.5+0.3)+2*(0.9+0.3)+5*(0.75+0.3)+1*(0.45+0.3)+3*(0.6+0.3)+1*(3+0.3)+4*(1.6+0.3)+2*(1.3+0.3)+4*(1.8+0.3)+1*(1.2+0.3)+6*(1.8+0.3)+10*(0.9+0.3)+2*(1.8+0...
B48: E20 FORMWORK - Formwork as described to:
A49: H | B49: Soffits of suspended slab | C49: =1134.6 -> 1134.6 | D49: m2 | E49: =RATES!$D$38 -> 170 | F49: =C49*E49 -> 192882 | G49: 1134.6
A51: J | B51: Edges of suspended slab 250mm high | C51: =294.6 -> 294.6 | D51: m | E51: =RATES!$D$40 -> 65 | F51: =C51*E51 -> 19149 | G51: 294.6
A53: K | B53: Sides and soffits of beams | C53: =166.8*(2*0.35+0.3)+33.1*(2*0.35+0.2) -> 196.59 | D53: m2 | E53: =RATES!$D$39 -> 200 | F53: =C53*E53 -> 39318 | G53: 166.8*(2*0.35+0.3)+33.1*(2*0.35+0.2)
A55: L | B55: Columns | C55: =5*2*(0.75+0.5)*3.05+1*2*(0.75+0.5)*3.05+2*2*(0.75+0.5)*3.05+1*2*(0.75+0.5)*3.05+3*2*(1.2+0.3)*3.05+6*2*(1.2+0.3)*3.05+1*2*(1.2+0.3)*3.05+15*2*(1.2+0.3)*3.05+1*2*(2.85+1.075)*3.05 -> 321.3175 | D55: m2 | E55: =RATES!$D$37 -> 190 | F55: =C55*E55 -> 61050.325 | G55: 5*2*(0.75+0.5)*3.05+1*2*(0.75+0.5)*3.05+2*2*(0.75+0.5)*3.05+1*2*(0.75+0.5)*3.05+3*2*(1.2+0.3)*3.05+6*2*(1.2+0.3)*3.05+1*2*(1.2+0.3)*3.05+15*2*(1.2+0.3)*3.05+1*2*(2.85+1.075)*3.05
A57: M | B57: Concrete wall (both faces) | C57: =2*22.05*3.05+2*21.825*3.05+2*25.57*3.05 -> 423.6145 | D57: m2 | E57: =RATES!$D$36 -> 185 | F57: =C57*E57 -> 78368.683 | G57: 2*22.05*3.05+2*21.825*3.05+2*25.57*3.05
A59: N | B59: Soffits of stair flights, landings and risers | C59: =(2*3.424*1.8+15.0+22*0.15*1.8)+(2*3.424*1.8+15.0+22*0.15*1.8) -> 66.5328 | D59: m2 | E59: =RATES!$D$42 -> 230 | F59: =C59*E59 -> 15302.544 | G59: (2*3.424*1.8+15.0+22*0.15*1.8)+(2*3.424*1.8+15.0+22*0.15*1.8)
A61: P | B61: Side and soffits of lintel / coping | C61: =(8*(1+0.3)+15*(0.9+0.3)+21*(0.75+0.3)+1*(0.7+0.3)+3*(1.2+0.3)+3*(1+0.3)+3*(1+0.3)+1*(0.9+0.3)+1*(1.5+0.3)+2*(0.9+0.3)+5*(0.75+0.3)+1*(0.45+0.3)+3*(0.6+0.3)+1*(3+0.3)+4*(1.6+0.3)+2*(1.3+0.3)+4*(1.8+0.3)+1*(1.2+0.3)+6*(1.8+0.3)+10*(0.9+0.3)+2*(1.8+0.3)+3*(1.2+0.3)+8*(1.2+0.3)+1*(1.2+0.3)+6*(1.5+0.3)+4*(1.5+0.3)+1*(2.4+0.3)+1*(3+0.3)+3*(1.8+0.3)+1*(0.75+0.3)+1*(1.45+0.3)+13*(0.9+0.3)+5*(0.75+0.3)+2*(0.6+0.3)+2*(1.2+0.3))*(2*0.225+0.15) -> 124.44 | D61: m2 | E61: =RATES!$D$43 -> 180 | F61: =C61*E61 -> 22399.2 | G61: (8*(1+0.3)+15*(0.9+0.3)+21*(0.75+0.3)+1*(0.7+0.3)+3*(1.2+0.3)+3*(1+0.3)+3*(1+0.3)+1*(0.9+0.3)+1*(1.5+0.3)+2*(0.9+0.3)+5*(0.75+0.3)+1*(0.45+0.3)+3*(0.6+0.3)+1*(3+0.3)+4*(1.6+0.3)+2*(1.3+0.3)+4*(1.8+0.3)+1*(1.2+0.3)+6*(1.8+0.3)+10*(0.9+0.3)+2*(1.8+0...
B63: E30 REINFORCEMENT - High tensile yield round bar reinforcement (standard) to BS 4449:
A64: Q | B64: 10mm diameter in columns | C64: =4.551 -> 4.551 | D64: t | E64: =RATES!$D$29 -> 20500 | F64: =C64*E64 -> 93295.5 | G64: 4.551
A66: R | B66: 20mm diameter in columns | C66: =7.133 -> 7.133 | D66: t | E66: =RATES!$D$32 -> 19000 | F66: =C66*E66 -> 135527 | G66: 7.133
A68: S | B68: 10mm diameter in beams (links) | C68: =1.806 -> 1.806 | D68: t | E68: =RATES!$D$29 -> 20500 | F68: =C68*E68 -> 37023 | G68: 1.806
A70: T | B70: 16mm diameter in beams | C70: =1.248 -> 1.248 | D70: t | E70: =RATES!$D$31 -> 19500 | F70: =C70*E70 -> 24336 | G70: 1.248
A72: U | B72: 20mm diameter in beams | C72: =2.135 -> 2.135 | D72: t | E72: =RATES!$D$32 -> 19000 | F72: =C72*E72 -> 40565 | G72: 2.135
A74: V | B74: 25mm diameter in beams | C74: =5.507 -> 5.507 | D74: t | E74: =RATES!$D$33 -> 19000 | F74: =C74*E74 -> 104633 | G74: 5.507
A76: W | B76: 10mm diameter in shear & lift walls (links) | C76: =1.442+0.636 -> 2.078 | D76: t | E76: =RATES!$D$29 -> 20500 | F76: =C76*E76 -> 42599 | G76: 1.442+0.636
A78: X | B78: 12mm diameter in shear, lift & ramp walls | C78: =1.917+0.866 -> 2.783 | D78: t | E78: =RATES!$D$30 -> 20000 | F78: =C78*E78 -> 55660 | G78: 1.917+0.866
A80: Y | B80: 20mm diameter in shear & lift walls | C80: =6.904+3.320 -> 10.224 | D80: t | E80: =RATES!$D$32 -> 19000 | F80: =C80*E80 -> 194256 | G80: 6.904+3.320
A82: Z | B82: 12mm diameter in stairs | C82: =0.880 -> 0.88 | D82: t | E82: =RATES!$D$30 -> 20000 | F82: =C82*E82 -> 17600 | G82: 0.880
A84: A | B84: 16mm diameter in stairs | C84: =1.434 -> 1.434 | D84: t | E84: =RATES!$D$31 -> 19500 | F84: =C84*E84 -> 27963 | G84: 1.434
A86: B | B86: 12mm diameter for suspended slab | C86: =49.804 -> 49.804 | D86: t | E86: =RATES!$D$30 -> 20000 | F86: =C86*E86 -> 996080 | G86: 49.804
A88: C | B88: 16mm diameter for suspended slab | C88: =0.151 -> 0.151 | D88: t | E88: =RATES!$D$31 -> 19500 | F88: =C88*E88 -> 2944.5 | G88: 0.151
B90: =B31 -> ELEMENT NO. 1: IN SITU CONCRETE/LARGE PRECAST CONCRETE | F90: =SUM(F33:F89) -> 3315382.1
B91: Carried to Bill Summary
B94: ELEMENT NO. 2: MASONRY
B96: F10 BRICK/BLOCK WALL - Solid sandcrete blockwork in cement and sand (1:4) mortar as described in:
A97: A | B97: 150mm thick wall | C97: =465.9*3.05+(8*1*(3.05-2.2)+15*0.9*(3.05-2.2)+21*0.75*(3.05-2.2)+1*0.7*(3.05-2.2)+3*1.2*(3.05-2.2)+3*1*(3.05-2.2)+3*1*(3.05-2.2)+1*0.9*(3.05-2.2)+1*1.5*(3.05-2.2)+2*0.9*(3.05-2.2)+5*0.75*(3.05-2.2)+1*0.45*(3.05-2.2)+3*0.6*(3.05-2.2)+1*3*(3.05-2.2)+4*1.6*(3.05-2.2)+2*1.3*(3.05-2.2)+4*1.8*(3.05-2.2)+1*1.2*(3.05-2.2)+6*1.8*(3.05-1.3)+10*0.9*(3.05-1.3)+2*1.8*(3.05-1.6)+3*1.2*(3.05-1.9)+8*1.2*(3.05-1.15)+1*1.2*(3.05-1.2)+6*1.5*(3.05-1.3)+4*1.5*(3.05-1.15)+1*2.4*(3.05-1.3)+1*3*(3.05-1.6)+3*1.8*(3.05-1.9)+1*0.75*(3.05-1.3)+1*1.45*(3.05-1.9)+13*0.9*(3.05-0.6)+5*0.75*(3.05-0.6)+2*0.6*(3.05-0.6)+2*1.2*(3.05-0.6))*0.903 -> 1621.8764 | D97: m2 | E97: =RATES!$D$46 -> 215 | F97: =C97*E97 -> 348703.42 | G97: 465.9*3.05+(8*1*(3.05-2.2)+15*0.9*(3.05-2.2)+21*0.75*(3.05-2.2)+1*0.7*(3.05-2.2)+3*1.2*(3.05-2.2)+3*1*(3.05-2.2)+3*1*(3.05-2.2)+1*0.9*(3.05-2.2)+1*1.5*(3.05-2.2)+2*0.9*(3.05-2.2)+5*0.75*(3.05-2.2)+1*0.45*(3.05-2.2)+3*0.6*(3.05-2.2)+1*3*(3.05-2.2)+...
A99: B | B99: 200mm thick wall | C99: =50.0*3.05+(8*1*(3.05-2.2)+15*0.9*(3.05-2.2)+21*0.75*(3.05-2.2)+1*0.7*(3.05-2.2)+3*1.2*(3.05-2.2)+3*1*(3.05-2.2)+3*1*(3.05-2.2)+1*0.9*(3.05-2.2)+1*1.5*(3.05-2.2)+2*0.9*(3.05-2.2)+5*0.75*(3.05-2.2)+1*0.45*(3.05-2.2)+3*0.6*(3.05-2.2)+1*3*(3.05-2.2)+4*1.6*(3.05-2.2)+2*1.3*(3.05-2.2)+4*1.8*(3.05-2.2)+1*1.2*(3.05-2.2)+6*1.8*(3.05-1.3)+10*0.9*(3.05-1.3)+2*1.8*(3.05-1.6)+3*1.2*(3.05-1.9)+8*1.2*(3.05-1.15)+1*1.2*(3.05-1.2)+6*1.5*(3.05-1.3)+4*1.5*(3.05-1.15)+1*2.4*(3.05-1.3)+1*3*(3.05-1.6)+3*1.8*(3.05-1.9)+1*0.75*(3.05-1.3)+1*1.45*(3.05-1.9)+13*0.9*(3.05-0.6)+5*0.75*(3.05-0.6)+2*0.6*(3.05-0.6)+2*1.2*(3.05-0.6))*0.097 -> 174.07862 | D99: m2 | E99: =RATES!$D$47 -> 265 | F99: =C99*E99 -> 46130.834 | G99: 50.0*3.05+(8*1*(3.05-2.2)+15*0.9*(3.05-2.2)+21*0.75*(3.05-2.2)+1*0.7*(3.05-2.2)+3*1.2*(3.05-2.2)+3*1*(3.05-2.2)+3*1*(3.05-2.2)+1*0.9*(3.05-2.2)+1*1.5*(3.05-2.2)+2*0.9*(3.05-2.2)+5*0.75*(3.05-2.2)+1*0.45*(3.05-2.2)+3*0.6*(3.05-2.2)+1*3*(3.05-2.2)+4...
B101: =B94 -> ELEMENT NO. 2: MASONRY | F101: =SUM(F96:F100) -> 394834.26
B102: Carried to Bill Summary
B105: ELEMENT NO. 4: WINDOWS/DOORS
B107: L20 DOORS - Supply and fix the following door assemblies complete with frames, ironmongery sets to steel doors and all accessories:
A108: A | B108: 1000mm x 2200mm 1-hour fire-rated galvanised steel single-leaf security door assembly (D2) | C108: =8 -> 8 | D108: nr | E108: =RATES!$D$75 -> 7800 | F108: =C108*E108 -> 62400 | G108: 8
A110: B | B110: 900mm x 2200mm single leaf timber panel door (D3) | C110: =15 -> 15 | D110: nr | E110: =RATES!$D$76 -> 3400 | F110: =C110*E110 -> 51000 | G110: 15
A112: C | B112: 750mm x 2200mm single leaf timber flush door (D6) | C112: =21 -> 21 | D112: nr | E112: =RATES!$D$79 -> 1900 | F112: =C112*E112 -> 39900 | G112: 21
A114: D | B114: 700mm x 2200mm single-leaf 2-hour fire-rated galvanised steel door (D7) | C114: =1 -> 1 | D114: nr | E114: =RATES!$D$80 -> 6800 | F114: =C114*E114 -> 6800 | G114: 1
A116: E | B116: 1200mm x 2200mm 1-hour fire-rated leaf-and-a-half galvanised steel security door assembly (D8) | C116: =3 -> 3 | D116: nr | E116: =RATES!$D$81 -> 9800 | F116: =C116*E116 -> 29400 | G116: 3
A118: F | B118: 1000mm x 2200mm 1-hour fire-rated galvanised steel single-leaf security door assembly - emergency stairs (ED1) | C118: =3 -> 3 | D118: nr | E118: =RATES!$D$82 -> 7200 | F118: =C118*E118 -> 21600 | G118: 3
A120: G | B120: 1000mm x 2200mm 1-hour fire-rated galvanised steel single-leaf security door with translucent glass panel (ED2) | C120: =3 -> 3 | D120: nr | E120: =RATES!$D$83 -> 8100 | F120: =C120*E120 -> 24300 | G120: 3
A122: H | B122: 900mm x 2200mm 1-hour fire-rated galvanised steel single-leaf security door assembly (D9) | C122: =1 -> 1 | D122: nr | E122: =RATES!$D$84 -> 6900 | F122: =C122*E122 -> 6900 | G122: 1
A124: J | B124: 1500mm x 2200mm timber bi-fold door (FD1) | C124: =1 -> 1 | D124: nr | E124: =RATES!$D$86 -> 4600 | F124: =C124*E124 -> 4600 | G124: 1
A126: K | B126: 900mm x 2200mm screw-fixed galvanised steel service access panel (M1) | C126: =2 -> 2 | D126: nr | E126: =RATES!$D$87 -> 2900 | F126: =C126*E126 -> 5800 | G126: 2
A128: L | B128: 750mm x 2200mm screw-fixed galvanised steel service access panel (M2) | C128: =5 -> 5 | D128: nr | E128: =RATES!$D$88 -> 2600 | F128: =C128*E128 -> 13000 | G128: 5
A130: M | B130: 450mm x 2200mm screw-fixed galvanised steel service access panel (M3) | C130: =1 -> 1 | D130: nr | E130: =RATES!$D$89 -> 1900 | F130: =C130*E130 -> 1900 | G130: 1
A132: N | B132: 600mm x 2200mm screw-fixed galvanised steel service access panel (M5) | C132: =3 -> 3 | D132: nr | E132: =RATES!$D$90 -> 2200 | F132: =C132*E132 -> 6600 | G132: 3
A134: P | B134: 3000mm x 2200mm 3-panel galvanised steel framed tempered glass sliding door (SD1) | C134: =1 -> 1 | D134: nr | E134: =RATES!$D$94 -> 14500 | F134: =C134*E134 -> 14500 | G134: 1
A136: Q | B136: 1600mm x 2200mm 2-panel galvanised steel framed tempered glass sliding door (SD2) | C136: =4 -> 4 | D136: nr | E136: =RATES!$D$95 -> 8800 | F136: =C136*E136 -> 35200 | G136: 4
A138: R | B138: 1300mm x 2200mm 2-panel galvanised steel framed tempered glass sliding door (SD3) | C138: =2 -> 2 | D138: nr | E138: =RATES!$D$96 -> 7600 | F138: =C138*E138 -> 15200 | G138: 2
A140: S | B140: 1800mm x 2200mm 2-panel galvanised steel framed tempered glass sliding door (SD4) | C140: =4 -> 4 | D140: nr | E140: =RATES!$D$97 -> 9300 | F140: =C140*E140 -> 37200 | G140: 4
A142: T | B142: 1200mm x 2200mm 2-panel galvanised steel framed tempered glass sliding door (SD5) | C142: =1 -> 1 | D142: nr | E142: =RATES!$D$98 -> 7200 | F142: =C142*E142 -> 7200 | G142: 1
A144: U | B144: 50mm x 150mm frames (to timber doors) | C144: =15*(2*2.2+0.9)+21*(2*2.2+0.75)+1*(2*2.2+1.5) -> 193.55 | D144: m | E144: =RATES!$D$100 -> 125 | F144: =C144*E144 -> 24193.75 | G144: 15*(2*2.2+0.9)+21*(2*2.2+0.75)+1*(2*2.2+1.5)
A146: V | B146: 50mm x 12mm door stop | C146: =15*(2*2.2+0.9)+21*(2*2.2+0.75)+1*(2*2.2+1.5) -> 193.55 | D146: m | E146: =RATES!$D$101 -> 28 | F146: =C146*E146 -> 5419.4 | G146: 15*(2*2.2+0.9)+21*(2*2.2+0.75)+1*(2*2.2+1.5)
B148: Ironmongery - Supply and fix the following approved ironmongery to hardwood with accompanying patented screws:
A149: W | B149: Pair 100mm brass butt hinges | C149: =54 -> 54 | D149: pr | E149: =RATES!$D$102 -> 125 | F149: =C149*E149 -> 6750 | G149: 54
A151: X | B151: Ordinary locks | C151: =15 -> 15 | D151: nr | E151: =RATES!$D$103 -> 480 | F151: =C151*E151 -> 7200 | G151: 15
A153: Y | B153: Approved high quality mortice indicator lock | C153: =21 -> 21 | D153: nr | E153: =RATES!$D$104 -> 560 | F153: =C153*E153 -> 11760 | G153: 21
B155: ALUMINIUM GLAZED WINDOWS - Supply and install Italian extruded aluminium glazed windows, ALCOA R50 series, powder coated aluminium profile, glazed with 6mm tinted reflective glass secured onto galvanized steel sub-frames, complete with all accessories as per Architect's detail:
A156: Z | B156: 2 bay alu. framed glass sliding window 1800mm x 1300mm (W2) | C156: =6 -> 6 | D156: nr | E156: =RATES!$D$109 -> 3861 | F156: =C156*E156 -> 23166 | G156: 6
A158: A | B158: 1 bay alu. framed glass awning window 900mm x 1300mm (W4) | C158: =10 -> 10 | D158: nr | E158: =RATES!$D$111 -> 1930.5 | F158: =C158*E158 -> 19305 | G158: 10
A160: B | B160: 2 bay alu. framed glass sliding window 1800mm x 1600mm (W7) | C160: =2 -> 2 | D160: nr | E160: =RATES!$D$114 -> 4752 | F160: =C160*E160 -> 9504 | G160: 2
A162: C | B162: 1 x 3 bay alu. framed glass awning window 1200mm x 1900mm (W8) | C162: =3 -> 3 | D162: nr | E162: =RATES!$D$115 -> 3762 | F162: =C162*E162 -> 11286 | G162: 3
A164: D | B164: 2 bay alu. framed glass sliding window 1200mm x 1150mm (W9) | C164: =8 -> 8 | D164: nr | E164: =RATES!$D$116 -> 2277 | F164: =C164*E164 -> 18216 | G164: 8
A166: E | B166: 2 bay alu. framed glass sliding window 1200mm x 1200mm (W10) | C166: =1 -> 1 | D166: nr | E166: =RATES!$D$117 -> 2376 | F166: =C166*E166 -> 2376 | G166: 1
A168: F | B168: 2 bay alu. framed glass sliding window 1500mm x 1300mm (W11) | C168: =6 -> 6 | D168: nr | E168: =RATES!$D$118 -> 3217.5 | F168: =C168*E168 -> 19305 | G168: 6
A170: G | B170: 2 bay alu. framed glass sliding window 1500mm x 1150mm (W12) | C170: =4 -> 4 | D170: nr | E170: =RATES!$D$119 -> 2846.25 | F170: =C170*E170 -> 11385 | G170: 4
A172: H | B172: 3 bay alu. framed glass awning window 2400mm x 1300mm (W13) | C172: =1 -> 1 | D172: nr | E172: =RATES!$D$120 -> 5148 | F172: =C172*E172 -> 5148 | G172: 1
A174: J | B174: 3 bay alu. framed glass sliding window 3000mm x 1600mm (W15) | C174: =1 -> 1 | D174: nr | E174: =RATES!$D$122 -> 7920 | F174: =C174*E174 -> 7920 | G174: 1
A176: K | B176: 2 x 3 alu. framed glass awning window 1800mm x 1900mm (W17) | C176: =3 -> 3 | D176: nr | E176: =RATES!$D$124 -> 5643 | F176: =C176*E176 -> 16929 | G176: 3
A178: L | B178: 1 bay alu. framed glass awning window 750mm x 1300mm (W18) | C178: =1 -> 1 | D178: nr | E178: =RATES!$D$125 -> 1608.75 | F178: =C178*E178 -> 1608.75 | G178: 1
A180: M | B180: 2 x 3 alu. framed glass awning window 1450mm x 1900mm (W20) | C180: =1 -> 1 | D180: nr | E180: =RATES!$D$127 -> 4545.75 | F180: =C180*E180 -> 4545.75 | G180: 1
A182: N | B182: 2 bay alu. framed glass sliding window 900mm x 600mm (HW1) | C182: =13 -> 13 | D182: nr | E182: =RATES!$D$128 -> 891 | F182: =C182*E182 -> 11583 | G182: 13
A184: P | B184: 2 bay alu. framed glass sliding window 750mm x 600mm (HW2) | C184: =5 -> 5 | D184: nr | E184: =RATES!$D$129 -> 742.5 | F184: =C184*E184 -> 3712.5 | G184: 5
A186: Q | B186: 2 bay alu. framed glass sliding window 600mm x 600mm (HW3) | C186: =2 -> 2 | D186: nr | E186: =RATES!$D$130 -> 594 | F186: =C186*E186 -> 1188 | G186: 2
A188: R | B188: 2 bay alu. framed glass sliding window 1200mm x 600mm (HW4) | C188: =2 -> 2 | D188: nr | E188: =RATES!$D$131 -> 1188 | F188: =C188*E188 -> 2376 | G188: 2
...

Sheet 7TH FLR   
A1: ='PRELIMS & GEN. ITEMS'!A2 -> PROJECT: BLOCK N REDEVELOPMENT
A2: ='PRELIMS & GEN. ITEMS'!A3 -> LOCATION: KANESHIE
A3: ='PRELIMS & GEN. ITEMS'!A4 -> CLIENT: STATE HOUSING LIMITED
A4: ='PRELIMS & GEN. ITEMS'!A5 -> DATE:9/30/2026
A5: ITEM | B5: DESCRIPTION | C5: QTY | D5: UNIT | E5: RATE | F5: AMOUNT - GHC | G5: Measurement basis / calculation
B7: MAIN BUILDING
B9: SEVENTH FLOOR
B11: BILL SUMMARY
A13: A | B13: ELEMENT NO. 1: IN SITU CONCRETE/LARGE PRECAST CONCRETE | F13: =F90 -> 3313248.4
A15: B | B15: ELEMENT NO. 2: MASONRY | F15: =F101 -> 381266.88
A17: C | B17: ELEMENT NO. 4: WINDOWS/DOORS | F17: =F190 -> 584032.95
A19: D | B19: ELEMENT NO. 5: FLOOR FINISHES | F19: =F211 -> 345672.24
A21: E | B21: ELEMENT NO. 6: WALL FINISHES | F21: =F228 -> 312099.76
A23: F | B23: ELEMENT NO. 7: PAINTING AND DECORATING | F23: =F249 -> 188326.49
B25: =B9 -> SEVENTH FLOOR | E25: GHC | F25: =SUM(F13:F24) -> 5124646.8
B26: To Bill General Summary
B29: BILL NR. 10 - SEVENTH FLOOR
B31: ELEMENT NO. 1: IN SITU CONCRETE/LARGE PRECAST CONCRETE
B33: Vibrated in-situ concrete C40 as described in:
A34: A | B34: Suspended slab 250mm thick | C34: =1134.6*0.25 -> 283.65 | D34: m3 | E34: =RATES!$D$22 -> 2650 | F34: =C34*E34 -> 751672.5 | G34: 1134.6*0.25
A36: B | B36: Beams (downstands below slab) | C36: =166.8*0.3*0.35+33.1*0.2*0.35 -> 19.831 | D36: m3 | E36: =RATES!$D$23 -> 2700 | F36: =C36*E36 -> 53543.7 | G36: 166.8*0.3*0.35+33.1*0.2*0.35
A38: C | B38: Columns | C38: =5*0.75*0.5*3.05+1*0.75*0.5*3.05+2*0.75*0.5*3.05+1*0.75*0.5*3.05+3*1.2*0.3*3.05+6*1.2*0.3*3.05+1*1.2*0.3*3.05+15*1.2*0.3*3.05+1*(2.85*0.25+0.825*0.25)*3.05 -> 40.545937 | D38: m3 | E38: =RATES!$D$21 -> 2800 | F38: =C38*E38 -> 113528.62 | G38: 5*0.75*0.5*3.05+1*0.75*0.5*3.05+2*0.75*0.5*3.05+1*0.75*0.5*3.05+3*1.2*0.3*3.05+6*1.2*0.3*3.05+1*1.2*0.3*3.05+15*1.2*0.3*3.05+1*(2.85*0.25+0.825*0.25)*3.05
A40: D | B40: Concrete wall - shear walls to main & emergency stair cores, 250mm thick | C40: =22.05*3.05*0.25+25.57*3.05*0.25 -> 36.31025 | D40: m3 | E40: =RATES!$D$20 -> 2750 | F40: =C40*E40 -> 99853.187 | G40: 22.05*3.05*0.25+25.57*3.05*0.25
A42: E | B42: Concrete wall - lift walls, 250mm thick | C42: =21.825*3.05*0.25 -> 16.641562 | D42: m3 | E42: =RATES!$D$20 -> 2750 | F42: =C42*E42 -> 45764.297 | G42: 21.825*3.05*0.25
A44: F | B44: Stairs | C44: =(2.966*3.3/3.3+2.625)+(2.966*3.3/3.3+2.625) -> 11.182 | D44: m3 | E44: =RATES!$D$24 -> 2850 | F44: =C44*E44 -> 31868.7 | G44: (2.966*3.3/3.3+2.625)+(2.966*3.3/3.3+2.625)
A46: G | B46: Lintels 150 x 225mm over door and window openings | C46: =(8*(1+0.3)+15*(0.9+0.3)+20*(0.75+0.3)+1*(0.7+0.3)+3*(1.2+0.3)+3*(1+0.3)+2*(1+0.3)+1*(0.9+0.3)+1*(1.5+0.3)+2*(0.9+0.3)+4*(0.75+0.3)+1*(0.45+0.3)+3*(0.6+0.3)+1*(3+0.3)+4*(1.6+0.3)+2*(1.3+0.3)+4*(1.8+0.3)+1*(1.2+0.3)+6*(1.8+0.3)+10*(0.9+0.3)+1*(1.8+0.3)+3*(1.2+0.3)+8*(1.2+0.3)+1*(1.2+0.3)+6*(1.5+0.3)+3*(1.5+0.3)+1*(2.4+0.3)+1*(3+0.3)+3*(1.8+0.3)+1*(0.75+0.3)+1*(1.45+0.3)+12*(0.9+0.3)+5*(0.75+0.3)+1*(0.6+0.3)+1*(1.2+0.3))*0.15*0.225 -> 6.631875 | D46: m3 | E46: =RATES!$D$25 -> 2600 | F46: =C46*E46 -> 17242.875 | G46: (8*(1+0.3)+15*(0.9+0.3)+20*(0.75+0.3)+1*(0.7+0.3)+3*(1.2+0.3)+3*(1+0.3)+2*(1+0.3)+1*(0.9+0.3)+1*(1.5+0.3)+2*(0.9+0.3)+4*(0.75+0.3)+1*(0.45+0.3)+3*(0.6+0.3)+1*(3+0.3)+4*(1.6+0.3)+2*(1.3+0.3)+4*(1.8+0.3)+1*(1.2+0.3)+6*(1.8+0.3)+10*(0.9+0.3)+1*(1.8+0...
B48: E20 FORMWORK - Formwork as described to:
A49: H | B49: Soffits of suspended slab | C49: =1134.6 -> 1134.6 | D49: m2 | E49: =RATES!$D$38 -> 170 | F49: =C49*E49 -> 192882 | G49: 1134.6
A51: J | B51: Edges of suspended slab 250mm high | C51: =294.6 -> 294.6 | D51: m | E51: =RATES!$D$40 -> 65 | F51: =C51*E51 -> 19149 | G51: 294.6
A53: K | B53: Sides and soffits of beams | C53: =166.8*(2*0.35+0.3)+33.1*(2*0.35+0.2) -> 196.59 | D53: m2 | E53: =RATES!$D$39 -> 200 | F53: =C53*E53 -> 39318 | G53: 166.8*(2*0.35+0.3)+33.1*(2*0.35+0.2)
A55: L | B55: Columns | C55: =5*2*(0.75+0.5)*3.05+1*2*(0.75+0.5)*3.05+2*2*(0.75+0.5)*3.05+1*2*(0.75+0.5)*3.05+3*2*(1.2+0.3)*3.05+6*2*(1.2+0.3)*3.05+1*2*(1.2+0.3)*3.05+15*2*(1.2+0.3)*3.05+1*2*(2.85+1.075)*3.05 -> 321.3175 | D55: m2 | E55: =RATES!$D$37 -> 190 | F55: =C55*E55 -> 61050.325 | G55: 5*2*(0.75+0.5)*3.05+1*2*(0.75+0.5)*3.05+2*2*(0.75+0.5)*3.05+1*2*(0.75+0.5)*3.05+3*2*(1.2+0.3)*3.05+6*2*(1.2+0.3)*3.05+1*2*(1.2+0.3)*3.05+15*2*(1.2+0.3)*3.05+1*2*(2.85+1.075)*3.05
A57: M | B57: Concrete wall (both faces) | C57: =2*22.05*3.05+2*21.825*3.05+2*25.57*3.05 -> 423.6145 | D57: m2 | E57: =RATES!$D$36 -> 185 | F57: =C57*E57 -> 78368.683 | G57: 2*22.05*3.05+2*21.825*3.05+2*25.57*3.05
A59: N | B59: Soffits of stair flights, landings and risers | C59: =(2*3.424*1.8+15.0+22*0.15*1.8)+(2*3.424*1.8+15.0+22*0.15*1.8) -> 66.5328 | D59: m2 | E59: =RATES!$D$42 -> 230 | F59: =C59*E59 -> 15302.544 | G59: (2*3.424*1.8+15.0+22*0.15*1.8)+(2*3.424*1.8+15.0+22*0.15*1.8)
A61: P | B61: Side and soffits of lintel / coping | C61: =(8*(1+0.3)+15*(0.9+0.3)+20*(0.75+0.3)+1*(0.7+0.3)+3*(1.2+0.3)+3*(1+0.3)+2*(1+0.3)+1*(0.9+0.3)+1*(1.5+0.3)+2*(0.9+0.3)+4*(0.75+0.3)+1*(0.45+0.3)+3*(0.6+0.3)+1*(3+0.3)+4*(1.6+0.3)+2*(1.3+0.3)+4*(1.8+0.3)+1*(1.2+0.3)+6*(1.8+0.3)+10*(0.9+0.3)+1*(1.8+0.3)+3*(1.2+0.3)+8*(1.2+0.3)+1*(1.2+0.3)+6*(1.5+0.3)+3*(1.5+0.3)+1*(2.4+0.3)+1*(3+0.3)+3*(1.8+0.3)+1*(0.75+0.3)+1*(1.45+0.3)+12*(0.9+0.3)+5*(0.75+0.3)+1*(0.6+0.3)+1*(1.2+0.3))*(2*0.225+0.15) -> 117.9 | D61: m2 | E61: =RATES!$D$43 -> 180 | F61: =C61*E61 -> 21222 | G61: (8*(1+0.3)+15*(0.9+0.3)+20*(0.75+0.3)+1*(0.7+0.3)+3*(1.2+0.3)+3*(1+0.3)+2*(1+0.3)+1*(0.9+0.3)+1*(1.5+0.3)+2*(0.9+0.3)+4*(0.75+0.3)+1*(0.45+0.3)+3*(0.6+0.3)+1*(3+0.3)+4*(1.6+0.3)+2*(1.3+0.3)+4*(1.8+0.3)+1*(1.2+0.3)+6*(1.8+0.3)+10*(0.9+0.3)+1*(1.8+0...
B63: E30 REINFORCEMENT - High tensile yield round bar reinforcement (standard) to BS 4449:
A64: Q | B64: 10mm diameter in columns | C64: =4.551 -> 4.551 | D64: t | E64: =RATES!$D$29 -> 20500 | F64: =C64*E64 -> 93295.5 | G64: 4.551
A66: R | B66: 20mm diameter in columns | C66: =7.133 -> 7.133 | D66: t | E66: =RATES!$D$32 -> 19000 | F66: =C66*E66 -> 135527 | G66: 7.133
A68: S | B68: 10mm diameter in beams (links) | C68: =1.806 -> 1.806 | D68: t | E68: =RATES!$D$29 -> 20500 | F68: =C68*E68 -> 37023 | G68: 1.806
A70: T | B70: 16mm diameter in beams | C70: =1.248 -> 1.248 | D70: t | E70: =RATES!$D$31 -> 19500 | F70: =C70*E70 -> 24336 | G70: 1.248
A72: U | B72: 20mm diameter in beams | C72: =2.135 -> 2.135 | D72: t | E72: =RATES!$D$32 -> 19000 | F72: =C72*E72 -> 40565 | G72: 2.135
A74: V | B74: 25mm diameter in beams | C74: =5.507 -> 5.507 | D74: t | E74: =RATES!$D$33 -> 19000 | F74: =C74*E74 -> 104633 | G74: 5.507
A76: W | B76: 10mm diameter in shear & lift walls (links) | C76: =1.442+0.636 -> 2.078 | D76: t | E76: =RATES!$D$29 -> 20500 | F76: =C76*E76 -> 42599 | G76: 1.442+0.636
A78: X | B78: 12mm diameter in shear, lift & ramp walls | C78: =1.917+0.866 -> 2.783 | D78: t | E78: =RATES!$D$30 -> 20000 | F78: =C78*E78 -> 55660 | G78: 1.917+0.866
A80: Y | B80: 20mm diameter in shear & lift walls | C80: =6.904+3.320 -> 10.224 | D80: t | E80: =RATES!$D$32 -> 19000 | F80: =C80*E80 -> 194256 | G80: 6.904+3.320
A82: Z | B82: 12mm diameter in stairs | C82: =0.880 -> 0.88 | D82: t | E82: =RATES!$D$30 -> 20000 | F82: =C82*E82 -> 17600 | G82: 0.880
A84: A | B84: 16mm diameter in stairs | C84: =1.434 -> 1.434 | D84: t | E84: =RATES!$D$31 -> 19500 | F84: =C84*E84 -> 27963 | G84: 1.434
A86: B | B86: 12mm diameter for suspended slab | C86: =49.804 -> 49.804 | D86: t | E86: =RATES!$D$30 -> 20000 | F86: =C86*E86 -> 996080 | G86: 49.804
A88: C | B88: 16mm diameter for suspended slab | C88: =0.151 -> 0.151 | D88: t | E88: =RATES!$D$31 -> 19500 | F88: =C88*E88 -> 2944.5 | G88: 0.151
B90: =B31 -> ELEMENT NO. 1: IN SITU CONCRETE/LARGE PRECAST CONCRETE | F90: =SUM(F33:F89) -> 3313248.4
B91: Carried to Bill Summary
B94: ELEMENT NO. 2: MASONRY
B96: F10 BRICK/BLOCK WALL - Solid sandcrete blockwork in cement and sand (1:4) mortar as described in:
A97: A | B97: 150mm thick wall | C97: =449.8*3.05+(8*1*(3.05-2.2)+15*0.9*(3.05-2.2)+20*0.75*(3.05-2.2)+1*0.7*(3.05-2.2)+3*1.2*(3.05-2.2)+3*1*(3.05-2.2)+2*1*(3.05-2.2)+1*0.9*(3.05-2.2)+1*1.5*(3.05-2.2)+2*0.9*(3.05-2.2)+4*0.75*(3.05-2.2)+1*0.45*(3.05-2.2)+3*0.6*(3.05-2.2)+1*3*(3.05-2.2)+4*1.6*(3.05-2.2)+2*1.3*(3.05-2.2)+4*1.8*(3.05-2.2)+1*1.2*(3.05-2.2)+6*1.8*(3.05-1.3)+10*0.9*(3.05-1.3)+1*1.8*(3.05-1.6)+3*1.2*(3.05-1.9)+8*1.2*(3.05-1.15)+1*1.2*(3.05-1.2)+6*1.5*(3.05-1.3)+3*1.5*(3.05-1.15)+1*2.4*(3.05-1.3)+1*3*(3.05-1.6)+3*1.8*(3.05-1.9)+1*0.75*(3.05-1.3)+1*1.45*(3.05-1.9)+12*0.9*(3.05-0.6)+5*0.75*(3.05-0.6)+1*0.6*(3.05-0.6)+1*1.2*(3.05-0.6))*0.900 -> 1559.324 | D97: m2 | E97: =RATES!$D$46 -> 215 | F97: =C97*E97 -> 335254.66 | G97: 449.8*3.05+(8*1*(3.05-2.2)+15*0.9*(3.05-2.2)+20*0.75*(3.05-2.2)+1*0.7*(3.05-2.2)+3*1.2*(3.05-2.2)+3*1*(3.05-2.2)+2*1*(3.05-2.2)+1*0.9*(3.05-2.2)+1*1.5*(3.05-2.2)+2*0.9*(3.05-2.2)+4*0.75*(3.05-2.2)+1*0.45*(3.05-2.2)+3*0.6*(3.05-2.2)+1*3*(3.05-2.2)+...
A99: B | B99: 200mm thick wall | C99: =50.1*3.05+(8*1*(3.05-2.2)+15*0.9*(3.05-2.2)+20*0.75*(3.05-2.2)+1*0.7*(3.05-2.2)+3*1.2*(3.05-2.2)+3*1*(3.05-2.2)+2*1*(3.05-2.2)+1*0.9*(3.05-2.2)+1*1.5*(3.05-2.2)+2*0.9*(3.05-2.2)+4*0.75*(3.05-2.2)+1*0.45*(3.05-2.2)+3*0.6*(3.05-2.2)+1*3*(3.05-2.2)+4*1.6*(3.05-2.2)+2*1.3*(3.05-2.2)+4*1.8*(3.05-2.2)+1*1.2*(3.05-2.2)+6*1.8*(3.05-1.3)+10*0.9*(3.05-1.3)+1*1.8*(3.05-1.6)+3*1.2*(3.05-1.9)+8*1.2*(3.05-1.15)+1*1.2*(3.05-1.2)+6*1.5*(3.05-1.3)+3*1.5*(3.05-1.15)+1*2.4*(3.05-1.3)+1*3*(3.05-1.6)+3*1.8*(3.05-1.9)+1*0.75*(3.05-1.3)+1*1.45*(3.05-1.9)+12*0.9*(3.05-0.6)+5*0.75*(3.05-0.6)+1*0.6*(3.05-0.6)+1*1.2*(3.05-0.6))*0.100 -> 173.631 | D99: m2 | E99: =RATES!$D$47 -> 265 | F99: =C99*E99 -> 46012.215 | G99: 50.1*3.05+(8*1*(3.05-2.2)+15*0.9*(3.05-2.2)+20*0.75*(3.05-2.2)+1*0.7*(3.05-2.2)+3*1.2*(3.05-2.2)+3*1*(3.05-2.2)+2*1*(3.05-2.2)+1*0.9*(3.05-2.2)+1*1.5*(3.05-2.2)+2*0.9*(3.05-2.2)+4*0.75*(3.05-2.2)+1*0.45*(3.05-2.2)+3*0.6*(3.05-2.2)+1*3*(3.05-2.2)+4...
B101: =B94 -> ELEMENT NO. 2: MASONRY | F101: =SUM(F96:F100) -> 381266.88
B102: Carried to Bill Summary
B105: ELEMENT NO. 4: WINDOWS/DOORS
B107: L20 DOORS - Supply and fix the following door assemblies complete with frames, ironmongery sets to steel doors and all accessories:
A108: A | B108: 1000mm x 2200mm 1-hour fire-rated galvanised steel single-leaf security door assembly (D2) | C108: =8 -> 8 | D108: nr | E108: =RATES!$D$75 -> 7800 | F108: =C108*E108 -> 62400 | G108: 8
A110: B | B110: 900mm x 2200mm single leaf timber panel door (D3) | C110: =15 -> 15 | D110: nr | E110: =RATES!$D$76 -> 3400 | F110: =C110*E110 -> 51000 | G110: 15
A112: C | B112: 750mm x 2200mm single leaf timber flush door (D6) | C112: =20 -> 20 | D112: nr | E112: =RATES!$D$79 -> 1900 | F112: =C112*E112 -> 38000 | G112: 20
A114: D | B114: 700mm x 2200mm single-leaf 2-hour fire-rated galvanised steel door (D7) | C114: =1 -> 1 | D114: nr | E114: =RATES!$D$80 -> 6800 | F114: =C114*E114 -> 6800 | G114: 1
A116: E | B116: 1200mm x 2200mm 1-hour fire-rated leaf-and-a-half galvanised steel security door assembly (D8) | C116: =3 -> 3 | D116: nr | E116: =RATES!$D$81 -> 9800 | F116: =C116*E116 -> 29400 | G116: 3
A118: F | B118: 1000mm x 2200mm 1-hour fire-rated galvanised steel single-leaf security door assembly - emergency stairs (ED1) | C118: =3 -> 3 | D118: nr | E118: =RATES!$D$82 -> 7200 | F118: =C118*E118 -> 21600 | G118: 3
A120: G | B120: 1000mm x 2200mm 1-hour fire-rated galvanised steel single-leaf security door with translucent glass panel (ED2) | C120: =2 -> 2 | D120: nr | E120: =RATES!$D$83 -> 8100 | F120: =C120*E120 -> 16200 | G120: 2
A122: H | B122: 900mm x 2200mm 1-hour fire-rated galvanised steel single-leaf security door assembly (D9) | C122: =1 -> 1 | D122: nr | E122: =RATES!$D$84 -> 6900 | F122: =C122*E122 -> 6900 | G122: 1
A124: J | B124: 1500mm x 2200mm timber bi-fold door (FD1) | C124: =1 -> 1 | D124: nr | E124: =RATES!$D$86 -> 4600 | F124: =C124*E124 -> 4600 | G124: 1
A126: K | B126: 900mm x 2200mm screw-fixed galvanised steel service access panel (M1) | C126: =2 -> 2 | D126: nr | E126: =RATES!$D$87 -> 2900 | F126: =C126*E126 -> 5800 | G126: 2
A128: L | B128: 750mm x 2200mm screw-fixed galvanised steel service access panel (M2) | C128: =4 -> 4 | D128: nr | E128: =RATES!$D$88 -> 2600 | F128: =C128*E128 -> 10400 | G128: 4
A130: M | B130: 450mm x 2200mm screw-fixed galvanised steel service access panel (M3) | C130: =1 -> 1 | D130: nr | E130: =RATES!$D$89 -> 1900 | F130: =C130*E130 -> 1900 | G130: 1
A132: N | B132: 600mm x 2200mm screw-fixed galvanised steel service access panel (M5) | C132: =3 -> 3 | D132: nr | E132: =RATES!$D$90 -> 2200 | F132: =C132*E132 -> 6600 | G132: 3
A134: P | B134: 3000mm x 2200mm 3-panel galvanised steel framed tempered glass sliding door (SD1) | C134: =1 -> 1 | D134: nr | E134: =RATES!$D$94 -> 14500 | F134: =C134*E134 -> 14500 | G134: 1
A136: Q | B136: 1600mm x 2200mm 2-panel galvanised steel framed tempered glass sliding door (SD2) | C136: =4 -> 4 | D136: nr | E136: =RATES!$D$95 -> 8800 | F136: =C136*E136 -> 35200 | G136: 4
A138: R | B138: 1300mm x 2200mm 2-panel galvanised steel framed tempered glass sliding door (SD3) | C138: =2 -> 2 | D138: nr | E138: =RATES!$D$96 -> 7600 | F138: =C138*E138 -> 15200 | G138: 2
A140: S | B140: 1800mm x 2200mm 2-panel galvanised steel framed tempered glass sliding door (SD4) | C140: =4 -> 4 | D140: nr | E140: =RATES!$D$97 -> 9300 | F140: =C140*E140 -> 37200 | G140: 4
A142: T | B142: 1200mm x 2200mm 2-panel galvanised steel framed tempered glass sliding door (SD5) | C142: =1 -> 1 | D142: nr | E142: =RATES!$D$98 -> 7200 | F142: =C142*E142 -> 7200 | G142: 1
A144: U | B144: 50mm x 150mm frames (to timber doors) | C144: =15*(2*2.2+0.9)+20*(2*2.2+0.75)+1*(2*2.2+1.5) -> 188.4 | D144: m | E144: =RATES!$D$100 -> 125 | F144: =C144*E144 -> 23550 | G144: 15*(2*2.2+0.9)+20*(2*2.2+0.75)+1*(2*2.2+1.5)
A146: V | B146: 50mm x 12mm door stop | C146: =15*(2*2.2+0.9)+20*(2*2.2+0.75)+1*(2*2.2+1.5) -> 188.4 | D146: m | E146: =RATES!$D$101 -> 28 | F146: =C146*E146 -> 5275.2 | G146: 15*(2*2.2+0.9)+20*(2*2.2+0.75)+1*(2*2.2+1.5)
B148: Ironmongery - Supply and fix the following approved ironmongery to hardwood with accompanying patented screws:
A149: W | B149: Pair 100mm brass butt hinges | C149: =53 -> 53 | D149: pr | E149: =RATES!$D$102 -> 125 | F149: =C149*E149 -> 6625 | G149: 53
A151: X | B151: Ordinary locks | C151: =15 -> 15 | D151: nr | E151: =RATES!$D$103 -> 480 | F151: =C151*E151 -> 7200 | G151: 15
A153: Y | B153: Approved high quality mortice indicator lock | C153: =20 -> 20 | D153: nr | E153: =RATES!$D$104 -> 560 | F153: =C153*E153 -> 11200 | G153: 20
B155: ALUMINIUM GLAZED WINDOWS - Supply and install Italian extruded aluminium glazed windows, ALCOA R50 series, powder coated aluminium profile, glazed with 6mm tinted reflective glass secured onto galvanized steel sub-frames, complete with all accessories as per Architect's detail:
A156: Z | B156: 2 bay alu. framed glass sliding window 1800mm x 1300mm (W2) | C156: =6 -> 6 | D156: nr | E156: =RATES!$D$109 -> 3861 | F156: =C156*E156 -> 23166 | G156: 6
A158: A | B158: 1 bay alu. framed glass awning window 900mm x 1300mm (W4) | C158: =10 -> 10 | D158: nr | E158: =RATES!$D$111 -> 1930.5 | F158: =C158*E158 -> 19305 | G158: 10
A160: B | B160: 2 bay alu. framed glass sliding window 1800mm x 1600mm (W7) | C160: =1 -> 1 | D160: nr | E160: =RATES!$D$114 -> 4752 | F160: =C160*E160 -> 4752 | G160: 1
A162: C | B162: 1 x 3 bay alu. framed glass awning window 1200mm x 1900mm (W8) | C162: =3 -> 3 | D162: nr | E162: =RATES!$D$115 -> 3762 | F162: =C162*E162 -> 11286 | G162: 3
A164: D | B164: 2 bay alu. framed glass sliding window 1200mm x 1150mm (W9) | C164: =8 -> 8 | D164: nr | E164: =RATES!$D$116 -> 2277 | F164: =C164*E164 -> 18216 | G164: 8
A166: E | B166: 2 bay alu. framed glass sliding window 1200mm x 1200mm (W10) | C166: =1 -> 1 | D166: nr | E166: =RATES!$D$117 -> 2376 | F166: =C166*E166 -> 2376 | G166: 1
A168: F | B168: 2 bay alu. framed glass sliding window 1500mm x 1300mm (W11) | C168: =6 -> 6 | D168: nr | E168: =RATES!$D$118 -> 3217.5 | F168: =C168*E168 -> 19305 | G168: 6
A170: G | B170: 2 bay alu. framed glass sliding window 1500mm x 1150mm (W12) | C170: =3 -> 3 | D170: nr | E170: =RATES!$D$119 -> 2846.25 | F170: =C170*E170 -> 8538.75 | G170: 3
A172: H | B172: 3 bay alu. framed glass awning window 2400mm x 1300mm (W13) | C172: =1 -> 1 | D172: nr | E172: =RATES!$D$120 -> 5148 | F172: =C172*E172 -> 5148 | G172: 1
A174: J | B174: 3 bay alu. framed glass sliding window 3000mm x 1600mm (W15) | C174: =1 -> 1 | D174: nr | E174: =RATES!$D$122 -> 7920 | F174: =C174*E174 -> 7920 | G174: 1
A176: K | B176: 2 x 3 alu. framed glass awning window 1800mm x 1900mm (W17) | C176: =3 -> 3 | D176: nr | E176: =RATES!$D$124 -> 5643 | F176: =C176*E176 -> 16929 | G176: 3
A178: L | B178: 1 bay alu. framed glass awning window 750mm x 1300mm (W18) | C178: =1 -> 1 | D178: nr | E178: =RATES!$D$125 -> 1608.75 | F178: =C178*E178 -> 1608.75 | G178: 1
A180: M | B180: 2 x 3 alu. framed glass awning window 1450mm x 1900mm (W20) | C180: =1 -> 1 | D180: nr | E180: =RATES!$D$127 -> 4545.75 | F180: =C180*E180 -> 4545.75 | G180: 1
A182: N | B182: 2 bay alu. framed glass sliding window 900mm x 600mm (HW1) | C182: =12 -> 12 | D182: nr | E182: =RATES!$D$128 -> 891 | F182: =C182*E182 -> 10692 | G182: 12
A184: P | B184: 2 bay alu. framed glass sliding window 750mm x 600mm (HW2) | C184: =5 -> 5 | D184: nr | E184: =RATES!$D$129 -> 742.5 | F184: =C184*E184 -> 3712.5 | G184: 5
A186: Q | B186: 2 bay alu. framed glass sliding window 600mm x 600mm (HW3) | C186: =1 -> 1 | D186: nr | E186: =RATES!$D$130 -> 594 | F186: =C186*E186 -> 594 | G186: 1
A188: R | B188: 2 bay alu. framed glass sliding window 1200mm x 600mm (HW4) | C188: =1 -> 1 | D188: nr | E188: =RATES!$D$131 -> 1188 | F188: =C188*E188 -> 1188 | G188: 1
...

Sheet 8TH FLR   
A1: ='PRELIMS & GEN. ITEMS'!A2 -> PROJECT: BLOCK N REDEVELOPMENT
A2: ='PRELIMS & GEN. ITEMS'!A3 -> LOCATION: KANESHIE
A3: ='PRELIMS & GEN. ITEMS'!A4 -> CLIENT: STATE HOUSING LIMITED
A4: ='PRELIMS & GEN. ITEMS'!A5 -> DATE:9/30/2026
A5: ITEM | B5: DESCRIPTION | C5: QTY | D5: UNIT | E5: RATE | F5: AMOUNT - GHC | G5: Measurement basis / calculation
B7: MAIN BUILDING
B9: EIGHTH FLOOR
B11: BILL SUMMARY
A13: A | B13: ELEMENT NO. 1: IN SITU CONCRETE/LARGE PRECAST CONCRETE | F13: =F92 -> 3309777.5
A15: B | B15: ELEMENT NO. 2: MASONRY | F15: =F103 -> 379547.96
A17: C | B17: ELEMENT NO. 4: WINDOWS/DOORS | F17: =F192 -> 587877.15
A19: D | B19: ELEMENT NO. 5: FLOOR FINISHES | F19: =F213 -> 345862.54
A21: E | B21: ELEMENT NO. 6: WALL FINISHES | F21: =F230 -> 311695.51
A23: F | B23: ELEMENT NO. 7: PAINTING AND DECORATING | F23: =F251 -> 185701.3
B25: =B9 -> EIGHTH FLOOR | E25: GHC | F25: =SUM(F13:F24) -> 5120461.9
B26: To Bill General Summary
B29: BILL NR. 11 - EIGHTH FLOOR
B31: ELEMENT NO. 1: IN SITU CONCRETE/LARGE PRECAST CONCRETE
B33: Vibrated in-situ concrete C40 as described in:
A34: A | B34: Suspended slab 250mm thick | C34: =1134.6*0.25 -> 283.65 | D34: m3 | E34: =RATES!$D$22 -> 2650 | F34: =C34*E34 -> 751672.5 | G34: 1134.6*0.25
A36: B | B36: Beams (downstands below slab) | C36: =166.8*0.3*0.35+33.1*0.2*0.35 -> 19.831 | D36: m3 | E36: =RATES!$D$23 -> 2700 | F36: =C36*E36 -> 53543.7 | G36: 166.8*0.3*0.35+33.1*0.2*0.35
A38: C | B38: Columns | C38: =5*0.75*0.5*3.05+1*0.75*0.5*3.05+2*0.75*0.5*3.05+1*0.75*0.5*3.05+3*1.2*0.3*3.05+6*1.2*0.3*3.05+1*1.2*0.3*3.05+15*1.2*0.3*3.05+1*(2.85*0.25+0.825*0.25)*3.05 -> 40.545937 | D38: m3 | E38: =RATES!$D$21 -> 2800 | F38: =C38*E38 -> 113528.62 | G38: 5*0.75*0.5*3.05+1*0.75*0.5*3.05+2*0.75*0.5*3.05+1*0.75*0.5*3.05+3*1.2*0.3*3.05+6*1.2*0.3*3.05+1*1.2*0.3*3.05+15*1.2*0.3*3.05+1*(2.85*0.25+0.825*0.25)*3.05
A40: D | B40: Concrete wall - shear walls to main & emergency stair cores, 250mm thick | C40: =22.05*3.05*0.25+25.57*3.05*0.25 -> 36.31025 | D40: m3 | E40: =RATES!$D$20 -> 2750 | F40: =C40*E40 -> 99853.187 | G40: 22.05*3.05*0.25+25.57*3.05*0.25
A42: E | B42: Concrete wall - lift walls, 250mm thick | C42: =21.825*3.05*0.25 -> 16.641562 | D42: m3 | E42: =RATES!$D$20 -> 2750 | F42: =C42*E42 -> 45764.297 | G42: 21.825*3.05*0.25
A44: F | B44: Stairs | C44: =(2.966*3.3/3.3+2.625)+(2.966*3.3/3.3+2.625) -> 11.182 | D44: m3 | E44: =RATES!$D$24 -> 2850 | F44: =C44*E44 -> 31868.7 | G44: (2.966*3.3/3.3+2.625)+(2.966*3.3/3.3+2.625)
A46: G | B46: Lintels 150 x 225mm over door and window openings | C46: =(8*(1+0.3)+15*(0.9+0.3)+21*(0.75+0.3)+1*(0.7+0.3)+2*(1.2+0.3)+3*(1+0.3)+2*(1+0.3)+1*(0.9+0.3)+1*(1.5+0.3)+2*(0.9+0.3)+4*(0.75+0.3)+1*(0.45+0.3)+3*(0.6+0.3)+1*(3+0.3)+4*(1.6+0.3)+2*(1.3+0.3)+4*(1.8+0.3)+1*(1.2+0.3)+6*(1.8+0.3)+10*(0.9+0.3)+2*(1.8+0.3)+3*(1.2+0.3)+8*(1.2+0.3)+1*(1.2+0.3)+6*(1.5+0.3)+4*(1.5+0.3)+1*(2.4+0.3)+1*(3+0.3)+3*(1.8+0.3)+1*(0.75+0.3)+1*(1.45+0.3)+13*(0.9+0.3)+5*(0.75+0.3)+2*(0.6+0.3)+2*(1.2+0.3))*0.15*0.225 -> 6.8698125 | D46: m3 | E46: =RATES!$D$25 -> 2600 | F46: =C46*E46 -> 17861.513 | G46: (8*(1+0.3)+15*(0.9+0.3)+21*(0.75+0.3)+1*(0.7+0.3)+2*(1.2+0.3)+3*(1+0.3)+2*(1+0.3)+1*(0.9+0.3)+1*(1.5+0.3)+2*(0.9+0.3)+4*(0.75+0.3)+1*(0.45+0.3)+3*(0.6+0.3)+1*(3+0.3)+4*(1.6+0.3)+2*(1.3+0.3)+4*(1.8+0.3)+1*(1.2+0.3)+6*(1.8+0.3)+10*(0.9+0.3)+2*(1.8+0...
B48: E20 FORMWORK - Formwork as described to:
A49: H | B49: Soffits of suspended slab | C49: =1134.6 -> 1134.6 | D49: m2 | E49: =RATES!$D$38 -> 170 | F49: =C49*E49 -> 192882 | G49: 1134.6
A51: J | B51: Edges of suspended slab 250mm high | C51: =294.6 -> 294.6 | D51: m | E51: =RATES!$D$40 -> 65 | F51: =C51*E51 -> 19149 | G51: 294.6
A53: K | B53: Sides and soffits of beams | C53: =166.8*(2*0.35+0.3)+33.1*(2*0.35+0.2) -> 196.59 | D53: m2 | E53: =RATES!$D$39 -> 200 | F53: =C53*E53 -> 39318 | G53: 166.8*(2*0.35+0.3)+33.1*(2*0.35+0.2)
A55: L | B55: Columns | C55: =5*2*(0.75+0.5)*3.05+1*2*(0.75+0.5)*3.05+2*2*(0.75+0.5)*3.05+1*2*(0.75+0.5)*3.05+3*2*(1.2+0.3)*3.05+6*2*(1.2+0.3)*3.05+1*2*(1.2+0.3)*3.05+15*2*(1.2+0.3)*3.05+1*2*(2.85+1.075)*3.05 -> 321.3175 | D55: m2 | E55: =RATES!$D$37 -> 190 | F55: =C55*E55 -> 61050.325 | G55: 5*2*(0.75+0.5)*3.05+1*2*(0.75+0.5)*3.05+2*2*(0.75+0.5)*3.05+1*2*(0.75+0.5)*3.05+3*2*(1.2+0.3)*3.05+6*2*(1.2+0.3)*3.05+1*2*(1.2+0.3)*3.05+15*2*(1.2+0.3)*3.05+1*2*(2.85+1.075)*3.05
A57: M | B57: Concrete wall (both faces) | C57: =2*22.05*3.05+2*21.825*3.05+2*25.57*3.05 -> 423.6145 | D57: m2 | E57: =RATES!$D$36 -> 185 | F57: =C57*E57 -> 78368.683 | G57: 2*22.05*3.05+2*21.825*3.05+2*25.57*3.05
A59: N | B59: Soffits of stair flights, landings and risers | C59: =(2*3.424*1.8+15.0+22*0.15*1.8)+(2*3.424*1.8+15.0+22*0.15*1.8) -> 66.5328 | D59: m2 | E59: =RATES!$D$42 -> 230 | F59: =C59*E59 -> 15302.544 | G59: (2*3.424*1.8+15.0+22*0.15*1.8)+(2*3.424*1.8+15.0+22*0.15*1.8)
A61: P | B61: Side and soffits of lintel / coping | C61: =(8*(1+0.3)+15*(0.9+0.3)+21*(0.75+0.3)+1*(0.7+0.3)+2*(1.2+0.3)+3*(1+0.3)+2*(1+0.3)+1*(0.9+0.3)+1*(1.5+0.3)+2*(0.9+0.3)+4*(0.75+0.3)+1*(0.45+0.3)+3*(0.6+0.3)+1*(3+0.3)+4*(1.6+0.3)+2*(1.3+0.3)+4*(1.8+0.3)+1*(1.2+0.3)+6*(1.8+0.3)+10*(0.9+0.3)+2*(1.8+0.3)+3*(1.2+0.3)+8*(1.2+0.3)+1*(1.2+0.3)+6*(1.5+0.3)+4*(1.5+0.3)+1*(2.4+0.3)+1*(3+0.3)+3*(1.8+0.3)+1*(0.75+0.3)+1*(1.45+0.3)+13*(0.9+0.3)+5*(0.75+0.3)+2*(0.6+0.3)+2*(1.2+0.3))*(2*0.225+0.15) -> 122.13 | D61: m2 | E61: =RATES!$D$43 -> 180 | F61: =C61*E61 -> 21983.4 | G61: (8*(1+0.3)+15*(0.9+0.3)+21*(0.75+0.3)+1*(0.7+0.3)+2*(1.2+0.3)+3*(1+0.3)+2*(1+0.3)+1*(0.9+0.3)+1*(1.5+0.3)+2*(0.9+0.3)+4*(0.75+0.3)+1*(0.45+0.3)+3*(0.6+0.3)+1*(3+0.3)+4*(1.6+0.3)+2*(1.3+0.3)+4*(1.8+0.3)+1*(1.2+0.3)+6*(1.8+0.3)+10*(0.9+0.3)+2*(1.8+0...
B63: E30 REINFORCEMENT - High tensile yield round bar reinforcement (standard) to BS 4449:
A64: Q | B64: 10mm diameter in columns | C64: =4.509 -> 4.509 | D64: t | E64: =RATES!$D$29 -> 20500 | F64: =C64*E64 -> 92434.5 | G64: 4.509
A66: R | B66: 20mm diameter in columns | C66: =6.299 -> 6.299 | D66: t | E66: =RATES!$D$32 -> 19000 | F66: =C66*E66 -> 119681 | G66: 6.299
A68: S | B68: 25mm diameter in columns | C68: =0.624 -> 0.624 | D68: t | E68: =RATES!$D$33 -> 19000 | F68: =C68*E68 -> 11856 | G68: 0.624
A70: T | B70: 10mm diameter in beams (links) | C70: =1.806 -> 1.806 | D70: t | E70: =RATES!$D$29 -> 20500 | F70: =C70*E70 -> 37023 | G70: 1.806
A72: U | B72: 16mm diameter in beams | C72: =1.248 -> 1.248 | D72: t | E72: =RATES!$D$31 -> 19500 | F72: =C72*E72 -> 24336 | G72: 1.248
A74: V | B74: 20mm diameter in beams | C74: =2.135 -> 2.135 | D74: t | E74: =RATES!$D$32 -> 19000 | F74: =C74*E74 -> 40565 | G74: 2.135
A76: W | B76: 25mm diameter in beams | C76: =5.507 -> 5.507 | D76: t | E76: =RATES!$D$33 -> 19000 | F76: =C76*E76 -> 104633 | G76: 5.507
A78: X | B78: 10mm diameter in shear & lift walls (links) | C78: =1.442+0.636 -> 2.078 | D78: t | E78: =RATES!$D$29 -> 20500 | F78: =C78*E78 -> 42599 | G78: 1.442+0.636
A80: Y | B80: 12mm diameter in shear, lift & ramp walls | C80: =1.917+0.866 -> 2.783 | D80: t | E80: =RATES!$D$30 -> 20000 | F80: =C80*E80 -> 55660 | G80: 1.917+0.866
A82: Z | B82: 20mm diameter in shear & lift walls | C82: =6.904+3.320 -> 10.224 | D82: t | E82: =RATES!$D$32 -> 19000 | F82: =C82*E82 -> 194256 | G82: 6.904+3.320
A84: A | B84: 12mm diameter in stairs | C84: =0.880 -> 0.88 | D84: t | E84: =RATES!$D$30 -> 20000 | F84: =C84*E84 -> 17600 | G84: 0.880
A86: B | B86: 16mm diameter in stairs | C86: =1.434 -> 1.434 | D86: t | E86: =RATES!$D$31 -> 19500 | F86: =C86*E86 -> 27963 | G86: 1.434
A88: C | B88: 12mm diameter for suspended slab | C88: =49.804 -> 49.804 | D88: t | E88: =RATES!$D$30 -> 20000 | F88: =C88*E88 -> 996080 | G88: 49.804
A90: D | B90: 16mm diameter for suspended slab | C90: =0.151 -> 0.151 | D90: t | E90: =RATES!$D$31 -> 19500 | F90: =C90*E90 -> 2944.5 | G90: 0.151
B92: =B31 -> ELEMENT NO. 1: IN SITU CONCRETE/LARGE PRECAST CONCRETE | F92: =SUM(F33:F91) -> 3309777.5
B93: Carried to Bill Summary
B96: ELEMENT NO. 2: MASONRY
B98: F10 BRICK/BLOCK WALL - Solid sandcrete blockwork in cement and sand (1:4) mortar as described in:
A99: A | B99: 150mm thick wall | C99: =441.2*3.05+(8*1*(3.05-2.2)+15*0.9*(3.05-2.2)+21*0.75*(3.05-2.2)+1*0.7*(3.05-2.2)+2*1.2*(3.05-2.2)+3*1*(3.05-2.2)+2*1*(3.05-2.2)+1*0.9*(3.05-2.2)+1*1.5*(3.05-2.2)+2*0.9*(3.05-2.2)+4*0.75*(3.05-2.2)+1*0.45*(3.05-2.2)+3*0.6*(3.05-2.2)+1*3*(3.05-2.2)+4*1.6*(3.05-2.2)+2*1.3*(3.05-2.2)+4*1.8*(3.05-2.2)+1*1.2*(3.05-2.2)+6*1.8*(3.05-1.3)+10*0.9*(3.05-1.3)+2*1.8*(3.05-1.6)+3*1.2*(3.05-1.9)+8*1.2*(3.05-1.15)+1*1.2*(3.05-1.2)+6*1.5*(3.05-1.3)+4*1.5*(3.05-1.15)+1*2.4*(3.05-1.3)+1*3*(3.05-1.6)+3*1.8*(3.05-1.9)+1*0.75*(3.05-1.3)+1*1.45*(3.05-1.9)+13*0.9*(3.05-0.6)+5*0.75*(3.05-0.6)+2*0.6*(3.05-0.6)+2*1.2*(3.05-0.6))*0.895 -> 1542.5175 | D99: m2 | E99: =RATES!$D$46 -> 215 | F99: =C99*E99 -> 331641.26 | G99: 441.2*3.05+(8*1*(3.05-2.2)+15*0.9*(3.05-2.2)+21*0.75*(3.05-2.2)+1*0.7*(3.05-2.2)+2*1.2*(3.05-2.2)+3*1*(3.05-2.2)+2*1*(3.05-2.2)+1*0.9*(3.05-2.2)+1*1.5*(3.05-2.2)+2*0.9*(3.05-2.2)+4*0.75*(3.05-2.2)+1*0.45*(3.05-2.2)+3*0.6*(3.05-2.2)+1*3*(3.05-2.2)+...
A101: B | B101: 200mm thick wall | C101: =51.7*3.05+(8*1*(3.05-2.2)+15*0.9*(3.05-2.2)+21*0.75*(3.05-2.2)+1*0.7*(3.05-2.2)+2*1.2*(3.05-2.2)+3*1*(3.05-2.2)+2*1*(3.05-2.2)+1*0.9*(3.05-2.2)+1*1.5*(3.05-2.2)+2*0.9*(3.05-2.2)+4*0.75*(3.05-2.2)+1*0.45*(3.05-2.2)+3*0.6*(3.05-2.2)+1*3*(3.05-2.2)+4*1.6*(3.05-2.2)+2*1.3*(3.05-2.2)+4*1.8*(3.05-2.2)+1*1.2*(3.05-2.2)+6*1.8*(3.05-1.3)+10*0.9*(3.05-1.3)+2*1.8*(3.05-1.6)+3*1.2*(3.05-1.9)+8*1.2*(3.05-1.15)+1*1.2*(3.05-1.2)+6*1.5*(3.05-1.3)+4*1.5*(3.05-1.15)+1*2.4*(3.05-1.3)+1*3*(3.05-1.6)+3*1.8*(3.05-1.9)+1*0.75*(3.05-1.3)+1*1.45*(3.05-1.9)+13*0.9*(3.05-0.6)+5*0.75*(3.05-0.6)+2*0.6*(3.05-0.6)+2*1.2*(3.05-0.6))*0.105 -> 180.78001 | D101: m2 | E101: =RATES!$D$47 -> 265 | F101: =C101*E101 -> 47906.703 | G101: 51.7*3.05+(8*1*(3.05-2.2)+15*0.9*(3.05-2.2)+21*0.75*(3.05-2.2)+1*0.7*(3.05-2.2)+2*1.2*(3.05-2.2)+3*1*(3.05-2.2)+2*1*(3.05-2.2)+1*0.9*(3.05-2.2)+1*1.5*(3.05-2.2)+2*0.9*(3.05-2.2)+4*0.75*(3.05-2.2)+1*0.45*(3.05-2.2)+3*0.6*(3.05-2.2)+1*3*(3.05-2.2)+4...
B103: =B96 -> ELEMENT NO. 2: MASONRY | F103: =SUM(F98:F102) -> 379547.96
B104: Carried to Bill Summary
B107: ELEMENT NO. 4: WINDOWS/DOORS
B109: L20 DOORS - Supply and fix the following door assemblies complete with frames, ironmongery sets to steel doors and all accessories:
A110: A | B110: 1000mm x 2200mm 1-hour fire-rated galvanised steel single-leaf security door assembly (D2) | C110: =8 -> 8 | D110: nr | E110: =RATES!$D$75 -> 7800 | F110: =C110*E110 -> 62400 | G110: 8
A112: B | B112: 900mm x 2200mm single leaf timber panel door (D3) | C112: =15 -> 15 | D112: nr | E112: =RATES!$D$76 -> 3400 | F112: =C112*E112 -> 51000 | G112: 15
A114: C | B114: 750mm x 2200mm single leaf timber flush door (D6) | C114: =21 -> 21 | D114: nr | E114: =RATES!$D$79 -> 1900 | F114: =C114*E114 -> 39900 | G114: 21
A116: D | B116: 700mm x 2200mm single-leaf 2-hour fire-rated galvanised steel door (D7) | C116: =1 -> 1 | D116: nr | E116: =RATES!$D$80 -> 6800 | F116: =C116*E116 -> 6800 | G116: 1
A118: E | B118: 1200mm x 2200mm 1-hour fire-rated leaf-and-a-half galvanised steel security door assembly (D8) | C118: =2 -> 2 | D118: nr | E118: =RATES!$D$81 -> 9800 | F118: =C118*E118 -> 19600 | G118: 2
A120: F | B120: 1000mm x 2200mm 1-hour fire-rated galvanised steel single-leaf security door assembly - emergency stairs (ED1) | C120: =3 -> 3 | D120: nr | E120: =RATES!$D$82 -> 7200 | F120: =C120*E120 -> 21600 | G120: 3
A122: G | B122: 1000mm x 2200mm 1-hour fire-rated galvanised steel single-leaf security door with translucent glass panel (ED2) | C122: =2 -> 2 | D122: nr | E122: =RATES!$D$83 -> 8100 | F122: =C122*E122 -> 16200 | G122: 2
A124: H | B124: 900mm x 2200mm 1-hour fire-rated galvanised steel single-leaf security door assembly (D9) | C124: =1 -> 1 | D124: nr | E124: =RATES!$D$84 -> 6900 | F124: =C124*E124 -> 6900 | G124: 1
A126: J | B126: 1500mm x 2200mm timber bi-fold door (FD1) | C126: =1 -> 1 | D126: nr | E126: =RATES!$D$86 -> 4600 | F126: =C126*E126 -> 4600 | G126: 1
A128: K | B128: 900mm x 2200mm screw-fixed galvanised steel service access panel (M1) | C128: =2 -> 2 | D128: nr | E128: =RATES!$D$87 -> 2900 | F128: =C128*E128 -> 5800 | G128: 2
A130: L | B130: 750mm x 2200mm screw-fixed galvanised steel service access panel (M2) | C130: =4 -> 4 | D130: nr | E130: =RATES!$D$88 -> 2600 | F130: =C130*E130 -> 10400 | G130: 4
A132: M | B132: 450mm x 2200mm screw-fixed galvanised steel service access panel (M3) | C132: =1 -> 1 | D132: nr | E132: =RATES!$D$89 -> 1900 | F132: =C132*E132 -> 1900 | G132: 1
A134: N | B134: 600mm x 2200mm screw-fixed galvanised steel service access panel (M5) | C134: =3 -> 3 | D134: nr | E134: =RATES!$D$90 -> 2200 | F134: =C134*E134 -> 6600 | G134: 3
A136: P | B136: 3000mm x 2200mm 3-panel galvanised steel framed tempered glass sliding door (SD1) | C136: =1 -> 1 | D136: nr | E136: =RATES!$D$94 -> 14500 | F136: =C136*E136 -> 14500 | G136: 1
A138: Q | B138: 1600mm x 2200mm 2-panel galvanised steel framed tempered glass sliding door (SD2) | C138: =4 -> 4 | D138: nr | E138: =RATES!$D$95 -> 8800 | F138: =C138*E138 -> 35200 | G138: 4
A140: R | B140: 1300mm x 2200mm 2-panel galvanised steel framed tempered glass sliding door (SD3) | C140: =2 -> 2 | D140: nr | E140: =RATES!$D$96 -> 7600 | F140: =C140*E140 -> 15200 | G140: 2
A142: S | B142: 1800mm x 2200mm 2-panel galvanised steel framed tempered glass sliding door (SD4) | C142: =4 -> 4 | D142: nr | E142: =RATES!$D$97 -> 9300 | F142: =C142*E142 -> 37200 | G142: 4
A144: T | B144: 1200mm x 2200mm 2-panel galvanised steel framed tempered glass sliding door (SD5) | C144: =1 -> 1 | D144: nr | E144: =RATES!$D$98 -> 7200 | F144: =C144*E144 -> 7200 | G144: 1
A146: U | B146: 50mm x 150mm frames (to timber doors) | C146: =15*(2*2.2+0.9)+21*(2*2.2+0.75)+1*(2*2.2+1.5) -> 193.55 | D146: m | E146: =RATES!$D$100 -> 125 | F146: =C146*E146 -> 24193.75 | G146: 15*(2*2.2+0.9)+21*(2*2.2+0.75)+1*(2*2.2+1.5)
A148: V | B148: 50mm x 12mm door stop | C148: =15*(2*2.2+0.9)+21*(2*2.2+0.75)+1*(2*2.2+1.5) -> 193.55 | D148: m | E148: =RATES!$D$101 -> 28 | F148: =C148*E148 -> 5419.4 | G148: 15*(2*2.2+0.9)+21*(2*2.2+0.75)+1*(2*2.2+1.5)
B150: Ironmongery - Supply and fix the following approved ironmongery to hardwood with accompanying patented screws:
A151: W | B151: Pair 100mm brass butt hinges | C151: =54 -> 54 | D151: pr | E151: =RATES!$D$102 -> 125 | F151: =C151*E151 -> 6750 | G151: 54
A153: X | B153: Ordinary locks | C153: =15 -> 15 | D153: nr | E153: =RATES!$D$103 -> 480 | F153: =C153*E153 -> 7200 | G153: 15
A155: Y | B155: Approved high quality mortice indicator lock | C155: =21 -> 21 | D155: nr | E155: =RATES!$D$104 -> 560 | F155: =C155*E155 -> 11760 | G155: 21
B157: ALUMINIUM GLAZED WINDOWS - Supply and install Italian extruded aluminium glazed windows, ALCOA R50 series, powder coated aluminium profile, glazed with 6mm tinted reflective glass secured onto galvanized steel sub-frames, complete with all accessories as per Architect's detail:
A158: Z | B158: 2 bay alu. framed glass sliding window 1800mm x 1300mm (W2) | C158: =6 -> 6 | D158: nr | E158: =RATES!$D$109 -> 3861 | F158: =C158*E158 -> 23166 | G158: 6
A160: A | B160: 1 bay alu. framed glass awning window 900mm x 1300mm (W4) | C160: =10 -> 10 | D160: nr | E160: =RATES!$D$111 -> 1930.5 | F160: =C160*E160 -> 19305 | G160: 10
A162: B | B162: 2 bay alu. framed glass sliding window 1800mm x 1600mm (W7) | C162: =2 -> 2 | D162: nr | E162: =RATES!$D$114 -> 4752 | F162: =C162*E162 -> 9504 | G162: 2
A164: C | B164: 1 x 3 bay alu. framed glass awning window 1200mm x 1900mm (W8) | C164: =3 -> 3 | D164: nr | E164: =RATES!$D$115 -> 3762 | F164: =C164*E164 -> 11286 | G164: 3
A166: D | B166: 2 bay alu. framed glass sliding window 1200mm x 1150mm (W9) | C166: =8 -> 8 | D166: nr | E166: =RATES!$D$116 -> 2277 | F166: =C166*E166 -> 18216 | G166: 8
A168: E | B168: 2 bay alu. framed glass sliding window 1200mm x 1200mm (W10) | C168: =1 -> 1 | D168: nr | E168: =RATES!$D$117 -> 2376 | F168: =C168*E168 -> 2376 | G168: 1
A170: F | B170: 2 bay alu. framed glass sliding window 1500mm x 1300mm (W11) | C170: =6 -> 6 | D170: nr | E170: =RATES!$D$118 -> 3217.5 | F170: =C170*E170 -> 19305 | G170: 6
A172: G | B172: 2 bay alu. framed glass sliding window 1500mm x 1150mm (W12) | C172: =4 -> 4 | D172: nr | E172: =RATES!$D$119 -> 2846.25 | F172: =C172*E172 -> 11385 | G172: 4
A174: H | B174: 3 bay alu. framed glass awning window 2400mm x 1300mm (W13) | C174: =1 -> 1 | D174: nr | E174: =RATES!$D$120 -> 5148 | F174: =C174*E174 -> 5148 | G174: 1
A176: J | B176: 3 bay alu. framed glass sliding window 3000mm x 1600mm (W15) | C176: =1 -> 1 | D176: nr | E176: =RATES!$D$122 -> 7920 | F176: =C176*E176 -> 7920 | G176: 1
A178: K | B178: 2 x 3 alu. framed glass awning window 1800mm x 1900mm (W17) | C178: =3 -> 3 | D178: nr | E178: =RATES!$D$124 -> 5643 | F178: =C178*E178 -> 16929 | G178: 3
A180: L | B180: 1 bay alu. framed glass awning window 750mm x 1300mm (W18) | C180: =1 -> 1 | D180: nr | E180: =RATES!$D$125 -> 1608.75 | F180: =C180*E180 -> 1608.75 | G180: 1
A182: M | B182: 2 x 3 alu. framed glass awning window 1450mm x 1900mm (W20) | C182: =1 -> 1 | D182: nr | E182: =RATES!$D$127 -> 4545.75 | F182: =C182*E182 -> 4545.75 | G182: 1
A184: N | B184: 2 bay alu. framed glass sliding window 900mm x 600mm (HW1) | C184: =13 -> 13 | D184: nr | E184: =RATES!$D$128 -> 891 | F184: =C184*E184 -> 11583 | G184: 13
A186: P | B186: 2 bay alu. framed glass sliding window 750mm x 600mm (HW2) | C186: =5 -> 5 | D186: nr | E186: =RATES!$D$129 -> 742.5 | F186: =C186*E186 -> 3712.5 | G186: 5
A188: Q | B188: 2 bay alu. framed glass sliding window 600mm x 600mm (HW3) | C188: =2 -> 2 | D188: nr | E188: =RATES!$D$130 -> 594 | F188: =C188*E188 -> 1188 | G188: 2
...

Sheet 9TH FLR    
A1: ='PRELIMS & GEN. ITEMS'!A2 -> PROJECT: BLOCK N REDEVELOPMENT
A2: ='PRELIMS & GEN. ITEMS'!A3 -> LOCATION: KANESHIE
A3: ='PRELIMS & GEN. ITEMS'!A4 -> CLIENT: STATE HOUSING LIMITED
A4: ='PRELIMS & GEN. ITEMS'!A5 -> DATE:9/30/2026
A5: ITEM | B5: DESCRIPTION | C5: QTY | D5: UNIT | E5: RATE | F5: AMOUNT - GHC | G5: Measurement basis / calculation
B7: MAIN BUILDING
B9: NINTH FLOOR
B11: BILL SUMMARY
A13: A | B13: ELEMENT NO. 1: IN SITU CONCRETE/LARGE PRECAST CONCRETE | F13: =F92 -> 3230623.2
A15: B | B15: ELEMENT NO. 2: MASONRY | F15: =F103 -> 310127.3
A17: C | B17: ELEMENT NO. 3: WATERPROOFING | F17: =F114 -> 79963.8
A19: D | B19: ELEMENT NO. 4: WINDOWS/DOORS | F19: =F193 -> 363603.35
A21: E | B21: ELEMENT NO. 5: FLOOR FINISHES | F21: =F216 -> 357394.34
A23: F | B23: ELEMENT NO. 6: WALL FINISHES | F23: =F233 -> 272188.02
A25: G | B25: ELEMENT NO. 7: PAINTING AND DECORATING | F25: =F254 -> 154620.02
B27: =B9 -> NINTH FLOOR | E27: GHC | F27: =SUM(F13:F26) -> 4768520
B28: To Bill General Summary
B31: BILL NR. 12 - NINTH FLOOR
B33: ELEMENT NO. 1: IN SITU CONCRETE/LARGE PRECAST CONCRETE
B35: Vibrated in-situ concrete C40 as described in:
A36: A | B36: Suspended slab 250mm thick | C36: =1134.4*0.25 -> 283.6 | D36: m3 | E36: =RATES!$D$22 -> 2650 | F36: =C36*E36 -> 751540 | G36: 1134.4*0.25
A38: B | B38: Beams (downstands below slab) | C38: =186.5*0.3*0.35+33.1*0.2*0.35 -> 21.8995 | D38: m3 | E38: =RATES!$D$23 -> 2700 | F38: =C38*E38 -> 59128.65 | G38: 186.5*0.3*0.35+33.1*0.2*0.35
A40: C | B40: Columns | C40: =1*0.75*0.5*3.05+2*0.75*0.5*3.05+1*0.75*0.5*3.05+6*1.2*0.3*3.05+1*1.2*0.3*3.05+15*1.2*0.3*3.05 -> 28.731 | D40: m3 | E40: =RATES!$D$21 -> 2800 | F40: =C40*E40 -> 80446.8 | G40: 1*0.75*0.5*3.05+2*0.75*0.5*3.05+1*0.75*0.5*3.05+6*1.2*0.3*3.05+1*1.2*0.3*3.05+15*1.2*0.3*3.05
A42: D | B42: Concrete wall - shear walls to main & emergency stair cores, 250mm thick | C42: =22.05*3.05*0.25+25.57*3.05*0.25 -> 36.31025 | D42: m3 | E42: =RATES!$D$20 -> 2750 | F42: =C42*E42 -> 99853.187 | G42: 22.05*3.05*0.25+25.57*3.05*0.25
A44: E | B44: Concrete wall - lift walls, 250mm thick | C44: =21.825*3.05*0.25 -> 16.641562 | D44: m3 | E44: =RATES!$D$20 -> 2750 | F44: =C44*E44 -> 45764.297 | G44: 21.825*3.05*0.25
A46: F | B46: Stairs | C46: =(2.966*3.3/3.3+2.625)+(2.966*3.3/3.3+2.625) -> 11.182 | D46: m3 | E46: =RATES!$D$24 -> 2850 | F46: =C46*E46 -> 31868.7 | G46: (2.966*3.3/3.3+2.625)+(2.966*3.3/3.3+2.625)
A48: G | B48: Lintels 150 x 225mm over door and window openings | C48: =(4*(1+0.3)+8*(0.9+0.3)+17*(0.75+0.3)+1*(0.7+0.3)+2*(1.2+0.3)+2*(1+0.3)+2*(1+0.3)+1*(0.9+0.3)+2*(0.9+0.3)+4*(0.75+0.3)+1*(0.45+0.3)+3*(0.6+0.3)+1*(3+0.3)+2*(1.6+0.3)+1*(1.3+0.3)+2*(1.8+0.3)+3*(1.8+0.3)+6*(0.9+0.3)+1*(1.8+0.3)+1*(1.2+0.3)+5*(1.2+0.3)+1*(1.2+0.3)+3*(1.5+0.3)+2*(1.5+0.3)+1*(3+0.3)+1*(1.8+0.3)+10*(0.9+0.3)+4*(0.75+0.3)+1*(0.6+0.3)+1*(1.2+0.3))*0.15*0.225 -> 4.222125 | D48: m3 | E48: =RATES!$D$25 -> 2600 | F48: =C48*E48 -> 10977.525 | G48: (4*(1+0.3)+8*(0.9+0.3)+17*(0.75+0.3)+1*(0.7+0.3)+2*(1.2+0.3)+2*(1+0.3)+2*(1+0.3)+1*(0.9+0.3)+2*(0.9+0.3)+4*(0.75+0.3)+1*(0.45+0.3)+3*(0.6+0.3)+1*(3+0.3)+2*(1.6+0.3)+1*(1.3+0.3)+2*(1.8+0.3)+3*(1.8+0.3)+6*(0.9+0.3)+1*(1.8+0.3)+1*(1.2+0.3)+5*(1.2+0.3...
B50: E20 FORMWORK - Formwork as described to:
A51: H | B51: Soffits of suspended slab | C51: =1134.4 -> 1134.4 | D51: m2 | E51: =RATES!$D$38 -> 170 | F51: =C51*E51 -> 192848 | G51: 1134.4
A53: J | B53: Edges of suspended slab 250mm high | C53: =294.5 -> 294.5 | D53: m | E53: =RATES!$D$40 -> 65 | F53: =C53*E53 -> 19142.5 | G53: 294.5
A55: K | B55: Sides and soffits of beams | C55: =186.5*(2*0.35+0.3)+33.1*(2*0.35+0.2) -> 216.29 | D55: m2 | E55: =RATES!$D$39 -> 200 | F55: =C55*E55 -> 43258 | G55: 186.5*(2*0.35+0.3)+33.1*(2*0.35+0.2)
A57: L | B57: Columns | C57: =1*2*(0.75+0.5)*3.05+2*2*(0.75+0.5)*3.05+1*2*(0.75+0.5)*3.05+6*2*(1.2+0.3)*3.05+1*2*(1.2+0.3)*3.05+15*2*(1.2+0.3)*3.05 -> 231.8 | D57: m2 | E57: =RATES!$D$37 -> 190 | F57: =C57*E57 -> 44042 | G57: 1*2*(0.75+0.5)*3.05+2*2*(0.75+0.5)*3.05+1*2*(0.75+0.5)*3.05+6*2*(1.2+0.3)*3.05+1*2*(1.2+0.3)*3.05+15*2*(1.2+0.3)*3.05
A59: M | B59: Concrete wall (both faces) | C59: =2*22.05*3.05+2*21.825*3.05+2*25.57*3.05 -> 423.6145 | D59: m2 | E59: =RATES!$D$36 -> 185 | F59: =C59*E59 -> 78368.683 | G59: 2*22.05*3.05+2*21.825*3.05+2*25.57*3.05
A61: N | B61: Soffits of stair flights, landings and risers | C61: =(2*3.424*1.8+15.0+22*0.15*1.8)+(2*3.424*1.8+15.0+22*0.15*1.8) -> 66.5328 | D61: m2 | E61: =RATES!$D$42 -> 230 | F61: =C61*E61 -> 15302.544 | G61: (2*3.424*1.8+15.0+22*0.15*1.8)+(2*3.424*1.8+15.0+22*0.15*1.8)
A63: P | B63: Side and soffits of lintel / coping | C63: =(4*(1+0.3)+8*(0.9+0.3)+17*(0.75+0.3)+1*(0.7+0.3)+2*(1.2+0.3)+2*(1+0.3)+2*(1+0.3)+1*(0.9+0.3)+2*(0.9+0.3)+4*(0.75+0.3)+1*(0.45+0.3)+3*(0.6+0.3)+1*(3+0.3)+2*(1.6+0.3)+1*(1.3+0.3)+2*(1.8+0.3)+3*(1.8+0.3)+6*(0.9+0.3)+1*(1.8+0.3)+1*(1.2+0.3)+5*(1.2+0.3)+1*(1.2+0.3)+3*(1.5+0.3)+2*(1.5+0.3)+1*(3+0.3)+1*(1.8+0.3)+10*(0.9+0.3)+4*(0.75+0.3)+1*(0.6+0.3)+1*(1.2+0.3))*(2*0.225+0.15) -> 75.06 | D63: m2 | E63: =RATES!$D$43 -> 180 | F63: =C63*E63 -> 13510.8 | G63: (4*(1+0.3)+8*(0.9+0.3)+17*(0.75+0.3)+1*(0.7+0.3)+2*(1.2+0.3)+2*(1+0.3)+2*(1+0.3)+1*(0.9+0.3)+2*(0.9+0.3)+4*(0.75+0.3)+1*(0.45+0.3)+3*(0.6+0.3)+1*(3+0.3)+2*(1.6+0.3)+1*(1.3+0.3)+2*(1.8+0.3)+3*(1.8+0.3)+6*(0.9+0.3)+1*(1.8+0.3)+1*(1.2+0.3)+5*(1.2+0.3...
B65: E30 REINFORCEMENT - High tensile yield round bar reinforcement (standard) to BS 4449:
A66: Q | B66: 10mm diameter in columns | C66: =3.235 -> 3.235 | D66: t | E66: =RATES!$D$29 -> 20500 | F66: =C66*E66 -> 66317.5 | G66: 3.235
A68: R | B68: 20mm diameter in columns | C68: =5.111 -> 5.111 | D68: t | E68: =RATES!$D$32 -> 19000 | F68: =C68*E68 -> 97109 | G68: 5.111
A70: S | B70: 10mm diameter in beams (links) | C70: =2.032 -> 2.032 | D70: t | E70: =RATES!$D$29 -> 20500 | F70: =C70*E70 -> 41656 | G70: 2.032
A72: T | B72: 16mm diameter in beams | C72: =1.163 -> 1.163 | D72: t | E72: =RATES!$D$31 -> 19500 | F72: =C72*E72 -> 22678.5 | G72: 1.163
A74: U | B74: 20mm diameter in beams | C74: =2.461 -> 2.461 | D74: t | E74: =RATES!$D$32 -> 19000 | F74: =C74*E74 -> 46759 | G74: 2.461
A76: V | B76: 25mm diameter in beams | C76: =6.491 -> 6.491 | D76: t | E76: =RATES!$D$33 -> 19000 | F76: =C76*E76 -> 123329 | G76: 6.491
A78: W | B78: 10mm diameter in shear & lift walls (links) | C78: =1.442+0.636 -> 2.078 | D78: t | E78: =RATES!$D$29 -> 20500 | F78: =C78*E78 -> 42599 | G78: 1.442+0.636
A80: X | B80: 12mm diameter in shear, lift & ramp walls | C80: =2.109+0.952 -> 3.061 | D80: t | E80: =RATES!$D$30 -> 20000 | F80: =C80*E80 -> 61220 | G80: 2.109+0.952
A82: Y | B82: 20mm diameter in shear & lift walls | C82: =6.904+3.320 -> 10.224 | D82: t | E82: =RATES!$D$32 -> 19000 | F82: =C82*E82 -> 194256 | G82: 6.904+3.320
A84: Z | B84: 12mm diameter in stairs | C84: =0.880 -> 0.88 | D84: t | E84: =RATES!$D$30 -> 20000 | F84: =C84*E84 -> 17600 | G84: 0.880
A86: A | B86: 16mm diameter in stairs | C86: =1.434 -> 1.434 | D86: t | E86: =RATES!$D$31 -> 19500 | F86: =C86*E86 -> 27963 | G86: 1.434
A88: B | B88: 12mm diameter for suspended slab | C88: =50.007 -> 50.007 | D88: t | E88: =RATES!$D$30 -> 20000 | F88: =C88*E88 -> 1000140 | G88: 50.007
A90: C | B90: 16mm diameter for suspended slab | C90: =0.151 -> 0.151 | D90: t | E90: =RATES!$D$31 -> 19500 | F90: =C90*E90 -> 2944.5 | G90: 0.151
B92: =B33 -> ELEMENT NO. 1: IN SITU CONCRETE/LARGE PRECAST CONCRETE | F92: =SUM(F35:F91) -> 3230623.2
B93: Carried to Bill Summary
B96: ELEMENT NO. 2: MASONRY
B98: F10 BRICK/BLOCK WALL - Solid sandcrete blockwork in cement and sand (1:4) mortar as described in:
A99: A | B99: 150mm thick wall | C99: =397.2*3.05+(4*1*(3.05-2.2)+8*0.9*(3.05-2.2)+17*0.75*(3.05-2.2)+1*0.7*(3.05-2.2)+2*1.2*(3.05-2.2)+2*1*(3.05-2.2)+2*1*(3.05-2.2)+1*0.9*(3.05-2.2)+2*0.9*(3.05-2.2)+4*0.75*(3.05-2.2)+1*0.45*(3.05-2.2)+3*0.6*(3.05-2.2)+1*3*(3.05-2.2)+2*1.6*(3.05-2.2)+1*1.3*(3.05-2.2)+2*1.8*(3.05-2.2)+3*1.8*(3.05-1.3)+6*0.9*(3.05-1.3)+1*1.8*(3.05-1.6)+1*1.2*(3.05-1.9)+5*1.2*(3.05-1.15)+1*1.2*(3.05-1.2)+3*1.5*(3.05-1.3)+2*1.5*(3.05-1.15)+1*3*(3.05-1.6)+1*1.8*(3.05-1.9)+10*0.9*(3.05-0.6)+4*0.75*(3.05-0.6)+1*0.6*(3.05-0.6)+1*1.2*(3.05-0.6))*0.940 -> 1336.386 | D99: m2 | E99: =RATES!$D$46 -> 215 | F99: =C99*E99 -> 287322.99 | G99: 397.2*3.05+(4*1*(3.05-2.2)+8*0.9*(3.05-2.2)+17*0.75*(3.05-2.2)+1*0.7*(3.05-2.2)+2*1.2*(3.05-2.2)+2*1*(3.05-2.2)+2*1*(3.05-2.2)+1*0.9*(3.05-2.2)+2*0.9*(3.05-2.2)+4*0.75*(3.05-2.2)+1*0.45*(3.05-2.2)+3*0.6*(3.05-2.2)+1*3*(3.05-2.2)+2*1.6*(3.05-2.2)+1...
A101: B | B101: 200mm thick wall | C101: =25.6*3.05+(4*1*(3.05-2.2)+8*0.9*(3.05-2.2)+17*0.75*(3.05-2.2)+1*0.7*(3.05-2.2)+2*1.2*(3.05-2.2)+2*1*(3.05-2.2)+2*1*(3.05-2.2)+1*0.9*(3.05-2.2)+2*0.9*(3.05-2.2)+4*0.75*(3.05-2.2)+1*0.45*(3.05-2.2)+3*0.6*(3.05-2.2)+1*3*(3.05-2.2)+2*1.6*(3.05-2.2)+1*1.3*(3.05-2.2)+2*1.8*(3.05-2.2)+3*1.8*(3.05-1.3)+6*0.9*(3.05-1.3)+1*1.8*(3.05-1.6)+1*1.2*(3.05-1.9)+5*1.2*(3.05-1.15)+1*1.2*(3.05-1.2)+3*1.5*(3.05-1.3)+2*1.5*(3.05-1.15)+1*3*(3.05-1.6)+1*1.8*(3.05-1.9)+10*0.9*(3.05-0.6)+4*0.75*(3.05-0.6)+1*0.6*(3.05-0.6)+1*1.2*(3.05-0.6))*0.060 -> 86.054 | D101: m2 | E101: =RATES!$D$47 -> 265 | F101: =C101*E101 -> 22804.31 | G101: 25.6*3.05+(4*1*(3.05-2.2)+8*0.9*(3.05-2.2)+17*0.75*(3.05-2.2)+1*0.7*(3.05-2.2)+2*1.2*(3.05-2.2)+2*1*(3.05-2.2)+2*1*(3.05-2.2)+1*0.9*(3.05-2.2)+2*0.9*(3.05-2.2)+4*0.75*(3.05-2.2)+1*0.45*(3.05-2.2)+3*0.6*(3.05-2.2)+1*3*(3.05-2.2)+2*1.6*(3.05-2.2)+1*...
B103: =B96 -> ELEMENT NO. 2: MASONRY | F103: =SUM(F98:F102) -> 310127.3
B104: Carried to Bill Summary
B107: ELEMENT NO. 3: WATERPROOFING
B109: WATERPROOFING
A110: A | B110: Liquid/applied waterproofing to roofs, terraces and wet external areas | C110: =337.4 -> 337.4 | D110: m2 | E110: =RATES!$D$68 -> 165 | F110: =C110*E110 -> 55671 | G110: 337.4
A112: B | B112: Protective cement-sand screed over waterproofing | C112: =337.4 -> 337.4 | D112: m2 | E112: =RATES!$D$69 -> 72 | F112: =C112*E112 -> 24292.8 | G112: 337.4
B114: =B107 -> ELEMENT NO. 3: WATERPROOFING | F114: =SUM(F109:F113) -> 79963.8
B115: Carried to Bill Summary
B118: ELEMENT NO. 4: WINDOWS/DOORS
B120: L20 DOORS - Supply and fix the following door assemblies complete with frames, ironmongery sets to steel doors and all accessories:
A121: A | B121: 1000mm x 2200mm 1-hour fire-rated galvanised steel single-leaf security door assembly (D2) | C121: =4 -> 4 | D121: nr | E121: =RATES!$D$75 -> 7800 | F121: =C121*E121 -> 31200 | G121: 4
A123: B | B123: 900mm x 2200mm single leaf timber panel door (D3) | C123: =8 -> 8 | D123: nr | E123: =RATES!$D$76 -> 3400 | F123: =C123*E123 -> 27200 | G123: 8
A125: C | B125: 750mm x 2200mm single leaf timber flush door (D6) | C125: =17 -> 17 | D125: nr | E125: =RATES!$D$79 -> 1900 | F125: =C125*E125 -> 32300 | G125: 17
A127: D | B127: 700mm x 2200mm single-leaf 2-hour fire-rated galvanised steel door (D7) | C127: =1 -> 1 | D127: nr | E127: =RATES!$D$80 -> 6800 | F127: =C127*E127 -> 6800 | G127: 1
A129: E | B129: 1200mm x 2200mm 1-hour fire-rated leaf-and-a-half galvanised steel security door assembly (D8) | C129: =2 -> 2 | D129: nr | E129: =RATES!$D$81 -> 9800 | F129: =C129*E129 -> 19600 | G129: 2
A131: F | B131: 1000mm x 2200mm 1-hour fire-rated galvanised steel single-leaf security door assembly - emergency stairs (ED1) | C131: =2 -> 2 | D131: nr | E131: =RATES!$D$82 -> 7200 | F131: =C131*E131 -> 14400 | G131: 2
A133: G | B133: 1000mm x 2200mm 1-hour fire-rated galvanised steel single-leaf security door with translucent glass panel (ED2) | C133: =2 -> 2 | D133: nr | E133: =RATES!$D$83 -> 8100 | F133: =C133*E133 -> 16200 | G133: 2
A135: H | B135: 900mm x 2200mm 1-hour fire-rated galvanised steel single-leaf security door assembly (D9) | C135: =1 -> 1 | D135: nr | E135: =RATES!$D$84 -> 6900 | F135: =C135*E135 -> 6900 | G135: 1
A137: J | B137: 900mm x 2200mm screw-fixed galvanised steel service access panel (M1) | C137: =2 -> 2 | D137: nr | E137: =RATES!$D$87 -> 2900 | F137: =C137*E137 -> 5800 | G137: 2
A139: K | B139: 750mm x 2200mm screw-fixed galvanised steel service access panel (M2) | C139: =4 -> 4 | D139: nr | E139: =RATES!$D$88 -> 2600 | F139: =C139*E139 -> 10400 | G139: 4
A141: L | B141: 450mm x 2200mm screw-fixed galvanised steel service access panel (M3) | C141: =1 -> 1 | D141: nr | E141: =RATES!$D$89 -> 1900 | F141: =C141*E141 -> 1900 | G141: 1
A143: M | B143: 600mm x 2200mm screw-fixed galvanised steel service access panel (M5) | C143: =3 -> 3 | D143: nr | E143: =RATES!$D$90 -> 2200 | F143: =C143*E143 -> 6600 | G143: 3
A145: N | B145: 3000mm x 2200mm 3-panel galvanised steel framed tempered glass sliding door (SD1) | C145: =1 -> 1 | D145: nr | E145: =RATES!$D$94 -> 14500 | F145: =C145*E145 -> 14500 | G145: 1
A147: P | B147: 1600mm x 2200mm 2-panel galvanised steel framed tempered glass sliding door (SD2) | C147: =2 -> 2 | D147: nr | E147: =RATES!$D$95 -> 8800 | F147: =C147*E147 -> 17600 | G147: 2
A149: Q | B149: 1300mm x 2200mm 2-panel galvanised steel framed tempered glass sliding door (SD3) | C149: =1 -> 1 | D149: nr | E149: =RATES!$D$96 -> 7600 | F149: =C149*E149 -> 7600 | G149: 1
A151: R | B151: 1800mm x 2200mm 2-panel galvanised steel framed tempered glass sliding door (SD4) | C151: =2 -> 2 | D151: nr | E151: =RATES!$D$97 -> 9300 | F151: =C151*E151 -> 18600 | G151: 2
A153: S | B153: 50mm x 150mm frames (to timber doors) | C153: =8*(2*2.2+0.9)+17*(2*2.2+0.75) -> 129.95 | D153: m | E153: =RATES!$D$100 -> 125 | F153: =C153*E153 -> 16243.75 | G153: 8*(2*2.2+0.9)+17*(2*2.2+0.75)
A155: T | B155: 50mm x 12mm door stop | C155: =8*(2*2.2+0.9)+17*(2*2.2+0.75) -> 129.95 | D155: m | E155: =RATES!$D$101 -> 28 | F155: =C155*E155 -> 3638.6 | G155: 8*(2*2.2+0.9)+17*(2*2.2+0.75)
B157: Ironmongery - Supply and fix the following approved ironmongery to hardwood with accompanying patented screws:
A158: U | B158: Pair 100mm brass butt hinges | C158: =38 -> 38 | D158: pr | E158: =RATES!$D$102 -> 125 | F158: =C158*E158 -> 4750 | G158: 38
A160: V | B160: Ordinary locks | C160: =8 -> 8 | D160: nr | E160: =RATES!$D$103 -> 480 | F160: =C160*E160 -> 3840 | G160: 8
A162: W | B162: Approved high quality mortice indicator lock | C162: =17 -> 17 | D162: nr | E162: =RATES!$D$104 -> 560 | F162: =C162*E162 -> 9520 | G162: 17
B164: ALUMINIUM GLAZED WINDOWS - Supply and install Italian extruded aluminium glazed windows, ALCOA R50 series, powder coated aluminium profile, glazed with 6mm tinted reflective glass secured onto galvanized steel sub-frames, complete with all accessories as per Architect's detail:
A165: X | B165: 2 bay alu. framed glass sliding window 1800mm x 1300mm (W2) | C165: =3 -> 3 | D165: nr | E165: =RATES!$D$109 -> 3861 | F165: =C165*E165 -> 11583 | G165: 3
A167: Y | B167: 1 bay alu. framed glass awning window 900mm x 1300mm (W4) | C167: =6 -> 6 | D167: nr | E167: =RATES!$D$111 -> 1930.5 | F167: =C167*E167 -> 11583 | G167: 6
A169: Z | B169: 2 bay alu. framed glass sliding window 1800mm x 1600mm (W7) | C169: =1 -> 1 | D169: nr | E169: =RATES!$D$114 -> 4752 | F169: =C169*E169 -> 4752 | G169: 1
A171: A | B171: 1 x 3 bay alu. framed glass awning window 1200mm x 1900mm (W8) | C171: =1 -> 1 | D171: nr | E171: =RATES!$D$115 -> 3762 | F171: =C171*E171 -> 3762 | G171: 1
A173: B | B173: 2 bay alu. framed glass sliding window 1200mm x 1150mm (W9) | C173: =5 -> 5 | D173: nr | E173: =RATES!$D$116 -> 2277 | F173: =C173*E173 -> 11385 | G173: 5
A175: C | B175: 2 bay alu. framed glass sliding window 1200mm x 1200mm (W10) | C175: =1 -> 1 | D175: nr | E175: =RATES!$D$117 -> 2376 | F175: =C175*E175 -> 2376 | G175: 1
A177: D | B177: 2 bay alu. framed glass sliding window 1500mm x 1300mm (W11) | C177: =3 -> 3 | D177: nr | E177: =RATES!$D$118 -> 3217.5 | F177: =C177*E177 -> 9652.5 | G177: 3
A179: E | B179: 2 bay alu. framed glass sliding window 1500mm x 1150mm (W12) | C179: =2 -> 2 | D179: nr | E179: =RATES!$D$119 -> 2846.25 | F179: =C179*E179 -> 5692.5 | G179: 2
A181: F | B181: 3 bay alu. framed glass sliding window 3000mm x 1600mm (W15) | C181: =1 -> 1 | D181: nr | E181: =RATES!$D$122 -> 7920 | F181: =C181*E181 -> 7920 | G181: 1
A183: G | B183: 2 x 3 alu. framed glass awning window 1800mm x 1900mm (W17) | C183: =1 -> 1 | D183: nr | E183: =RATES!$D$124 -> 5643 | F183: =C183*E183 -> 5643 | G183: 1
A185: H | B185: 2 bay alu. framed glass sliding window 900mm x 600mm (HW1) | C185: =10 -> 10 | D185: nr | E185: =RATES!$D$128 -> 891 | F185: =C185*E185 -> 8910 | G185: 10
A187: J | B187: 2 bay alu. framed glass sliding window 750mm x 600mm (HW2) | C187: =4 -> 4 | D187: nr | E187: =RATES!$D$129 -> 742.5 | F187: =C187*E187 -> 2970 | G187: 4
...

Sheet 10TH FLR   
A1: ='PRELIMS & GEN. ITEMS'!A2 -> PROJECT: BLOCK N REDEVELOPMENT
A2: ='PRELIMS & GEN. ITEMS'!A3 -> LOCATION: KANESHIE
A3: ='PRELIMS & GEN. ITEMS'!A4 -> CLIENT: STATE HOUSING LIMITED
A4: ='PRELIMS & GEN. ITEMS'!A5 -> DATE:9/30/2026
A5: ITEM | B5: DESCRIPTION | C5: QTY | D5: UNIT | E5: RATE | F5: AMOUNT - GHC | G5: Measurement basis / calculation
B7: MAIN BUILDING
B9: TENTH FLOOR
B11: BILL SUMMARY
A13: A | B13: ELEMENT NO. 1: IN SITU CONCRETE/LARGE PRECAST CONCRETE | F13: =F90 -> 2565762.6
A15: B | B15: ELEMENT NO. 2: MASONRY | F15: =F101 -> 293194.08
A17: C | B17: ELEMENT NO. 4: WINDOWS/DOORS | F17: =F186 -> 459099.8
A19: D | B19: ELEMENT NO. 5: FLOOR FINISHES | F19: =F207 -> 264471.94
A21: E | B21: ELEMENT NO. 6: WALL FINISHES | F21: =F224 -> 235040.25
A23: F | B23: ELEMENT NO. 7: PAINTING AND DECORATING | F23: =F245 -> 140426.27
B25: =B9 -> TENTH FLOOR | E25: GHC | F25: =SUM(F13:F24) -> 3957995
B26: To Bill General Summary
B29: BILL NR. 13 - TENTH FLOOR
B31: ELEMENT NO. 1: IN SITU CONCRETE/LARGE PRECAST CONCRETE
B33: Vibrated in-situ concrete C40 as described in:
A34: A | B34: Suspended slab 250mm thick | C34: =868.4*0.25 -> 217.1 | D34: m3 | E34: =RATES!$D$22 -> 2650 | F34: =C34*E34 -> 575315 | G34: 868.4*0.25
A36: B | B36: Beams (downstands below slab) | C36: =122.2*0.3*0.35+14.2*0.2*0.35 -> 13.825 | D36: m3 | E36: =RATES!$D$23 -> 2700 | F36: =C36*E36 -> 37327.5 | G36: 122.2*0.3*0.35+14.2*0.2*0.35
A38: C | B38: Columns | C38: =1*0.75*0.5*3.05+2*0.75*0.5*3.05+1*0.75*0.5*3.05+6*1.2*0.3*3.05+1*1.2*0.3*3.05+15*1.2*0.3*3.05 -> 28.731 | D38: m3 | E38: =RATES!$D$21 -> 2800 | F38: =C38*E38 -> 80446.8 | G38: 1*0.75*0.5*3.05+2*0.75*0.5*3.05+1*0.75*0.5*3.05+6*1.2*0.3*3.05+1*1.2*0.3*3.05+15*1.2*0.3*3.05
A40: D | B40: Concrete wall - shear walls to main & emergency stair cores, 250mm thick | C40: =22.05*3.05*0.25+25.57*3.05*0.25 -> 36.31025 | D40: m3 | E40: =RATES!$D$20 -> 2750 | F40: =C40*E40 -> 99853.187 | G40: 22.05*3.05*0.25+25.57*3.05*0.25
A42: E | B42: Concrete wall - lift walls, 250mm thick | C42: =21.825*3.05*0.25 -> 16.641562 | D42: m3 | E42: =RATES!$D$20 -> 2750 | F42: =C42*E42 -> 45764.297 | G42: 21.825*3.05*0.25
A44: F | B44: Stairs | C44: =(2.966*3.3/3.3+2.625)+(2.966*3.3/3.3+2.625) -> 11.182 | D44: m3 | E44: =RATES!$D$24 -> 2850 | F44: =C44*E44 -> 31868.7 | G44: (2.966*3.3/3.3+2.625)+(2.966*3.3/3.3+2.625)
A46: G | B46: Lintels 150 x 225mm over door and window openings | C46: =(6*(1+0.3)+11*(0.9+0.3)+16*(0.75+0.3)+1*(0.7+0.3)+2*(1.2+0.3)+2*(1+0.3)+2*(1+0.3)+1*(0.9+0.3)+1*(1.5+0.3)+2*(0.9+0.3)+4*(0.75+0.3)+1*(0.45+0.3)+3*(0.6+0.3)+1*(3+0.3)+3*(1.6+0.3)+2*(1.3+0.3)+3*(1.8+0.3)+1*(1.2+0.3)+4*(1.8+0.3)+8*(0.9+0.3)+1*(1.8+0.3)+2*(1.2+0.3)+6*(1.2+0.3)+1*(1.2+0.3)+5*(1.5+0.3)+3*(1.5+0.3)+1*(3+0.3)+2*(1.8+0.3)+1*(0.75+0.3)+10*(0.9+0.3)+4*(0.75+0.3)+1*(0.6+0.3)+1*(1.2+0.3))*0.15*0.225 -> 5.238 | D46: m3 | E46: =RATES!$D$25 -> 2600 | F46: =C46*E46 -> 13618.8 | G46: (6*(1+0.3)+11*(0.9+0.3)+16*(0.75+0.3)+1*(0.7+0.3)+2*(1.2+0.3)+2*(1+0.3)+2*(1+0.3)+1*(0.9+0.3)+1*(1.5+0.3)+2*(0.9+0.3)+4*(0.75+0.3)+1*(0.45+0.3)+3*(0.6+0.3)+1*(3+0.3)+3*(1.6+0.3)+2*(1.3+0.3)+3*(1.8+0.3)+1*(1.2+0.3)+4*(1.8+0.3)+8*(0.9+0.3)+1*(1.8+0....
B48: E20 FORMWORK - Formwork as described to:
A49: H | B49: Soffits of suspended slab | C49: =868.4 -> 868.4 | D49: m2 | E49: =RATES!$D$38 -> 170 | F49: =C49*E49 -> 147628 | G49: 868.4
A51: J | B51: Edges of suspended slab 250mm high | C51: =252.6 -> 252.6 | D51: m | E51: =RATES!$D$40 -> 65 | F51: =C51*E51 -> 16419 | G51: 252.6
A53: K | B53: Sides and soffits of beams | C53: =122.2*(2*0.35+0.3)+14.2*(2*0.35+0.2) -> 134.98 | D53: m2 | E53: =RATES!$D$39 -> 200 | F53: =C53*E53 -> 26996 | G53: 122.2*(2*0.35+0.3)+14.2*(2*0.35+0.2)
A55: L | B55: Columns | C55: =1*2*(0.75+0.5)*3.05+2*2*(0.75+0.5)*3.05+1*2*(0.75+0.5)*3.05+6*2*(1.2+0.3)*3.05+1*2*(1.2+0.3)*3.05+15*2*(1.2+0.3)*3.05 -> 231.8 | D55: m2 | E55: =RATES!$D$37 -> 190 | F55: =C55*E55 -> 44042 | G55: 1*2*(0.75+0.5)*3.05+2*2*(0.75+0.5)*3.05+1*2*(0.75+0.5)*3.05+6*2*(1.2+0.3)*3.05+1*2*(1.2+0.3)*3.05+15*2*(1.2+0.3)*3.05
A57: M | B57: Concrete wall (both faces) | C57: =2*22.05*3.05+2*21.825*3.05+2*25.57*3.05 -> 423.6145 | D57: m2 | E57: =RATES!$D$36 -> 185 | F57: =C57*E57 -> 78368.683 | G57: 2*22.05*3.05+2*21.825*3.05+2*25.57*3.05
A59: N | B59: Soffits of stair flights, landings and risers | C59: =(2*3.424*1.8+15.0+22*0.15*1.8)+(2*3.424*1.8+15.0+22*0.15*1.8) -> 66.5328 | D59: m2 | E59: =RATES!$D$42 -> 230 | F59: =C59*E59 -> 15302.544 | G59: (2*3.424*1.8+15.0+22*0.15*1.8)+(2*3.424*1.8+15.0+22*0.15*1.8)
A61: P | B61: Side and soffits of lintel / coping | C61: =(6*(1+0.3)+11*(0.9+0.3)+16*(0.75+0.3)+1*(0.7+0.3)+2*(1.2+0.3)+2*(1+0.3)+2*(1+0.3)+1*(0.9+0.3)+1*(1.5+0.3)+2*(0.9+0.3)+4*(0.75+0.3)+1*(0.45+0.3)+3*(0.6+0.3)+1*(3+0.3)+3*(1.6+0.3)+2*(1.3+0.3)+3*(1.8+0.3)+1*(1.2+0.3)+4*(1.8+0.3)+8*(0.9+0.3)+1*(1.8+0.3)+2*(1.2+0.3)+6*(1.2+0.3)+1*(1.2+0.3)+5*(1.5+0.3)+3*(1.5+0.3)+1*(3+0.3)+2*(1.8+0.3)+1*(0.75+0.3)+10*(0.9+0.3)+4*(0.75+0.3)+1*(0.6+0.3)+1*(1.2+0.3))*(2*0.225+0.15) -> 93.12 | D61: m2 | E61: =RATES!$D$43 -> 180 | F61: =C61*E61 -> 16761.6 | G61: (6*(1+0.3)+11*(0.9+0.3)+16*(0.75+0.3)+1*(0.7+0.3)+2*(1.2+0.3)+2*(1+0.3)+2*(1+0.3)+1*(0.9+0.3)+1*(1.5+0.3)+2*(0.9+0.3)+4*(0.75+0.3)+1*(0.45+0.3)+3*(0.6+0.3)+1*(3+0.3)+3*(1.6+0.3)+2*(1.3+0.3)+3*(1.8+0.3)+1*(1.2+0.3)+4*(1.8+0.3)+8*(0.9+0.3)+1*(1.8+0....
B63: E30 REINFORCEMENT - High tensile yield round bar reinforcement (standard) to BS 4449:
A64: Q | B64: 10mm diameter in columns | C64: =2.468 -> 2.468 | D64: t | E64: =RATES!$D$29 -> 20500 | F64: =C64*E64 -> 50594 | G64: 2.468
A66: R | B66: 20mm diameter in columns | C66: =4.084 -> 4.084 | D66: t | E66: =RATES!$D$32 -> 19000 | F66: =C66*E66 -> 77596 | G66: 4.084
A68: S | B68: 10mm diameter in beams (links) | C68: =1.226 -> 1.226 | D68: t | E68: =RATES!$D$29 -> 20500 | F68: =C68*E68 -> 25133 | G68: 1.226
A70: T | B70: 16mm diameter in beams | C70: =1.219 -> 1.219 | D70: t | E70: =RATES!$D$31 -> 19500 | F70: =C70*E70 -> 23770.5 | G70: 1.219
A72: U | B72: 20mm diameter in beams | C72: =0.810 -> 0.81 | D72: t | E72: =RATES!$D$32 -> 19000 | F72: =C72*E72 -> 15390 | G72: 0.810
A74: V | B74: 25mm diameter in beams | C74: =4.057 -> 4.057 | D74: t | E74: =RATES!$D$33 -> 19000 | F74: =C74*E74 -> 77083 | G74: 4.057
A76: W | B76: 10mm diameter in shear & lift walls (links) | C76: =1.442+0.636 -> 2.078 | D76: t | E76: =RATES!$D$29 -> 20500 | F76: =C76*E76 -> 42599 | G76: 1.442+0.636
A78: X | B78: 12mm diameter in shear, lift & ramp walls | C78: =1.917+0.866 -> 2.783 | D78: t | E78: =RATES!$D$30 -> 20000 | F78: =C78*E78 -> 55660 | G78: 1.917+0.866
A80: Y | B80: 20mm diameter in shear & lift walls | C80: =6.904+3.320 -> 10.224 | D80: t | E80: =RATES!$D$32 -> 19000 | F80: =C80*E80 -> 194256 | G80: 6.904+3.320
A82: Z | B82: 12mm diameter in stairs | C82: =0.880 -> 0.88 | D82: t | E82: =RATES!$D$30 -> 20000 | F82: =C82*E82 -> 17600 | G82: 0.880
A84: A | B84: 16mm diameter in stairs | C84: =1.434 -> 1.434 | D84: t | E84: =RATES!$D$31 -> 19500 | F84: =C84*E84 -> 27963 | G84: 1.434
A86: B | B86: 12mm diameter for suspended slab | C86: =36.276 -> 36.276 | D86: t | E86: =RATES!$D$30 -> 20000 | F86: =C86*E86 -> 725520 | G86: 36.276
A88: C | B88: 16mm diameter for suspended slab | C88: =0.148 -> 0.148 | D88: t | E88: =RATES!$D$31 -> 19500 | F88: =C88*E88 -> 2886 | G88: 0.148
B90: =B31 -> ELEMENT NO. 1: IN SITU CONCRETE/LARGE PRECAST CONCRETE | F90: =SUM(F33:F89) -> 2565762.6
B91: Carried to Bill Summary
B94: ELEMENT NO. 2: MASONRY
B96: F10 BRICK/BLOCK WALL - Solid sandcrete blockwork in cement and sand (1:4) mortar as described in:
A97: A | B97: 150mm thick wall | C97: =354.0*3.05+(6*1*(3.05-2.2)+11*0.9*(3.05-2.2)+16*0.75*(3.05-2.2)+1*0.7*(3.05-2.2)+2*1.2*(3.05-2.2)+2*1*(3.05-2.2)+2*1*(3.05-2.2)+1*0.9*(3.05-2.2)+1*1.5*(3.05-2.2)+2*0.9*(3.05-2.2)+4*0.75*(3.05-2.2)+1*0.45*(3.05-2.2)+3*0.6*(3.05-2.2)+1*3*(3.05-2.2)+3*1.6*(3.05-2.2)+2*1.3*(3.05-2.2)+3*1.8*(3.05-2.2)+1*1.2*(3.05-2.2)+4*1.8*(3.05-1.3)+8*0.9*(3.05-1.3)+1*1.8*(3.05-1.6)+2*1.2*(3.05-1.9)+6*1.2*(3.05-1.15)+1*1.2*(3.05-1.2)+5*1.5*(3.05-1.3)+3*1.5*(3.05-1.15)+1*3*(3.05-1.6)+2*1.8*(3.05-1.9)+1*0.75*(3.05-1.3)+10*0.9*(3.05-0.6)+4*0.75*(3.05-0.6)+1*0.6*(3.05-0.6)+1*1.2*(3.05-0.6))*0.919 -> 1230.4068 | D97: m2 | E97: =RATES!$D$46 -> 215 | F97: =C97*E97 -> 264537.46 | G97: 354.0*3.05+(6*1*(3.05-2.2)+11*0.9*(3.05-2.2)+16*0.75*(3.05-2.2)+1*0.7*(3.05-2.2)+2*1.2*(3.05-2.2)+2*1*(3.05-2.2)+2*1*(3.05-2.2)+1*0.9*(3.05-2.2)+1*1.5*(3.05-2.2)+2*0.9*(3.05-2.2)+4*0.75*(3.05-2.2)+1*0.45*(3.05-2.2)+3*0.6*(3.05-2.2)+1*3*(3.05-2.2)+...
A99: B | B99: 200mm thick wall | C99: =31.1*3.05+(6*1*(3.05-2.2)+11*0.9*(3.05-2.2)+16*0.75*(3.05-2.2)+1*0.7*(3.05-2.2)+2*1.2*(3.05-2.2)+2*1*(3.05-2.2)+2*1*(3.05-2.2)+1*0.9*(3.05-2.2)+1*1.5*(3.05-2.2)+2*0.9*(3.05-2.2)+4*0.75*(3.05-2.2)+1*0.45*(3.05-2.2)+3*0.6*(3.05-2.2)+1*3*(3.05-2.2)+3*1.6*(3.05-2.2)+2*1.3*(3.05-2.2)+3*1.8*(3.05-2.2)+1*1.2*(3.05-2.2)+4*1.8*(3.05-1.3)+8*0.9*(3.05-1.3)+1*1.8*(3.05-1.6)+2*1.2*(3.05-1.9)+6*1.2*(3.05-1.15)+1*1.2*(3.05-1.2)+5*1.5*(3.05-1.3)+3*1.5*(3.05-1.15)+1*3*(3.05-1.6)+2*1.8*(3.05-1.9)+1*0.75*(3.05-1.3)+10*0.9*(3.05-0.6)+4*0.75*(3.05-0.6)+1*0.6*(3.05-0.6)+1*1.2*(3.05-0.6))*0.081 -> 108.13819 | D99: m2 | E99: =RATES!$D$47 -> 265 | F99: =C99*E99 -> 28656.62 | G99: 31.1*3.05+(6*1*(3.05-2.2)+11*0.9*(3.05-2.2)+16*0.75*(3.05-2.2)+1*0.7*(3.05-2.2)+2*1.2*(3.05-2.2)+2*1*(3.05-2.2)+2*1*(3.05-2.2)+1*0.9*(3.05-2.2)+1*1.5*(3.05-2.2)+2*0.9*(3.05-2.2)+4*0.75*(3.05-2.2)+1*0.45*(3.05-2.2)+3*0.6*(3.05-2.2)+1*3*(3.05-2.2)+3...
B101: =B94 -> ELEMENT NO. 2: MASONRY | F101: =SUM(F96:F100) -> 293194.08
B102: Carried to Bill Summary
B105: ELEMENT NO. 4: WINDOWS/DOORS
B107: L20 DOORS - Supply and fix the following door assemblies complete with frames, ironmongery sets to steel doors and all accessories:
A108: A | B108: 1000mm x 2200mm 1-hour fire-rated galvanised steel single-leaf security door assembly (D2) | C108: =6 -> 6 | D108: nr | E108: =RATES!$D$75 -> 7800 | F108: =C108*E108 -> 46800 | G108: 6
A110: B | B110: 900mm x 2200mm single leaf timber panel door (D3) | C110: =11 -> 11 | D110: nr | E110: =RATES!$D$76 -> 3400 | F110: =C110*E110 -> 37400 | G110: 11
A112: C | B112: 750mm x 2200mm single leaf timber flush door (D6) | C112: =16 -> 16 | D112: nr | E112: =RATES!$D$79 -> 1900 | F112: =C112*E112 -> 30400 | G112: 16
A114: D | B114: 700mm x 2200mm single-leaf 2-hour fire-rated galvanised steel door (D7) | C114: =1 -> 1 | D114: nr | E114: =RATES!$D$80 -> 6800 | F114: =C114*E114 -> 6800 | G114: 1
A116: E | B116: 1200mm x 2200mm 1-hour fire-rated leaf-and-a-half galvanised steel security door assembly (D8) | C116: =2 -> 2 | D116: nr | E116: =RATES!$D$81 -> 9800 | F116: =C116*E116 -> 19600 | G116: 2
A118: F | B118: 1000mm x 2200mm 1-hour fire-rated galvanised steel single-leaf security door assembly - emergency stairs (ED1) | C118: =2 -> 2 | D118: nr | E118: =RATES!$D$82 -> 7200 | F118: =C118*E118 -> 14400 | G118: 2
A120: G | B120: 1000mm x 2200mm 1-hour fire-rated galvanised steel single-leaf security door with translucent glass panel (ED2) | C120: =2 -> 2 | D120: nr | E120: =RATES!$D$83 -> 8100 | F120: =C120*E120 -> 16200 | G120: 2
A122: H | B122: 900mm x 2200mm 1-hour fire-rated galvanised steel single-leaf security door assembly (D9) | C122: =1 -> 1 | D122: nr | E122: =RATES!$D$84 -> 6900 | F122: =C122*E122 -> 6900 | G122: 1
A124: J | B124: 1500mm x 2200mm timber bi-fold door (FD1) | C124: =1 -> 1 | D124: nr | E124: =RATES!$D$86 -> 4600 | F124: =C124*E124 -> 4600 | G124: 1
A126: K | B126: 900mm x 2200mm screw-fixed galvanised steel service access panel (M1) | C126: =2 -> 2 | D126: nr | E126: =RATES!$D$87 -> 2900 | F126: =C126*E126 -> 5800 | G126: 2
A128: L | B128: 750mm x 2200mm screw-fixed galvanised steel service access panel (M2) | C128: =4 -> 4 | D128: nr | E128: =RATES!$D$88 -> 2600 | F128: =C128*E128 -> 10400 | G128: 4
A130: M | B130: 450mm x 2200mm screw-fixed galvanised steel service access panel (M3) | C130: =1 -> 1 | D130: nr | E130: =RATES!$D$89 -> 1900 | F130: =C130*E130 -> 1900 | G130: 1
A132: N | B132: 600mm x 2200mm screw-fixed galvanised steel service access panel (M5) | C132: =3 -> 3 | D132: nr | E132: =RATES!$D$90 -> 2200 | F132: =C132*E132 -> 6600 | G132: 3
A134: P | B134: 3000mm x 2200mm 3-panel galvanised steel framed tempered glass sliding door (SD1) | C134: =1 -> 1 | D134: nr | E134: =RATES!$D$94 -> 14500 | F134: =C134*E134 -> 14500 | G134: 1
A136: Q | B136: 1600mm x 2200mm 2-panel galvanised steel framed tempered glass sliding door (SD2) | C136: =3 -> 3 | D136: nr | E136: =RATES!$D$95 -> 8800 | F136: =C136*E136 -> 26400 | G136: 3
A138: R | B138: 1300mm x 2200mm 2-panel galvanised steel framed tempered glass sliding door (SD3) | C138: =2 -> 2 | D138: nr | E138: =RATES!$D$96 -> 7600 | F138: =C138*E138 -> 15200 | G138: 2
A140: S | B140: 1800mm x 2200mm 2-panel galvanised steel framed tempered glass sliding door (SD4) | C140: =3 -> 3 | D140: nr | E140: =RATES!$D$97 -> 9300 | F140: =C140*E140 -> 27900 | G140: 3
A142: T | B142: 1200mm x 2200mm 2-panel galvanised steel framed tempered glass sliding door (SD5) | C142: =1 -> 1 | D142: nr | E142: =RATES!$D$98 -> 7200 | F142: =C142*E142 -> 7200 | G142: 1
