Workbook

Sheet Cover Page .
A9: S | B9: CASHFLOW FORECAST FOR PROPOSED HEAD OFFICE FOR PRIORITY INSURANCE
F21: OCTOBER, 2026
C23: www.spektra.global // +233 30 321 7241 // | F23: SPEKTRA GLOBAL LTD
B182: GROUND TOTAL TO SUMMARY

Sheet CASHFLOW SUMMARY
A1: PROPOSED CASH FLOW AGGREGATED
A2: PAYMENT NO. | B2: MONTH, YEAR | C2: AMOUNT (US$)
A3: PMT 1 (ADV.) | B3: =' CASHFLOW'!E1 | C3: =SUM(' CASHFLOW'!E97:E97)
A4: PMT 2 | B4: =' CASHFLOW'!I1 | C4: =SUM(' CASHFLOW'!F97:I97)
A5: PMT 3 | B5: =' CASHFLOW'!M1 | C5: =SUM(' CASHFLOW'!J97:M97)
A6: PMT 4 | B6: =' CASHFLOW'!Q1 | C6: =SUM(' CASHFLOW'!N97:Q97)
A7: PMT 5 | B7: =' CASHFLOW'!U1 | C7: =SUM(' CASHFLOW'!R97:U97)
A8: PMT 6 | B8: =' CASHFLOW'!Y1 | C8: =SUM(' CASHFLOW'!V97:Y97)
A9: PMT 7 | B9: =' CASHFLOW'!AC1 | C9: =SUM(' CASHFLOW'!Z97:AC97)
A10: PMT 8 | B10: =' CASHFLOW'!AD1 | C10: =SUM(' CASHFLOW'!AD97:AD97)
A11: PMT 9 | B11: =' CASHFLOW'!AE1 | C11: =SUM(' CASHFLOW'!AE97:AE97)
A12: TOTAL PAYMENT | C12: =SUM(C3:C11)
A15: PROPOSED CASH FLOW MONTHLY
A16: PAYMENT NO. | B16: MONTH, YEAR | C16: AMOUNT (US$)
A17: PMT 1 (ADV) | B17: =' CASHFLOW'!E1 | C17: =' CASHFLOW'!E97 | D17: =' CASHFLOW'!E98
A18: PMT 2 | B18: =' CASHFLOW'!F1 | C18: =' CASHFLOW'!F97 | D18: =' CASHFLOW'!F98
A19: PMT 3 | B19: =' CASHFLOW'!G1 | C19: =' CASHFLOW'!G97 | D19: =' CASHFLOW'!G98
A20: PMT 4 | B20: =' CASHFLOW'!H1 | C20: =' CASHFLOW'!H97 | D20: =' CASHFLOW'!H98
A21: PMT 5 | B21: =' CASHFLOW'!I1 | C21: =' CASHFLOW'!I97 | D21: =' CASHFLOW'!I98
A22: PMT 6 | B22: =' CASHFLOW'!J1 | C22: =' CASHFLOW'!J97 | D22: =' CASHFLOW'!J98
A23: PMT 7 | B23: =' CASHFLOW'!K1 | C23: =' CASHFLOW'!K97 | D23: =' CASHFLOW'!K98
A24: PMT 8 | B24: =' CASHFLOW'!L1 | C24: =' CASHFLOW'!L97 | D24: =' CASHFLOW'!L98
A25: PMT 9 | B25: =' CASHFLOW'!M1 | C25: =' CASHFLOW'!M97 | D25: =' CASHFLOW'!M98
A26: PMT 10 | B26: =' CASHFLOW'!N1 | C26: =' CASHFLOW'!N97 | D26: =' CASHFLOW'!N98
A27: PMT 11 | B27: =' CASHFLOW'!O1 | C27: =' CASHFLOW'!O97 | D27: =' CASHFLOW'!O98
A28: PMT 12 | B28: =' CASHFLOW'!P1 | C28: =' CASHFLOW'!P97 | D28: =' CASHFLOW'!P98
A29: PMT 13 | B29: =' CASHFLOW'!Q1 | C29: =' CASHFLOW'!Q97 | D29: =' CASHFLOW'!Q98
A30: PMT 14 | B30: =' CASHFLOW'!R1 | C30: =' CASHFLOW'!R97 | D30: =' CASHFLOW'!R98
A31: PMT 15 | B31: =' CASHFLOW'!S1 | C31: =' CASHFLOW'!S97 | D31: =' CASHFLOW'!S98
A32: PMT 16 | B32: =' CASHFLOW'!T1 | C32: =' CASHFLOW'!T97 | D32: =' CASHFLOW'!T98
A33: PMT 17 | B33: =' CASHFLOW'!U1 | C33: =' CASHFLOW'!U97 | D33: =' CASHFLOW'!U98
A34: PMT 18 | B34: =' CASHFLOW'!V1 | C34: =' CASHFLOW'!V97 | D34: =' CASHFLOW'!V98
A35: PMT 19 | B35: =' CASHFLOW'!W1 | C35: =' CASHFLOW'!W97 | D35: =' CASHFLOW'!W98
A36: PMT 20 | B36: =' CASHFLOW'!X1 | C36: =' CASHFLOW'!X97 | D36: =' CASHFLOW'!X98
A37: PMT 21 | B37: =' CASHFLOW'!Y1 | C37: =' CASHFLOW'!Y97 | D37: =' CASHFLOW'!Y98
A38: PMT 22 | B38: =' CASHFLOW'!Z1 | C38: =' CASHFLOW'!Z97 | D38: =' CASHFLOW'!Z98
A39: PMT 23 | B39: =' CASHFLOW'!AA1 | C39: =' CASHFLOW'!AA97 | D39: =' CASHFLOW'!AA98
A40: PMT 24 | B40: =' CASHFLOW'!AB1 | C40: =' CASHFLOW'!AB97 | D40: =' CASHFLOW'!AB98
A41: PMT 25 | B41: =' CASHFLOW'!AC1 | C41: =' CASHFLOW'!AC97 | D41: =' CASHFLOW'!AC98
A42: PMT 26 | B42: =' CASHFLOW'!AD1 | C42: =' CASHFLOW'!AD97 | D42: =' CASHFLOW'!AD98
A43: PMT 27 | B43: =' CASHFLOW'!AE1 | C43: =' CASHFLOW'!AE97 | D43: =' CASHFLOW'!AE98
A44: TOTAL PAYMENT | C44: =SUM(C17:C43)

Sheet CASHFLOW SUMMARY CHART

Sheet  CASHFLOW
A1: ITEM | B1: DESCRIPTION | D1: TOTAL | E1: =EOMONTH($C$107,E2) | F1: =EOMONTH($C$107,F2) | G1: =EOMONTH($C$107,G2) | H1: =EOMONTH($C$107,H2) | I1: =EOMONTH($C$107,I2) | J1: =EOMONTH($C$107,J2) | K1: =EOMONTH($C$107,K2) | L1: =EOMONTH($C$107,L2) | ... AE1: =EOMONTH($C$107,AE2) | AF1: TOTAL | AH1: START MONTH | AI1: DURATION (MONTHS)
E2: 0 | F2: =E2+1 | G2: =F2+1 | H2: =G2+1 | I2: =H2+1 | J2: =I2+1 | K2: =J2+1 | L2: =K2+1 | M2: =L2+1 | ... AC2: =AB2+1 | AD2: =$C$108+1 | AE2: =$C$108+$C$110
A3: A | B3: ADVANCE MOBILIZATION | D3: =$C$103*$C$101 | E3: =IF(AND(E$2>=$AH4,E$2<$AH4+$AI4),$D4/$AI4,0) | F3: =IF(AND(F$2>=$AH4,F$2<$AH4+$AI4),$D4/$AI4,0) | G3: =IF(AND(G$2>=$AH4,G$2<$AH4+$AI4),$D4/$AI4,0) | H3: =IF(AND(H$2>=$AH4,H$2<$AH4+$AI4),$D4/$AI4,0) | I3: =IF(AND(I$2>=$AH4,I$2<$AH4+$AI4),$D4/$AI4,0) | J3: =IF(AND(J$2>=$AH4,J$2<$AH4+$AI4),$D4/$AI4,0) | K3: =IF(AND(K$2>=$AH4,K$2<$AH4+$AI4),$D4/$AI4,0) | L3: =IF(AND(L$2>=$AH4,L$2<$AH4+$AI4),$D4/$AI4,0) | ... AE3: =IF(AND(AE$2>=$AH4,AE$2<$AH4+$AI4),$D4/$AI4,0) | AF3: =SUM(E3:AE3)
B4: Contract Signing | C4: 1 | D4: =C4*$D$3 | AH4: 0 | AI4: 1
A6: B | B6: ='GEN SUMMARY.'!B7 | D6: ='GEN SUMMARY.'!E7 | E6: =IF(AND(E$2>=$AH7,E$2<$AH7+$AI7),$D7/$AI7,0)+IF(AND(E$2>=$AH8,E$2<$AH8+$AI8),$D8/$AI8,0)+IF(AND(E$2>=$AH9,E$2<$AH9+$AI9),$D9/$AI9,0) | F6: =IF(AND(F$2>=$AH7,F$2<$AH7+$AI7),$D7/$AI7,0)+IF(AND(F$2>=$AH8,F$2<$AH8+$AI8),$D8/$AI8,0)+IF(AND(F$2>=$AH9,F$2<$AH9+$AI9),$D9/$AI9,0) | G6: =IF(AND(G$2>=$AH7,G$2<$AH7+$AI7),$D7/$AI7,0)+IF(AND(G$2>=$AH8,G$2<$AH8+$AI8),$D8/$AI8,0)+IF(AND(G$2>=$AH9,G$2<$AH9+$AI9),$D9/$AI9,0) | H6: =IF(AND(H$2>=$AH7,H$2<$AH7+$AI7),$D7/$AI7,0)+IF(AND(H$2>=$AH8,H$2<$AH8+$AI8),$D8/$AI8,0)+IF(AND(H$2>=$AH9,H$2<$AH9+$AI9),$D9/$AI9,0) | I6: =IF(AND(I$2>=$AH7,I$2<$AH7+$AI7),$D7/$AI7,0)+IF(AND(I$2>=$AH8,I$2<$AH8+$AI8),$D8/$AI8,0)+IF(AND(I$2>=$AH9,I$2<$AH9+$AI9),$D9/$AI9,0) | J6: =IF(AND(J$2>=$AH7,J$2<$AH7+$AI7),$D7/$AI7,0)+IF(AND(J$2>=$AH8,J$2<$AH8+$AI8),$D8/$AI8,0)+IF(AND(J$2>=$AH9,J$2<$AH9+$AI9),$D9/$AI9,0) | K6: =IF(AND(K$2>=$AH7,K$2<$AH7+$AI7),$D7/$AI7,0)+IF(AND(K$2>=$AH8,K$2<$AH8+$AI8),$D8/$AI8,0)+IF(AND(K$2>=$AH9,K$2<$AH9+$AI9),$D9/$AI9,0) | L6: =IF(AND(L$2>=$AH7,L$2<$AH7+$AI7),$D7/$AI7,0)+IF(AND(L$2>=$AH8,L$2<$AH8+$AI8),$D8/$AI8,0)+IF(AND(L$2>=$AH9,L$2<$AH9+$AI9),$D9/$AI9,0) | ... AE6: =IF(AND(AE$2>=$AH7,AE$2<$AH7+$AI7),$D7/$AI7,0)+IF(AND(AE$2>=$AH8,AE$2<$AH8+$AI8),$D8/$AI8,0)+IF(AND(AE$2>=$AH9,AE$2<$AH9+$AI9),$D9/$AI9,0) | AF6: =SUM(E6:AE6)
B7: (100%) Site Possession and Hoarding | C7: 0.3 | D7: =C7*$D$6 | AH7: 1 | AI7: 1
B8: (100%) Site Setup and Mobilization | C8: 0.2 | D8: =C8*$D$6 | AH8: 2 | AI8: 1
B9: (100%) Site Maintenance | C9: 0.5 | D9: =C9*$D$6 | AH9: 3 | AI9: 22
A11: C | B11: ='GEN SUMMARY.'!B9 | D11: ='GEN SUMMARY.'!E9 | E11: =IF(AND(E$2>=$AH12,E$2<$AH12+$AI12),$D12/$AI12,0)+IF(AND(E$2>=$AH13,E$2<$AH13+$AI13),$D13/$AI13,0) | F11: =IF(AND(F$2>=$AH12,F$2<$AH12+$AI12),$D12/$AI12,0)+IF(AND(F$2>=$AH13,F$2<$AH13+$AI13),$D13/$AI13,0) | G11: =IF(AND(G$2>=$AH12,G$2<$AH12+$AI12),$D12/$AI12,0)+IF(AND(G$2>=$AH13,G$2<$AH13+$AI13),$D13/$AI13,0) | H11: =IF(AND(H$2>=$AH12,H$2<$AH12+$AI12),$D12/$AI12,0)+IF(AND(H$2>=$AH13,H$2<$AH13+$AI13),$D13/$AI13,0) | I11: =IF(AND(I$2>=$AH12,I$2<$AH12+$AI12),$D12/$AI12,0)+IF(AND(I$2>=$AH13,I$2<$AH13+$AI13),$D13/$AI13,0) | J11: =IF(AND(J$2>=$AH12,J$2<$AH12+$AI12),$D12/$AI12,0)+IF(AND(J$2>=$AH13,J$2<$AH13+$AI13),$D13/$AI13,0) | K11: =IF(AND(K$2>=$AH12,K$2<$AH12+$AI12),$D12/$AI12,0)+IF(AND(K$2>=$AH13,K$2<$AH13+$AI13),$D13/$AI13,0) | L11: =IF(AND(L$2>=$AH12,L$2<$AH12+$AI12),$D12/$AI12,0)+IF(AND(L$2>=$AH13,L$2<$AH13+$AI13),$D13/$AI13,0) | ... AE11: =IF(AND(AE$2>=$AH12,AE$2<$AH12+$AI12),$D12/$AI12,0)+IF(AND(AE$2>=$AH13,AE$2<$AH13+$AI13),$D13/$AI13,0) | AF11: =SUM(E11:AE11)
B12: (0%) Start of Demolition Works | C12: 0.8 | D12: =C12*$D$11 | AH12: 1 | AI12: 1
B13: (100%) End of Demolition Works | C13: 0.2 | D13: =C13*$D$11 | AH13: 2 | AI13: 1
A15: D | B15: ='GEN SUMMARY.'!B11 | D15: ='GEN SUMMARY.'!E11 | E15: =IF(AND(E$2>=$AH16,E$2<$AH16+$AI16),$D16/$AI16,0)+IF(AND(E$2>=$AH17,E$2<$AH17+$AI17),$D17/$AI17,0)+IF(AND(E$2>=$AH18,E$2<$AH18+$AI18),$D18/$AI18,0) | F15: =IF(AND(F$2>=$AH16,F$2<$AH16+$AI16),$D16/$AI16,0)+IF(AND(F$2>=$AH17,F$2<$AH17+$AI17),$D17/$AI17,0)+IF(AND(F$2>=$AH18,F$2<$AH18+$AI18),$D18/$AI18,0) | G15: =IF(AND(G$2>=$AH16,G$2<$AH16+$AI16),$D16/$AI16,0)+IF(AND(G$2>=$AH17,G$2<$AH17+$AI17),$D17/$AI17,0)+IF(AND(G$2>=$AH18,G$2<$AH18+$AI18),$D18/$AI18,0) | H15: =IF(AND(H$2>=$AH16,H$2<$AH16+$AI16),$D16/$AI16,0)+IF(AND(H$2>=$AH17,H$2<$AH17+$AI17),$D17/$AI17,0)+IF(AND(H$2>=$AH18,H$2<$AH18+$AI18),$D18/$AI18,0) | I15: =IF(AND(I$2>=$AH16,I$2<$AH16+$AI16),$D16/$AI16,0)+IF(AND(I$2>=$AH17,I$2<$AH17+$AI17),$D17/$AI17,0)+IF(AND(I$2>=$AH18,I$2<$AH18+$AI18),$D18/$AI18,0) | J15: =IF(AND(J$2>=$AH16,J$2<$AH16+$AI16),$D16/$AI16,0)+IF(AND(J$2>=$AH17,J$2<$AH17+$AI17),$D17/$AI17,0)+IF(AND(J$2>=$AH18,J$2<$AH18+$AI18),$D18/$AI18,0) | K15: =IF(AND(K$2>=$AH16,K$2<$AH16+$AI16),$D16/$AI16,0)+IF(AND(K$2>=$AH17,K$2<$AH17+$AI17),$D17/$AI17,0)+IF(AND(K$2>=$AH18,K$2<$AH18+$AI18),$D18/$AI18,0) | L15: =IF(AND(L$2>=$AH16,L$2<$AH16+$AI16),$D16/$AI16,0)+IF(AND(L$2>=$AH17,L$2<$AH17+$AI17),$D17/$AI17,0)+IF(AND(L$2>=$AH18,L$2<$AH18+$AI18),$D18/$AI18,0) | ... AE15: =IF(AND(AE$2>=$AH16,AE$2<$AH16+$AI16),$D16/$AI16,0)+IF(AND(AE$2>=$AH17,AE$2<$AH17+$AI17),$D17/$AI17,0)+IF(AND(AE$2>=$AH18,AE$2<$AH18+$AI18),$D18/$AI18,0) | AF15: =SUM(E15:AE15)
B16: Procurement Phase I (Substructure materials on site and in transit) (0%) | C16: 0.5 | D16: =C16*$D$15 | AH16: 1 | AI16: 2
B17: (50%) Completion of Ground Works | C17: 0.25 | D17: =C17*$D$15 | AH17: 3 | AI17: 1
B18: (100%) Completion of Substructure Concrete Works | C18: 0.25 | D18: =C18*$D$15 | AH18: 4 | AI18: 1
A20: E | B20: ='GEN SUMMARY.'!B13 | D20: ='GEN SUMMARY.'!E13 | E20: =IF(AND(E$2>=$AH21,E$2<$AH21+$AI21),$D21/$AI21,0)+IF(AND(E$2>=$AH22,E$2<$AH22+$AI22),$D22/$AI22,0)+IF(AND(E$2>=$AH23,E$2<$AH23+$AI23),$D23/$AI23,0)+IF(AND(E$2>=$AH24,E$2<$AH24+$AI24),$D24/$AI24,0) | F20: =IF(AND(F$2>=$AH21,F$2<$AH21+$AI21),$D21/$AI21,0)+IF(AND(F$2>=$AH22,F$2<$AH22+$AI22),$D22/$AI22,0)+IF(AND(F$2>=$AH23,F$2<$AH23+$AI23),$D23/$AI23,0)+IF(AND(F$2>=$AH24,F$2<$AH24+$AI24),$D24/$AI24,0) | G20: =IF(AND(G$2>=$AH21,G$2<$AH21+$AI21),$D21/$AI21,0)+IF(AND(G$2>=$AH22,G$2<$AH22+$AI22),$D22/$AI22,0)+IF(AND(G$2>=$AH23,G$2<$AH23+$AI23),$D23/$AI23,0)+IF(AND(G$2>=$AH24,G$2<$AH24+$AI24),$D24/$AI24,0) | H20: =IF(AND(H$2>=$AH21,H$2<$AH21+$AI21),$D21/$AI21,0)+IF(AND(H$2>=$AH22,H$2<$AH22+$AI22),$D22/$AI22,0)+IF(AND(H$2>=$AH23,H$2<$AH23+$AI23),$D23/$AI23,0)+IF(AND(H$2>=$AH24,H$2<$AH24+$AI24),$D24/$AI24,0) | I20: =IF(AND(I$2>=$AH21,I$2<$AH21+$AI21),$D21/$AI21,0)+IF(AND(I$2>=$AH22,I$2<$AH22+$AI22),$D22/$AI22,0)+IF(AND(I$2>=$AH23,I$2<$AH23+$AI23),$D23/$AI23,0)+IF(AND(I$2>=$AH24,I$2<$AH24+$AI24),$D24/$AI24,0) | J20: =IF(AND(J$2>=$AH21,J$2<$AH21+$AI21),$D21/$AI21,0)+IF(AND(J$2>=$AH22,J$2<$AH22+$AI22),$D22/$AI22,0)+IF(AND(J$2>=$AH23,J$2<$AH23+$AI23),$D23/$AI23,0)+IF(AND(J$2>=$AH24,J$2<$AH24+$AI24),$D24/$AI24,0) | K20: =IF(AND(K$2>=$AH21,K$2<$AH21+$AI21),$D21/$AI21,0)+IF(AND(K$2>=$AH22,K$2<$AH22+$AI22),$D22/$AI22,0)+IF(AND(K$2>=$AH23,K$2<$AH23+$AI23),$D23/$AI23,0)+IF(AND(K$2>=$AH24,K$2<$AH24+$AI24),$D24/$AI24,0) | L20: =IF(AND(L$2>=$AH21,L$2<$AH21+$AI21),$D21/$AI21,0)+IF(AND(L$2>=$AH22,L$2<$AH22+$AI22),$D22/$AI22,0)+IF(AND(L$2>=$AH23,L$2<$AH23+$AI23),$D23/$AI23,0)+IF(AND(L$2>=$AH24,L$2<$AH24+$AI24),$D24/$AI24,0) | ... AE20: =IF(AND(AE$2>=$AH21,AE$2<$AH21+$AI21),$D21/$AI21,0)+IF(AND(AE$2>=$AH22,AE$2<$AH22+$AI22),$D22/$AI22,0)+IF(AND(AE$2>=$AH23,AE$2<$AH23+$AI23),$D23/$AI23,0)+IF(AND(AE$2>=$AH24,AE$2<$AH24+$AI24),$D24/$AI24,0) | AF20: =SUM(E20:AE20)
B21: (0%) Start of Sub-Basement Floor Structure | C21: 0.3 | D21: =C21*$D$20 | AH21: 3 | AI21: 3
B22: (100%) Completion of Structure | C22: 0.2 | D22: =C22*$D$20 | AH22: 6 | AI22: 1
B23: (0%) Start of Finishings and MEP | C23: 0.3 | D23: =C23*$D$20 | AH23: 7 | AI23: 10
B24: (100%) Completion of Finishings and MEP | C24: 0.2 | D24: =C24*$D$20 | AH24: 17 | AI24: 2
A26: F | B26: ='GEN SUMMARY.'!B15 | D26: ='GEN SUMMARY.'!E15 | E26: =IF(AND(E$2>=$AH27,E$2<$AH27+$AI27),$D27/$AI27,0)+IF(AND(E$2>=$AH28,E$2<$AH28+$AI28),$D28/$AI28,0)+IF(AND(E$2>=$AH29,E$2<$AH29+$AI29),$D29/$AI29,0)+IF(AND(E$2>=$AH30,E$2<$AH30+$AI30),$D30/$AI30,0) | F26: =IF(AND(F$2>=$AH27,F$2<$AH27+$AI27),$D27/$AI27,0)+IF(AND(F$2>=$AH28,F$2<$AH28+$AI28),$D28/$AI28,0)+IF(AND(F$2>=$AH29,F$2<$AH29+$AI29),$D29/$AI29,0)+IF(AND(F$2>=$AH30,F$2<$AH30+$AI30),$D30/$AI30,0) | G26: =IF(AND(G$2>=$AH27,G$2<$AH27+$AI27),$D27/$AI27,0)+IF(AND(G$2>=$AH28,G$2<$AH28+$AI28),$D28/$AI28,0)+IF(AND(G$2>=$AH29,G$2<$AH29+$AI29),$D29/$AI29,0)+IF(AND(G$2>=$AH30,G$2<$AH30+$AI30),$D30/$AI30,0) | H26: =IF(AND(H$2>=$AH27,H$2<$AH27+$AI27),$D27/$AI27,0)+IF(AND(H$2>=$AH28,H$2<$AH28+$AI28),$D28/$AI28,0)+IF(AND(H$2>=$AH29,H$2<$AH29+$AI29),$D29/$AI29,0)+IF(AND(H$2>=$AH30,H$2<$AH30+$AI30),$D30/$AI30,0) | I26: =IF(AND(I$2>=$AH27,I$2<$AH27+$AI27),$D27/$AI27,0)+IF(AND(I$2>=$AH28,I$2<$AH28+$AI28),$D28/$AI28,0)+IF(AND(I$2>=$AH29,I$2<$AH29+$AI29),$D29/$AI29,0)+IF(AND(I$2>=$AH30,I$2<$AH30+$AI30),$D30/$AI30,0) | J26: =IF(AND(J$2>=$AH27,J$2<$AH27+$AI27),$D27/$AI27,0)+IF(AND(J$2>=$AH28,J$2<$AH28+$AI28),$D28/$AI28,0)+IF(AND(J$2>=$AH29,J$2<$AH29+$AI29),$D29/$AI29,0)+IF(AND(J$2>=$AH30,J$2<$AH30+$AI30),$D30/$AI30,0) | K26: =IF(AND(K$2>=$AH27,K$2<$AH27+$AI27),$D27/$AI27,0)+IF(AND(K$2>=$AH28,K$2<$AH28+$AI28),$D28/$AI28,0)+IF(AND(K$2>=$AH29,K$2<$AH29+$AI29),$D29/$AI29,0)+IF(AND(K$2>=$AH30,K$2<$AH30+$AI30),$D30/$AI30,0) | L26: =IF(AND(L$2>=$AH27,L$2<$AH27+$AI27),$D27/$AI27,0)+IF(AND(L$2>=$AH28,L$2<$AH28+$AI28),$D28/$AI28,0)+IF(AND(L$2>=$AH29,L$2<$AH29+$AI29),$D29/$AI29,0)+IF(AND(L$2>=$AH30,L$2<$AH30+$AI30),$D30/$AI30,0) | ... AE26: =IF(AND(AE$2>=$AH27,AE$2<$AH27+$AI27),$D27/$AI27,0)+IF(AND(AE$2>=$AH28,AE$2<$AH28+$AI28),$D28/$AI28,0)+IF(AND(AE$2>=$AH29,AE$2<$AH29+$AI29),$D29/$AI29,0)+IF(AND(AE$2>=$AH30,AE$2<$AH30+$AI30),$D30/$AI30,0) | AF26: =SUM(E26:AE26)
B27: (0%) Start of Ground Floor Structure | C27: 0.3 | D27: =C27*$D$26 | AH27: 5 | AI27: 2
B28: (100%) Completion of Structure | C28: 0.2 | D28: =C28*$D$26 | AH28: 7 | AI28: 1
B29: (0%) Start of Finishings and MEP | C29: 0.3 | D29: =C29*$D$26 | AH29: 8 | AI29: 11
B30: (100%) Completion of Finishings and MEP | C30: 0.2 | D30: =C30*$D$26 | AH30: 19 | AI30: 2
A32: G | B32: ='GEN SUMMARY.'!B17 | D32: ='GEN SUMMARY.'!E17 | E32: =IF(AND(E$2>=$AH33,E$2<$AH33+$AI33),$D33/$AI33,0)+IF(AND(E$2>=$AH34,E$2<$AH34+$AI34),$D34/$AI34,0)+IF(AND(E$2>=$AH35,E$2<$AH35+$AI35),$D35/$AI35,0)+IF(AND(E$2>=$AH36,E$2<$AH36+$AI36),$D36/$AI36,0) | F32: =IF(AND(F$2>=$AH33,F$2<$AH33+$AI33),$D33/$AI33,0)+IF(AND(F$2>=$AH34,F$2<$AH34+$AI34),$D34/$AI34,0)+IF(AND(F$2>=$AH35,F$2<$AH35+$AI35),$D35/$AI35,0)+IF(AND(F$2>=$AH36,F$2<$AH36+$AI36),$D36/$AI36,0) | G32: =IF(AND(G$2>=$AH33,G$2<$AH33+$AI33),$D33/$AI33,0)+IF(AND(G$2>=$AH34,G$2<$AH34+$AI34),$D34/$AI34,0)+IF(AND(G$2>=$AH35,G$2<$AH35+$AI35),$D35/$AI35,0)+IF(AND(G$2>=$AH36,G$2<$AH36+$AI36),$D36/$AI36,0) | H32: =IF(AND(H$2>=$AH33,H$2<$AH33+$AI33),$D33/$AI33,0)+IF(AND(H$2>=$AH34,H$2<$AH34+$AI34),$D34/$AI34,0)+IF(AND(H$2>=$AH35,H$2<$AH35+$AI35),$D35/$AI35,0)+IF(AND(H$2>=$AH36,H$2<$AH36+$AI36),$D36/$AI36,0) | I32: =IF(AND(I$2>=$AH33,I$2<$AH33+$AI33),$D33/$AI33,0)+IF(AND(I$2>=$AH34,I$2<$AH34+$AI34),$D34/$AI34,0)+IF(AND(I$2>=$AH35,I$2<$AH35+$AI35),$D35/$AI35,0)+IF(AND(I$2>=$AH36,I$2<$AH36+$AI36),$D36/$AI36,0) | J32: =IF(AND(J$2>=$AH33,J$2<$AH33+$AI33),$D33/$AI33,0)+IF(AND(J$2>=$AH34,J$2<$AH34+$AI34),$D34/$AI34,0)+IF(AND(J$2>=$AH35,J$2<$AH35+$AI35),$D35/$AI35,0)+IF(AND(J$2>=$AH36,J$2<$AH36+$AI36),$D36/$AI36,0) | K32: =IF(AND(K$2>=$AH33,K$2<$AH33+$AI33),$D33/$AI33,0)+IF(AND(K$2>=$AH34,K$2<$AH34+$AI34),$D34/$AI34,0)+IF(AND(K$2>=$AH35,K$2<$AH35+$AI35),$D35/$AI35,0)+IF(AND(K$2>=$AH36,K$2<$AH36+$AI36),$D36/$AI36,0) | L32: =IF(AND(L$2>=$AH33,L$2<$AH33+$AI33),$D33/$AI33,0)+IF(AND(L$2>=$AH34,L$2<$AH34+$AI34),$D34/$AI34,0)+IF(AND(L$2>=$AH35,L$2<$AH35+$AI35),$D35/$AI35,0)+IF(AND(L$2>=$AH36,L$2<$AH36+$AI36),$D36/$AI36,0) | ... AE32: =IF(AND(AE$2>=$AH33,AE$2<$AH33+$AI33),$D33/$AI33,0)+IF(AND(AE$2>=$AH34,AE$2<$AH34+$AI34),$D34/$AI34,0)+IF(AND(AE$2>=$AH35,AE$2<$AH35+$AI35),$D35/$AI35,0)+IF(AND(AE$2>=$AH36,AE$2<$AH36+$AI36),$D36/$AI36,0) | AF32: =SUM(E32:AE32)
B33: (0%) Start of First Floor Structure | C33: 0.3 | D33: =C33*$D$32 | AH33: 7 | AI33: 2
B34: (100%) Completion of Structure | C34: 0.2 | D34: =C34*$D$32 | AH34: 9 | AI34: 1
B35: (0%) Start of Finishings and MEP | C35: 0.3 | D35: =C35*$D$32 | AH35: 10 | AI35: 10
B36: (100%) Completion of Finishings and MEP | C36: 0.2 | D36: =C36*$D$32 | AH36: 20 | AI36: 2
A38: H | B38: ='GEN SUMMARY.'!B19 | D38: ='GEN SUMMARY.'!E19 | E38: =IF(AND(E$2>=$AH39,E$2<$AH39+$AI39),$D39/$AI39,0)+IF(AND(E$2>=$AH40,E$2<$AH40+$AI40),$D40/$AI40,0)+IF(AND(E$2>=$AH41,E$2<$AH41+$AI41),$D41/$AI41,0)+IF(AND(E$2>=$AH42,E$2<$AH42+$AI42),$D42/$AI42,0) | F38: =IF(AND(F$2>=$AH39,F$2<$AH39+$AI39),$D39/$AI39,0)+IF(AND(F$2>=$AH40,F$2<$AH40+$AI40),$D40/$AI40,0)+IF(AND(F$2>=$AH41,F$2<$AH41+$AI41),$D41/$AI41,0)+IF(AND(F$2>=$AH42,F$2<$AH42+$AI42),$D42/$AI42,0) | G38: =IF(AND(G$2>=$AH39,G$2<$AH39+$AI39),$D39/$AI39,0)+IF(AND(G$2>=$AH40,G$2<$AH40+$AI40),$D40/$AI40,0)+IF(AND(G$2>=$AH41,G$2<$AH41+$AI41),$D41/$AI41,0)+IF(AND(G$2>=$AH42,G$2<$AH42+$AI42),$D42/$AI42,0) | H38: =IF(AND(H$2>=$AH39,H$2<$AH39+$AI39),$D39/$AI39,0)+IF(AND(H$2>=$AH40,H$2<$AH40+$AI40),$D40/$AI40,0)+IF(AND(H$2>=$AH41,H$2<$AH41+$AI41),$D41/$AI41,0)+IF(AND(H$2>=$AH42,H$2<$AH42+$AI42),$D42/$AI42,0) | I38: =IF(AND(I$2>=$AH39,I$2<$AH39+$AI39),$D39/$AI39,0)+IF(AND(I$2>=$AH40,I$2<$AH40+$AI40),$D40/$AI40,0)+IF(AND(I$2>=$AH41,I$2<$AH41+$AI41),$D41/$AI41,0)+IF(AND(I$2>=$AH42,I$2<$AH42+$AI42),$D42/$AI42,0) | J38: =IF(AND(J$2>=$AH39,J$2<$AH39+$AI39),$D39/$AI39,0)+IF(AND(J$2>=$AH40,J$2<$AH40+$AI40),$D40/$AI40,0)+IF(AND(J$2>=$AH41,J$2<$AH41+$AI41),$D41/$AI41,0)+IF(AND(J$2>=$AH42,J$2<$AH42+$AI42),$D42/$AI42,0) | K38: =IF(AND(K$2>=$AH39,K$2<$AH39+$AI39),$D39/$AI39,0)+IF(AND(K$2>=$AH40,K$2<$AH40+$AI40),$D40/$AI40,0)+IF(AND(K$2>=$AH41,K$2<$AH41+$AI41),$D41/$AI41,0)+IF(AND(K$2>=$AH42,K$2<$AH42+$AI42),$D42/$AI42,0) | L38: =IF(AND(L$2>=$AH39,L$2<$AH39+$AI39),$D39/$AI39,0)+IF(AND(L$2>=$AH40,L$2<$AH40+$AI40),$D40/$AI40,0)+IF(AND(L$2>=$AH41,L$2<$AH41+$AI41),$D41/$AI41,0)+IF(AND(L$2>=$AH42,L$2<$AH42+$AI42),$D42/$AI42,0) | ... AE38: =IF(AND(AE$2>=$AH39,AE$2<$AH39+$AI39),$D39/$AI39,0)+IF(AND(AE$2>=$AH40,AE$2<$AH40+$AI40),$D40/$AI40,0)+IF(AND(AE$2>=$AH41,AE$2<$AH41+$AI41),$D41/$AI41,0)+IF(AND(AE$2>=$AH42,AE$2<$AH42+$AI42),$D42/$AI42,0) | AF38: =SUM(E38:AE38)
B39: (0%) Start of Second Floor Structure | C39: 0.3 | D39: =C39*$D$38 | AH39: 9 | AI39: 2
B40: (100%) Completion of Structure | C40: 0.2 | D40: =C40*$D$38 | AH40: 11 | AI40: 1
B41: (0%) Start of Finishings and MEP | C41: 0.3 | D41: =C41*$D$38 | AH41: 12 | AI41: 8
B42: (100%) Completion of Finishings and MEP | C42: 0.2 | D42: =C42*$D$38 | AH42: 20 | AI42: 2
A44: J | B44: ='GEN SUMMARY.'!B21 | D44: ='GEN SUMMARY.'!E21 | E44: =IF(AND(E$2>=$AH45,E$2<$AH45+$AI45),$D45/$AI45,0)+IF(AND(E$2>=$AH46,E$2<$AH46+$AI46),$D46/$AI46,0)+IF(AND(E$2>=$AH47,E$2<$AH47+$AI47),$D47/$AI47,0)+IF(AND(E$2>=$AH48,E$2<$AH48+$AI48),$D48/$AI48,0) | F44: =IF(AND(F$2>=$AH45,F$2<$AH45+$AI45),$D45/$AI45,0)+IF(AND(F$2>=$AH46,F$2<$AH46+$AI46),$D46/$AI46,0)+IF(AND(F$2>=$AH47,F$2<$AH47+$AI47),$D47/$AI47,0)+IF(AND(F$2>=$AH48,F$2<$AH48+$AI48),$D48/$AI48,0) | G44: =IF(AND(G$2>=$AH45,G$2<$AH45+$AI45),$D45/$AI45,0)+IF(AND(G$2>=$AH46,G$2<$AH46+$AI46),$D46/$AI46,0)+IF(AND(G$2>=$AH47,G$2<$AH47+$AI47),$D47/$AI47,0)+IF(AND(G$2>=$AH48,G$2<$AH48+$AI48),$D48/$AI48,0) | H44: =IF(AND(H$2>=$AH45,H$2<$AH45+$AI45),$D45/$AI45,0)+IF(AND(H$2>=$AH46,H$2<$AH46+$AI46),$D46/$AI46,0)+IF(AND(H$2>=$AH47,H$2<$AH47+$AI47),$D47/$AI47,0)+IF(AND(H$2>=$AH48,H$2<$AH48+$AI48),$D48/$AI48,0) | I44: =IF(AND(I$2>=$AH45,I$2<$AH45+$AI45),$D45/$AI45,0)+IF(AND(I$2>=$AH46,I$2<$AH46+$AI46),$D46/$AI46,0)+IF(AND(I$2>=$AH47,I$2<$AH47+$AI47),$D47/$AI47,0)+IF(AND(I$2>=$AH48,I$2<$AH48+$AI48),$D48/$AI48,0) | J44: =IF(AND(J$2>=$AH45,J$2<$AH45+$AI45),$D45/$AI45,0)+IF(AND(J$2>=$AH46,J$2<$AH46+$AI46),$D46/$AI46,0)+IF(AND(J$2>=$AH47,J$2<$AH47+$AI47),$D47/$AI47,0)+IF(AND(J$2>=$AH48,J$2<$AH48+$AI48),$D48/$AI48,0) | K44: =IF(AND(K$2>=$AH45,K$2<$AH45+$AI45),$D45/$AI45,0)+IF(AND(K$2>=$AH46,K$2<$AH46+$AI46),$D46/$AI46,0)+IF(AND(K$2>=$AH47,K$2<$AH47+$AI47),$D47/$AI47,0)+IF(AND(K$2>=$AH48,K$2<$AH48+$AI48),$D48/$AI48,0) | L44: =IF(AND(L$2>=$AH45,L$2<$AH45+$AI45),$D45/$AI45,0)+IF(AND(L$2>=$AH46,L$2<$AH46+$AI46),$D46/$AI46,0)+IF(AND(L$2>=$AH47,L$2<$AH47+$AI47),$D47/$AI47,0)+IF(AND(L$2>=$AH48,L$2<$AH48+$AI48),$D48/$AI48,0) | ... AE44: =IF(AND(AE$2>=$AH45,AE$2<$AH45+$AI45),$D45/$AI45,0)+IF(AND(AE$2>=$AH46,AE$2<$AH46+$AI46),$D46/$AI46,0)+IF(AND(AE$2>=$AH47,AE$2<$AH47+$AI47),$D47/$AI47,0)+IF(AND(AE$2>=$AH48,AE$2<$AH48+$AI48),$D48/$AI48,0) | AF44: =SUM(E44:AE44)
B45: (0%) Start of Third Floor Structure | C45: 0.3 | D45: =C45*$D$44 | AH45: 11 | AI45: 2
B46: (100%) Completion of Structure | C46: 0.2 | D46: =C46*$D$44 | AH46: 13 | AI46: 1
B47: (0%) Start of Finishings and MEP | C47: 0.3 | D47: =C47*$D$44 | AH47: 14 | AI47: 7
B48: (100%) Completion of Finishings and MEP | C48: 0.2 | D48: =C48*$D$44 | AH48: 21 | AI48: 2
A50: K | B50: ='GEN SUMMARY.'!B23 | D50: ='GEN SUMMARY.'!E23 | E50: =IF(AND(E$2>=$AH51,E$2<$AH51+$AI51),$D51/$AI51,0)+IF(AND(E$2>=$AH52,E$2<$AH52+$AI52),$D52/$AI52,0)+IF(AND(E$2>=$AH53,E$2<$AH53+$AI53),$D53/$AI53,0)+IF(AND(E$2>=$AH54,E$2<$AH54+$AI54),$D54/$AI54,0) | F50: =IF(AND(F$2>=$AH51,F$2<$AH51+$AI51),$D51/$AI51,0)+IF(AND(F$2>=$AH52,F$2<$AH52+$AI52),$D52/$AI52,0)+IF(AND(F$2>=$AH53,F$2<$AH53+$AI53),$D53/$AI53,0)+IF(AND(F$2>=$AH54,F$2<$AH54+$AI54),$D54/$AI54,0) | G50: =IF(AND(G$2>=$AH51,G$2<$AH51+$AI51),$D51/$AI51,0)+IF(AND(G$2>=$AH52,G$2<$AH52+$AI52),$D52/$AI52,0)+IF(AND(G$2>=$AH53,G$2<$AH53+$AI53),$D53/$AI53,0)+IF(AND(G$2>=$AH54,G$2<$AH54+$AI54),$D54/$AI54,0) | H50: =IF(AND(H$2>=$AH51,H$2<$AH51+$AI51),$D51/$AI51,0)+IF(AND(H$2>=$AH52,H$2<$AH52+$AI52),$D52/$AI52,0)+IF(AND(H$2>=$AH53,H$2<$AH53+$AI53),$D53/$AI53,0)+IF(AND(H$2>=$AH54,H$2<$AH54+$AI54),$D54/$AI54,0) | I50: =IF(AND(I$2>=$AH51,I$2<$AH51+$AI51),$D51/$AI51,0)+IF(AND(I$2>=$AH52,I$2<$AH52+$AI52),$D52/$AI52,0)+IF(AND(I$2>=$AH53,I$2<$AH53+$AI53),$D53/$AI53,0)+IF(AND(I$2>=$AH54,I$2<$AH54+$AI54),$D54/$AI54,0) | J50: =IF(AND(J$2>=$AH51,J$2<$AH51+$AI51),$D51/$AI51,0)+IF(AND(J$2>=$AH52,J$2<$AH52+$AI52),$D52/$AI52,0)+IF(AND(J$2>=$AH53,J$2<$AH53+$AI53),$D53/$AI53,0)+IF(AND(J$2>=$AH54,J$2<$AH54+$AI54),$D54/$AI54,0) | K50: =IF(AND(K$2>=$AH51,K$2<$AH51+$AI51),$D51/$AI51,0)+IF(AND(K$2>=$AH52,K$2<$AH52+$AI52),$D52/$AI52,0)+IF(AND(K$2>=$AH53,K$2<$AH53+$AI53),$D53/$AI53,0)+IF(AND(K$2>=$AH54,K$2<$AH54+$AI54),$D54/$AI54,0) | L50: =IF(AND(L$2>=$AH51,L$2<$AH51+$AI51),$D51/$AI51,0)+IF(AND(L$2>=$AH52,L$2<$AH52+$AI52),$D52/$AI52,0)+IF(AND(L$2>=$AH53,L$2<$AH53+$AI53),$D53/$AI53,0)+IF(AND(L$2>=$AH54,L$2<$AH54+$AI54),$D54/$AI54,0) | ... AE50: =IF(AND(AE$2>=$AH51,AE$2<$AH51+$AI51),$D51/$AI51,0)+IF(AND(AE$2>=$AH52,AE$2<$AH52+$AI52),$D52/$AI52,0)+IF(AND(AE$2>=$AH53,AE$2<$AH53+$AI53),$D53/$AI53,0)+IF(AND(AE$2>=$AH54,AE$2<$AH54+$AI54),$D54/$AI54,0) | AF50: =SUM(E50:AE50)
B51: (0%) Start of Fourth Floor Structure | C51: 0.3 | D51: =C51*$D$50 | AH51: 13 | AI51: 2
B52: (100%) Completion of Structure | C52: 0.2 | D52: =C52*$D$50 | AH52: 15 | AI52: 1
B53: (0%) Start of Finishings and MEP | C53: 0.3 | D53: =C53*$D$50 | AH53: 16 | AI53: 5
B54: (100%) Completion of Finishings and MEP | C54: 0.2 | D54: =C54*$D$50 | AH54: 21 | AI54: 2
A56: L | B56: ='GEN SUMMARY.'!B25 | D56: ='GEN SUMMARY.'!E25 | E56: =IF(AND(E$2>=$AH57,E$2<$AH57+$AI57),$D57/$AI57,0)+IF(AND(E$2>=$AH58,E$2<$AH58+$AI58),$D58/$AI58,0)+IF(AND(E$2>=$AH59,E$2<$AH59+$AI59),$D59/$AI59,0)+IF(AND(E$2>=$AH60,E$2<$AH60+$AI60),$D60/$AI60,0) | F56: =IF(AND(F$2>=$AH57,F$2<$AH57+$AI57),$D57/$AI57,0)+IF(AND(F$2>=$AH58,F$2<$AH58+$AI58),$D58/$AI58,0)+IF(AND(F$2>=$AH59,F$2<$AH59+$AI59),$D59/$AI59,0)+IF(AND(F$2>=$AH60,F$2<$AH60+$AI60),$D60/$AI60,0) | G56: =IF(AND(G$2>=$AH57,G$2<$AH57+$AI57),$D57/$AI57,0)+IF(AND(G$2>=$AH58,G$2<$AH58+$AI58),$D58/$AI58,0)+IF(AND(G$2>=$AH59,G$2<$AH59+$AI59),$D59/$AI59,0)+IF(AND(G$2>=$AH60,G$2<$AH60+$AI60),$D60/$AI60,0) | H56: =IF(AND(H$2>=$AH57,H$2<$AH57+$AI57),$D57/$AI57,0)+IF(AND(H$2>=$AH58,H$2<$AH58+$AI58),$D58/$AI58,0)+IF(AND(H$2>=$AH59,H$2<$AH59+$AI59),$D59/$AI59,0)+IF(AND(H$2>=$AH60,H$2<$AH60+$AI60),$D60/$AI60,0) | I56: =IF(AND(I$2>=$AH57,I$2<$AH57+$AI57),$D57/$AI57,0)+IF(AND(I$2>=$AH58,I$2<$AH58+$AI58),$D58/$AI58,0)+IF(AND(I$2>=$AH59,I$2<$AH59+$AI59),$D59/$AI59,0)+IF(AND(I$2>=$AH60,I$2<$AH60+$AI60),$D60/$AI60,0) | J56: =IF(AND(J$2>=$AH57,J$2<$AH57+$AI57),$D57/$AI57,0)+IF(AND(J$2>=$AH58,J$2<$AH58+$AI58),$D58/$AI58,0)+IF(AND(J$2>=$AH59,J$2<$AH59+$AI59),$D59/$AI59,0)+IF(AND(J$2>=$AH60,J$2<$AH60+$AI60),$D60/$AI60,0) | K56: =IF(AND(K$2>=$AH57,K$2<$AH57+$AI57),$D57/$AI57,0)+IF(AND(K$2>=$AH58,K$2<$AH58+$AI58),$D58/$AI58,0)+IF(AND(K$2>=$AH59,K$2<$AH59+$AI59),$D59/$AI59,0)+IF(AND(K$2>=$AH60,K$2<$AH60+$AI60),$D60/$AI60,0) | L56: =IF(AND(L$2>=$AH57,L$2<$AH57+$AI57),$D57/$AI57,0)+IF(AND(L$2>=$AH58,L$2<$AH58+$AI58),$D58/$AI58,0)+IF(AND(L$2>=$AH59,L$2<$AH59+$AI59),$D59/$AI59,0)+IF(AND(L$2>=$AH60,L$2<$AH60+$AI60),$D60/$AI60,0) | ... AE56: =IF(AND(AE$2>=$AH57,AE$2<$AH57+$AI57),$D57/$AI57,0)+IF(AND(AE$2>=$AH58,AE$2<$AH58+$AI58),$D58/$AI58,0)+IF(AND(AE$2>=$AH59,AE$2<$AH59+$AI59),$D59/$AI59,0)+IF(AND(AE$2>=$AH60,AE$2<$AH60+$AI60),$D60/$AI60,0) | AF56: =SUM(E56:AE56)
B57: (0%) Start of Fifth Floor Structure | C57: 0.3 | D57: =C57*$D$56 | AH57: 15 | AI57: 2
B58: (100%) Completion of Structure | C58: 0.2 | D58: =C58*$D$56 | AH58: 17 | AI58: 1
B59: (0%) Start of Finishings and MEP | C59: 0.3 | D59: =C59*$D$56 | AH59: 18 | AI59: 3
B60: (100%) Completion of Finishings and MEP | C60: 0.2 | D60: =C60*$D$56 | AH60: 21 | AI60: 2
A62: M | B62: ='GEN SUMMARY.'!B27 | D62: ='GEN SUMMARY.'!E27 | E62: =IF(AND(E$2>=$AH63,E$2<$AH63+$AI63),$D63/$AI63,0)+IF(AND(E$2>=$AH64,E$2<$AH64+$AI64),$D64/$AI64,0)+IF(AND(E$2>=$AH65,E$2<$AH65+$AI65),$D65/$AI65,0) | F62: =IF(AND(F$2>=$AH63,F$2<$AH63+$AI63),$D63/$AI63,0)+IF(AND(F$2>=$AH64,F$2<$AH64+$AI64),$D64/$AI64,0)+IF(AND(F$2>=$AH65,F$2<$AH65+$AI65),$D65/$AI65,0) | G62: =IF(AND(G$2>=$AH63,G$2<$AH63+$AI63),$D63/$AI63,0)+IF(AND(G$2>=$AH64,G$2<$AH64+$AI64),$D64/$AI64,0)+IF(AND(G$2>=$AH65,G$2<$AH65+$AI65),$D65/$AI65,0) | H62: =IF(AND(H$2>=$AH63,H$2<$AH63+$AI63),$D63/$AI63,0)+IF(AND(H$2>=$AH64,H$2<$AH64+$AI64),$D64/$AI64,0)+IF(AND(H$2>=$AH65,H$2<$AH65+$AI65),$D65/$AI65,0) | I62: =IF(AND(I$2>=$AH63,I$2<$AH63+$AI63),$D63/$AI63,0)+IF(AND(I$2>=$AH64,I$2<$AH64+$AI64),$D64/$AI64,0)+IF(AND(I$2>=$AH65,I$2<$AH65+$AI65),$D65/$AI65,0) | J62: =IF(AND(J$2>=$AH63,J$2<$AH63+$AI63),$D63/$AI63,0)+IF(AND(J$2>=$AH64,J$2<$AH64+$AI64),$D64/$AI64,0)+IF(AND(J$2>=$AH65,J$2<$AH65+$AI65),$D65/$AI65,0) | K62: =IF(AND(K$2>=$AH63,K$2<$AH63+$AI63),$D63/$AI63,0)+IF(AND(K$2>=$AH64,K$2<$AH64+$AI64),$D64/$AI64,0)+IF(AND(K$2>=$AH65,K$2<$AH65+$AI65),$D65/$AI65,0) | L62: =IF(AND(L$2>=$AH63,L$2<$AH63+$AI63),$D63/$AI63,0)+IF(AND(L$2>=$AH64,L$2<$AH64+$AI64),$D64/$AI64,0)+IF(AND(L$2>=$AH65,L$2<$AH65+$AI65),$D65/$AI65,0) | ... AE62: =IF(AND(AE$2>=$AH63,AE$2<$AH63+$AI63),$D63/$AI63,0)+IF(AND(AE$2>=$AH64,AE$2<$AH64+$AI64),$D64/$AI64,0)+IF(AND(AE$2>=$AH65,AE$2<$AH65+$AI65),$D65/$AI65,0) | AF62: =SUM(E62:AE62)
B63: (0%) Start of Kitchen Cabinetry/Wall Cladding works | C63: 0.7 | D63: =C63*$D$62 | AH63: 16 | AI63: 1
B64: 100% of works fabricated | C64: 0.2 | D64: =C64*$D$62 | AH64: 19 | AI64: 2
B65: 100% of works installed on site | C65: 0.1 | D65: =C65*$D$62 | AH65: 22 | AI65: 1
A67: N | B67: ='GEN SUMMARY.'!B29 | D67: ='GEN SUMMARY.'!E29 | E67: =IF(AND(E$2>=$AH68,E$2<$AH68+$AI68),$D68/$AI68,0)+IF(AND(E$2>=$AH69,E$2<$AH69+$AI69),$D69/$AI69,0) | F67: =IF(AND(F$2>=$AH68,F$2<$AH68+$AI68),$D68/$AI68,0)+IF(AND(F$2>=$AH69,F$2<$AH69+$AI69),$D69/$AI69,0) | G67: =IF(AND(G$2>=$AH68,G$2<$AH68+$AI68),$D68/$AI68,0)+IF(AND(G$2>=$AH69,G$2<$AH69+$AI69),$D69/$AI69,0) | H67: =IF(AND(H$2>=$AH68,H$2<$AH68+$AI68),$D68/$AI68,0)+IF(AND(H$2>=$AH69,H$2<$AH69+$AI69),$D69/$AI69,0) | I67: =IF(AND(I$2>=$AH68,I$2<$AH68+$AI68),$D68/$AI68,0)+IF(AND(I$2>=$AH69,I$2<$AH69+$AI69),$D69/$AI69,0) | J67: =IF(AND(J$2>=$AH68,J$2<$AH68+$AI68),$D68/$AI68,0)+IF(AND(J$2>=$AH69,J$2<$AH69+$AI69),$D69/$AI69,0) | K67: =IF(AND(K$2>=$AH68,K$2<$AH68+$AI68),$D68/$AI68,0)+IF(AND(K$2>=$AH69,K$2<$AH69+$AI69),$D69/$AI69,0) | L67: =IF(AND(L$2>=$AH68,L$2<$AH68+$AI68),$D68/$AI68,0)+IF(AND(L$2>=$AH69,L$2<$AH69+$AI69),$D69/$AI69,0) | ... AE67: =IF(AND(AE$2>=$AH68,AE$2<$AH68+$AI68),$D68/$AI68,0)+IF(AND(AE$2>=$AH69,AE$2<$AH69+$AI69),$D69/$AI69,0) | AF67: =SUM(E67:AE67)
B68: First fix, sleeves and pipework | C68: 0.6 | D68: =C68*$D$67 | AH68: 4 | AI68: 15
B69: Second fix, testing and commissioning | C69: 0.4 | D69: =C69*$D$67 | AH69: 19 | AI69: 5
A71: P | B71: ='GEN SUMMARY.'!B31 | D71: ='GEN SUMMARY.'!E31 | E71: =IF(AND(E$2>=$AH72,E$2<$AH72+$AI72),$D72/$AI72,0)+IF(AND(E$2>=$AH73,E$2<$AH73+$AI73),$D73/$AI73,0) | F71: =IF(AND(F$2>=$AH72,F$2<$AH72+$AI72),$D72/$AI72,0)+IF(AND(F$2>=$AH73,F$2<$AH73+$AI73),$D73/$AI73,0) | G71: =IF(AND(G$2>=$AH72,G$2<$AH72+$AI72),$D72/$AI72,0)+IF(AND(G$2>=$AH73,G$2<$AH73+$AI73),$D73/$AI73,0) | H71: =IF(AND(H$2>=$AH72,H$2<$AH72+$AI72),$D72/$AI72,0)+IF(AND(H$2>=$AH73,H$2<$AH73+$AI73),$D73/$AI73,0) | I71: =IF(AND(I$2>=$AH72,I$2<$AH72+$AI72),$D72/$AI72,0)+IF(AND(I$2>=$AH73,I$2<$AH73+$AI73),$D73/$AI73,0) | J71: =IF(AND(J$2>=$AH72,J$2<$AH72+$AI72),$D72/$AI72,0)+IF(AND(J$2>=$AH73,J$2<$AH73+$AI73),$D73/$AI73,0) | K71: =IF(AND(K$2>=$AH72,K$2<$AH72+$AI72),$D72/$AI72,0)+IF(AND(K$2>=$AH73,K$2<$AH73+$AI73),$D73/$AI73,0) | L71: =IF(AND(L$2>=$AH72,L$2<$AH72+$AI72),$D72/$AI72,0)+IF(AND(L$2>=$AH73,L$2<$AH73+$AI73),$D73/$AI73,0) | ... AE71: =IF(AND(AE$2>=$AH72,AE$2<$AH72+$AI72),$D72/$AI72,0)+IF(AND(AE$2>=$AH73,AE$2<$AH73+$AI73),$D73/$AI73,0) | AF71: =SUM(E71:AE71)
B72: First fix, conduits and containment | C72: 0.6 | D72: =C72*$D$71 | AH72: 4 | AI72: 15
B73: Second fix, testing and commissioning | C73: 0.4 | D73: =C73*$D$71 | AH73: 19 | AI73: 5
A75: Q | B75: ='GEN SUMMARY.'!B33 | D75: ='GEN SUMMARY.'!E33 | E75: =IF(AND(E$2>=$AH76,E$2<$AH76+$AI76),$D76/$AI76,0)+IF(AND(E$2>=$AH77,E$2<$AH77+$AI77),$D77/$AI77,0) | F75: =IF(AND(F$2>=$AH76,F$2<$AH76+$AI76),$D76/$AI76,0)+IF(AND(F$2>=$AH77,F$2<$AH77+$AI77),$D77/$AI77,0) | G75: =IF(AND(G$2>=$AH76,G$2<$AH76+$AI76),$D76/$AI76,0)+IF(AND(G$2>=$AH77,G$2<$AH77+$AI77),$D77/$AI77,0) | H75: =IF(AND(H$2>=$AH76,H$2<$AH76+$AI76),$D76/$AI76,0)+IF(AND(H$2>=$AH77,H$2<$AH77+$AI77),$D77/$AI77,0) | I75: =IF(AND(I$2>=$AH76,I$2<$AH76+$AI76),$D76/$AI76,0)+IF(AND(I$2>=$AH77,I$2<$AH77+$AI77),$D77/$AI77,0) | J75: =IF(AND(J$2>=$AH76,J$2<$AH76+$AI76),$D76/$AI76,0)+IF(AND(J$2>=$AH77,J$2<$AH77+$AI77),$D77/$AI77,0) | K75: =IF(AND(K$2>=$AH76,K$2<$AH76+$AI76),$D76/$AI76,0)+IF(AND(K$2>=$AH77,K$2<$AH77+$AI77),$D77/$AI77,0) | L75: =IF(AND(L$2>=$AH76,L$2<$AH76+$AI76),$D76/$AI76,0)+IF(AND(L$2>=$AH77,L$2<$AH77+$AI77),$D77/$AI77,0) | ... AE75: =IF(AND(AE$2>=$AH76,AE$2<$AH76+$AI76),$D76/$AI76,0)+IF(AND(AE$2>=$AH77,AE$2<$AH77+$AI77),$D77/$AI77,0) | AF75: =SUM(E75:AE75)
B76: Procurement and fabrication of facade materials | C76: 0.7 | D76: =C76*$D$75 | AH76: 12 | AI76: 3
B77: Installation of facade | C77: 0.3 | D77: =C77*$D$75 | AH77: 15 | AI77: 8
A79: R | B79: ='GEN SUMMARY.'!B35 | D79: ='GEN SUMMARY.'!E35 | E79: =IF(AND(E$2>=$AH80,E$2<$AH80+$AI80),$D80/$AI80,0)+IF(AND(E$2>=$AH81,E$2<$AH81+$AI81),$D81/$AI81,0) | F79: =IF(AND(F$2>=$AH80,F$2<$AH80+$AI80),$D80/$AI80,0)+IF(AND(F$2>=$AH81,F$2<$AH81+$AI81),$D81/$AI81,0) | G79: =IF(AND(G$2>=$AH80,G$2<$AH80+$AI80),$D80/$AI80,0)+IF(AND(G$2>=$AH81,G$2<$AH81+$AI81),$D81/$AI81,0) | H79: =IF(AND(H$2>=$AH80,H$2<$AH80+$AI80),$D80/$AI80,0)+IF(AND(H$2>=$AH81,H$2<$AH81+$AI81),$D81/$AI81,0) | I79: =IF(AND(I$2>=$AH80,I$2<$AH80+$AI80),$D80/$AI80,0)+IF(AND(I$2>=$AH81,I$2<$AH81+$AI81),$D81/$AI81,0) | J79: =IF(AND(J$2>=$AH80,J$2<$AH80+$AI80),$D80/$AI80,0)+IF(AND(J$2>=$AH81,J$2<$AH81+$AI81),$D81/$AI81,0) | K79: =IF(AND(K$2>=$AH80,K$2<$AH80+$AI80),$D80/$AI80,0)+IF(AND(K$2>=$AH81,K$2<$AH81+$AI81),$D81/$AI81,0) | L79: =IF(AND(L$2>=$AH80,L$2<$AH80+$AI80),$D80/$AI80,0)+IF(AND(L$2>=$AH81,L$2<$AH81+$AI81),$D81/$AI81,0) | ... AE79: =IF(AND(AE$2>=$AH80,AE$2<$AH80+$AI80),$D80/$AI80,0)+IF(AND(AE$2>=$AH81,AE$2<$AH81+$AI81),$D81/$AI81,0) | AF79: =SUM(E79:AE79)
B80: (50%) External works | C80: 0.5 | D80: =C80*$D$79 | AH80: 20 | AI80: 3
B81: (100%) Completion of External works | C81: 0.5 | D81: =C81*$D$79 | AH81: 23 | AI81: 2
A83: S | B83: ='GEN SUMMARY.'!B37 | D83: ='GEN SUMMARY.'!E37 | E83: =IF(AND(E$2>=$AH84,E$2<$AH84+$AI84),$D84/$AI84,0)+IF(AND(E$2>=$AH85,E$2<$AH85+$AI85),$D85/$AI85,0) | F83: =IF(AND(F$2>=$AH84,F$2<$AH84+$AI84),$D84/$AI84,0)+IF(AND(F$2>=$AH85,F$2<$AH85+$AI85),$D85/$AI85,0) | G83: =IF(AND(G$2>=$AH84,G$2<$AH84+$AI84),$D84/$AI84,0)+IF(AND(G$2>=$AH85,G$2<$AH85+$AI85),$D85/$AI85,0) | H83: =IF(AND(H$2>=$AH84,H$2<$AH84+$AI84),$D84/$AI84,0)+IF(AND(H$2>=$AH85,H$2<$AH85+$AI85),$D85/$AI85,0) | I83: =IF(AND(I$2>=$AH84,I$2<$AH84+$AI84),$D84/$AI84,0)+IF(AND(I$2>=$AH85,I$2<$AH85+$AI85),$D85/$AI85,0) | J83: =IF(AND(J$2>=$AH84,J$2<$AH84+$AI84),$D84/$AI84,0)+IF(AND(J$2>=$AH85,J$2<$AH85+$AI85),$D85/$AI85,0) | K83: =IF(AND(K$2>=$AH84,K$2<$AH84+$AI84),$D84/$AI84,0)+IF(AND(K$2>=$AH85,K$2<$AH85+$AI85),$D85/$AI85,0) | L83: =IF(AND(L$2>=$AH84,L$2<$AH84+$AI84),$D84/$AI84,0)+IF(AND(L$2>=$AH85,L$2<$AH85+$AI85),$D85/$AI85,0) | ... AE83: =IF(AND(AE$2>=$AH84,AE$2<$AH84+$AI84),$D84/$AI84,0)+IF(AND(AE$2>=$AH85,AE$2<$AH85+$AI85),$D85/$AI85,0) | AF83: =SUM(E83:AE83)
B84: Design fees - 1st instalment | C84: 0.5 | D84: =C84*$D$83 | AH84: 1 | AI84: 1
B85: Design fees - balance | C85: 0.5 | D85: =C85*$D$83 | AH85: 2 | AI85: 11
A87: T | B87: ='GEN SUMMARY.'!B39 | D87: ='GEN SUMMARY.'!E39 | E87: =IF(AND(E$2>=$AH88,E$2<$AH88+$AI88),$D88/$AI88,0) | F87: =IF(AND(F$2>=$AH88,F$2<$AH88+$AI88),$D88/$AI88,0) | G87: =IF(AND(G$2>=$AH88,G$2<$AH88+$AI88),$D88/$AI88,0) | H87: =IF(AND(H$2>=$AH88,H$2<$AH88+$AI88),$D88/$AI88,0) | I87: =IF(AND(I$2>=$AH88,I$2<$AH88+$AI88),$D88/$AI88,0) | J87: =IF(AND(J$2>=$AH88,J$2<$AH88+$AI88),$D88/$AI88,0) | K87: =IF(AND(K$2>=$AH88,K$2<$AH88+$AI88),$D88/$AI88,0) | L87: =IF(AND(L$2>=$AH88,L$2<$AH88+$AI88),$D88/$AI88,0) | ... AE87: =IF(AND(AE$2>=$AH88,AE$2<$AH88+$AI88),$D88/$AI88,0) | AF87: =SUM(E87:AE87)
B88: Monthly project management | C88: 1 | D88: =C88*$D$87 | AH88: 1 | AI88: 24
B90: ESTIMATED MONTHLY VALUATION (EXCL. ADVANCE) | E90: =E6+E11+E15+E20+E26+E32+E38+E44+E50+E56+E62+E67+E71+E75+E79+E83+E87 | F90: =F6+F11+F15+F20+F26+F32+F38+F44+F50+F56+F62+F67+F71+F75+F79+F83+F87 | G90: =G6+G11+G15+G20+G26+G32+G38+G44+G50+G56+G62+G67+G71+G75+G79+G83+G87 | H90: =H6+H11+H15+H20+H26+H32+H38+H44+H50+H56+H62+H67+H71+H75+H79+H83+H87 | I90: =I6+I11+I15+I20+I26+I32+I38+I44+I50+I56+I62+I67+I71+I75+I79+I83+I87 | J90: =J6+J11+J15+J20+J26+J32+J38+J44+J50+J56+J62+J67+J71+J75+J79+J83+J87 | K90: =K6+K11+K15+K20+K26+K32+K38+K44+K50+K56+K62+K67+K71+K75+K79+K83+K87 | L90: =L6+L11+L15+L20+L26+L32+L38+L44+L50+L56+L62+L67+L71+L75+L79+L83+L87 | ... AE90: =AE6+AE11+AE15+AE20+AE26+AE32+AE38+AE44+AE50+AE56+AE62+AE67+AE71+AE75+AE79+AE83+AE87 | AF90: =SUM(E90:AE90)
B91: CUMULATIVE VALUATION | E91: =E90 | F91: =E91+F90 | G91: =F91+G90 | H91: =G91+H90 | I91: =H91+I90 | J91: =I91+J90 | K91: =J91+K90 | L91: =K91+L90 | M91: =L91+M90 | ... AE91: =AD91+AE90
B92: DEDUCT RETENTION | E92: =MIN($C$104*E90,MAX(0,$C$102-0)) | F92: =MIN($C$104*F90,MAX(0,$C$102-E93)) | G92: =MIN($C$104*G90,MAX(0,$C$102-F93)) | H92: =MIN($C$104*H90,MAX(0,$C$102-G93)) | I92: =MIN($C$104*I90,MAX(0,$C$102-H93)) | J92: =MIN($C$104*J90,MAX(0,$C$102-I93)) | K92: =MIN($C$104*K90,MAX(0,$C$102-J93)) | L92: =MIN($C$104*L90,MAX(0,$C$102-K93)) | M92: =MIN($C$104*M90,MAX(0,$C$102-L93)) | ... AC92: =MIN($C$104*AC90,MAX(0,$C$102-AB93)) | AD92: =-ROUND(AC93*$C$106,2) | AE92: =-AD93 | AF92: =SUM(E92:AE92)
B93: CUMULATIVE RETENTION | E93: =0+E92 | F93: =E93+F92 | G93: =F93+G92 | H93: =G93+H92 | I93: =H93+I92 | J93: =I93+J92 | K93: =J93+K92 | L93: =K93+L92 | M93: =L93+M92 | ... AE93: =AD93+AE92
B94: SUB TOTAL | E94: =E3+E90-E92 | F94: =F3+F90-F92 | G94: =G3+G90-G92 | H94: =H3+H90-H92 | I94: =I3+I90-I92 | J94: =J3+J90-J92 | K94: =K3+K90-K92 | L94: =L3+L90-L92 | ... AE94: =AE3+AE90-AE92 | AF94: =SUM(E94:AE94)
B95: ADVANCE REPAYMENT | E95: =IF(AND(E$2>=$C$112,E$2<$C$112+$C$113),$D$3/$C$113,0) | F95: =IF(AND(F$2>=$C$112,F$2<$C$112+$C$113),$D$3/$C$113,0) | G95: =IF(AND(G$2>=$C$112,G$2<$C$112+$C$113),$D$3/$C$113,0) | H95: =IF(AND(H$2>=$C$112,H$2<$C$112+$C$113),$D$3/$C$113,0) | I95: =IF(AND(I$2>=$C$112,I$2<$C$112+$C$113),$D$3/$C$113,0) | J95: =IF(AND(J$2>=$C$112,J$2<$C$112+$C$113),$D$3/$C$113,0) | K95: =IF(AND(K$2>=$C$112,K$2<$C$112+$C$113),$D$3/$C$113,0) | L95: =IF(AND(L$2>=$C$112,L$2<$C$112+$C$113),$D$3/$C$113,0) | ... AE95: =IF(AND(AE$2>=$C$112,AE$2<$C$112+$C$113),$D$3/$C$113,0) | AF95: =SUM(E95:AE95)
B96: CUMULATIVE ADVANCE REPAYMENT | E96: =E95 | F96: =E96+F95 | G96: =F96+G95 | H96: =G96+H95 | I96: =H96+I95 | J96: =I96+J95 | K96: =J96+K95 | L96: =K96+L95 | M96: =L96+M95 | ... AE96: =AD96+AE95
B97: ESTIMATED MONTHLY PAYMENT | E97: =E94-E95 | F97: =F94-F95 | G97: =G94-G95 | H97: =H94-H95 | I97: =I94-I95 | J97: =J94-J95 | K97: =K94-K95 | L97: =L94-L95 | ... AE97: =AE94-AE95 | AF97: =SUM(E97:AE97)
B98: CUMULATIVE MONTHLY PAYMENT | E98: =E97 | F98: =E98+F97 | G98: =F98+G97 | H98: =G98+H97 | I98: =H98+I97 | J98: =I98+J97 | K98: =J98+K97 | L98: =K98+L97 | M98: =L98+M97 | ... AE98: =AD98+AE97
A100: ITEM | B100: DESCRIPTION | C100: AMOUNT
A101: A | B101: AGREED CONTRACT SUM (DISCOUNTED, LESS TAXES) | C101: ='GEN SUMMARY.'!D51
A102: B | B102: LIMIT OF RETENTION | C102: =$C$105*$C$101
A103: C | B103: ADVANCE MOBILIZATION (% OF CONTRACT SUM) | C103: 0.25
A104: D | B104: RETENTION DEDUCTED PER VALUATION | C104: 0.1
A105: E | B105: LIMIT OF RETENTION (% OF CONTRACT SUM) | C105: 0.05
A106: F | B106: RETENTION RELEASED AT PRACTICAL COMPLETION | C106: 0.5
A107: G | B107: COMMENCEMENT DATE (MONTH 0) | C107: 46295
A108: H | B108: CONTRACT PERIOD (MONTHS) | C108: 24
A109: J | B109: PRACTICAL COMPLETION DATE | C109: =EOMONTH($C$107,$C$108)
A110: K | B110: DEFECTS LIABILITY PERIOD (MONTHS) | C110: 6
A111: L | B111: END OF DEFECTS LIABILITY PERIOD | C111: =EOMONTH(C109,$C$110)
A112: M | B112: ADVANCE REPAYMENT STARTS (MONTH NO.) | C112: 3
A113: N | B113: ADVANCE REPAYMENT PERIOD (MONTHS) | C113: 18
B115: CHECK: TOTAL PAYMENT LESS CONTRACT SUM (MUST BE NIL) | C115: =ROUND(AF97-$C$101,2)
B118: NOTES:
B119: 1. TAXES NOT INCLUDED
B120: 2. PAYMENTS PROJECTED TO BE AT THE END OF THE RESPECTIVE MONTHS.
B121: 3. EACH BILL IS SPREAD OVER ITS SUB-ITEMS USING THE START MONTH AND DURATION IN COLUMNS AH AND AI; AMOUNTS LINK TO GEN SUMMARY.
B122: 4. RETENTION IS DEDUCTED UNTIL THE LIMIT OF RETENTION IS REACHED; HALF IS RELEASED THE MONTH AFTER PRACTICAL COMPLETION AND THE BALANCE AT THE END OF THE DEFECTS LIABILITY PERIOD.

Sheet GEN SUMMARY.
A1: PROJECT: PROPOSED HEAD OFFICE FOR PRIORITY INSURANCE
A2: LOCATION: RIDGE, ACCRA
A3: CLIENT: PRIORITY INSURANCE
A4: DATE: 07/10/2026 (PRELIMINARY ESTIMATE REV. 6)
A5: ITEM | B5: GENERAL SUMMARY | D5: AMOUNT USD | E5: DISCOUNTED AMOUNT USD
A7: A | B7: BILL NO. 1- PRELIMINARIES AND GENERAL ITEMS | D7: =366625+50000 | E7: =D7*$D$48/$D$44
A9: B | B9: BILL NO. 2- DEMOLITIONS AND ALTERATIONS | D9: 50000 | E9: =D9*$D$48/$D$44
A11: C | B11: BILL NO. 3 -SUBSTRUCTURE (ALL PROVISIONAL) | D11: =1585*350 | E11: =D11*$D$48/$D$44
A13: D | B13: BILL NO. 4 -SUB-BASEMENT FLOOR | D13: =1585*400 | E13: =D13*$D$48/$D$44
A15: E | B15: BILL NO. 5 - GROUND FLOOR | D15: =450*500 | E15: =D15*$D$48/$D$44
A17: F | B17: BILL NO. 6 - FIRST FLOOR | D17: =600*500 | E17: =D17*$D$48/$D$44
A19: G | B19: BILL NO. 7- SECOND FLOOR | D19: =600*500 | E19: =D19*$D$48/$D$44
A21: H | B21: BILL NO. 8 -THIRD FLOOR | D21: =600*500 | E21: =D21*$D$48/$D$44
A23: J | B23: BILL NO. 9 -FOURTH FLOOR | D23: =600*500 | E23: =D23*$D$48/$D$44
A25: K | B25: BILL NO. 10 - FIFTH FLOOR | D25: =600*500 | E25: =D25*$D$48/$D$44
A27: L | B27: BILL NO. 11 - KITCHEN CABINETRY/WALL CLADDING | D27: 134515.22 | E27: =D27*$D$48/$D$44
A29: M | B29: BILL NO. 12. PLUMBING, FIRE-FIGHTING AND MECHANICAL | D29: =659925+125000 | E29: =D29*$D$48/$D$44
A31: N | B31: BILL NO. 13: ELECTRICAL WORKS | D31: =1026550+50000 | E31: =D31*$D$48/$D$44
A33: P | B33: BILL NO. 14. EXTERNAL FAÇADE WORKS | D33: =606968.250712613+50000 | E33: =D33*$D$48/$D$44
A35: Q | B35: BILL NO. 15.- EXTERNAL WORKS (ALL PROVISIONAL) | D35: 47193.436 | E35: =D35*$D$48/$D$44
A37: R | B37: DESIGN FEES | D37: 194211.36 | E37: =D37*$D$48/$D$44
A39: S | B39: PROJECT MANAGEMENT FEES | D39: =623262.5-175000 | E39: =D39*$D$48/$D$44
B44: SUB - TOTAL (1) | C44: US $ | D44: =SUM(D7:D40) | E44: =SUM(E7:E40)
B46: LESS: DISCOUNT | D46: =D44-D48
B48: AGREED DISCOUNTED CONTRACT SUM | D48: 6250000
B51: TOTAL COST OF THE WORKS (EXCLUDING TAXES) | C51: US $ | D51: =D44-D46 | E51: =E44
B54: SIGNED: ……………………………………………………………
B57: DATE: ………………………………………...........………….
